Workbook

Sheet DQE
A1: RÉALISATION DE VOILES (2 × 170 m, H = 2,40 m) ET RADIER (170 m × 4,00 m × 0,20 m)
A2: DEVIS QUANTITATIF ET ESTIMATIF (DQE) + DÉBOURSÉ SEC
A3: Lieu des travaux : BOUAFLÉ (Marahoué) – aménagement du thalweg en canal BA | Établi par : Moulo Jean Claude – Technicien Génie Civil BTP | Date : 01/10/2026 | FCFA
A4: Normes : EC2 (NF EN 1992-1-1) / BAEL 91 mod. 99 – Aciers FE500 (HA) – Contexte : sol latéritique, climat tropical humide
A6: N° prix | B6: Désignation des ouvrages | C6: Unité | D6: Quantité | E6: Déboursé sec unitaire | F6: Déboursé sec total | G6: Prix unitaire HT (DS × K) | H6: Montant HT
A7: 000 – INSTALLATION
A8: 000 | B8: Installation et repli de chantier | C8: Ft | D8: =1 | E8: ='Deboursé sec'!$F$16 | F8: =D8*E8 | G8: =ROUND(E8*Hypotheses!$C$88,0) | H8: =D8*G8
A9: 100 – TRAVAUX PRÉPARATOIRES ET TERRASSEMENTS
A10: 101 | B10: Implantation et piquetage | C10: Ft | D10: =1 | E10: ='Deboursé sec'!$F$27 | F10: =D10*E10 | G10: =ROUND(E10*Hypotheses!$C$88,0) | H10: =D10*G10
A11: 104 | B11: Débroussaillage et nettoyage de l'emprise | C11: m² | D11: ='Avant-metre'!$H$10 | E11: ='Deboursé sec'!$F$47 | F11: =D11*E11 | G11: =ROUND(E11*Hypotheses!$C$88,0) | H11: =D11*G11
A12: 105 | B12: Enlèvement et évacuation des ordures / déchets | C12: m³ | D12: ='Avant-metre'!$H$11 | E12: ='Deboursé sec'!$F$57 | F12: =D12*E12 | G12: =ROUND(E12*Hypotheses!$C$88,0) | H12: =D12*G12
A13: 102 | B13: Déblai mécanique en fouille et évacuation | C13: m³ | D13: ='Avant-metre'!$H$9 | E13: ='Deboursé sec'!$F$38 | F13: =D13*E13 | G13: =ROUND(E13*Hypotheses!$C$88,0) | H13: =D13*G13
A14: 103 | B14: Compactage du fond de fouille à 95 % OPM | C14: m² | D14: ='Avant-metre'!$H$12 | E14: ='Deboursé sec'!$F$89 | F14: =D14*E14 | G14: =ROUND(E14*Hypotheses!$C$88,0) | H14: =D14*G14
A15: 106 | B15: Couche de forme en latérite compactée, ép. 20 cm | C15: m³ | D15: ='Avant-metre'!$H$13 | E15: ='Deboursé sec'!$F$68 | F15: =D15*E15 | G15: =ROUND(E15*Hypotheses!$C$88,0) | H15: =D15*G15
A16: 107 | B16: Remblai latéral en latérite compactée derrière les voiles | C16: m³ | D16: ='Avant-metre'!$H$14 | E16: ='Deboursé sec'!$F$79 | F16: =D16*E16 | G16: =ROUND(E16*Hypotheses!$C$88,0) | H16: =D16*G16
A17: 200 – BÉTONS
A18: 201 | B18: Béton de propreté dosé à 150 kg/m³, ép. 5 cm | C18: m³ | D18: ='Avant-metre'!$H$16 | E18: ='Deboursé sec'!$F$105 | F18: =D18*E18 | G18: =ROUND(E18*Hypotheses!$C$88,0) | H18: =D18*G18
A19: 202 | B19: Béton pour radier dosé à 350 kg/m³ (C25/30), ép. 20 cm | C19: m³ | D19: ='Avant-metre'!$H$17 | E19: ='Deboursé sec'!$F$121 | F19: =D19*E19 | G19: =ROUND(E19*Hypotheses!$C$88,0) | H19: =D19*G19
A20: 203 | B20: Béton pour voiles dosé à 350 kg/m³ (C25/30) | C20: m³ | D20: ='Avant-metre'!$H$18 | E20: ='Deboursé sec'!$F$137 | F20: =D20*E20 | G20: =ROUND(E20*Hypotheses!$C$88,0) | H20: =D20*G20
A21: 300 – COFFRAGES
A22: 301 | B22: Coffrage des rives du radier | C22: m² | D22: ='Avant-metre'!$H$20 | E22: ='Deboursé sec'!$F$148 | F22: =D22*E22 | G22: =ROUND(E22*Hypotheses!$C$88,0) | H22: =D22*G22
A23: 302 | B23: Coffrage des voiles (2 faces) | C23: m² | D23: ='Avant-metre'!$H$21 | E23: ='Deboursé sec'!$F$160 | F23: =D23*E23 | G23: =ROUND(E23*Hypotheses!$C$88,0) | H23: =D23*G23
A24: 400 – ACIERS FE500
A25: 401 | B25: Acier HA8 (voiles horiz. face intérieure, épingles, plantants en U e = 20 cm) | C25: kg | D25: ='Avant-metre'!$H$40 | E25: ='Deboursé sec'!$F$171 | F25: =D25*E25 | G25: =ROUND(E25*Hypotheses!$C$88,0) | H25: =D25*G25
A26: 402 | B26: Acier HA10 (voiles horiz. face extérieure, radier longitudinal + chaises) | C26: kg | D26: ='Avant-metre'!$H$41 | E26: ='Deboursé sec'!$F$182 | F26: =D26*E26 | G26: =ROUND(E26*Hypotheses!$C$88,0) | H26: =D26*G26
A27: 403 | B27: Acier HA12 (voiles verticaux ext. e=12,5 / int. e=20 + radier transversal inf. e=15 / sup. e=20) | C27: kg | D27: ='Avant-metre'!$H$42 | E27: ='Deboursé sec'!$F$193 | F27: =D27*E27 | G27: =ROUND(E27*Hypotheses!$C$88,0) | H27: =D27*G27
A28: 500 – DIVERS
A29: 501 | B29: Joint de dilatation (tous les 15 m) | C29: ml | D29: ='Avant-metre'!$H$26 | E29: ='Deboursé sec'!$F$232 | F29: =D29*E29 | G29: =ROUND(E29*Hypotheses!$C$88,0) | H29: =D29*G29
A30: 502 | B30: Déviation provisoire des eaux et épuisement | C30: Ft | D30: ='Avant-metre'!$H$23 | E30: ='Deboursé sec'!$F$203 | F30: =D30*E30 | G30: =ROUND(E30*Hypotheses!$C$88,0) | H30: =D30*G30
A31: 503 | B31: Barbacanes PVC Ø75 avec filtre | C31: u | D31: ='Avant-metre'!$H$24 | E31: ='Deboursé sec'!$F$212 | F31: =D31*E31 | G31: =ROUND(E31*Hypotheses!$C$88,0) | H31: =D31*G31
A32: 504 | B32: Raccordements aux ouvrages existants | C32: u | D32: ='Avant-metre'!$H$25 | E32: ='Deboursé sec'!$F$222 | F32: =D32*E32 | G32: =ROUND(E32*Hypotheses!$C$88,0) | H32: =D32*G32
A33: TOTAL HORS TAXES (FCFA) | F33: =SUM(F7:F32) | H33: =SUM(H7:H32)
A34: TVA 18 % | H34: =H33*Hypotheses!$C$89
A35: TOTAL TOUTES TAXES COMPRISES (FCFA) | H35: =H33+H34
A37: Coefficient K appliqué | H37: =Hypotheses!$C$88
A38: Marge brute (HT − DS) | H38: =H33-F33
A39: Coût au mètre linéaire d'ouvrage – DS (FCFA/ml) | H39: =F33/Hypotheses!$C$8
A40: Coût au mètre linéaire d'ouvrage – HT (FCFA/ml) | H40: =H33/Hypotheses!$C$8
A42: NOTES
A43: • Hypothèses à confirmer : épaisseur des voiles 20 cm (non fournie), profondeur de déblai 0,60 m, remblai latéral 1,00 m de large derrière chaque voile, volume d'ordures 150 m³ (à confirmer par levé topographique), espacements des aciers 20 cm.
A44: • Faces extérieures (côté terre) justifiées par la note de calcul : voiles HA12 verticaux e = 12,5 cm, radier nappe inférieure HA12 e = 15 cm ; faces intérieures HA12 e = 20 cm.
A45: • Voiles – aciers horizontaux : HA10 sur la face extérieure (reprise de la poussée) et HA8 sur la face intérieure, e = 20 cm.
A46: • Plantants en U HA8 e = 20 cm : U ancré dans le radier, une jambe de 0,60 m dans chaque nappe du voile (jonction voile/radier).
A47: • Béton fabriqué sur chantier à la bétonnière ; cure humide d'au moins 7 jours obligatoire (chaleur tropicale) ; bétonnage de préférence le matin.
A48: • Site de Bouaflé (vidéo du 01/10/2026) : thalweg en terre avec écoulement permanent, ordures et berges érodées → déviation des eaux, couche de forme en latérite et barbacanes prévues.
A49: • Prix de base indicatifs rendus Bouaflé 2026 (transport depuis Abidjan / Yamoussoukro inclus) – à actualiser selon les cotations fournisseurs (feuille « Hypotheses », cellules jaunes).
B51: Établi par : Moulo Jean Claude | F51: Visa / Approbation :

Sheet Note de calcul
A1: RÉALISATION DE VOILES (2 × 170 m, H = 2,40 m) ET RADIER (170 m × 4,00 m × 0,20 m)
A2: NOTE DE CALCUL SIMPLIFIÉE – VOILES ET ANGLE VOILE/RADIER SOUS POUSSÉE DES TERRES
A3: Lieu des travaux : BOUAFLÉ (Marahoué) – aménagement du thalweg en canal BA | Établi par : Moulo Jean Claude – Technicien Génie Civil BTP | Date : 01/10/2026 | FCFA
A4: Normes : EC2 (NF EN 1992-1-1) / BAEL 91 mod. 99 – Aciers FE500 (HA) – Contexte : sol latéritique, climat tropical humide
A6: Grandeur | B6: Symbole / formule | C6: Unité | D6: Valeur | E6: Commentaire
A7: 1. DONNÉES (site de Bouaflé – canal en U dans un thalweg, remblai latéritique derrière les voiles)
A8: Hauteur de terre retenue | B8: H | C8: m | D8: =Hypotheses!$C$10 | E8: Voile totalement remblayé (cas défavorable)
A9: Poids volumique du remblai latéritique | B9: γ | C9: kN/m³ | D9: 20 | E9: Latérite compactée
A10: Angle de frottement interne | B10: φ | C10: ° | D10: 30 | E10: Latérite compactée – valeur prudente
A11: Surcharge en tête de berge | B11: q | C11: kN/m² | D11: 10 | E11: Voie / circulation piétonne et légère au bord du thalweg (vidéo)
A12: Résistance du béton (C25/30) | B12: fck = fc28 | C12: MPa | D12: 25 | E12: Béton dosé à 350 kg/m³
A13: Limite élastique des aciers FE500 | B13: fyk = fe | C13: MPa | D13: 500
A14: Épaisseur du voile | B14: e | C14: m | D14: =Hypotheses!$C$11
A15: Épaisseur du radier | B15: e_r | C15: m | D15: =Hypotheses!$C$13
A16: Enrobage nominal | B16: c | C16: m | D16: =Hypotheses!$C$14 | E16: XC2/XC4
A17: 2. SOLLICITATIONS PAR MÈTRE LINÉAIRE À L'ENCASTREMENT VOILE / RADIER (console)
A18: Coefficient de poussée active (Rankine) | B18: Ka = tan²(π/4 − φ/2) | C18: - | D18: =TAN(PI()/4-RADIANS($D$10)/2)^2
A19: Moment dû aux terres | B19: Mg = Ka·γ·H³/6 | C19: kN·m/m | D19: =$D$18*$D$9*$D$8^3/6
A20: Moment dû à la surcharge | B20: Mq = Ka·q·H²/2 | C20: kN·m/m | D20: =$D$18*$D$11*$D$8^2/2
A21: Moment de service | B21: Mser = Mg + Mq | C21: kN·m/m | D21: =$D$19+$D$20 | E21: ELS
A22: Moment ultime | B22: MEd = 1,35·Mg + 1,5·Mq | C22: kN·m/m | D22: =1.35*$D$19+1.5*$D$20 | E22: ELU (EC0 / BAEL)
A23: Effort tranchant ultime | B23: VEd = 1,35·Ka·γ·H²/2 + 1,5·Ka·q·H | C23: kN/m | D23: =1.35*$D$18*$D$9*$D$8^2/2+1.5*$D$18*$D$11*$D$8
A24: 3. MATÉRIAUX
A25: Résistance de calcul du béton | B25: fcd = fck/1,5 | C25: MPa | D25: =$D$12/1.5 | E25: EC2
A26: Résistance de calcul de l'acier | B26: fyd = fyk/1,15 | C26: MPa | D26: =$D$13/1.15 | E26: EC2
A27: Résistance en traction du béton | B27: ft28 = 0,6 + 0,06·fc28 | C27: MPa | D27: =0.6+0.06*$D$12 | E27: BAEL
A28: Contrainte limite acier – fissuration préjudiciable | B28: σ̄s = min(2/3·fe ; max(0,5·fe ; 110·√(η·ft28))) | C28: MPa | D28: =MIN(2/3*$D$13,MAX(0.5*$D$13,110*SQRT(1.6*$D$27))) | E28: BAEL A.4.5,33 – milieu humide (canal)
A29: 4. VOILE – FACE EXTÉRIEURE (côté terre, tendue à l'encastrement)
A30: Hauteur utile | B30: d | C30: m | D30: =$D$14-$D$16-0.010-0.006 | E30: d = e − c − Ø horiz. HA10 − Ø/2 (verticaux derrière les horizontaux)
A31: Moment réduit | B31: μ = MEd/(b·d²·fcd) | C31: - | D31: =$D$22/(1*$D$30^2*$D$25*1000) | E31: b = 1 m ; μ < 0,372 → pas d'acier comprimé
B32: α = 1,25·(1 − √(1 − 2μ)) | C32: - | D32: =1.25*(1-SQRT(1-2*$D$31))
A33: Bras de levier | B33: z = d·(1 − 0,4·α) | C33: m | D33: =$D$30*(1-0.4*$D$32)
A34: Section requise ELU | B34: As = MEd/(z·fyd) | C34: mm²/m | D34: =$D$22/($D$33*$D$26*1000)*1e6
A35: Espacement retenu HA12 | B35: s | C35: m | D35: =Hypotheses!$C$27 | E35: Modifiable dans « Hypotheses »
A36: Section fournie HA12 | B36: As = π·12²/4 / s | C36: mm²/m | D36: =PI()*12^2/4/$D$35
A37: Vérification ELU | B37: As fournie ≥ As requise | C37: - | D37: =IF($D$36>=$D$34,"OK","NON – réduire s")
A38: Axe neutre ELS (n = 15) | B38: b·x²/2 = n·As·(d − x) | C38: m | D38: =(-15*$D$36/1e6+SQRT((15*$D$36/1e6)^2+2*15*$D$36/1e6*$D$30))
A39: Contrainte de l'acier en service | B39: σs = Mser/(As·(d − x/3)) | C39: MPa | D39: =$D$21/($D$36/1e6*($D$30-$D$38/3))/1000
A40: Vérification ELS (fissuration) | B40: σs ≤ σ̄s | C40: - | D40: =IF($D$39<=$D$28,"OK","NON – réduire s") | E40: BAEL strict ; EC2 tab. 7.2N : Ø12 admis jusqu'à σs ≈ 280 MPa (wk = 0,3 mm)
A41: 5. RADIER – NAPPE INFÉRIEURE TRANSVERSALE (angle tendu, continuité du moment du voile)
A42: Hauteur utile | B42: d | C42: m | D42: =$D$15-$D$16-0.006 | E42: d = e_r − c − Ø/2 (transversaux en lit extérieur)
A43: Moment réduit | B43: μ = MEd/(b·d²·fcd) | C43: - | D43: =$D$22/(1*$D$42^2*$D$25*1000) | E43: b = 1 m ; μ < 0,372 → pas d'acier comprimé
B44: α = 1,25·(1 − √(1 − 2μ)) | C44: - | D44: =1.25*(1-SQRT(1-2*$D$43))
A45: Bras de levier | B45: z = d·(1 − 0,4·α) | C45: m | D45: =$D$42*(1-0.4*$D$44)
A46: Section requise ELU | B46: As = MEd/(z·fyd) | C46: mm²/m | D46: =$D$22/($D$45*$D$26*1000)*1e6
A47: Espacement retenu HA12 | B47: s | C47: m | D47: =Hypotheses!$C$30 | E47: Modifiable dans « Hypotheses »
A48: Section fournie HA12 | B48: As = π·12²/4 / s | C48: mm²/m | D48: =PI()*12^2/4/$D$47
A49: Vérification ELU | B49: As fournie ≥ As requise | C49: - | D49: =IF($D$48>=$D$46,"OK","NON – réduire s")
A50: Axe neutre ELS (n = 15) | B50: b·x²/2 = n·As·(d − x) | C50: m | D50: =(-15*$D$48/1e6+SQRT((15*$D$48/1e6)^2+2*15*$D$48/1e6*$D$42))
A51: Contrainte de l'acier en service | B51: σs = Mser/(As·(d − x/3)) | C51: MPa | D51: =$D$21/($D$48/1e6*($D$42-$D$50/3))/1000
A52: Vérification ELS (fissuration) | B52: σs ≤ σ̄s | C52: - | D52: =IF($D$51<=$D$28,"OK","NON – réduire s") | E52: BAEL strict ; EC2 tab. 7.2N : Ø12 admis jusqu'à σs ≈ 280 MPa (wk = 0,3 mm)
A53: 6. EFFORT TRANCHANT (EC2 §6.2.2 – sans armatures d'effort tranchant)
B54: k = 1 + √(200/d) ≤ 2 | C54: - | D54: =MIN(2,1+SQRT(200/($D$30*1000)))
B55: ρl = As/(b·d) ≤ 0,02 | C55: - | D55: =MIN(0.02,$D$36/1e6/$D$30)
A56: Résistance à l'effort tranchant | B56: VRd,c = max(0,12·k·(100·ρl·fck)^(1/3) ; 0,035·k^1,5·√fck)·b·d | C56: kN/m | D56: =MAX(0.12*$D$54*(100*$D$55*$D$12)^(1/3),0.035*$D$54^1.5*SQRT($D$12))*$D$30*1000
A57: Vérification | B57: VEd ≤ VRd,c | C57: - | D57: =IF($D$23<=$D$56,"OK","NON")
A58: 7. CONCLUSIONS
A59: • Faces EXTÉRIEURES (côté terre) : voiles HA12 verticaux e = 12,5 cm ; radier nappe inférieure transversale HA12 e = 15 cm ; retour des HA12 extérieurs de 0,60 m (50Ø) le long de la nappe inférieure du radier (angle tendu).
A60: • Voile : HA12 e = 20 cm insuffisant à l'ELU (565 < 593 mm²/m) ; HA12 e = 15 cm vérifie l'ELU mais σs ≈ 258 MPa > 250 MPa (BAEL fissuration préjudiciable) → HA12 e = 12,5 cm retenu (σs ≈ 217 MPa).
A61: • Horizontaux : HA10 e = 20 cm côté extérieur (retrait / répartition, ≥ 25 % des verticaux) et HA8 e = 20 cm côté intérieur – conformes EC2 §9.6.3.
A62: • Faces INTÉRIEURES : HA12 e = 20 cm (voile et nappe supérieure du radier) – armatures minimales EC2 suffisantes, À CONDITION que le remblai latéral soit en place et compacté avant la mise en eau du canal (sinon la poussée de l'eau, Mser ≈ 23 kN·m/m, tend la face intérieure).
A63: • Barbacanes obligatoires (pas de pression d'eau derrière les voiles prise en compte dans ce calcul).
A64: • Note simplifiée (console encastrée, 1 ml) : à faire valider par un bureau d'études avant exécution.
A66: Établi par : Moulo Jean Claude – Technicien Génie Civil BTP

Sheet Hypotheses
A1: RÉALISATION DE VOILES (2 × 170 m, H = 2,40 m) ET RADIER (170 m × 4,00 m × 0,20 m)
A2: HYPOTHÈSES DE CALCUL ET PRIX DE BASE (cellules jaunes modifiables)
A3: Lieu des travaux : BOUAFLÉ (Marahoué) – aménagement du thalweg en canal BA | Établi par : Moulo Jean Claude – Technicien Génie Civil BTP | Date : 01/10/2026 | FCFA
A4: Normes : EC2 (NF EN 1992-1-1) / BAEL 91 mod. 99 – Aciers FE500 (HA) – Contexte : sol latéritique, climat tropical humide
A6: Paramètre | B6: Unité | C6: Valeur | D6: Source / commentaire
A7: GÉOMÉTRIE
A8: Longueur d'ouvrage | B8: m | C8: 170 | D8: Donnée client
A9: Nombre de voiles | B9: u | C9: 2 | D9: Donnée client (170 m × 2)
A10: Hauteur des voiles (au-dessus du radier) | B10: m | C10: 2.4 | D10: Donnée client
A11: Épaisseur des voiles | B11: m | C11: 0.2 | D11: HYPOTHÈSE (non fournie) – mini 15 cm pour nappe double, 20 cm retenus
A12: Largeur du radier | B12: m | C12: 4 | D12: Donnée client
A13: Épaisseur du radier | B13: m | C13: 0.2 | D13: Donnée client
A14: Enrobage nominal | B14: m | C14: 0.04 | D14: EC2 §4.4 – classe XC2/XC4 (contact sol, humidité tropicale)
A15: Surlargeur de fouille par côté | B15: m | C15: 0.6 | D15: Hypothèse – espace de travail coffrage (berges irrégulières du thalweg)
A16: Profondeur moyenne de déblai (curage + reprofilage du fond + couche de forme) | B16: m | C16: 0.6 | D16: HYPOTHÈSE d'après la vidéo du site – à confirmer par levé topographique / profils en travers
A17: Épaisseur béton de propreté | B17: m | C17: 0.05 | D17: Usuel
A18: Débord béton de propreté par côté | B18: m | C18: 0.1 | D18: Usuel
A19: Épaisseur couche de forme (latérite ou tout-venant) sous radier | B19: m | C19: 0.2 | D19: Fond de thalweg humide – substitution du sol vaseux
... A25: Coefficient de foisonnement (latérite) | B25: - | C25: 1.25 | D25: Sol latéritique – 1,20 à 1,30
A26: ARMATURES FE500
A27: Voiles – HA12 verticaux FACE EXTÉRIEURE (côté terre), espacement | B27: m | C27: 0.125 | D27: Note de calcul (poussée des terres + surcharge) – EC2 ELU / BAEL ELS
A28: Voiles – HA12 verticaux face intérieure, espacement | B28: m | C28: 0.2 | D28: EC2 §9.6.2 : s ≤ min(3h ; 400 mm)
A29: Voiles – horizontaux HA10 ext. / HA8 int., espacement | B29: m | C29: 0.2 | D29: EC2 §9.6.3 : s ≤ 400 mm
A30: Radier – HA12 transversaux NAPPE INFÉRIEURE (extérieure), espacement | B30: m | C30: 0.15 | D30: Note de calcul – continuité du moment d'encastrement du voile
A31: Radier – HA12 transversaux nappe supérieure, espacement | B31: m | C31: 0.2 | D31: Disposition constructive / mini EC2
A32: Radier – HA10 longitudinaux, espacement (2 nappes) | B32: m | C32: 0.2 | D32: Hypothèse – à confirmer par note de calcul
A33: Plantants en U HA8 – espacement | B33: m | C33: 0.2 | D33: Demande client
A34: Plantants en U – hauteur de jambe dans le voile | B34: m | C34: 0.6 | D34: Hypothèse ≥ recouvrement 50Ø HA12 = 0,60 m
A35: Épingles HA8 de liaison des nappes voile | B35: u/m² | C35: 4 | D35: Disposition constructive usuelle (EC2 §9.6.4)
A36: Chaises HA10 support nappe sup. radier | B36: u/m² | C36: 1 | D36: Disposition constructive usuelle
A37: Retour / crochet d'extrémité | B37: m | C37: 0.15 | D37: Usuel
A38: Retour d'ancrage des HA12 de voile (face int.) dans le radier | B38: m | C38: 0.3 | D38: BAEL / EC2 – ancrage avec retour à 90°
... A46: Espacement des joints de dilatation | B46: m | C46: 15 | D46: Climat tropical (fortes amplitudes) – 12 à 20 m
A47: PRIX DES MATÉRIAUX (rendus chantier BOUAFLÉ, transport inclus – à actualiser)
A48: Ciment CPJ 42.5 (sac 50 kg) | B48: FCFA/sac | C48: 6200 | D48: Indicatif Bouaflé 2026 (Abidjan ≈ 5 500 + transport)
A49: Sable de rivière / de carrière | B49: FCFA/m³ | C49: 12000 | D49: Indicatif Bouaflé (sable local)
A50: Gravier concassé 5/15 – 15/25 | B50: FCFA/m³ | C50: 30000 | D50: Indicatif – carrières de la région de Yamoussoukro + transport
A51: Eau de gâchage | B51: FCFA/m³ | C51: 1000 | D51: Indicatif
A52: Acier HA8 FE500 | B52: FCFA/kg | C52: 690 | D52: Indicatif Bouaflé (Abidjan + transport ≈ 40 FCFA/kg)
A53: Acier HA10 FE500 | B53: FCFA/kg | C53: 660 | D53: Indicatif Bouaflé
A54: Acier HA12 FE500 | B54: FCFA/kg | C54: 660 | D54: Indicatif Bouaflé
A55: Fil recuit (ligature) | B55: FCFA/kg | C55: 1000 | D55: Indicatif
A56: Consommation fil recuit | B56: kg/kg acier | C56: 0.01 | D56: 10 kg/tonne
A57: Coffrage bois/contreplaqué amorti (4 réemplois) | B57: FCFA/m² | C57: 3000 | D57: Indicatif
A58: Accessoires coffrage (pointes, huile, tiges, cales) | B58: FCFA/m² | C58: 500 | D58: Indicatif
A59: Étaiement / échafaudage voiles | B59: FCFA/m² | C59: 800 | D59: Indicatif
... A65: Pertes matériaux béton | B65: % | C65: 0.05 | D65: Usuel
A66: MAIN D'ŒUVRE (FCFA / jour)
A67: Chef d'équipe | B67: FCFA/j | C67: 15000 | D67: Indicatif (personnel qualifié déplacé)
A68: Ouvrier qualifié (maçon, coffreur, ferrailleur) | B68: FCFA/j | C68: 10000 | D68: Indicatif
A69: Manœuvre | B69: FCFA/j | C69: 4000 | D69: Indicatif – recrutement local Bouaflé
A70: MATÉRIEL ET RENDEMENTS
A71: Pelle hydraulique avec conducteur et carburant | B71: FCFA/j | C71: 350000 | D71: Location indicative
A72: Rendement pelle (déblai) | B72: m³/j | C72: 250 | D72: Hypothèse
A73: Camion benne (évacuation) | B73: FCFA/j | C73: 150000 | D73: Location indicative
A74: Rendement évacuation par camion | B74: m³/j | C74: 60 | D74: Hypothèse – décharge ≤ 5 km
A75: Compacteur (plaque/rouleau) + carburant | B75: FCFA/j | C75: 75000 | D75: Location indicative
A76: Rendement compactage | B76: m²/j | C76: 800 | D76: Hypothèse
A77: Bétonnière 350 L + aiguille vibrante + carburant | B77: FCFA/j | C77: 45000 | D77: Location indicative
A78: Rendement bétonnage radier (1 chef, 2 maçons, 8 manœuvres) | B78: m³/j | C78: 12 | D78: Hypothèse
A79: Rendement bétonnage voiles (même équipe) | B79: m³/j | C79: 8 | D79: Hypothèse
A80: Rendement béton de propreté | B80: m³/j | C80: 15 | D80: Hypothèse
A81: Rendement coffrage voiles (1 coffreur + 1 aide) | B81: m²/j | C81: 12 | D81: Pose + décoffrage
A82: Rendement coffrage rives radier | B82: m²/j | C82: 20 | D82: Pose + décoffrage
... A86: Rendement remblai compacté par couches de 20 cm | B86: m³/j | C86: 80 | D86: Hypothèse
A87: COEFFICIENTS
A88: Coefficient de vente K (FG + aléas + bénéfice) | B88: - | C88: 1.3 | D88: Hypothèse : FG 15 % + aléas 5 % + bénéfice 10 %
A89: TVA | B89: % | C89: 0.18 | D89: Côte d'Ivoire

Sheet Avant-metre
A1: RÉALISATION DE VOILES (2 × 170 m, H = 2,40 m) ET RADIER (170 m × 4,00 m × 0,20 m)
A2: AVANT-MÉTRÉ ET NOMENCLATURE DES ACIERS
A3: Lieu des travaux : BOUAFLÉ (Marahoué) – aménagement du thalweg en canal BA | Établi par : Moulo Jean Claude – Technicien Génie Civil BTP | Date : 01/10/2026 | FCFA
A4: Normes : EC2 (NF EN 1992-1-1) / BAEL 91 mod. 99 – Aciers FE500 (HA) – Contexte : sol latéritique, climat tropical humide
A6: Réf. | B6: Désignation | C6: Unité | D6: Formule / détail | H6: Quantité | I6: Observation
A7: 1. TERRASSEMENTS
A8: T1 | B8: Implantation et piquetage | C8: ml | D8: L | H8: =Hypotheses!$C$8
A9: T2 | B9: Déblai en fouille (radier) | C9: m³ | D9: L × (B + 2×surlargeur) × profondeur | H9: =Hypotheses!$C$8*(Hypotheses!$C$12+2*Hypotheses!$C$15)*Hypotheses!$C$16
A10: T0 | B10: Débroussaillage et nettoyage de l'emprise | C10: m² | D10: L × largeur d'emprise | H10: =Hypotheses!$C$8*Hypotheses!$C$20 | I10: Vidéo : herbes hautes, broussailles
A11: T0b | B11: Enlèvement et évacuation des ordures / déchets | C11: m³ | D11: Volume estimé | H11: =Hypotheses!$C$21 | I11: À constater contradictoirement
A12: T3 | B12: Compactage du fond de fouille à 95 % OPM | C12: m² | D12: L × (B + 2×surlargeur) | H12: =Hypotheses!$C$8*(Hypotheses!$C$12+2*Hypotheses!$C$15) | I12: Purge des poches argileuses si rencontrées
A13: T4 | B13: Couche de forme en latérite compactée sous radier | C13: m³ | D13: L × (B + 2×débord) × e | H13: =Hypotheses!$C$8*(Hypotheses!$C$12+2*Hypotheses!$C$18)*Hypotheses!$C$19 | I13: Fond de thalweg humide
A14: T5 | B14: Remblai latéral en latérite compactée derrière les voiles | C14: m³ | D14: Nv × L × largeur moy. × H | H14: =Hypotheses!$C$9*Hypotheses!$C$8*Hypotheses!$C$22*Hypotheses!$C$10 | I14: Couches de 20 cm à 95 % OPM
A15: 2. BÉTONS
A16: B1 | B16: Béton de propreté dosé à 150 kg/m³ | C16: m³ | D16: L × (B + 2×débord) × e | H16: =Hypotheses!$C$8*(Hypotheses!$C$12+2*Hypotheses!$C$18)*Hypotheses!$C$17
A17: B2 | B17: Béton armé radier dosé à 350 kg/m³ (C25/30) | C17: m³ | D17: L × B × e | H17: =Hypotheses!$C$8*Hypotheses!$C$12*Hypotheses!$C$13
A18: B3 | B18: Béton armé voiles dosé à 350 kg/m³ (C25/30) | C18: m³ | D18: Nv × L × H × e | H18: =Hypotheses!$C$9*Hypotheses!$C$8*Hypotheses!$C$10*Hypotheses!$C$11 | I18: Épaisseur 20 cm supposée
A19: 3. COFFRAGES
A20: C1 | B20: Coffrage des rives du radier | C20: m² | D20: Périmètre × e | H20: =(2*Hypotheses!$C$8+2*Hypotheses!$C$12)*Hypotheses!$C$13
A21: C2 | B21: Coffrage des voiles (2 faces + abouts) | C21: m² | D21: Nv × (2 faces × L × H + 2 abouts) | H21: =Hypotheses!$C$9*(2*Hypotheses!$C$8*Hypotheses!$C$10+2*Hypotheses!$C$11*Hypotheses!$C$10)
A22: 4. DIVERS
A23: D1 | B23: Déviation provisoire des eaux et épuisement | C23: Ft | D23: Batardeaux + pompage | H23: =1 | I23: Écoulement permanent constaté sur la vidéo
A24: BA | B24: Barbacanes PVC Ø75 avec filtre | C24: u | D24: Nv × (L/esp + 1) | H24: =Hypotheses!$C$9*(ROUNDUP(Hypotheses!$C$8/Hypotheses!$C$23,0)+1) | I24: 1 rang à 0,40 m au-dessus du radier
A25: RC | B25: Raccordements aux ouvrages existants (caniveau amont, buses aval) | C25: Ft | D25: 2 raccordements | H25: =2 | I25: Vus sur la vidéo
A26: J1 | B26: Joints de dilatation (radier + 2 voiles) | C26: ml | D26: (nb joints) × (B + Nv × H) | H26: =(ROUNDUP(Hypotheses!$C$8/Hypotheses!$C$46,0)-1)*(Hypotheses!$C$12+Hypotheses!$C$9*Hypotheses!$C$10) | I26: Joint tous les 15 m
A28: 5. NOMENCLATURE DES ACIERS FE500 (quantités nettes, pertes comptées au déboursé)
A29: Rep. | B29: Désignation | C29: Ø (mm) | D29: Esp. (m) | E29: Nb barres | F29: L unit. (m) | G29: L totale (m) | H29: Masse (kg) | I29: Mode de calcul
A30: V1e | B30: Voiles – barres verticales FACE EXTÉRIEURE (côté terre) | C30: 12 | D30: =Hypotheses!$C$27 | E30: =(ROUNDUP(Hypotheses!$C$8/D30,0)+1)*Hypotheses!$C$9 | F30: =Hypotheses!$C$10-Hypotheses!$C$14+Hypotheses!$C$13-Hypotheses!$C$14+Hypotheses!$C$39 | G30: =E30*F30 | H30: =G30*Hypotheses!$C$44 | I30: (L/esp + 1) × Nv ; L = H − enr. + hauteur radier + retour 50Ø dans la nappe inf.
A31: V1i | B31: Voiles – barres verticales face intérieure | C31: 12 | D31: =Hypotheses!$C$28 | E31: =(ROUNDUP(Hypotheses!$C$8/D31,0)+1)*Hypotheses!$C$9 | F31: =Hypotheses!$C$10-Hypotheses!$C$14+Hypotheses!$C$13-Hypotheses!$C$14+Hypotheses!$C$38 | G31: =E31*F31 | H31: =G31*Hypotheses!$C$44 | I31: (L/esp + 1) × Nv ; L = H − enr. + ancrage radier + retour
A32: V2a | B32: Voiles – barres horizontales, nappe EXTÉRIEURE (côté poussée) | C32: 10 | D32: =Hypotheses!$C$29 | E32: =(ROUNDUP((Hypotheses!$C$10-Hypotheses!$C$14)/D32,0)+1)*Hypotheses!$C$9 | F32: =Hypotheses!$C$8-2*Hypotheses!$C$14+2*Hypotheses!$C$37+(ROUNDUP(Hypotheses!$C$8/Hypotheses!$C$41,0)-1)*Hypotheses!$C$40*10/1000 | G32: =E32*F32 | H32: =G32*Hypotheses!$C$43 | I32: Nb filants = (H/esp + 1) × Nv ; L = L + retours + recouvrements 50Ø – HA10 à cause de la poussée
A33: V2b | B33: Voiles – barres horizontales, nappe INTÉRIEURE | C33: 8 | D33: =Hypotheses!$C$29 | E33: =(ROUNDUP((Hypotheses!$C$10-Hypotheses!$C$14)/D33,0)+1)*Hypotheses!$C$9 | F33: =Hypotheses!$C$8-2*Hypotheses!$C$14+2*Hypotheses!$C$37+(ROUNDUP(Hypotheses!$C$8/Hypotheses!$C$41,0)-1)*Hypotheses!$C$40*8/1000 | G33: =E33*F33 | H33: =G33*Hypotheses!$C$42 | I33: Nb filants = (H/esp + 1) × Nv ; L = L + retours + recouvrements 50Ø
A34: V3 | B34: Voiles – épingles de liaison des nappes | C34: 8 | E34: =ROUNDUP(Hypotheses!$C$9*Hypotheses!$C$8*Hypotheses!$C$10*Hypotheses!$C$35,0) | F34: =Hypotheses!$C$11-2*Hypotheses!$C$14+2*0.10 | G34: =E34*F34 | H34: =G34*Hypotheses!$C$42 | I34: 4 u/m² ; L = e − 2 enr. + 2 crochets
A35: V4 | B35: Plantants en U (jonction voile / radier) | C35: 8 | D35: =Hypotheses!$C$33 | E35: =(ROUNDUP(Hypotheses!$C$8/D35,0)+1)*Hypotheses!$C$9 | F35: =2*(Hypotheses!$C$34+Hypotheses!$C$13-Hypotheses!$C$14)+(Hypotheses!$C$11-2*Hypotheses!$C$14) | G35: =E35*F35 | H35: =G35*Hypotheses!$C$42 | I35: U ancré dans le radier, 2 jambes de 0,60 m dans le voile (une par nappe)
A36: R1i | B36: Radier – barres transversales NAPPE INFÉRIEURE (extérieure) | C36: 12 | D36: =Hypotheses!$C$30 | E36: =ROUNDUP(Hypotheses!$C$8/D36,0)+1 | F36: =Hypotheses!$C$12-2*Hypotheses!$C$14+2*Hypotheses!$C$37 | G36: =E36*F36 | H36: =G36*Hypotheses!$C$44 | I36: L/esp + 1 ; L = B − 2 enr. + 2 retours
A37: R1s | B37: Radier – barres transversales nappe supérieure | C37: 12 | D37: =Hypotheses!$C$31 | E37: =ROUNDUP(Hypotheses!$C$8/D37,0)+1 | F37: =Hypotheses!$C$12-2*Hypotheses!$C$14+2*Hypotheses!$C$37 | G37: =E37*F37 | H37: =G37*Hypotheses!$C$44 | I37: L/esp + 1 ; L = B − 2 enr. + 2 retours
A38: R2 | B38: Radier – barres longitudinales, 2 nappes | C38: 10 | D38: =Hypotheses!$C$32 | E38: =(ROUNDUP((Hypotheses!$C$12-2*Hypotheses!$C$14)/D38,0)+1)*2 | F38: =Hypotheses!$C$8-2*Hypotheses!$C$14+2*Hypotheses!$C$37+(ROUNDUP(Hypotheses!$C$8/Hypotheses!$C$41,0)-1)*Hypotheses!$C$40*10/1000 | G38: =E38*F38 | H38: =G38*Hypotheses!$C$43 | I38: Nb filants = (B/esp + 1) × 2 ; L avec recouvrements 50Ø
A39: R3 | B39: Radier – chaises support nappe supérieure | C39: 10 | E39: =ROUNDUP(Hypotheses!$C$8*Hypotheses!$C$12*Hypotheses!$C$36,0) | F39: =0.60 | G39: =E39*F39 | H39: =G39*Hypotheses!$C$43 | I39: 1 u/m²
A40: TOTAL HA8 (kg nets) | H40: =SUMIF($C$30:$C$39,8,$H$30:$H$39)
A41: TOTAL HA10 (kg nets) | H41: =SUMIF($C$30:$C$39,10,$H$30:$H$39)
A42: TOTAL HA12 (kg nets) | H42: =SUMIF($C$30:$C$39,12,$H$30:$H$39)
A43: TOTAL ACIERS (kg nets) | H43: =SUM(H40:H42)
A44: Ratio acier (kg/m³ de béton armé) | H44: =H43/('Avant-metre'!$H$17+'Avant-metre'!$H$18) | I44: Ordre de grandeur usuel voiles/radiers : 60 à 120 kg/m³
A46: 6. VÉRIFICATION DES SECTIONS MINIMALES (EC2 §9.6 et §9.3 / BAEL)
A47: Élément | B47: Vérification | C47: Unité | D47: Calcul | H47: Valeur | I47: Conclusion
A48: Voile | B48: As,v fourni (HA12 ext. e=12,5 + HA12 int. e=20) | C48: mm²/m | D48: π×12²/4 × (1/s_ext + 1/s_int) | H48: =PI()*12^2/4/Hypotheses!$C$27+PI()*12^2/4/Hypotheses!$C$28 | I48: =IF(H48>=H49,"OK","À renforcer")
A49: Voile | B49: As,v,min = 0,002·Ac | C49: mm²/m | D49: EC2 §9.6.2(1) | H49: =0.002*Hypotheses!$C$11*1000*1000
A50: Voile | B50: As,h fourni (HA10 ext. + HA8 int.) | C50: mm²/m | D50: (π×10²/4 + π×8²/4) / s | H50: =(PI()*10^2/4+PI()*8^2/4)/Hypotheses!$C$29 | I50: =IF(H50>=H51,"OK","À renforcer")
A51: Voile | B51: As,h,min = max(25 % As,v ; 0,001·Ac) | C51: mm²/m | D51: EC2 §9.6.3(1) | H51: =MAX(0.25*H48,0.001*Hypotheses!$C$11*1e6)
A52: Radier | B52: As transv. nappe sup. (HA12, la plus faible) | C52: mm²/m | D52: π×12²/4 / s | H52: =PI()*12^2/4/Hypotheses!$C$31 | I52: =IF(H52>=H53,"OK","À renforcer")
A53: Radier | B53: As,min = max(0,26·fctm/fyk ; 0,0013)·b·d | C53: mm²/m | D53: C25/30 : fctm = 2,6 MPa ; d = e − enr. − Ø/2 | H53: =MAX(0.26*2.6/500,0.0013)*1000*(Hypotheses!$C$13-Hypotheses!$C$14-0.006)*1000
A54: Radier | B54: As long. fourni par nappe (HA10) | C54: mm²/m | D54: π×10²/4 / s | H54: =PI()*10^2/4/Hypotheses!$C$32 | I54: =IF(H54>=0.2*H52,"OK (≥ 20 % As princ.)","À renforcer")
A56: NB : ces vérifications portent uniquement sur les sections minimales et les espacements réglementaires. Les sections réelles doivent être confirmées par une note de calcul (poussée des terres/eau sur voiles, réaction du sol latéritique sous radier).

Sheet Deboursé sec
A1: RÉALISATION DE VOILES (2 × 170 m, H = 2,40 m) ET RADIER (170 m × 4,00 m × 0,20 m)
A2: SOUS-DÉTAILS DE PRIX – DÉBOURSÉ SEC UNITAIRE
A3: Lieu des travaux : BOUAFLÉ (Marahoué) – aménagement du thalweg en canal BA | Établi par : Moulo Jean Claude – Technicien Génie Civil BTP | Date : 01/10/2026 | FCFA
A4: Normes : EC2 (NF EN 1992-1-1) / BAEL 91 mod. 99 – Aciers FE500 (HA) – Contexte : sol latéritique, climat tropical humide
A6: Prix 000 – Installation et repli de chantier (unité : Ft)
A7: Nature | B7: Désignation | C7: Unité | D7: Quantité | E7: Prix unitaire | F7: Montant
A8: MTL | B8: Amenée et repli du matériel (Abidjan → Bouaflé ≈ 300 km) | C8: Ft | D8: 1 | E8: 1500000 | F8: =D8*E8
A9: MAT | B9: Logement / base vie du personnel déplacé | C9: Ft | D9: 1 | E9: 600000 | F9: =D9*E9
A10: MAT | B10: Magasin / abri de chantier | C10: Ft | D10: 1 | E10: 250000 | F10: =D10*E10
A11: MAT | B11: Panneau de chantier | C11: Ft | D11: 1 | E11: 150000 | F11: =D11*E11
A12: MAT | B12: Équipements HSE (EPI, signalisation, trousse de secours) | C12: Ft | D12: 1 | E12: 200000 | F12: =D12*E12
A13: Sous-total matériaux | F13: =SUMIF($A$8:$A$12,"MAT",$F$8:$F$12)
A14: Sous-total main d'œuvre | F14: =SUMIF($A$8:$A$12,"MO",$F$8:$F$12)
A15: Sous-total matériel | F15: =SUMIF($A$8:$A$12,"MTL",$F$8:$F$12)
A16: DÉBOURSÉ SEC UNITAIRE (FCFA / Ft) | F16: =SUM(F8:F12)
A18: Prix 101 – Implantation et piquetage (unité : Ft)
A19: Nature | B19: Désignation | C19: Unité | D19: Quantité | E19: Prix unitaire | F19: Montant
A20: MO | B20: Topographe | C20: j | D20: 1.5 | E20: 25000 | F20: =D20*E20
A21: MO | B21: Aides (2) | C21: j | D21: 3 | E21: =Hypotheses!$C$69 | F21: =D21*E21
A22: MTL | B22: Station totale / niveau | C22: j | D22: 1.5 | E22: 75000 | F22: =D22*E22
A23: MAT | B23: Piquets, chaises d'implantation, peinture | C23: Ft | D23: 1 | E23: 25000 | F23: =D23*E23
A24: Sous-total matériaux | F24: =SUMIF($A$20:$A$23,"MAT",$F$20:$F$23)
A25: Sous-total main d'œuvre | F25: =SUMIF($A$20:$A$23,"MO",$F$20:$F$23)
A26: Sous-total matériel | F26: =SUMIF($A$20:$A$23,"MTL",$F$20:$F$23)
A27: DÉBOURSÉ SEC UNITAIRE (FCFA / Ft) | F27: =SUM(F20:F23)
A29: Prix 102 – Déblai mécanique en fouille et évacuation (unité : m³)
A30: Nature | B30: Désignation | C30: Unité | D30: Quantité | E30: Prix unitaire | F30: Montant
A31: MTL | B31: Pelle hydraulique | C31: j | D31: =1/Hypotheses!$C$72 | E31: =Hypotheses!$C$71 | F31: =D31*E31
A32: MTL | B32: Camion benne – évacuation (avec foisonnement) | C32: j | D32: =Hypotheses!$C$25/Hypotheses!$C$74 | E32: =Hypotheses!$C$73 | F32: =D32*E32
A33: MO | B33: Chef d'équipe | C33: j | D33: =1/Hypotheses!$C$72 | E33: =Hypotheses!$C$67 | F33: =D33*E33
A34: MO | B34: Manœuvres – réglage manuel (2) | C34: j | D34: =2/Hypotheses!$C$72 | E34: =Hypotheses!$C$69 | F34: =D34*E34
A35: Sous-total matériaux | F35: =SUMIF($A$31:$A$34,"MAT",$F$31:$F$34)
A36: Sous-total main d'œuvre | F36: =SUMIF($A$31:$A$34,"MO",$F$31:$F$34)
A37: Sous-total matériel | F37: =SUMIF($A$31:$A$34,"MTL",$F$31:$F$34)
A38: DÉBOURSÉ SEC UNITAIRE (FCFA / m³) | F38: =SUM(F31:F34)
A40: Prix 104 – Débroussaillage et nettoyage de l'emprise (unité : m²)
A41: Nature | B41: Désignation | C41: Unité | D41: Quantité | E41: Prix unitaire | F41: Montant
A42: MO | B42: Manœuvre | C42: j | D42: =1/Hypotheses!$C$85 | E42: =Hypotheses!$C$69 | F42: =D42*E42
A43: MAT | B43: Petit outillage (machettes, râteaux, brouettes) | C43: m² | D43: 1 | E43: 30 | F43: =D43*E43
A44: Sous-total matériaux | F44: =SUMIF($A$42:$A$43,"MAT",$F$42:$F$43)
A45: Sous-total main d'œuvre | F45: =SUMIF($A$42:$A$43,"MO",$F$42:$F$43)
A46: Sous-total matériel | F46: =SUMIF($A$42:$A$43,"MTL",$F$42:$F$43)
A47: DÉBOURSÉ SEC UNITAIRE (FCFA / m²) | F47: =SUM(F42:F43)
A49: Prix 105 – Enlèvement et évacuation des ordures / déchets (unité : m³)
A50: Nature | B50: Désignation | C50: Unité | D50: Quantité | E50: Prix unitaire | F50: Montant
A51: MO | B51: Manœuvres – ramassage et chargement (4) | C51: j | D51: =4/40 | E51: =Hypotheses!$C$69 | F51: =D51*E51
A52: MTL | B52: Camion benne – évacuation vers décharge | C52: j | D52: =1/Hypotheses!$C$74 | E52: =Hypotheses!$C$73 | F52: =D52*E52
A53: MAT | B53: EPI renforcés (gants, bottes, masques) | C53: m³ | D53: 1 | E53: 300 | F53: =D53*E53
A54: Sous-total matériaux | F54: =SUMIF($A$51:$A$53,"MAT",$F$51:$F$53)
A55: Sous-total main d'œuvre | F55: =SUMIF($A$51:$A$53,"MO",$F$51:$F$53)
A56: Sous-total matériel | F56: =SUMIF($A$51:$A$53,"MTL",$F$51:$F$53)
A57: DÉBOURSÉ SEC UNITAIRE (FCFA / m³) | F57: =SUM(F51:F53)
A59: Prix 106 – Couche de forme en latérite compactée (unité : m³)
A60: Nature | B60: Désignation | C60: Unité | D60: Quantité | E60: Prix unitaire | F60: Montant
A61: MAT | B61: Latérite d'apport (avec foisonnement) | C61: m³ | D61: =Hypotheses!$C$25 | E61: =Hypotheses!$C$60 | F61: =D61*E61
A62: MTL | B62: Compacteur | C62: j | D62: =1/Hypotheses!$C$86 | E62: =Hypotheses!$C$75 | F62: =D62*E62
A63: MAT | B63: Eau d'arrosage | C63: m³ | D63: 0.1 | E63: =Hypotheses!$C$51 | F63: =D63*E63
A64: MO | B64: Manœuvres – régalage (3) | C64: j | D64: =3/Hypotheses!$C$86 | E64: =Hypotheses!$C$69 | F64: =D64*E64
A65: Sous-total matériaux | F65: =SUMIF($A$61:$A$64,"MAT",$F$61:$F$64)
A66: Sous-total main d'œuvre | F66: =SUMIF($A$61:$A$64,"MO",$F$61:$F$64)
A67: Sous-total matériel | F67: =SUMIF($A$61:$A$64,"MTL",$F$61:$F$64)
A68: DÉBOURSÉ SEC UNITAIRE (FCFA / m³) | F68: =SUM(F61:F64)
A70: Prix 107 – Remblai latéral en latérite compactée derrière les voiles (unité : m³)
A71: Nature | B71: Désignation | C71: Unité | D71: Quantité | E71: Prix unitaire | F71: Montant
A72: MAT | B72: Latérite d'apport (avec foisonnement) | C72: m³ | D72: =Hypotheses!$C$25 | E72: =Hypotheses!$C$60 | F72: =D72*E72
A73: MTL | B73: Compacteur (plaque vibrante, couches de 20 cm) | C73: j | D73: =1/Hypotheses!$C$86 | E73: =Hypotheses!$C$75 | F73: =D73*E73
A74: MAT | B74: Eau d'arrosage | C74: m³ | D74: 0.1 | E74: =Hypotheses!$C$51 | F74: =D74*E74
A75: MO | B75: Manœuvres – régalage (3) | C75: j | D75: =3/Hypotheses!$C$86 | E75: =Hypotheses!$C$69 | F75: =D75*E75
A76: Sous-total matériaux | F76: =SUMIF($A$72:$A$75,"MAT",$F$72:$F$75)
A77: Sous-total main d'œuvre | F77: =SUMIF($A$72:$A$75,"MO",$F$72:$F$75)
A78: Sous-total matériel | F78: =SUMIF($A$72:$A$75,"MTL",$F$72:$F$75)
A79: DÉBOURSÉ SEC UNITAIRE (FCFA / m³) | F79: =SUM(F72:F75)
A81: Prix 103 – Compactage du fond de fouille à 95 % OPM (unité : m²)
A82: Nature | B82: Désignation | C82: Unité | D82: Quantité | E82: Prix unitaire | F82: Montant
A83: MTL | B83: Compacteur | C83: j | D83: =1/Hypotheses!$C$76 | E83: =Hypotheses!$C$75 | F83: =D83*E83
A84: MAT | B84: Eau d'arrosage (teneur en eau OPM) | C84: m³ | D84: 0.02 | E84: =Hypotheses!$C$51 | F84: =D84*E84
A85: MO | B85: Manœuvres (2) | C85: j | D85: =2/Hypotheses!$C$76 | E85: =Hypotheses!$C$69 | F85: =D85*E85
A86: Sous-total matériaux | F86: =SUMIF($A$83:$A$85,"MAT",$F$83:$F$85)
A87: Sous-total main d'œuvre | F87: =SUMIF($A$83:$A$85,"MO",$F$83:$F$85)
A88: Sous-total matériel | F88: =SUMIF($A$83:$A$85,"MTL",$F$83:$F$85)
A89: DÉBOURSÉ SEC UNITAIRE (FCFA / m²) | F89: =SUM(F83:F85)
A91: Prix 201 – Béton de propreté dosé à 150 kg/m³ (unité : m³)
A92: Nature | B92: Désignation | C92: Unité | D92: Quantité | E92: Prix unitaire | F92: Montant
A93: MAT | B93: Ciment CPJ 42.5 (150 kg/m³) | C93: sac | D93: =150/50*(1+Hypotheses!$C$65) | E93: =Hypotheses!$C$48 | F93: =D93*E93
A94: MAT | B94: Sable | C94: m³ | D94: =0.45*(1+Hypotheses!$C$65) | E94: =Hypotheses!$C$49 | F94: =D94*E94
A95: MAT | B95: Gravier concassé | C95: m³ | D95: =0.85*(1+Hypotheses!$C$65) | E95: =Hypotheses!$C$50 | F95: =D95*E95
A96: MAT | B96: Eau de gâchage | C96: m³ | D96: 0.18 | E96: =Hypotheses!$C$51 | F96: =D96*E96
A97: MAT | B97: Cure du béton (arrosage / produit de cure) | C97: m³ | D97: 1 | E97: =Hypotheses!$C$63 | F97: =D97*E97
A98: MO | B98: Chef d'équipe | C98: j | D98: =1/Hypotheses!$C$80 | E98: =Hypotheses!$C$67 | F98: =D98*E98
A99: MO | B99: Maçons (2) | C99: j | D99: =2/Hypotheses!$C$80 | E99: =Hypotheses!$C$68 | F99: =D99*E99
A100: MO | B100: Manœuvres (8) | C100: j | D100: =8/Hypotheses!$C$80 | E100: =Hypotheses!$C$69 | F100: =D100*E100
A101: MTL | B101: Bétonnière + vibreur | C101: j | D101: =1/Hypotheses!$C$80 | E101: =Hypotheses!$C$77 | F101: =D101*E101
A102: Sous-total matériaux | F102: =SUMIF($A$93:$A$101,"MAT",$F$93:$F$101)
A103: Sous-total main d'œuvre | F103: =SUMIF($A$93:$A$101,"MO",$F$93:$F$101)
A104: Sous-total matériel | F104: =SUMIF($A$93:$A$101,"MTL",$F$93:$F$101)
A105: DÉBOURSÉ SEC UNITAIRE (FCFA / m³) | F105: =SUM(F93:F101)
A107: Prix 202 – Béton radier dosé à 350 kg/m³ (hors acier et coffrage) (unité : m³)
A108: Nature | B108: Désignation | C108: Unité | D108: Quantité | E108: Prix unitaire | F108: Montant
A109: MAT | B109: Ciment CPJ 42.5 (350 kg/m³) | C109: sac | D109: =350/50*(1+Hypotheses!$C$65) | E109: =Hypotheses!$C$48 | F109: =D109*E109
A110: MAT | B110: Sable | C110: m³ | D110: =0.4*(1+Hypotheses!$C$65) | E110: =Hypotheses!$C$49 | F110: =D110*E110
...
