Workbook

Sheet ACCUEIL
A1: QUANTITATIF – ESTIMATION – ESQUISSES : BÂTIMENT INDUSTRIEL EN CHARPENTE MÉTALLIQUE
B2: Charpente : EC3 / EC1 (vent, sans neige) · Béton armé et fondations : BAEL 91 mod. 99 / EC2 · Contexte : Côte d'Ivoire – sol latéritique, climat tropical humide · Monnaie : FCFA · TVA 18 %
B4: MODE D'EMPLOI : 1) choisir un gabarit ci-dessous ; 2) ajuster les cellules JAUNES de PARAMÈTRES ; 3) lire les résultats ici, dans le DQE et dans PLANS.
B6: GABARIT (portée × longueur) | D6: 20 × 40 | E6: ← liste déroulante (PERSONNALISÉ : dimensions dans PARAMÈTRES)
B7: Légende : cellule jaune = saisie ; cellule bleu clair = résultat ; rouge = contrôle en alerte
B9: Résumé | D9: Valeur | E9: Unité
B10: Portée | D10: ='PARAMÈTRES'!$C$9 -> 20 | E10: m
B11: Longueur | D11: ='PARAMÈTRES'!$C$10 -> 40 | E11: m
B12: Hauteur sous sablière | D12: ='PARAMÈTRES'!$C$11 -> 6 | E12: m
B13: Hauteur au faîtage | D13: ='PRÉDIMENSIONNEMENT'!$C$34 -> 7.6 | E13: m
B14: Pente | D14: ='PARAMÈTRES'!$C$12 -> 0.16 | E14: %
B15: Système structurel | D15: ='PRÉDIMENSIONNEMENT'!$C$26 -> Portique IPE avec jarrets
B16: Nombre de portiques | D16: ='PRÉDIMENSIONNEMENT'!$C$29 -> 8 | E16: u
B17: Type de façade | D17: ='PARAMÈTRES'!$C$51 -> Bardage bac acier
B18: SURFACE COUVERTE | D18: ='PRÉDIMENSIONNEMENT'!$C$46 -> 800 | E18: m²
B19: TONNAGE ACIER CHARPENTE | D19: ='QUANTITATIF_CHARPENTE'!$I$77 -> 25.987835 | E19: t
B20: Ratio acier | D20: ='QUANTITATIF_CHARPENTE'!$I$78 -> 32.484794 | E20: kg/m²
B21: Tôles de couverture | D21: ='QUANTITATIF_CHARPENTE'!$E$36 -> 816.56792 | E21: m²
B22: BÉTON (propreté + armé) | D22: ='GROS_ŒUVRE'!$E$98 -> 188.0365 | E22: m³
B23: Aciers HA | D23: ='GROS_ŒUVRE'!$I$109 -> 6214.2789 | E23: kg
B24: COÛT TOTAL HT | D24: ='DQE_DEVIS'!$G$64 -> 94639719 | E24: FCFA
B25: TVA 18 % | D25: ='DQE_DEVIS'!$G$65 -> 17035149 | E25: FCFA
B26: COÛT TOTAL TTC | D26: ='DQE_DEVIS'!$G$66 -> 1.1167487e+08 | E26: FCFA
B27: Coût HT au m² | D27: ='DQE_DEVIS'!$G$67 -> 118299.65 | E27: FCFA/m²
B29: Contrôles automatiques
B30: =IF(AND('PARAMÈTRES'!$C$9>30,'PARAMÈTRES'!$C$21="Non"),"ALERTE : portée > 30 m sans poteau intermédiaire – prévoir une file centrale (indispensable au-delà de 40 m sans appui)","OK : portée / appuis") -> OK : portée / appuis
B31: =IF('PARAMÈTRES'!$C$12<0.05,"ALERTE : pente < 5 % – risque de stagnation, revoir la pente","OK : pente ≥ 5 %") -> OK : pente ≥ 5 %
B32: =IF(AND('PARAMÈTRES'!$C$114="15 cm",'PARAMÈTRES'!$C$115="Nappe double"),"ALERTE : dallage 15 cm en nappe double (peu courant)","OK : dallage / ferraillage") -> OK : dallage / ferraillage
B33: =IF(OR('QUANTITATIF_CHARPENTE'!$I$78<18,'QUANTITATIF_CHARPENTE'!$I$78>45),"ALERTE : ratio acier "&FIXED('QUANTITATIF_CHARPENTE'!$I$78,1,TRUE)&" kg/m² hors fourchette 18–45","OK : ratio acier "&FIXED('QUANTITATIF_CHARPENTE'!$I$78,1,TRUE)&" kg/m²") -> OK : ratio acier 32.5 kg/m²
B34: =IF('PARAMÈTRES'!$C$47<0.4,"ALERTE : tôle < 0,40 mm","OK : épaisseur de tôle") -> OK : épaisseur de tôle
B36: Feuilles : PARAMÈTRES (saisies) · BASE_PROFILÉS / BASE_ACIERS (poids) · PRÉDIMENSIONNEMENT · QUANTITATIF_CHARPENTE · GROS_ŒUVRE · DQE_DEVIS · RÉCAP_GABARITS · PLANS (7 esquisses dynamiques).
B37: Les esquisses sont des graphiques Nuage de points alimentés par la feuille masquée COORD_PLANS : aucune macro, compatible Excel mobile (Microsoft 365).
B38: Classeur entièrement modifiable (aucune protection). Saisir de préférence dans les cellules jaunes : les autres cellules contiennent les formules de calcul.
B39: PDF des plans : feuille PLANS > Fichier > Enregistrer sous > PDF, ou générateur Generateur_Plans.html (coller le CODE PLANS ci-dessous puis « Enregistrer en PDF ».
B40: Estimation de prédimensionnement : à confirmer par une note de calcul (EC3 / EC1 / BAEL) avant exécution.
B42: CODE PLANS (copier la cellule D ci-contre et la coller dans Generateur_Plans.html) | D42: ="PLAN1"&";gab="&'ACCUEIL'!$D$6&";B="&FIXED('PARAMÈTRES'!$C$9,4,TRUE)&";L="&FIXED('PARAMÈTRES'!$C$10,4,TRUE)&";H="&FIXED('PARAMÈTRES'!$C$11,4,TRUE)&";p="&FIXED('PARAMÈTRES'!$C$12*100,4,TRUE)&";ep="&FIXED('PARAMÈTRES'!$C$15,4,TRUE)&";epan="&FIXED('PARAMÈTRES'!$C$16,4,TRUE)&";elis="&FIXED('PARAMÈTRES'!$C$17,4,TRUE)&";epp="&FIXED('PARAMÈTRES'!$C$18,4,TRUE)&";deb="&FIXED('PARAMÈTRES'!$C$19,4,TRUE)&";sys="&'PARAMÈTRES'!$C$20&";fint="&'PARAMÈTRES'!$C$21&";rtr="&FIXED('PARAMÈTRES'!$C$22,4,TRUE)&";pas="&FIXED('PARAMÈTRES'!$C$23,4,TRUE)&";rj="&FIXED('PARAMÈTRES'!$C$24*100,4,TRUE)&";nacc="&FIXED('PARAMÈTRES'!$C$25,4,TRUE)&";ppot="&'PRÉDIMENSIONNEMENT'!$E$69&";ptrav="&'PRÉDIMENSIONNEMENT'!$E$70&";pmsup="&'PRÉDIMENSIONNEMENT'!$E$71&";pminf="&'PRÉDIMENSIONNEMENT'!$E$72&";ppp="&'PRÉDIMENSIONNEMENT'!$E$75&";ppanne="&'PRÉDIMENSIONNEMENT'!$E$77&";plisse="&'PRÉDIMENSIONNEMENT'!$E$78&";npc="&FIXED('PARAMÈTRES'!$C$28,4,TRUE)&";lpc="&FIXED('PARAMÈTRES'!$C$29,4,TRUE)&";hpc="&FIXED('PARAMÈTRES'!$C$30,4,TRUE)&";epc="&'PARAMÈTRES'!$C$31&";npt="&FIXED('PARAMÈTRES'!$C$32,4,TRUE)&";lpt="&FIXED('PARAMÈTRES'!$C$33,4,TRUE)&";hpt="&FIXED('PARAMÈTRES'!$C$34,4,TRUE)&";ept="&'PARAMÈTRES'!$C$35&";nsky="&FIXED('PARAMÈTRES'!$C$37,4,TRUE)&";asky="&FIXED('PARAMÈTRES'!$C$38,4,TRUE)&";bsky="&FIXED('PARAMÈTRES'!$C$39,4,TRUE)&";pct="&FIXED('PARAMÈTRES'!$C$45*100,4,TRUE)&";sdesc="&FIXED('PARAMÈTRES'!$C$48,4,TRUE)&";acr="&'PARAMÈTRES'!$C$42&";hacr="&FIXED('PARAMÈTRES'!$C$43,4,TRUE)&";fac="&'PARAMÈTRES'!$C$51&";hs="&FIXED('PARAMÈTRES'!$C$52,4,TRUE)&";D="&FIXED('PARAMÈTRES'!$C$83,4,TRUE)&";eprop="&FIXED('PARAMÈTRES'!$C$88,4,TRUE)&";a1="&FIXED('PARAMÈTRES'!$C$89,4,TRUE)&";hs1="&FIXED('PARAMÈTRES'!$C$90,4,TRUE)&";f1="&FIXED('PARAMÈTRES'!$C$91,4,TRUE)&";a2="&FIXED('PARAMÈTRES'!$C$92,4,TRUE)&";hfut="&FIXED('PARAMÈTRES'!$C$95,4,TRUE)&";bf="&FIXED('PARAMÈTRES'!$C$102,4,TRUE)&";hfil="&FIXED('PARAMÈTRES'!$C$103,4,TRUE)&";hmf="&FIXED('PARAMÈTRES'!$C$111,4,TRUE)&";edal="&'PARAMÈTRES'!$C$114&";erem="&'PARAMÈTRES'!$C$86&";esab="&FIXED('PARAMÈTRES'!$C$87,4,TRUE)&";ferr="&'PARAMÈTRES'!$C$115&";hix="&'PARAMÈTRES'!$C$116&";hiy="&'PARAMÈTRES'!$C$117&";hsx="&'PARAMÈTRES'!$C$118&";hsy="&'PARAMÈTRES'!$C$119&";maille="&'PARAMÈTRES'!$C$120&";hasem="&'PARAMÈTRES'!$C$97&";msem="&FIXED('PARAMÈTRES'!$C$96,4,TRUE)&";nbf="&FIXED('PARAMÈTRES'!$C$99,4,TRUE)&";hafut="&'PARAMÈTRES'!$C$98&";hacad="&'PARAMÈTRES'!$C$100&";ecad="&FIXED('PARAMÈTRES'!$C$101,4,TRUE)&";nfil="&FIXED('PARAMÈTRES'!$C$105,4,TRUE)&";hafil="&'PARAMÈTRES'!$C$104&";harep="&'PARAMÈTRES'!$C$106&";erep="&FIXED('PARAMÈTRES'!$C$107,4,TRUE)&";dtige="&'PARAMÈTRES'!$C$72&";ltige="&FIXED('PARAMÈTRES'!$C$73,4,TRUE)&";bch="&FIXED('PARAMÈTRES'!$C$129,4,TRUE)&";hch="&FIXED('PARAMÈTRES'!$C$130,4,TRUE)&";brd="&FIXED('PARAMÈTRES'!$C$135,4,TRUE)&";nrd="&FIXED('PARAMÈTRES'!$C$136,4,TRUE)&";hachl="&'PARAMÈTRES'!$C$131&";hachc="&'PARAMÈTRES'!$C$133&";echc="&FIXED('PARAMÈTRES'!$C$134,4,TRUE) -> PLAN1;gab=20 × 40;B=20.0000;L=40.0000;H=6.0000;p=16.0000;ep=6.0000;epan=1.3500;elis=1.8000;epp=6.0000;deb=0.3000;sys=IPE renforcé;fint=Non;rtr=30.0000;pas=2.0000;rj=10.0000;nacc=2.0000;ppot=IPE 330;ptrav=IPE 300;pmsup=L 70x7;pminf=L 60x6;ppp=IPE 220;ppanne=Z 200;plisse=C 160;npc=1.0000;lpc=4.0000;hpc=4.5000;epc=Pignon;npt=1.0000;lpt=5.5000;hpt=4.0000;ept=Long-pan;nsky=4.0000;asky=1.2000;bsky=1.2000;pct=10.0000;sdesc=180.0000;acr=Non;hacr=1.0000;fac=Bardage bac acier;hs=1.5000;D=1.2000;eprop=0.0500;a1=1.2000;hs1=0.4000;f1=0.4000;a2=0.8000;hfut=1.2000;bf=0.6000;hfil=0.2000;hmf=1.0000;edal=20 cm;erem=20 cm;esab=0.0500;ferr=Nappe simple;hix=HA10;hiy=HA10;hsx=HA8;hsy=HA8;maille=20 cm;hasem=HA12;msem=0.1500;nbf=4.0000;hafut=HA12;hacad=HA6;ecad=0.1500;nfil=4.0000;hafil=HA10;harep=HA8;erep=0.2000;dtige=Rond 24;ltige=0.6000;bch=0.1500;hch=0.2000;brd=0.1500;nrd=3.0000;hachl=HA10;hachc=HA6;echc=0.2000

Sheet PARAMÈTRES
A1: PARAMÈTRES – toutes les données saisissables
A2: Cellules JAUNES = saisie. Cellules bleu clair = valeurs calculées. Les gabarits prédéfinis utilisent la hauteur et la pente ci-dessous ; PERSONNALISÉ utilise sa propre ligne du tableau (col. G à K).
B4: Paramètre | C4: Valeur | D4: Unité | E4: Plage conseillée / commentaire | G4: Gabarit | H4: Portée (m) | I4: Longueur (m) | J4: Hauteur (m) | K4: Pente
B5: 1. GABARIT ET GÉOMÉTRIE | G5: 10 × 30 | H5: 10 | I5: 30 | J5: =$C$6 -> 6 | K5: =$C$7 -> 0.16
B6: Hauteur sous sablière (gabarits prédéfinis) | C6: 6 | D6: m | E6: 4 à 12 m | G6: 15 × 20 | H6: 15 | I6: 20 | J6: =$C$6 -> 6 | K6: =$C$7 -> 0.16
B7: Pente de toiture (gabarits prédéfinis) | C7: 0.16 | D7: % | E7: 10 à 20 % conseillé ; < 5 % = alerte | G7: 15 × 30 | H7: 15 | I7: 30 | J7: =$C$6 -> 6 | K7: =$C$7 -> 0.16
B8: Gabarit actif (choisi en ACCUEIL) | C8: ='ACCUEIL'!$D$6 -> 20 × 40 | G8: 20 × 20 | H8: 20 | I8: 20 | J8: =$C$6 -> 6 | K8: =$C$7 -> 0.16
B9: Portée active | C9: =INDEX('PARAMÈTRES'!$H$5:$H$12,MATCH('ACCUEIL'!$D$6,'PARAMÈTRES'!$G$5:$G$12,0)) -> 20 | D9: m | E9: Valeur du gabarit actif | G9: 20 × 40 | H9: 20 | I9: 40 | J9: =$C$6 -> 6 | K9: =$C$7 -> 0.16
B10: Longueur active | C10: =INDEX('PARAMÈTRES'!$I$5:$I$12,MATCH('ACCUEIL'!$D$6,'PARAMÈTRES'!$G$5:$G$12,0)) -> 40 | D10: m | E10: Valeur du gabarit actif | G10: 30 × 40 | H10: 30 | I10: 40 | J10: =$C$6 -> 6 | K10: =$C$7 -> 0.16
B11: Hauteur sous sablière active | C11: =INDEX('PARAMÈTRES'!$J$5:$J$12,MATCH('ACCUEIL'!$D$6,'PARAMÈTRES'!$G$5:$G$12,0)) -> 6 | D11: m | E11: Valeur du gabarit actif | G11: 40 × 40 | H11: 40 | I11: 40 | J11: =$C$6 -> 6 | K11: =$C$7 -> 0.16
B12: Pente active | C12: =INDEX('PARAMÈTRES'!$K$5:$K$12,MATCH('ACCUEIL'!$D$6,'PARAMÈTRES'!$G$5:$G$12,0)) -> 0.16 | D12: % | E12: Valeur du gabarit actif | G12: PERSONNALISÉ | H12: 40 | I12: 48 | J12: 6 | K12: 0.16
G13: Ligne PERSONNALISÉ : saisir portée, longueur, hauteur et pente. Valeurs proposées = modèle de référence 40 × 48 m, H 6 m, pente 16 %.
B14: 2. CHARPENTE – TRAMES ET SYSTÈME
B15: Entraxe des portiques | C15: 6 | D15: m | E15: 6 m par défaut
B16: Entraxe des pannes | C16: 1.35 | D16: m | E16: 1,20 à 1,50 m | G16: PLATINES ET PIÈCES PLATES (dimensions modifiables)
B17: Entraxe des lisses de bardage | C17: 1.8 | D17: m | E17: 1,50 à 2,00 m | G17: Pièce | H17: L (m) | I17: l (m) | J17: e (m) | K17: kg/u
B18: Espacement des poteaux de pignon | C18: 6 | D18: m | E18: 5 à 6 m | G18: Platine de pied – poteau de portique | H18: 0.45 | I18: 0.35 | J18: 0.02 | K18: =H18*I18*J18*'PARAMÈTRES'!$C$57 -> 24.7275
B19: Débord des pannes aux pignons | C19: 0.3 | D19: m | G19: Platine de pied – poteau de pignon | H19: 0.3 | I19: 0.25 | J19: 0.015 | K19: =H19*I19*J19*'PARAMÈTRES'!$C$57 -> 8.83125
B20: Système pour portée de 20 à 30 m | C20: IPE renforcé | E20: IPE renforcé ou Ferme treillis | G20: Platine de tête de poteau / about de jarret | H20: 0.55 | I20: 0.25 | J20: 0.02 | K20: =H20*I20*J20*'PARAMÈTRES'!$C$57 -> 21.5875
B21: File de poteaux intermédiaires (file centrale) | C21: Non | E21: Conseillé au-delà de 30 m | G21: Platine de tête – poteau de pignon | H21: 0.25 | I21: 0.2 | J21: 0.012 | K21: =H21*I21*J21*'PARAMÈTRES'!$C$57 -> 4.71
B22: Hauteur de ferme aux appuis = portée / … | C22: 30 | E22: 25 à 35 | G22: Éclisse de faîtage (une plaque) | H22: 0.5 | I22: 0.25 | J22: 0.015 | K22: =H22*I22*J22*'PARAMÈTRES'!$C$57 -> 14.71875
B23: Pas des nœuds du treillis | C23: 2 | D23: m | E23: 1,5 à 2,5 m | G23: Gousset de nœud de treillis | H23: 0.3 | I23: 0.3 | J23: 0.01 | K23: =H23*I23*J23*'PARAMÈTRES'!$C$57 -> 7.065
B24: Longueur de jarret (en % de la portée) | C24: 0.1 | D24: % | E24: 8 à 12 %
B25: Nombre de cornières accolées par membrure | C25: 2 | D25: u | E25: 2 cornières dos à dos
B27: 3. OUVERTURES – SKYDOMES
B28: Portes coulissantes : nombre | C28: 1 | D28: u
B29: Portes coulissantes : largeur | C29: 4 | D29: m
B30: Portes coulissantes : hauteur | C30: 4.5 | D30: m
B31: Portes coulissantes : emplacement | C31: Pignon | E31: Long-pan ou Pignon
B32: Portillons : nombre | C32: 1 | D32: u | E32: Modèle de référence : portillon de 5,50 m en long-pan
B33: Portillons : largeur | C33: 5.5 | D33: m
B34: Portillons : hauteur | C34: 4 | D34: m
B35: Portillons : emplacement | C35: Long-pan | E35: Long-pan ou Pignon
B36: Débord du larmier de porte coulissante | C36: 0.2 | D36: m | E36: ml = largeur + 0,20 m
B37: Nombre de skydomes | C37: 4 | D37: u
B38: Skydome : longueur | C38: 1.2 | D38: m
B39: Skydome : largeur | C39: 1.2 | D39: m
B41: 4. COUVERTURE – BARDAGE – FAÇADE
B42: Présence d'acrotère | C42: Non | E42: Oui / Non
B43: Hauteur d'acrotère | C43: 1 | D43: m
B44: Espacement des baïonnettes d'acrotère | C44: 1.25 | D44: m | E44: 1,0 à 1,5 m
B45: Translucides (% de la surface de couverture) | C45: 0.1 | D45: % | E45: 10 % par défaut
B46: Recouvrements des tôles (majoration) | C46: 0.1 | D46: % | E46: 8 à 12 %
B47: Épaisseur des tôles (bac acier) | C47: 0.45 | D47: mm | E47: 0,40 à 0,50 mm mini (climat tropical humide)
B48: Surface de toiture par descente EP | C48: 180 | D48: m² | E48: 150 à 200 m²
B49: Vis autoforeuses par m² de tôle | C49: 6 | D49: u/m² | E49: environ 6 /m²
B50: Rivets par ml de chéneau | C50: 5 | D50: u/ml
B51: Type de façade | C51: Bardage bac acier | E51: Bardage / Agglos 15 creux / Mixte
B52: Hauteur du soubassement en agglos (variante Mixte) | C52: 1.5 | D52: m
B54: 5. ACIER – ASSEMBLAGES – PROTECTION ANTICORROSION
B55: Chutes sur profilés | C55: 0.05 | D55: % | E55: 5 % par défaut
B56: Boulonnerie : minimum en % du tonnage | C56: 0.02 | D56: % | E56: On retient le maximum entre détail et %
B57: Masse volumique de l'acier | C57: 7850 | D57: kg/m³
B58: Longueur commerciale des barres et profilés | C58: 12 | D58: m
B59: Protection anticorrosion | C59: Galvanisation à chaud | E59: Climat tropical humide : protection obligatoire
B60: Surface à peindre par tonne d'acier | C60: 25 | D60: m²/t | E60: 20 à 30 m²/t
B61: Poids d'une échantignole (taquet de panne) | C61: 1.8 | D61: kg/u
B62: Poids d'une éclisse de panne | C62: 2.5 | D62: kg/u
B63: Boulons HR M20 par assemblage poteau-traverse | C63: 8 | D63: u
B64: Boulons HR M20 par faîtage | C64: 8 | D64: u
B65: Boulons M12 par échantignole | C65: 2 | D65: u
B66: Boulons HR M16 par extrémité de diagonale | C66: 2 | D66: u
B67: Boulons M12 par attache de lisse | C67: 2 | D67: u
B68: Boulons M12 par éclisse de panne | C68: 4 | D68: u
B69: Poids boulon HR M20 (écrou + rondelles) | C69: 0.45 | D69: kg/u
B70: Poids boulon HR M16 (écrou + rondelles) | C70: 0.25 | D70: kg/u
B71: Poids boulon ordinaire M12 (écrou + rondelle) | C71: 0.1 | D71: kg/u
B72: Tiges d'ancrage poteaux de portique : diamètre | C72: Rond 24
B73: Tiges d'ancrage poteaux de portique : longueur | C73: 0.6 | D73: m
B74: Tiges d'ancrage par poteau de portique | C74: 4 | D74: u
B75: Tiges d'ancrage poteaux de pignon : diamètre | C75: Rond 20
B76: Tiges d'ancrage poteaux de pignon : longueur | C76: 0.5 | D76: m
B77: Tiges d'ancrage par poteau de pignon | C77: 2 | D77: u
B79: 6. GROS ŒUVRE – TERRASSEMENTS ET FONDATIONS
B80: Épaisseur de décapage | C80: 0.2 | D80: m
B81: Débord de décapage autour de l'emprise | C81: 1 | D81: m
B82: Surlargeur de fouille (de chaque côté) | C82: 0.1 | D82: m
B83: Profondeur de fondation | C83: 1.2 | D83: m | E83: 1,20 m (sol latéritique)
B84: Coefficient de foisonnement | C84: 1.25 | E84: 1,25
B85: Épaisseur des murs (agglos de 15) | C85: 0.15 | D85: m
B86: Épaisseur du remblai compacté (latérite 95 % OPM) | C86: 20 cm | E86: 20 cm / 40 cm
B87: Lit de sable de réglage sous dallage | C87: 0.05 | D87: m | E87: 5 cm
B88: Béton de propreté | C88: 0.05 | D88: m | E88: 5 cm
B89: Semelle isolée poteau de portique : côté | C89: 1.2 | D89: m | E89: 120 × 120 cm
B90: Semelle isolée poteau de portique : hauteur | C90: 0.4 | D90: m
B91: Fût poteau de portique : côté | C91: 0.4 | D91: m | E91: 40 × 40 cm
B92: Semelle isolée poteau de pignon : côté | C92: 0.8 | D92: m | E92: 80 × 80 cm
B93: Semelle isolée poteau de pignon : hauteur | C93: 0.3 | D93: m
B94: Fût poteau de pignon : côté | C94: 0.3 | D94: m | E94: 30 × 30 cm
B95: Hauteur des fûts (amorces) jusqu'au dallage | C95: 1.2 | D95: m | E95: 1,20 m
B96: Maille du quadrillage des semelles isolées | C96: 0.15 | D96: m
B97: Quadrillage inférieur des semelles : acier | C97: HA12
B98: Aciers longitudinaux des fûts | C98: HA12
B99: Nombre de barres par fût | C99: 4 | D99: u | E99: 4 HA12
B100: Cadres des fûts | C100: HA6
B101: Espacement des cadres des fûts | C101: 0.15 | D101: m | E101: 15 cm
B102: Semelle filante : largeur | C102: 0.6 | D102: m | E102: 60 cm
B103: Semelle filante : hauteur | C103: 0.2 | D103: m | E103: 20 cm
B104: Semelle filante : aciers filants | C104: HA10
B105: Semelle filante : nombre de filants | C105: 4 | D105: u | E105: 4 HA10
...

Sheet BASE_PROFILÉS
A1: BASE DES PROFILÉS – poids en kg/ml
A2: Valeurs indicatives (catalogues usuels). Recherche par RECHERCHEX dans toutes les feuilles. Ajouter de nouveaux profilés en fin de tableau.
B4: Désignation | C4: Famille | D4: kg/ml | E4: h (mm) | F4: Remarque
B5: IPE 160 | C5: IPE | D5: 15.8 | E5: 160 | F5: Membrures de treillis : poids multiplié par le nombre de cornières accolées
B6: IPE 180 | C6: IPE | D6: 18.8 | E6: 180
B7: IPE 200 | C7: IPE | D7: 22.4 | E7: 200
B8: IPE 220 | C8: IPE | D8: 26.2 | E8: 220
B9: IPE 240 | C9: IPE | D9: 30.7 | E9: 240
B10: IPE 270 | C10: IPE | D10: 36.1 | E10: 270
B11: IPE 300 | C11: IPE | D11: 42.2 | E11: 300
B12: IPE 330 | C12: IPE | D12: 49.1 | E12: 330
B13: IPE 360 | C13: IPE | D13: 57.1 | E13: 360
B14: IPE 400 | C14: IPE | D14: 66.3 | E14: 400
B15: IPE 450 | C15: IPE | D15: 77.6 | E15: 450
B16: IPE 500 | C16: IPE | D16: 90.7 | E16: 500
B17: IPE 550 | C17: IPE | D17: 106 | E17: 550
... B85: Rond 30 | C85: Rond plein (tirants, liernes, tiges) | D85: 5.55 | E85: 30

Sheet BASE_ACIERS
A1: BASE DES ACIERS HA – poids en kg/ml
A2: Aciers à haute adhérence FeE500 – barres commerciales de 12 m
B4: Désignation | C4: Ø (mm) | D4: kg/ml | E4: Section (cm²) | F4: Remarque
B5: HA6 | C5: 6 | D5: 0.222 | E5: =PI()*C5^2/400 -> 0.28274334 | F5: Poids = 7 850 kg/m³ × π Ø² / 4
B6: HA8 | C6: 8 | D6: 0.395 | E6: =PI()*C6^2/400 -> 0.50265482
B7: HA10 | C7: 10 | D7: 0.617 | E7: =PI()*C7^2/400 -> 0.78539816
B8: HA12 | C8: 12 | D8: 0.888 | E8: =PI()*C8^2/400 -> 1.1309734
B9: HA14 | C9: 14 | D9: 1.208 | E9: =PI()*C9^2/400 -> 1.5393804
B10: HA16 | C10: 16 | D10: 1.578 | E10: =PI()*C10^2/400 -> 2.0106193
B11: HA20 | C11: 20 | D11: 2.466 | E11: =PI()*C11^2/400 -> 3.1415927
B12: HA25 | C12: 25 | D12: 3.853 | E12: =PI()*C12^2/400 -> 4.9087385

Sheet PRÉDIMENSIONNEMENT
A1: PRÉDIMENSIONNEMENT – choix automatique des profilés (modifiable en jaune)
A2: Portée ≤ 20 m : portique IPE avec jarrets · 20 à 30 m : IPE renforcé ou ferme treillis · > 30 m : ferme treillis (cornières) + alerte file intermédiaire. Valeurs de prédimensionnement à confirmer par une note de calcul EC3 / EC1 (vent).
B4: A. RÈGLES DE CHOIX SELON LA PORTÉE
B5: Portée ≤ (m) | C5: Système indicatif | D5: Poteau (portique IPE) | E5: Traverse IPE | F5: Poteau (treillis) | G5: Membrure sup. | H5: Membrure inf. | I5: Montants | J5: Diagonales
B6: 10 | C6: Portique IPE + jarrets | D6: IPE 220 | E6: IPE 200 | F6: HEA 180 | G6: L 50x5 | H6: L 45x4.5 | I6: L 40x4 | J6: L 40x4
B7: 15 | C7: Portique IPE + jarrets | D7: IPE 270 | E7: IPE 240 | F7: HEA 200 | G7: L 60x6 | H7: L 50x5 | I7: L 40x4 | J7: L 45x4.5
B8: 20 | C8: Portique IPE + jarrets | D8: IPE 330 | E8: IPE 300 | F8: HEA 220 | G8: L 70x7 | H8: L 60x6 | I8: L 45x4.5 | J8: L 50x5
B9: 25 | C9: IPE renforcé ou treillis | D9: IPE 400 | E9: IPE 360 | F9: HEA 240 | G9: L 70x7 | H9: L 60x6 | I9: L 50x5 | J9: L 50x5
B10: 30 | C10: IPE renforcé ou treillis | D10: IPE 450 | E10: IPE 400 | F10: HEA 260 | G10: L 80x8 | H10: L 70x7 | I10: L 50x5 | J10: L 60x6
B11: 35 | C11: Ferme treillis | D11: IPE 500 | E11: IPE 450 | F11: HEA 280 | G11: L 90x9 | H11: L 80x8 | I11: L 50x5 | J11: L 60x6
B12: 40 | C12: Ferme treillis | D12: IPE 550 | E12: IPE 500 | F12: HEA 300 | G12: L 100x10 | H12: L 90x9 | I12: L 60x6 | J12: L 70x7
B13: 50 | C13: Ferme treillis + file intermédiaire | D13: IPE 600 | E13: IPE 550 | F13: HEA 340 | G13: L 100x10 | H13: L 100x10 | I13: L 60x6 | J13: L 80x8
B14: 1000 | C14: Ferme treillis + file intermédiaire | D14: IPE 600 | E14: IPE 600 | F14: HEA 400 | G14: L 100x10 | H14: L 100x10 | I14: L 70x7 | J14: L 90x9
B16: H faîtage ≤ (m) | C16: Poteau de pignon | F16: Entraxe ≤ (m) | G16: Panne | H16: Lisse
B17: 6 | C17: IPE 180 | F17: 5 | G17: Z 160 | H17: C 140
B18: 8 | C18: IPE 220 | F18: 6 | G18: Z 200 | H18: C 160
B19: 10 | C19: IPE 270 | F19: 7 | G19: Z 220 | H19: C 180
B20: 12 | C20: IPE 300 | F20: 1000 | G20: Z 250 | H20: C 200
B21: 1000 | C21: IPE 360
B23: B. GÉOMÉTRIE ET GRANDEURS CALCULÉES
B24: Grandeur | C24: Valeur | D24: Unité | E24: Règle de calcul
B25: Ligne de règle (selon portée) | C25: =COUNTIF('PRÉDIMENSIONNEMENT'!$B$6:$B$14,"<"&'PARAMÈTRES'!$C$9)+1 -> 3 | E25: Rang de la portée dans le tableau A
B26: Système structurel retenu | C26: =IF('PARAMÈTRES'!$C$9<=20,"Portique IPE avec jarrets",IF('PARAMÈTRES'!$C$9<=30,IF('PARAMÈTRES'!$C$20="Ferme treillis","Ferme treillis","Portique IPE renforcé"),"Ferme treillis")) -> Portique IPE avec jarrets | E26: Selon portée et choix 20–30 m
B27: Ferme treillis (1 = oui) | C27: =IF('PRÉDIMENSIONNEMENT'!$C$26="Ferme treillis",1,0) -> 0
B28: Nombre de travées | C28: =MAX(1,ROUNDUP('PARAMÈTRES'!$C$10/'PARAMÈTRES'!$C$15,0)) -> 7 | D28: u | E28: ARRONDI.SUP(L / entraxe)
B29: Nombre de portiques N | C29: ='PRÉDIMENSIONNEMENT'!$C$28+1 -> 8 | D29: u | E29: N = ARRONDI.SUP(Longueur / entraxe) + 1
B30: Entraxe réel des portiques | C30: ='PARAMÈTRES'!$C$10/'PRÉDIMENSIONNEMENT'!$C$28 -> 5.7142857 | D30: m | E30: L / nombre de travées
B31: Longueur rampante d'un versant | C31: =('PARAMÈTRES'!$C$9/2)/COS(ATAN('PARAMÈTRES'!$C$12)) -> 10.127191 | D31: m | E31: (portée / 2) / cos(arctan(pente))
B32: Hauteur de ferme aux appuis | C32: ='PRÉDIMENSIONNEMENT'!$C$27*'PARAMÈTRES'!$C$9/'PARAMÈTRES'!$C$22 -> 0 | D32: m | E32: portée / ratio (0 si portique IPE)
B33: Hauteur des murs à l'égout | C33: ='PARAMÈTRES'!$C$11+'PRÉDIMENSIONNEMENT'!$C$32 -> 6 | D33: m | E33: H sablière + hauteur de ferme aux appuis
B34: Hauteur au faîtage | C34: ='PRÉDIMENSIONNEMENT'!$C$33+'PARAMÈTRES'!$C$12*'PARAMÈTRES'!$C$9/2 -> 7.6 | D34: m | E34: Hm + pente × portée / 2
B35: Intervalles entre poteaux de pignon (par pignon) | C35: =MAX(1,ROUNDUP('PARAMÈTRES'!$C$9/'PARAMÈTRES'!$C$18,0)) -> 4 | D35: u | E35: ARRONDI.SUP(portée / espacement)
B36: Espacement réel des poteaux de pignon | C36: ='PARAMÈTRES'!$C$9/'PRÉDIMENSIONNEMENT'!$C$35 -> 5 | D36: m
B37: Poteaux de pignon (2 pignons) | C37: =2*('PRÉDIMENSIONNEMENT'!$C$35-1) -> 6 | D37: u | E37: 2 × (intervalles − 1)
B38: Poteaux intermédiaires (file centrale) | C38: =IF('PARAMÈTRES'!$C$21="Oui",'PRÉDIMENSIONNEMENT'!$C$29,0) -> 0 | D38: u | E38: 1 par portique si file centrale
B39: Panneaux du treillis | C39: ='PRÉDIMENSIONNEMENT'!$C$27*2*ROUNDUP('PARAMÈTRES'!$C$9/2/'PARAMÈTRES'!$C$23,0) -> 0 | D39: u | E39: nombre pair ≈ portée / pas
B40: Pannes par versant | C40: =ROUNDUP('PRÉDIMENSIONNEMENT'!$C$31/'PARAMÈTRES'!$C$16,0)+1 -> 9 | D40: u | E40: ARRONDI.SUP(rampant / entraxe) + 1
B41: Entraxe réel des pannes | C41: ='PRÉDIMENSIONNEMENT'!$C$31/('PRÉDIMENSIONNEMENT'!$C$40-1) -> 1.2658989 | D41: m
B42: Longueur des pannes (avec débords) | C42: ='PARAMÈTRES'!$C$10+2*'PARAMÈTRES'!$C$19 -> 40.6 | D42: m | E42: L + 2 × débord
B43: Lignes de liernes par travée | C43: =IF('PRÉDIMENSIONNEMENT'!$C$30>6,2,1) -> 1 | D43: u | E43: mi-portée ; au tiers si entraxe > 6 m
B44: Travées contreventées | C44: =IF('PRÉDIMENSIONNEMENT'!$C$28<=2,'PRÉDIMENSIONNEMENT'!$C$28,2+INT(('PRÉDIMENSIONNEMENT'!$C$28-1)/5)) -> 3 | D44: u | E44: 2 travées d'extrémité + 1 travée sur 5
B45: Panneaux de poutre au vent par versant | C45: =MAX(1,ROUND('PRÉDIMENSIONNEMENT'!$C$31/'PRÉDIMENSIONNEMENT'!$C$30,0)) -> 2 | D45: u | E45: panneaux ≈ carrés
B46: Surface couverte (emprise) | C46: ='PARAMÈTRES'!$C$9*'PARAMÈTRES'!$C$10 -> 800 | D46: m² | E46: portée × longueur
B47: Périmètre | C47: =2*('PARAMÈTRES'!$C$9+'PARAMÈTRES'!$C$10) -> 120 | D47: m | E47: 2 × (portée + longueur)
B48: Type de façade (scénario) | C48: ='PARAMÈTRES'!$C$51 -> Bardage bac acier | E48: PARAMÈTRES (comparatif : bardage puis agglos)
B49: Hauteur de maçonnerie d'élévation (base du bardage) | C49: =IF('PRÉDIMENSIONNEMENT'!$C$48="Agglos 15 creux",'PRÉDIMENSIONNEMENT'!$C$33,IF('PRÉDIMENSIONNEMENT'!$C$48="Mixte",MIN('PARAMÈTRES'!$C$52,'PRÉDIMENSIONNEMENT'!$C$33),0)) -> 0 | D49: m | E49: 0 en bardage · Hm en agglos · soubassement en mixte
B50: Bardage présent (1 = oui) | C50: =IF('PRÉDIMENSIONNEMENT'!$C$48="Agglos 15 creux",0,1) -> 1 | E50: 0 si façade en agglos
B51: Maçonnerie d'élévation présente (1 = oui) | C51: =IF('PRÉDIMENSIONNEMENT'!$C$48="Bardage bac acier",0,1) -> 0
B52: Panneaux de treillis (calcul sécurisé) | C52: =MAX(1,'PRÉDIMENSIONNEMENT'!$C$39) -> 1 | D52: u | E52: évite la division par 0
B53: Portes coulissantes en long-pan | C53: =IF('PARAMÈTRES'!$C$31="Long-pan",'PARAMÈTRES'!$C$28,0) -> 0 | D53: u
B54: Portillons en long-pan | C54: =IF('PARAMÈTRES'!$C$35="Long-pan",'PARAMÈTRES'!$C$32,0) -> 1 | D54: u
B55: Surface totale des ouvertures | C55: ='PARAMÈTRES'!$C$28*'PARAMÈTRES'!$C$29*'PARAMÈTRES'!$C$30+'PARAMÈTRES'!$C$32*'PARAMÈTRES'!$C$33*'PARAMÈTRES'!$C$34 -> 40 | D55: m²
B56: Largeur cumulée des ouvertures | C56: ='PARAMÈTRES'!$C$28*'PARAMÈTRES'!$C$29+'PARAMÈTRES'!$C$32*'PARAMÈTRES'!$C$33 -> 9.5 | D56: m
B57: Ouvertures dans la zone bardée | C57: ='PRÉDIMENSIONNEMENT'!$C$50*('PARAMÈTRES'!$C$28*'PARAMÈTRES'!$C$29*MAX(0,'PARAMÈTRES'!$C$30-'PRÉDIMENSIONNEMENT'!$C$49)+'PARAMÈTRES'!$C$32*'PARAMÈTRES'!$C$33*MAX(0,'PARAMÈTRES'!$C$34-'PRÉDIMENSIONNEMENT'!$C$49)) -> 40 | D57: m² | E57: partie au-dessus de z0
B58: Ouvertures dans la maçonnerie | C58: ='PRÉDIMENSIONNEMENT'!$C$51*('PARAMÈTRES'!$C$28*'PARAMÈTRES'!$C$29*MIN('PARAMÈTRES'!$C$30,'PRÉDIMENSIONNEMENT'!$C$49)+'PARAMÈTRES'!$C$32*'PARAMÈTRES'!$C$33*MIN('PARAMÈTRES'!$C$34,'PRÉDIMENSIONNEMENT'!$C$49)) -> 0 | D58: m² | E58: partie sous z0
B59: Rangées de lisses en long-pan | C59: ='PRÉDIMENSIONNEMENT'!$C$50*ROUNDUP(('PRÉDIMENSIONNEMENT'!$C$33-'PRÉDIMENSIONNEMENT'!$C$49)/'PARAMÈTRES'!$C$17,0) -> 4 | D59: u | E59: ARRONDI.SUP(hauteur bardée / entraxe)
B60: Rangées de lisses coupées par une porte coulissante | C60: =MIN('PRÉDIMENSIONNEMENT'!$C$59,MAX(0,ROUNDUP(('PARAMÈTRES'!$C$30-'PRÉDIMENSIONNEMENT'!$C$49)/'PARAMÈTRES'!$C$17,0))) -> 3 | D60: u
B61: Rangées de lisses coupées par un portillon | C61: =MIN('PRÉDIMENSIONNEMENT'!$C$59,MAX(0,ROUNDUP(('PARAMÈTRES'!$C$34-'PRÉDIMENSIONNEMENT'!$C$49)/'PARAMÈTRES'!$C$17,0))) -> 3 | D61: u
B62: Surface brute des 2 pignons dans la zone bardée | C62: ='PRÉDIMENSIONNEMENT'!$C$50*2*('PARAMÈTRES'!$C$9*('PRÉDIMENSIONNEMENT'!$C$33-'PRÉDIMENSIONNEMENT'!$C$49)+'PARAMÈTRES'!$C$12*'PARAMÈTRES'!$C$9^2/4) -> 272 | D62: m² | E62: trapèze : B × h + pente × B² / 4
B63: Surface de couverture (rampants) | C63: =2*'PRÉDIMENSIONNEMENT'!$C$31*'PRÉDIMENSIONNEMENT'!$C$42 -> 822.32792 | D63: m² | E63: 2 × rampant × longueur couverte
B64: Descentes EP | C64: =MAX(2,2*ROUNDUP('PRÉDIMENSIONNEMENT'!$C$46/(2*'PARAMÈTRES'!$C$48),0)) -> 6 | D64: u | E64: 1 pour 150 à 200 m², réparties sur les 2 long-pans
B65: Coût de protection ramené au kg | C65: ='PARAMÈTRES'!$C$160*IF('PARAMÈTRES'!$C$59="Galvanisation à chaud",1,0)+'PARAMÈTRES'!$C$161*'PARAMÈTRES'!$C$60/1000*IF('PARAMÈTRES'!$C$59="Galvanisation à chaud",0,1) -> 450 | D65: FCFA/kg | E65: galvanisation au kg ou peinture × m²/t
B67: C. PROFILÉS RETENUS
B68: Élément | C68: Profilé automatique | D68: Forçage (saisie) | E68: Profilé retenu | F68: kg/ml | G68: h (mm) | H68: Règle
B69: Poteaux de portique | C69: =IF('PRÉDIMENSIONNEMENT'!$C$27=1,INDEX('PRÉDIMENSIONNEMENT'!$F$6:$F$14,'PRÉDIMENSIONNEMENT'!$C$25),INDEX('PRÉDIMENSIONNEMENT'!$D$6:$D$14,'PRÉDIMENSIONNEMENT'!$C$25)) -> IPE 330 | E69: =IF('PRÉDIMENSIONNEMENT'!$D$69="",'PRÉDIMENSIONNEMENT'!$C$69,'PRÉDIMENSIONNEMENT'!$D$69) -> IPE 330 | F69: =IFERROR(_xlfn.XLOOKUP('PRÉDIMENSIONNEMENT'!$E$69,'BASE_PROFILÉS'!$B$5:$B$200,'BASE_PROFILÉS'!$D$5:$D$200),IFERROR(INDEX('BASE_PROFILÉS'!$D$5:$D$200,MATCH('PRÉDIMENSIONNEMENT'!$E$69,'BASE_PROFILÉS'!$B$5:$B$200,0)),0)) -> 49.1 | G69: =IFERROR(_xlfn.XLOOKUP('PRÉDIMENSIONNEMENT'!$E$69,'BASE_PROFILÉS'!$B$5:$B$200,'BASE_PROFILÉS'!$E$5:$E$200),IFERROR(INDEX('BASE_PROFILÉS'!$E$5:$E$200,MATCH('PRÉDIMENSIONNEMENT'!$E$69,'BASE_PROFILÉS'!$B$5:$B$200,0)),0)) -> 330 | H69: Tableau A selon portée et système
B70: Traverses (portique IPE) | C70: =INDEX('PRÉDIMENSIONNEMENT'!$E$6:$E$14,'PRÉDIMENSIONNEMENT'!$C$25) -> IPE 300 | E70: =IF('PRÉDIMENSIONNEMENT'!$D$70="",'PRÉDIMENSIONNEMENT'!$C$70,'PRÉDIMENSIONNEMENT'!$D$70) -> IPE 300 | F70: =IFERROR(_xlfn.XLOOKUP('PRÉDIMENSIONNEMENT'!$E$70,'BASE_PROFILÉS'!$B$5:$B$200,'BASE_PROFILÉS'!$D$5:$D$200),IFERROR(INDEX('BASE_PROFILÉS'!$D$5:$D$200,MATCH('PRÉDIMENSIONNEMENT'!$E$70,'BASE_PROFILÉS'!$B$5:$B$200,0)),0)) -> 42.2 | G70: =IFERROR(_xlfn.XLOOKUP('PRÉDIMENSIONNEMENT'!$E$70,'BASE_PROFILÉS'!$B$5:$B$200,'BASE_PROFILÉS'!$E$5:$E$200),IFERROR(INDEX('BASE_PROFILÉS'!$E$5:$E$200,MATCH('PRÉDIMENSIONNEMENT'!$E$70,'BASE_PROFILÉS'!$B$5:$B$200,0)),0)) -> 300 | H70: Tableau A
B71: Membrures supérieures (treillis) | C71: =INDEX('PRÉDIMENSIONNEMENT'!$G$6:$G$14,'PRÉDIMENSIONNEMENT'!$C$25) -> L 70x7 | E71: =IF('PRÉDIMENSIONNEMENT'!$D$71="",'PRÉDIMENSIONNEMENT'!$C$71,'PRÉDIMENSIONNEMENT'!$D$71) -> L 70x7 | F71: =IFERROR(_xlfn.XLOOKUP('PRÉDIMENSIONNEMENT'!$E$71,'BASE_PROFILÉS'!$B$5:$B$200,'BASE_PROFILÉS'!$D$5:$D$200),IFERROR(INDEX('BASE_PROFILÉS'!$D$5:$D$200,MATCH('PRÉDIMENSIONNEMENT'!$E$71,'BASE_PROFILÉS'!$B$5:$B$200,0)),0))*'PARAMÈTRES'!$C$25 -> 14.76 | G71: =IFERROR(_xlfn.XLOOKUP('PRÉDIMENSIONNEMENT'!$E$71,'BASE_PROFILÉS'!$B$5:$B$200,'BASE_PROFILÉS'!$E$5:$E$200),IFERROR(INDEX('BASE_PROFILÉS'!$E$5:$E$200,MATCH('PRÉDIMENSIONNEMENT'!$E$71,'BASE_PROFILÉS'!$B$5:$B$200,0)),0)) -> 70 | H71: Tableau A – cornières accolées
B72: Membrures inférieures (treillis) | C72: =INDEX('PRÉDIMENSIONNEMENT'!$H$6:$H$14,'PRÉDIMENSIONNEMENT'!$C$25) -> L 60x6 | E72: =IF('PRÉDIMENSIONNEMENT'!$D$72="",'PRÉDIMENSIONNEMENT'!$C$72,'PRÉDIMENSIONNEMENT'!$D$72) -> L 60x6 | F72: =IFERROR(_xlfn.XLOOKUP('PRÉDIMENSIONNEMENT'!$E$72,'BASE_PROFILÉS'!$B$5:$B$200,'BASE_PROFILÉS'!$D$5:$D$200),IFERROR(INDEX('BASE_PROFILÉS'!$D$5:$D$200,MATCH('PRÉDIMENSIONNEMENT'!$E$72,'BASE_PROFILÉS'!$B$5:$B$200,0)),0))*'PARAMÈTRES'!$C$25 -> 10.84 | G72: =IFERROR(_xlfn.XLOOKUP('PRÉDIMENSIONNEMENT'!$E$72,'BASE_PROFILÉS'!$B$5:$B$200,'BASE_PROFILÉS'!$E$5:$E$200),IFERROR(INDEX('BASE_PROFILÉS'!$E$5:$E$200,MATCH('PRÉDIMENSIONNEMENT'!$E$72,'BASE_PROFILÉS'!$B$5:$B$200,0)),0)) -> 60 | H72: Tableau A – cornières accolées
B73: Montants (treillis) | C73: =INDEX('PRÉDIMENSIONNEMENT'!$I$6:$I$14,'PRÉDIMENSIONNEMENT'!$C$25) -> L 45x4.5 | E73: =IF('PRÉDIMENSIONNEMENT'!$D$73="",'PRÉDIMENSIONNEMENT'!$C$73,'PRÉDIMENSIONNEMENT'!$D$73) -> L 45x4.5 | F73: =IFERROR(_xlfn.XLOOKUP('PRÉDIMENSIONNEMENT'!$E$73,'BASE_PROFILÉS'!$B$5:$B$200,'BASE_PROFILÉS'!$D$5:$D$200),IFERROR(INDEX('BASE_PROFILÉS'!$D$5:$D$200,MATCH('PRÉDIMENSIONNEMENT'!$E$73,'BASE_PROFILÉS'!$B$5:$B$200,0)),0)) -> 3.06 | G73: =IFERROR(_xlfn.XLOOKUP('PRÉDIMENSIONNEMENT'!$E$73,'BASE_PROFILÉS'!$B$5:$B$200,'BASE_PROFILÉS'!$E$5:$E$200),IFERROR(INDEX('BASE_PROFILÉS'!$E$5:$E$200,MATCH('PRÉDIMENSIONNEMENT'!$E$73,'BASE_PROFILÉS'!$B$5:$B$200,0)),0)) -> 45 | H73: Tableau A
B74: Diagonales (treillis) | C74: =INDEX('PRÉDIMENSIONNEMENT'!$J$6:$J$14,'PRÉDIMENSIONNEMENT'!$C$25) -> L 50x5 | E74: =IF('PRÉDIMENSIONNEMENT'!$D$74="",'PRÉDIMENSIONNEMENT'!$C$74,'PRÉDIMENSIONNEMENT'!$D$74) -> L 50x5 | F74: =IFERROR(_xlfn.XLOOKUP('PRÉDIMENSIONNEMENT'!$E$74,'BASE_PROFILÉS'!$B$5:$B$200,'BASE_PROFILÉS'!$D$5:$D$200),IFERROR(INDEX('BASE_PROFILÉS'!$D$5:$D$200,MATCH('PRÉDIMENSIONNEMENT'!$E$74,'BASE_PROFILÉS'!$B$5:$B$200,0)),0)) -> 3.77 | G74: =IFERROR(_xlfn.XLOOKUP('PRÉDIMENSIONNEMENT'!$E$74,'BASE_PROFILÉS'!$B$5:$B$200,'BASE_PROFILÉS'!$E$5:$E$200),IFERROR(INDEX('BASE_PROFILÉS'!$E$5:$E$200,MATCH('PRÉDIMENSIONNEMENT'!$E$74,'BASE_PROFILÉS'!$B$5:$B$200,0)),0)) -> 50 | H74: Tableau A
B75: Poteaux de pignon | C75: =INDEX('PRÉDIMENSIONNEMENT'!$C$17:$C$21,COUNTIF('PRÉDIMENSIONNEMENT'!$B$17:$B$21,"<"&'PRÉDIMENSIONNEMENT'!$C$34)+1) -> IPE 220 | E75: =IF('PRÉDIMENSIONNEMENT'!$D$75="",'PRÉDIMENSIONNEMENT'!$C$75,'PRÉDIMENSIONNEMENT'!$D$75) -> IPE 220 | F75: =IFERROR(_xlfn.XLOOKUP('PRÉDIMENSIONNEMENT'!$E$75,'BASE_PROFILÉS'!$B$5:$B$200,'BASE_PROFILÉS'!$D$5:$D$200),IFERROR(INDEX('BASE_PROFILÉS'!$D$5:$D$200,MATCH('PRÉDIMENSIONNEMENT'!$E$75,'BASE_PROFILÉS'!$B$5:$B$200,0)),0)) -> 26.2 | G75: =IFERROR(_xlfn.XLOOKUP('PRÉDIMENSIONNEMENT'!$E$75,'BASE_PROFILÉS'!$B$5:$B$200,'BASE_PROFILÉS'!$E$5:$E$200),IFERROR(INDEX('BASE_PROFILÉS'!$E$5:$E$200,MATCH('PRÉDIMENSIONNEMENT'!$E$75,'BASE_PROFILÉS'!$B$5:$B$200,0)),0)) -> 220 | H75: Selon hauteur au faîtage
B76: Poteaux intermédiaires (file centrale) | C76: ="HEA 200" -> HEA 200 | E76: =IF('PRÉDIMENSIONNEMENT'!$D$76="",'PRÉDIMENSIONNEMENT'!$C$76,'PRÉDIMENSIONNEMENT'!$D$76) -> HEA 200 | F76: =IFERROR(_xlfn.XLOOKUP('PRÉDIMENSIONNEMENT'!$E$76,'BASE_PROFILÉS'!$B$5:$B$200,'BASE_PROFILÉS'!$D$5:$D$200),IFERROR(INDEX('BASE_PROFILÉS'!$D$5:$D$200,MATCH('PRÉDIMENSIONNEMENT'!$E$76,'BASE_PROFILÉS'!$B$5:$B$200,0)),0)) -> 42.3 | G76: =IFERROR(_xlfn.XLOOKUP('PRÉDIMENSIONNEMENT'!$E$76,'BASE_PROFILÉS'!$B$5:$B$200,'BASE_PROFILÉS'!$E$5:$E$200),IFERROR(INDEX('BASE_PROFILÉS'!$E$5:$E$200,MATCH('PRÉDIMENSIONNEMENT'!$E$76,'BASE_PROFILÉS'!$B$5:$B$200,0)),0)) -> 190 | H76: Valeur proposée
B77: Pannes | C77: =INDEX('PRÉDIMENSIONNEMENT'!$G$17:$G$20,COUNTIF('PRÉDIMENSIONNEMENT'!$F$17:$F$20,"<"&'PRÉDIMENSIONNEMENT'!$C$30)+1) -> Z 200 | E77: =IF('PRÉDIMENSIONNEMENT'!$D$77="",'PRÉDIMENSIONNEMENT'!$C$77,'PRÉDIMENSIONNEMENT'!$D$77) -> Z 200 | F77: =IFERROR(_xlfn.XLOOKUP('PRÉDIMENSIONNEMENT'!$E$77,'BASE_PROFILÉS'!$B$5:$B$200,'BASE_PROFILÉS'!$D$5:$D$200),IFERROR(INDEX('BASE_PROFILÉS'!$D$5:$D$200,MATCH('PRÉDIMENSIONNEMENT'!$E$77,'BASE_PROFILÉS'!$B$5:$B$200,0)),0)) -> 5.2 | G77: =IFERROR(_xlfn.XLOOKUP('PRÉDIMENSIONNEMENT'!$E$77,'BASE_PROFILÉS'!$B$5:$B$200,'BASE_PROFILÉS'!$E$5:$E$200),IFERROR(INDEX('BASE_PROFILÉS'!$E$5:$E$200,MATCH('PRÉDIMENSIONNEMENT'!$E$77,'BASE_PROFILÉS'!$B$5:$B$200,0)),0)) -> 200 | H77: Selon entraxe des portiques
B78: Lisses de bardage | C78: =INDEX('PRÉDIMENSIONNEMENT'!$H$17:$H$20,COUNTIF('PRÉDIMENSIONNEMENT'!$F$17:$F$20,"<"&'PRÉDIMENSIONNEMENT'!$C$30)+1) -> C 160 | E78: =IF('PRÉDIMENSIONNEMENT'!$D$78="",'PRÉDIMENSIONNEMENT'!$C$78,'PRÉDIMENSIONNEMENT'!$D$78) -> C 160 | F78: =IFERROR(_xlfn.XLOOKUP('PRÉDIMENSIONNEMENT'!$E$78,'BASE_PROFILÉS'!$B$5:$B$200,'BASE_PROFILÉS'!$D$5:$D$200),IFERROR(INDEX('BASE_PROFILÉS'!$D$5:$D$200,MATCH('PRÉDIMENSIONNEMENT'!$E$78,'BASE_PROFILÉS'!$B$5:$B$200,0)),0)) -> 4.57 | G78: =IFERROR(_xlfn.XLOOKUP('PRÉDIMENSIONNEMENT'!$E$78,'BASE_PROFILÉS'!$B$5:$B$200,'BASE_PROFILÉS'!$E$5:$E$200),IFERROR(INDEX('BASE_PROFILÉS'!$E$5:$E$200,MATCH('PRÉDIMENSIONNEMENT'!$E$78,'BASE_PROFILÉS'!$B$5:$B$200,0)),0)) -> 160 | H78: Selon entraxe des portiques
B79: Contreventements verticaux (croix) | C79: ="L 70x7" -> L 70x7 | E79: =IF('PRÉDIMENSIONNEMENT'!$D$79="",'PRÉDIMENSIONNEMENT'!$C$79,'PRÉDIMENSIONNEMENT'!$D$79) -> L 70x7 | F79: =IFERROR(_xlfn.XLOOKUP('PRÉDIMENSIONNEMENT'!$E$79,'BASE_PROFILÉS'!$B$5:$B$200,'BASE_PROFILÉS'!$D$5:$D$200),IFERROR(INDEX('BASE_PROFILÉS'!$D$5:$D$200,MATCH('PRÉDIMENSIONNEMENT'!$E$79,'BASE_PROFILÉS'!$B$5:$B$200,0)),0)) -> 7.38 | G79: =IFERROR(_xlfn.XLOOKUP('PRÉDIMENSIONNEMENT'!$E$79,'BASE_PROFILÉS'!$B$5:$B$200,'BASE_PROFILÉS'!$E$5:$E$200),IFERROR(INDEX('BASE_PROFILÉS'!$E$5:$E$200,MATCH('PRÉDIMENSIONNEMENT'!$E$79,'BASE_PROFILÉS'!$B$5:$B$200,0)),0)) -> 70 | H79: Cornière proposée
B80: Contreventements de couverture (poutre au vent) | C80: ="L 60x6" -> L 60x6 | E80: =IF('PRÉDIMENSIONNEMENT'!$D$80="",'PRÉDIMENSIONNEMENT'!$C$80,'PRÉDIMENSIONNEMENT'!$D$80) -> L 60x6 | F80: =IFERROR(_xlfn.XLOOKUP('PRÉDIMENSIONNEMENT'!$E$80,'BASE_PROFILÉS'!$B$5:$B$200,'BASE_PROFILÉS'!$D$5:$D$200),IFERROR(INDEX('BASE_PROFILÉS'!$D$5:$D$200,MATCH('PRÉDIMENSIONNEMENT'!$E$80,'BASE_PROFILÉS'!$B$5:$B$200,0)),0)) -> 5.42 | G80: =IFERROR(_xlfn.XLOOKUP('PRÉDIMENSIONNEMENT'!$E$80,'BASE_PROFILÉS'!$B$5:$B$200,'BASE_PROFILÉS'!$E$5:$E$200),IFERROR(INDEX('BASE_PROFILÉS'!$E$5:$E$200,MATCH('PRÉDIMENSIONNEMENT'!$E$80,'BASE_PROFILÉS'!$B$5:$B$200,0)),0)) -> 60 | H80: Cornière proposée
B81: Liernes et bretelles | C81: ="Rond 12" -> Rond 12 | E81: =IF('PRÉDIMENSIONNEMENT'!$D$81="",'PRÉDIMENSIONNEMENT'!$C$81,'PRÉDIMENSIONNEMENT'!$D$81) -> Rond 12 | F81: =IFERROR(_xlfn.XLOOKUP('PRÉDIMENSIONNEMENT'!$E$81,'BASE_PROFILÉS'!$B$5:$B$200,'BASE_PROFILÉS'!$D$5:$D$200),IFERROR(INDEX('BASE_PROFILÉS'!$D$5:$D$200,MATCH('PRÉDIMENSIONNEMENT'!$E$81,'BASE_PROFILÉS'!$B$5:$B$200,0)),0)) -> 0.888 | G81: =IFERROR(_xlfn.XLOOKUP('PRÉDIMENSIONNEMENT'!$E$81,'BASE_PROFILÉS'!$B$5:$B$200,'BASE_PROFILÉS'!$E$5:$E$200),IFERROR(INDEX('BASE_PROFILÉS'!$E$5:$E$200,MATCH('PRÉDIMENSIONNEMENT'!$E$81,'BASE_PROFILÉS'!$B$5:$B$200,0)),0)) -> 12 | H81: Rond Ø12
B82: Chevêtres de skydome | C82: ="L 60x6" -> L 60x6 | E82: =IF('PRÉDIMENSIONNEMENT'!$D$82="",'PRÉDIMENSIONNEMENT'!$C$82,'PRÉDIMENSIONNEMENT'!$D$82) -> L 60x6 | F82: =IFERROR(_xlfn.XLOOKUP('PRÉDIMENSIONNEMENT'!$E$82,'BASE_PROFILÉS'!$B$5:$B$200,'BASE_PROFILÉS'!$D$5:$D$200),IFERROR(INDEX('BASE_PROFILÉS'!$D$5:$D$200,MATCH('PRÉDIMENSIONNEMENT'!$E$82,'BASE_PROFILÉS'!$B$5:$B$200,0)),0)) -> 5.42 | G82: =IFERROR(_xlfn.XLOOKUP('PRÉDIMENSIONNEMENT'!$E$82,'BASE_PROFILÉS'!$B$5:$B$200,'BASE_PROFILÉS'!$E$5:$E$200),IFERROR(INDEX('BASE_PROFILÉS'!$E$5:$E$200,MATCH('PRÉDIMENSIONNEMENT'!$E$82,'BASE_PROFILÉS'!$B$5:$B$200,0)),0)) -> 60 | H82: Cadre en cornière
B83: Baïonnettes d'acrotère | C83: ="L 50x5" -> L 50x5 | E83: =IF('PRÉDIMENSIONNEMENT'!$D$83="",'PRÉDIMENSIONNEMENT'!$C$83,'PRÉDIMENSIONNEMENT'!$D$83) -> L 50x5 | F83: =IFERROR(_xlfn.XLOOKUP('PRÉDIMENSIONNEMENT'!$E$83,'BASE_PROFILÉS'!$B$5:$B$200,'BASE_PROFILÉS'!$D$5:$D$200),IFERROR(INDEX('BASE_PROFILÉS'!$D$5:$D$200,MATCH('PRÉDIMENSIONNEMENT'!$E$83,'BASE_PROFILÉS'!$B$5:$B$200,0)),0)) -> 3.77 | G83: =IFERROR(_xlfn.XLOOKUP('PRÉDIMENSIONNEMENT'!$E$83,'BASE_PROFILÉS'!$B$5:$B$200,'BASE_PROFILÉS'!$E$5:$E$200),IFERROR(INDEX('BASE_PROFILÉS'!$E$5:$E$200,MATCH('PRÉDIMENSIONNEMENT'!$E$83,'BASE_PROFILÉS'!$B$5:$B$200,0)),0)) -> 50 | H83: Cornière
B84: Linteaux et potelets de baies | C84: ="UPN 140" -> UPN 140 | E84: =IF('PRÉDIMENSIONNEMENT'!$D$84="",'PRÉDIMENSIONNEMENT'!$C$84,'PRÉDIMENSIONNEMENT'!$D$84) -> UPN 140 | F84: =IFERROR(_xlfn.XLOOKUP('PRÉDIMENSIONNEMENT'!$E$84,'BASE_PROFILÉS'!$B$5:$B$200,'BASE_PROFILÉS'!$D$5:$D$200),IFERROR(INDEX('BASE_PROFILÉS'!$D$5:$D$200,MATCH('PRÉDIMENSIONNEMENT'!$E$84,'BASE_PROFILÉS'!$B$5:$B$200,0)),0)) -> 16 | G84: =IFERROR(_xlfn.XLOOKUP('PRÉDIMENSIONNEMENT'!$E$84,'BASE_PROFILÉS'!$B$5:$B$200,'BASE_PROFILÉS'!$E$5:$E$200),IFERROR(INDEX('BASE_PROFILÉS'!$E$5:$E$200,MATCH('PRÉDIMENSIONNEMENT'!$E$84,'BASE_PROFILÉS'!$B$5:$B$200,0)),0)) -> 140 | H84: UPN
B86: D. ALERTES DE PRÉDIMENSIONNEMENT
B87: =IF(AND('PARAMÈTRES'!$C$9>30,'PARAMÈTRES'!$C$21="Non"),"ALERTE : portée > 30 m sans poteau intermédiaire – prévoir une file centrale (indispensable au-delà de 40 m sans appui)","OK : portée / appuis") -> OK : portée / appuis
B88: =IF('PARAMÈTRES'!$C$12<0.05,"ALERTE : pente < 5 % – risque de stagnation, revoir la pente","OK : pente ≥ 5 %") -> OK : pente ≥ 5 %
B89: =IF(AND('PARAMÈTRES'!$C$114="15 cm",'PARAMÈTRES'!$C$115="Nappe double"),"ALERTE : dallage 15 cm en nappe double (peu courant)","OK : dallage / ferraillage") -> OK : dallage / ferraillage
B90: =IF(OR('QUANTITATIF_CHARPENTE'!$I$78<18,'QUANTITATIF_CHARPENTE'!$I$78>45),"ALERTE : ratio acier "&FIXED('QUANTITATIF_CHARPENTE'!$I$78,1,TRUE)&" kg/m² hors fourchette 18–45","OK : ratio acier "&FIXED('QUANTITATIF_CHARPENTE'!$I$78,1,TRUE)&" kg/m²") -> OK : ratio acier 32.5 kg/m²
B91: =IF('PARAMÈTRES'!$C$47<0.4,"ALERTE : tôle < 0,40 mm","OK : épaisseur de tôle") -> OK : épaisseur de tôle
B92: =IF(AND('PRÉDIMENSIONNEMENT'!$C$30>6.5,'PRÉDIMENSIONNEMENT'!$E$77="Z 250"),"ALERTE : entraxe de portiques élevé, vérifier les pannes","OK : entraxe des portiques") -> OK : entraxe des portiques

Sheet QUANTITATIF_CHARPENTE
A1: QUANTITATIF CHARPENTE MÉTALLIQUE (EC3 / EC1)
A2: Une ligne par élément. Toutes les quantités se recalculent depuis PARAMÈTRES et PRÉDIMENSIONNEMENT.
B4: Désignation | C4: Profilé / section | D4: Unité | E4: Quantité | F4: Long. unitaire (m) | G4: Long. totale (m) | H4: kg/ml ou kg/u | I4: Poids total (kg) | J4: Règle de calcul (aussi en commentaire)
B5: A1. OSSATURE
B6: Poteaux de portiques (2 par portique) | C6: ='PRÉDIMENSIONNEMENT'!$E$69 -> IPE 330 | D6: ml | E6: =2*'PRÉDIMENSIONNEMENT'!$C$29 -> 16 | F6: ='PRÉDIMENSIONNEMENT'!$C$33 -> 6 | G6: ='QUANTITATIF_CHARPENTE'!$E$6*'QUANTITATIF_CHARPENTE'!$F$6 -> 96 | H6: ='PRÉDIMENSIONNEMENT'!$F$69 -> 49.1 | I6: ='QUANTITATIF_CHARPENTE'!$G$6*'QUANTITATIF_CHARPENTE'!$H$6 -> 4713.6 | J6: 2 × N poteaux × hauteur à l'égout (H + hauteur de ferme)
B7: Poteaux de pignon (hauteur variable avec la pente) | C7: ='PRÉDIMENSIONNEMENT'!$E$75 -> IPE 220 | D7: ml | E7: ='PRÉDIMENSIONNEMENT'!$C$37 -> 6 | F7: =IF('QUANTITATIF_CHARPENTE'!$E$7>0,'QUANTITATIF_CHARPENTE'!$G$7/'QUANTITATIF_CHARPENTE'!$E$7,0) -> 7.0666667 | G7: =2*(('PRÉDIMENSIONNEMENT'!$C$35-1)*'PRÉDIMENSIONNEMENT'!$C$33+'PARAMÈTRES'!$C$12*'PRÉDIMENSIONNEMENT'!$C$36*INT('PRÉDIMENSIONNEMENT'!$C$35^2/4)) -> 42.4 | H7: ='PRÉDIMENSIONNEMENT'!$F$75 -> 26.2 | I7: ='QUANTITATIF_CHARPENTE'!$G$7*'QUANTITATIF_CHARPENTE'!$H$7 -> 1110.88 | J7: 2 pignons × Σ (Hm + pente × min(x ; B − x)) ; Σ min = (B / n) × ENT(n² / 4)
B8: Poteaux intermédiaires (file centrale) | C8: ='PRÉDIMENSIONNEMENT'!$E$76 -> HEA 200 | D8: ml | E8: ='PRÉDIMENSIONNEMENT'!$C$38 -> 0 | F8: =IF('PRÉDIMENSIONNEMENT'!$C$27=1,'PARAMÈTRES'!$C$11,'PRÉDIMENSIONNEMENT'!$C$34) -> 7.6 | G8: ='QUANTITATIF_CHARPENTE'!$E$8*'QUANTITATIF_CHARPENTE'!$F$8 -> 0 | H8: ='PRÉDIMENSIONNEMENT'!$F$76 -> 42.3 | I8: ='QUANTITATIF_CHARPENTE'!$G$8*'QUANTITATIF_CHARPENTE'!$H$8 -> 0 | J8: 1 par portique si file centrale = Oui
B9: Traverses de portique (2 versants) | C9: ='PRÉDIMENSIONNEMENT'!$E$70 -> IPE 300 | D9: ml | E9: ='PRÉDIMENSIONNEMENT'!$C$29*(1-'PRÉDIMENSIONNEMENT'!$C$27) -> 8 | F9: =2*'PRÉDIMENSIONNEMENT'!$C$31 -> 20.254382 | G9: ='QUANTITATIF_CHARPENTE'!$E$9*'QUANTITATIF_CHARPENTE'!$F$9 -> 162.03506 | H9: ='PRÉDIMENSIONNEMENT'!$F$70 -> 42.2 | I9: ='QUANTITATIF_CHARPENTE'!$G$9*'QUANTITATIF_CHARPENTE'!$H$9 -> 6837.8794 | J9: Longueur rampante = (portée / 2) / cos(arctan(pente)) × 2
B10: Jarrets (renforts poteau-traverse) | C10: ='PRÉDIMENSIONNEMENT'!$E$70 -> IPE 300 | D10: ml | E10: =2*'PRÉDIMENSIONNEMENT'!$C$29*(1-'PRÉDIMENSIONNEMENT'!$C$27) -> 16 | F10: ='PARAMÈTRES'!$C$24*'PARAMÈTRES'!$C$9 -> 2 | G10: ='QUANTITATIF_CHARPENTE'!$E$10*'QUANTITATIF_CHARPENTE'!$F$10 -> 32 | H10: ='PRÉDIMENSIONNEMENT'!$F$70 -> 42.2 | I10: ='QUANTITATIF_CHARPENTE'!$G$10*'QUANTITATIF_CHARPENTE'!$H$10 -> 1350.4 | J10: 2 par portique, longueur = % × portée, découpés dans le profil de traverse
B11: Ferme treillis – membrures supérieures | C11: ='PRÉDIMENSIONNEMENT'!$E$71 -> L 70x7 | D11: ml | E11: ='PRÉDIMENSIONNEMENT'!$C$29*'PRÉDIMENSIONNEMENT'!$C$27 -> 0 | F11: =2*'PRÉDIMENSIONNEMENT'!$C$31 -> 20.254382 | G11: ='QUANTITATIF_CHARPENTE'!$E$11*'QUANTITATIF_CHARPENTE'!$F$11 -> 0 | H11: ='PRÉDIMENSIONNEMENT'!$F$71 -> 14.76 | I11: ='QUANTITATIF_CHARPENTE'!$G$11*'QUANTITATIF_CHARPENTE'!$H$11 -> 0 | J11: 1 par ferme, longueur = 2 × rampant ; poids × cornières accolées
B12: Ferme treillis – membrures inférieures | C12: ='PRÉDIMENSIONNEMENT'!$E$72 -> L 60x6 | D12: ml | E12: ='PRÉDIMENSIONNEMENT'!$C$29*'PRÉDIMENSIONNEMENT'!$C$27 -> 0 | F12: ='PARAMÈTRES'!$C$9 -> 20 | G12: ='QUANTITATIF_CHARPENTE'!$E$12*'QUANTITATIF_CHARPENTE'!$F$12 -> 0 | H12: ='PRÉDIMENSIONNEMENT'!$F$72 -> 10.84 | I12: ='QUANTITATIF_CHARPENTE'!$G$12*'QUANTITATIF_CHARPENTE'!$H$12 -> 0 | J12: 1 par ferme, longueur = portée
B13: Ferme treillis – montants | C13: ='PRÉDIMENSIONNEMENT'!$E$73 -> L 45x4.5 | D13: ml | E13: ='PRÉDIMENSIONNEMENT'!$C$29*'PRÉDIMENSIONNEMENT'!$C$27*('PRÉDIMENSIONNEMENT'!$C$39+1) -> 0 | F13: =IF('QUANTITATIF_CHARPENTE'!$E$13>0,'QUANTITATIF_CHARPENTE'!$G$13/'QUANTITATIF_CHARPENTE'!$E$13,0) -> 0 | G13: ='PRÉDIMENSIONNEMENT'!$C$29*'PRÉDIMENSIONNEMENT'!$C$27*(('PRÉDIMENSIONNEMENT'!$C$39+1)*'PRÉDIMENSIONNEMENT'!$C$32+'PARAMÈTRES'!$C$12*('PARAMÈTRES'!$C$9/'PRÉDIMENSIONNEMENT'!$C$52)*INT('PRÉDIMENSIONNEMENT'!$C$39^2/4)) -> 0 | H13: ='PRÉDIMENSIONNEMENT'!$F$73 -> 3.06 | I13: ='QUANTITATIF_CHARPENTE'!$G$13*'QUANTITATIF_CHARPENTE'!$H$13 -> 0 | J13: (n + 1) montants par ferme, hauteur h0 + pente × min(x ; B − x)
B14: Ferme treillis – diagonales | C14: ='PRÉDIMENSIONNEMENT'!$E$74 -> L 50x5 | D14: ml | E14: ='PRÉDIMENSIONNEMENT'!$C$29*'PRÉDIMENSIONNEMENT'!$C$27*'PRÉDIMENSIONNEMENT'!$C$39 -> 0 | F14: ='PRÉDIMENSIONNEMENT'!$C$27*SQRT(('PARAMÈTRES'!$C$9/'PRÉDIMENSIONNEMENT'!$C$52)^2+('PRÉDIMENSIONNEMENT'!$C$32+'PARAMÈTRES'!$C$12*'PARAMÈTRES'!$C$9/4)^2) -> 0 | G14: ='QUANTITATIF_CHARPENTE'!$E$14*'QUANTITATIF_CHARPENTE'!$F$14 -> 0 | H14: ='PRÉDIMENSIONNEMENT'!$F$74 -> 3.77 | I14: ='QUANTITATIF_CHARPENTE'!$G$14*'QUANTITATIF_CHARPENTE'!$H$14 -> 0 | J14: n diagonales par ferme, longueur √(pas² + h moyenne²)
B15: Platines de pied – poteaux de portique | C15: ="PL" -> PL | D15: u | E15: =2*'PRÉDIMENSIONNEMENT'!$C$29+'PRÉDIMENSIONNEMENT'!$C$38 -> 16 | H15: ='PARAMÈTRES'!$K$18 -> 24.7275 | I15: ='QUANTITATIF_CHARPENTE'!$E$15*'QUANTITATIF_CHARPENTE'!$H$15 -> 395.64 | J15: 1 par poteau de portique ou intermédiaire
B16: Platines de pied – poteaux de pignon | C16: ="PL" -> PL | D16: u | E16: ='PRÉDIMENSIONNEMENT'!$C$37 -> 6 | H16: ='PARAMÈTRES'!$K$19 -> 8.83125 | I16: ='QUANTITATIF_CHARPENTE'!$E$16*'QUANTITATIF_CHARPENTE'!$H$16 -> 52.9875 | J16: 1 par poteau de pignon
B17: Platines de tête de poteau et d'about de jarret | C17: ="PL" -> PL | D17: u | E17: =IF('PRÉDIMENSIONNEMENT'!$C$27=1,2,4)*'PRÉDIMENSIONNEMENT'!$C$29 -> 32 | H17: ='PARAMÈTRES'!$K$20 -> 21.5875 | I17: ='QUANTITATIF_CHARPENTE'!$E$17*'QUANTITATIF_CHARPENTE'!$H$17 -> 690.8 | J17: Portique : 2 platines par nœud × 2 nœuds ; treillis : 1 platine de tête par poteau
B18: Platines de tête – poteaux de pignon | C18: ="PL" -> PL | D18: u | E18: ='PRÉDIMENSIONNEMENT'!$C$37 -> 6 | H18: ='PARAMÈTRES'!$K$21 -> 4.71 | I18: ='QUANTITATIF_CHARPENTE'!$E$18*'QUANTITATIF_CHARPENTE'!$H$18 -> 28.26 | J18: 1 par poteau de pignon
B19: Goussets de nœuds de treillis | C19: ="PL" -> PL | D19: u | E19: ='PRÉDIMENSIONNEMENT'!$C$29*'PRÉDIMENSIONNEMENT'!$C$27*(2*'PRÉDIMENSIONNEMENT'!$C$39+2) -> 0 | H19: ='PARAMÈTRES'!$K$23 -> 7.065 | I19: ='QUANTITATIF_CHARPENTE'!$E$19*'QUANTITATIF_CHARPENTE'!$H$19 -> 0 | J19: 2 (n + 1) nœuds par ferme
B20: Éclisses de faîtage (paires de plaques) | C20: ="PL" -> PL | D20: u | E20: ='PRÉDIMENSIONNEMENT'!$C$29 -> 8 | H20: =2*'PARAMÈTRES'!$K$22 -> 29.4375 | I20: ='QUANTITATIF_CHARPENTE'!$E$20*'QUANTITATIF_CHARPENTE'!$H$20 -> 235.5 | J20: 1 paire par portique
B21: Éclisses de pannes (à chaque raboutage) | C21: ="PL" -> PL | D21: u | E21: =2*'PRÉDIMENSIONNEMENT'!$C$40*MAX(0,ROUNDUP('PRÉDIMENSIONNEMENT'!$C$42/'PARAMÈTRES'!$C$58,0)-1) -> 54 | H21: ='PARAMÈTRES'!$C$62 -> 2.5 | I21: ='QUANTITATIF_CHARPENTE'!$E$21*'QUANTITATIF_CHARPENTE'!$H$21 -> 135 | J21: Pannes × (ARRONDI.SUP(longueur / 12 m) − 1)
B23: A2. STABILITÉ
B24: Contreventements verticaux – croix de Saint-André (long-pans) | C24: ='PRÉDIMENSIONNEMENT'!$E$79 -> L 70x7 | D24: ml | E24: ='PRÉDIMENSIONNEMENT'!$C$44*2*2 -> 12 | F24: =SQRT('PRÉDIMENSIONNEMENT'!$C$30^2+'PRÉDIMENSIONNEMENT'!$C$33^2) -> 8.2857143 | G24: ='QUANTITATIF_CHARPENTE'!$E$24*'QUANTITATIF_CHARPENTE'!$F$24 -> 99.428571 | H24: ='PRÉDIMENSIONNEMENT'!$F$79 -> 7.38 | I24: ='QUANTITATIF_CHARPENTE'!$G$24*'QUANTITATIF_CHARPENTE'!$H$24 -> 733.78286 | J24: Travées d'extrémité + 1 sur 5 ; 2 long-pans × 2 diagonales
B25: Contreventements de couverture – poutre au vent | C25: ='PRÉDIMENSIONNEMENT'!$E$80 -> L 60x6 | D25: ml | E25: ='PRÉDIMENSIONNEMENT'!$C$44*2*'PRÉDIMENSIONNEMENT'!$C$45*2 -> 24 | F25: =SQRT('PRÉDIMENSIONNEMENT'!$C$30^2+('PRÉDIMENSIONNEMENT'!$C$31/'PRÉDIMENSIONNEMENT'!$C$45)^2) -> 7.6349893 | G25: ='QUANTITATIF_CHARPENTE'!$E$25*'QUANTITATIF_CHARPENTE'!$F$25 -> 183.23974 | H25: ='PRÉDIMENSIONNEMENT'!$F$80 -> 5.42 | I25: ='QUANTITATIF_CHARPENTE'!$G$25*'QUANTITATIF_CHARPENTE'!$H$25 -> 993.1594 | J25: Mêmes travées ; 2 versants × panneaux × 2 diagonales
B26: Liernes de pannes | C26: ='PRÉDIMENSIONNEMENT'!$E$81 -> Rond 12 | D26: ml | E26: ='PRÉDIMENSIONNEMENT'!$C$28*'PRÉDIMENSIONNEMENT'!$C$43*2*('PRÉDIMENSIONNEMENT'!$C$40-1) -> 112 | F26: ='PRÉDIMENSIONNEMENT'!$C$41 -> 1.2658989 | G26: ='QUANTITATIF_CHARPENTE'!$E$26*'QUANTITATIF_CHARPENTE'!$F$26 -> 141.78068 | H26: ='PRÉDIMENSIONNEMENT'!$F$81 -> 0.888 | I26: ='QUANTITATIF_CHARPENTE'!$G$26*'QUANTITATIF_CHARPENTE'!$H$26 -> 125.90124 | J26: À mi-portée (au tiers si entraxe > 6 m), entre pannes successives
B27: Bretelles de faîtage | C27: ='PRÉDIMENSIONNEMENT'!$E$81 -> Rond 12 | D27: ml | E27: ='PRÉDIMENSIONNEMENT'!$C$28*'PRÉDIMENSIONNEMENT'!$C$43*2 -> 14 | F27: =SQRT(('PRÉDIMENSIONNEMENT'!$C$30/('PRÉDIMENSIONNEMENT'!$C$43+1))^2+'PRÉDIMENSIONNEMENT'!$C$41^2) -> 3.1250224 | G27: ='QUANTITATIF_CHARPENTE'!$E$27*'QUANTITATIF_CHARPENTE'!$F$27 -> 43.750314 | H27: ='PRÉDIMENSIONNEMENT'!$F$81 -> 0.888 | I27: ='QUANTITATIF_CHARPENTE'!$G$27*'QUANTITATIF_CHARPENTE'!$H$27 -> 38.850279 | J27: 2 par ligne de liernes au faîtage
B28: Liernes de lisses – long-pans | C28: ='PRÉDIMENSIONNEMENT'!$E$81 -> Rond 12 | D28: ml | E28: ='PRÉDIMENSIONNEMENT'!$C$28*'PRÉDIMENSIONNEMENT'!$C$43*2*'PRÉDIMENSIONNEMENT'!$C$59 -> 56 | F28: =IF('PRÉDIMENSIONNEMENT'!$C$59>0,('PRÉDIMENSIONNEMENT'!$C$33-'PRÉDIMENSIONNEMENT'!$C$49)/'PRÉDIMENSIONNEMENT'!$C$59,0) -> 1.5 | G28: ='QUANTITATIF_CHARPENTE'!$E$28*'QUANTITATIF_CHARPENTE'!$F$28 -> 84 | H28: ='PRÉDIMENSIONNEMENT'!$F$81 -> 0.888 | I28: ='QUANTITATIF_CHARPENTE'!$G$28*'QUANTITATIF_CHARPENTE'!$H$28 -> 74.592 | J28: Par ligne de liernes : hauteur bardée ; 0 en façade agglos
B29: Liernes de lisses – pignons | C29: ='PRÉDIMENSIONNEMENT'!$E$81 -> Rond 12 | D29: ml | E29: ='PRÉDIMENSIONNEMENT'!$C$50*2*'PRÉDIMENSIONNEMENT'!$C$35 -> 8 | F29: =IF('QUANTITATIF_CHARPENTE'!$E$29>0,'QUANTITATIF_CHARPENTE'!$G$29/'QUANTITATIF_CHARPENTE'!$E$29,0) -> 6.8 | G29: ='PRÉDIMENSIONNEMENT'!$C$50*2*'PRÉDIMENSIONNEMENT'!$C$35*(('PRÉDIMENSIONNEMENT'!$C$33-'PRÉDIMENSIONNEMENT'!$C$49)+'PARAMÈTRES'!$C$12*'PARAMÈTRES'!$C$9/4) -> 54.4 | H29: ='PRÉDIMENSIONNEMENT'!$F$81 -> 0.888 | I29: ='QUANTITATIF_CHARPENTE'!$G$29*'QUANTITATIF_CHARPENTE'!$H$29 -> 48.3072 | J29: 1 par intervalle de pignon, hauteur moyenne
B31: A3. COUVERTURE
B32: Pannes | C32: ='PRÉDIMENSIONNEMENT'!$E$77 -> Z 200 | D32: ml | E32: =2*'PRÉDIMENSIONNEMENT'!$C$40 -> 18 | F32: ='PRÉDIMENSIONNEMENT'!$C$42 -> 40.6 | G32: ='QUANTITATIF_CHARPENTE'!$E$32*'QUANTITATIF_CHARPENTE'!$F$32 -> 730.8 | H32: ='PRÉDIMENSIONNEMENT'!$F$77 -> 5.2 | I32: ='QUANTITATIF_CHARPENTE'!$G$32*'QUANTITATIF_CHARPENTE'!$H$32 -> 3800.16 | J32: Par versant : ARRONDI.SUP(rampant / entraxe) + 1 ; longueur = L + débords
B33: Échantignoles (taquets de pannes) | C33: ="Taquet" -> Taquet | D33: u | E33: =2*'PRÉDIMENSIONNEMENT'!$C$40*'PRÉDIMENSIONNEMENT'!$C$29 -> 144 | H33: ='PARAMÈTRES'!$C$61 -> 1.8 | I33: ='QUANTITATIF_CHARPENTE'!$E$33*'QUANTITATIF_CHARPENTE'!$H$33 -> 259.2 | J33: 1 par panne et par portique
B34: Chevêtres de skydomes | C34: ='PRÉDIMENSIONNEMENT'!$E$82 -> L 60x6 | D34: ml | E34: ='PARAMÈTRES'!$C$37 -> 4 | F34: =2*('PARAMÈTRES'!$C$38+'PARAMÈTRES'!$C$39) -> 4.8 | G34: ='QUANTITATIF_CHARPENTE'!$E$34*'QUANTITATIF_CHARPENTE'!$F$34 -> 19.2 | H34: ='PRÉDIMENSIONNEMENT'!$F$82 -> 5.42 | I34: ='QUANTITATIF_CHARPENTE'!$G$34*'QUANTITATIF_CHARPENTE'!$H$34 -> 104.064 | J34: 1 cadre par skydome
B35: Baïonnettes d'acrotère | C35: ='PRÉDIMENSIONNEMENT'!$E$83 -> L 50x5 | D35: ml | E35: =IF('PARAMÈTRES'!$C$42="Oui",ROUNDUP('PRÉDIMENSIONNEMENT'!$C$47/'PARAMÈTRES'!$C$44,0),0) -> 0 | F35: ='PARAMÈTRES'!$C$43 -> 1 | G35: ='QUANTITATIF_CHARPENTE'!$E$35*'QUANTITATIF_CHARPENTE'!$F$35 -> 0 | H35: ='PRÉDIMENSIONNEMENT'!$F$83 -> 3.77 | I35: ='QUANTITATIF_CHARPENTE'!$G$35*'QUANTITATIF_CHARPENTE'!$H$35 -> 0 | J35: 1 tous les 1,0 à 1,5 m de périmètre si acrotère
B36: Tôles bac acier (ép. selon paramètre) | C36: ="Bac acier "&FIXED('PARAMÈTRES'!$C$47,2,TRUE)&" mm" -> Bac acier 0.45 mm | D36: m² | E36: ='PRÉDIMENSIONNEMENT'!$C$63*(1+'PARAMÈTRES'!$C$46)-'PARAMÈTRES'!$C$45*'PRÉDIMENSIONNEMENT'!$C$63-'PARAMÈTRES'!$C$37*'PARAMÈTRES'!$C$38*'PARAMÈTRES'!$C$39 -> 816.56792 | J36: rampant × longueur × 2 × (1 + recouvrement) − translucides − skydomes
B37: Panneaux sandwich translucides | C37: ="Translucide" -> Translucide | D37: m² | E37: ='PARAMÈTRES'!$C$45*'PRÉDIMENSIONNEMENT'!$C$63 -> 82.232792 | J37: % × surface de couverture
B38: Faîtières | C38: ="Faîtière" -> Faîtière | D38: ml | E38: ='PRÉDIMENSIONNEMENT'!$C$42 -> 40.6 | J38: Longueur couverte
B39: Rives | C39: ="Rive" -> Rive | D39: ml | E39: =4*'PRÉDIMENSIONNEMENT'!$C$31 -> 40.508764 | J39: 2 pignons × 2 versants × rampant
B40: Larmiers / bavettes de couverture | C40: ="Bavette" -> Bavette | D40: ml | E40: =2*'PRÉDIMENSIONNEMENT'!$C$42 -> 81.2 | J40: 2 égouts
B41: Chéneaux d'eau (2 côtés) | C41: ="Chéneau" -> Chéneau | D41: ml | E41: =2*'PARAMÈTRES'!$C$10 -> 80 | J41: 2 × longueur
B42: Naissances EP | C42: ="Naissance" -> Naissance | D42: u | E42: ='PRÉDIMENSIONNEMENT'!$C$64 -> 6 | J42: 1 descente pour 150 à 200 m² de toiture
B43: Descentes EP | C43: ="PVC Ø110" -> PVC Ø110 | D43: ml | E43: ='PRÉDIMENSIONNEMENT'!$C$64*'PRÉDIMENSIONNEMENT'!$C$33 -> 36 | J43: Nombre × hauteur
B44: Skydomes | C44: ="Skydome" -> Skydome | D44: u | E44: ='PARAMÈTRES'!$C$37 -> 4 | J44: Paramètre
B45: Rivets de chéneaux | C45: ="Rivet" -> Rivet | D45: u | E45: ='QUANTITATIF_CHARPENTE'!$E$41*'PARAMÈTRES'!$C$50 -> 400 | J45: ml de chéneaux × rivets / ml
B47: A4. BARDAGE ET BAIES
B48: Lisses de bardage – long-pans | C48: ='PRÉDIMENSIONNEMENT'!$E$78 -> C 160 | D48: ml | E48: =2*'PRÉDIMENSIONNEMENT'!$C$59*'PRÉDIMENSIONNEMENT'!$C$28 -> 56 | F48: =IF('QUANTITATIF_CHARPENTE'!$E$48>0,'QUANTITATIF_CHARPENTE'!$G$48/'QUANTITATIF_CHARPENTE'!$E$48,0) -> 5.4196429 | G48: =MAX(0,2*'PRÉDIMENSIONNEMENT'!$C$59*'PARAMÈTRES'!$C$10-'PRÉDIMENSIONNEMENT'!$C$53*'PARAMÈTRES'!$C$29*'PRÉDIMENSIONNEMENT'!$C$60-'PRÉDIMENSIONNEMENT'!$C$54*'PARAMÈTRES'!$C$33*'PRÉDIMENSIONNEMENT'!$C$61) -> 303.5 | H48: ='PRÉDIMENSIONNEMENT'!$F$78 -> 4.57 | I48: ='QUANTITATIF_CHARPENTE'!$G$48*'QUANTITATIF_CHARPENTE'!$H$48 -> 1386.995 | J48: Rangées × 2 × L − ouvertures coupées ; 0 si agglos, au-dessus du soubassement si mixte
B49: Lisses de bardage – pignons | C49: ='PRÉDIMENSIONNEMENT'!$E$78 -> C 160 | D49: ml | E49: =ROUNDUP('QUANTITATIF_CHARPENTE'!$G$49/'PRÉDIMENSIONNEMENT'!$C$36,0) -> 28 | F49: =IF('QUANTITATIF_CHARPENTE'!$E$49>0,'QUANTITATIF_CHARPENTE'!$G$49/'QUANTITATIF_CHARPENTE'!$E$49,0) -> 4.968254 | G49: =MAX(0,'PRÉDIMENSIONNEMENT'!$C$62/'PARAMÈTRES'!$C$17-('PARAMÈTRES'!$C$28-'PRÉDIMENSIONNEMENT'!$C$53)*'PARAMÈTRES'!$C$29*'PRÉDIMENSIONNEMENT'!$C$60-('PARAMÈTRES'!$C$32-'PRÉDIMENSIONNEMENT'!$C$54)*'PARAMÈTRES'!$C$33*'PRÉDIMENSIONNEMENT'!$C$61) -> 139.11111 | H49: ='PRÉDIMENSIONNEMENT'!$F$78 -> 4.57 | I49: ='QUANTITATIF_CHARPENTE'!$G$49*'QUANTITATIF_CHARPENTE'!$H$49 -> 635.73778 | J49: Surface du trapèze bardé / entraxe − ouvertures coupées
B50: Linteaux de baies | C50: ='PRÉDIMENSIONNEMENT'!$E$84 -> UPN 140 | D50: ml | E50: ='PARAMÈTRES'!$C$28+'PARAMÈTRES'!$C$32 -> 2 | F50: =IF('QUANTITATIF_CHARPENTE'!$E$50>0,'QUANTITATIF_CHARPENTE'!$G$50/'QUANTITATIF_CHARPENTE'!$E$50,0) -> 4.75 | G50: ='PRÉDIMENSIONNEMENT'!$C$56 -> 9.5 | H50: ='PRÉDIMENSIONNEMENT'!$F$84 -> 16 | I50: ='QUANTITATIF_CHARPENTE'!$G$50*'QUANTITATIF_CHARPENTE'!$H$50 -> 152 | J50: 1 au-dessus de chaque porte ou portillon
B51: Potelets de baies | C51: ='PRÉDIMENSIONNEMENT'!$E$84 -> UPN 140 | D51: ml | E51: =2*('PARAMÈTRES'!$C$28+'PARAMÈTRES'!$C$32) -> 4 | F51: ='PRÉDIMENSIONNEMENT'!$C$33 -> 6 | G51: ='QUANTITATIF_CHARPENTE'!$E$51*'QUANTITATIF_CHARPENTE'!$F$51 -> 24 | H51: ='PRÉDIMENSIONNEMENT'!$F$84 -> 16 | I51: ='QUANTITATIF_CHARPENTE'!$G$51*'QUANTITATIF_CHARPENTE'!$H$51 -> 384 | J51: 2 par baie, toute hauteur
B52: Bardage bac acier | C52: ="Bac acier" -> Bac acier | D52: m² | E52: =('PRÉDIMENSIONNEMENT'!$C$50*2*'PARAMÈTRES'!$C$10*('PRÉDIMENSIONNEMENT'!$C$33-'PRÉDIMENSIONNEMENT'!$C$49)+'PRÉDIMENSIONNEMENT'!$C$62-'PRÉDIMENSIONNEMENT'!$C$57)*(1+'PARAMÈTRES'!$C$46)+IF('PARAMÈTRES'!$C$42="Oui",'PRÉDIMENSIONNEMENT'!$C$50*'PRÉDIMENSIONNEMENT'!$C$47*'PARAMÈTRES'!$C$43,0) -> 783.2 | J52: Long-pans + pignons en trapèze − ouvertures, × (1 + recouvrement) ; 0 si agglos
B53: Larmiers de portes coulissantes | C53: ="Larmier" -> Larmier | D53: ml | E53: ='PARAMÈTRES'!$C$28*('PARAMÈTRES'!$C$29+'PARAMÈTRES'!$C$36) -> 4.2 | J53: Largeur de porte + 0,20 m
B54: Rails hauts de portes coulissantes | C54: ="Rail" -> Rail | D54: ml | E54: ='PARAMÈTRES'!$C$28*2*'PARAMÈTRES'!$C$29 -> 8 | J54: 2 × largeur par porte
B55: Larmiers de bardage (pied + angles) | C55: ="Larmier" -> Larmier | D55: ml | E55: ='PRÉDIMENSIONNEMENT'!$C$50*(MAX(0,'PRÉDIMENSIONNEMENT'!$C$47-'PRÉDIMENSIONNEMENT'!$C$56)+4*('PRÉDIMENSIONNEMENT'!$C$33-'PRÉDIMENSIONNEMENT'!$C$49)) -> 134.5 | J55: Périmètre − portes + 4 angles ; 0 si agglos
B57: A5. ASSEMBLAGES ET ANCRAGES
B58: Boulons HR M20 – assemblages poteau-traverse / jarrets | C58: ="HR M20" -> HR M20 | D58: u | E58: =2*'PRÉDIMENSIONNEMENT'!$C$29*'PARAMÈTRES'!$C$63 -> 128 | H58: ='PARAMÈTRES'!$C$69 -> 0.45 | I58: ='QUANTITATIF_CHARPENTE'!$E$58*'QUANTITATIF_CHARPENTE'!$H$58 -> 57.6 | J58: 2 nœuds par portique × boulons par nœud
B59: Boulons HR M20 – faîtage | C59: ="HR M20" -> HR M20 | D59: u | E59: ='PRÉDIMENSIONNEMENT'!$C$29*'PARAMÈTRES'!$C$64 -> 64 | H59: ='PARAMÈTRES'!$C$69 -> 0.45 | I59: ='QUANTITATIF_CHARPENTE'!$E$59*'QUANTITATIF_CHARPENTE'!$H$59 -> 28.8 | J59: 1 faîtage par portique
B60: Boulons M12 – pannes sur échantignoles | C60: ="M12" -> M12 | D60: u | E60: ='QUANTITATIF_CHARPENTE'!$E$33*'PARAMÈTRES'!$C$65 -> 288 | H60: ='PARAMÈTRES'!$C$71 -> 0.1 | I60: ='QUANTITATIF_CHARPENTE'!$E$60*'QUANTITATIF_CHARPENTE'!$H$60 -> 28.8 | J60: Échantignoles × boulons
B61: Boulons M12 – éclisses de pannes | C61: ="M12" -> M12 | D61: u | E61: ='QUANTITATIF_CHARPENTE'!$E$21*'PARAMÈTRES'!$C$68 -> 216 | H61: ='PARAMÈTRES'!$C$71 -> 0.1 | I61: ='QUANTITATIF_CHARPENTE'!$E$61*'QUANTITATIF_CHARPENTE'!$H$61 -> 21.6 | J61: Éclisses × boulons
B62: Boulons HR M16 – contreventements | C62: ="HR M16" -> HR M16 | D62: u | E62: =('QUANTITATIF_CHARPENTE'!$E$24+'QUANTITATIF_CHARPENTE'!$E$25)*2*'PARAMÈTRES'!$C$66 -> 144 | H62: ='PARAMÈTRES'!$C$70 -> 0.25 | I62: ='QUANTITATIF_CHARPENTE'!$E$62*'QUANTITATIF_CHARPENTE'!$H$62 -> 36 | J62: Diagonales × 2 extrémités × boulons
B63: Boulons M12 – lisses | C63: ="M12" -> M12 | D63: u | E63: =('QUANTITATIF_CHARPENTE'!$E$48+'QUANTITATIF_CHARPENTE'!$E$49)*2*'PARAMÈTRES'!$C$67 -> 336 | H63: ='PARAMÈTRES'!$C$71 -> 0.1 | I63: ='QUANTITATIF_CHARPENTE'!$E$63*'QUANTITATIF_CHARPENTE'!$H$63 -> 33.6 | J63: Tronçons de lisses × 2 attaches × boulons
B64: Tiges d'ancrage – poteaux de portique | C64: ='PARAMÈTRES'!$C$72 -> Rond 24 | D64: ml | E64: =(2*'PRÉDIMENSIONNEMENT'!$C$29+'PRÉDIMENSIONNEMENT'!$C$38)*'PARAMÈTRES'!$C$74 -> 64 | F64: ='PARAMÈTRES'!$C$73 -> 0.6 | G64: ='QUANTITATIF_CHARPENTE'!$E$64*'QUANTITATIF_CHARPENTE'!$F$64 -> 38.4 | H64: =IFERROR(_xlfn.XLOOKUP('PARAMÈTRES'!$C$72,'BASE_PROFILÉS'!$B$5:$B$200,'BASE_PROFILÉS'!$D$5:$D$200),IFERROR(INDEX('BASE_PROFILÉS'!$D$5:$D$200,MATCH('PARAMÈTRES'!$C$72,'BASE_PROFILÉS'!$B$5:$B$200,0)),0)) -> 3.55 | I64: ='QUANTITATIF_CHARPENTE'!$G$64*'QUANTITATIF_CHARPENTE'!$H$64 -> 136.32 | J64: 4 par poteau de portique
B65: Tiges d'ancrage – poteaux de pignon | C65: ='PARAMÈTRES'!$C$75 -> Rond 20 | D65: ml | E65: ='PRÉDIMENSIONNEMENT'!$C$37*'PARAMÈTRES'!$C$77 -> 12 | F65: ='PARAMÈTRES'!$C$76 -> 0.5 | G65: ='QUANTITATIF_CHARPENTE'!$E$65*'QUANTITATIF_CHARPENTE'!$F$65 -> 6 | H65: =IFERROR(_xlfn.XLOOKUP('PARAMÈTRES'!$C$75,'BASE_PROFILÉS'!$B$5:$B$200,'BASE_PROFILÉS'!$D$5:$D$200),IFERROR(INDEX('BASE_PROFILÉS'!$D$5:$D$200,MATCH('PARAMÈTRES'!$C$75,'BASE_PROFILÉS'!$B$5:$B$200,0)),0)) -> 2.47 | I65: ='QUANTITATIF_CHARPENTE'!$G$65*'QUANTITATIF_CHARPENTE'!$H$65 -> 14.82 | J65: 2 par poteau de pignon
B66: Écrous de tiges d'ancrage | C66: ="Écrou" -> Écrou | D66: u | E66: =2*('QUANTITATIF_CHARPENTE'!$E$64+'QUANTITATIF_CHARPENTE'!$E$65) -> 152 | J66: 2 par tige
B67: Rondelles de tiges d'ancrage | C67: ="Rondelle" -> Rondelle | D67: u | E67: =2*('QUANTITATIF_CHARPENTE'!$E$64+'QUANTITATIF_CHARPENTE'!$E$65) -> 152 | J67: 2 par tige
B68: Gabarits de pose des tiges | C68: ="Gabarit" -> Gabarit | D68: u | E68: =2*'PRÉDIMENSIONNEMENT'!$C$29+'PRÉDIMENSIONNEMENT'!$C$38+'PRÉDIMENSIONNEMENT'!$C$37 -> 22 | J68: 1 par poteau
B69: Vis autoforeuses | C69: ="Vis" -> Vis | D69: u | E69: =ROUNDUP('PARAMÈTRES'!$C$49*('QUANTITATIF_CHARPENTE'!$E$36+'QUANTITATIF_CHARPENTE'!$E$37+'QUANTITATIF_CHARPENTE'!$E$52),0) -> 10093 | J69: ≈ 6 par m² de tôle, translucide et bardage
B71: A6. TOTAUX CHARPENTE
B72: Acier de structure (profilés, platines, pièces) | D72: kg | I72: ='QUANTITATIF_CHARPENTE'!$I$6+'QUANTITATIF_CHARPENTE'!$I$7+'QUANTITATIF_CHARPENTE'!$I$8+'QUANTITATIF_CHARPENTE'!$I$9+'QUANTITATIF_CHARPENTE'!$I$10+'QUANTITATIF_CHARPENTE'!$I$11+'QUANTITATIF_CHARPENTE'!$I$12+'QUANTITATIF_CHARPENTE'!$I$13+'QUANTITATIF_CHARPENTE'!$I$14+'QUANTITATIF_CHARPENTE'!$I$15+'QUANTITATIF_CHARPENTE'!$I$16+'QUANTITATIF_CHARPENTE'!$I$17+'QUANTITATIF_CHARPENTE'!$I$18+'QUANTITATIF_CHARPENTE'!$I$19+'QUANTITATIF_CHARPENTE'!$I$20+'QUANTITATIF_CHARPENTE'!$I$21+'QUANTITATIF_CHARPENTE'!$I$24+'QUANTITATIF_CHARPENTE'!$I$25+'QUANTITATIF_CHARPENTE'!$I$26+'QUANTITATIF_CHARPENTE'!$I$27+'QUANTITATIF_CHARPENTE'!$I$28+'QUANTITATIF_CHARPENTE'!$I$29+'QUANTITATIF_CHARPENTE'!$I$32+'QUANTITATIF_CHARPENTE'!$I$33+'QUANTITATIF_CHARPENTE'!$I$34+'QUANTITATIF_CHARPENTE'!$I$35+'QUANTITATIF_CHARPENTE'!$I$48+'QUANTITATIF_CHARPENTE'!$I$49+'QUANTITATIF_CHARPENTE'!$I$50+'QUANTITATIF_CHARPENTE'!$I$51 -> 24287.697 | J72: Somme des lignes acier A1 à A4
B73: Boulonnerie et tiges d'ancrage (détail) | D73: kg | I73: ='QUANTITATIF_CHARPENTE'!$I$58+'QUANTITATIF_CHARPENTE'!$I$59+'QUANTITATIF_CHARPENTE'!$I$60+'QUANTITATIF_CHARPENTE'!$I$61+'QUANTITATIF_CHARPENTE'!$I$62+'QUANTITATIF_CHARPENTE'!$I$63+'QUANTITATIF_CHARPENTE'!$I$64+'QUANTITATIF_CHARPENTE'!$I$65 -> 357.54 | J73: Somme A5
B74: Boulonnerie retenue | D74: kg | I74: =MAX('QUANTITATIF_CHARPENTE'!$I$73,'PARAMÈTRES'!$C$56*'QUANTITATIF_CHARPENTE'!$I$72) -> 485.75393 | J74: Maximum (détail ; % du tonnage)
B75: Chutes | D75: kg | I75: ='PARAMÈTRES'!$C$55*'QUANTITATIF_CHARPENTE'!$I$72 -> 1214.3848 | J75: % chutes × acier de structure
B76: TONNAGE TOTAL CHARPENTE | D76: kg | I76: ='QUANTITATIF_CHARPENTE'!$I$72+'QUANTITATIF_CHARPENTE'!$I$74+'QUANTITATIF_CHARPENTE'!$I$75 -> 25987.835 | J76: Structure + boulonnerie + chutes
B77: Tonnage total | D77: t | I77: ='QUANTITATIF_CHARPENTE'!$I$76/1000 -> 25.987835
B78: Ratio acier | D78: kg/m² | I78: ='QUANTITATIF_CHARPENTE'!$I$76/'PRÉDIMENSIONNEMENT'!$C$46 -> 32.484794 | J78: Contrôle : 18 à 45 kg/m²
B79: Protection : galvanisation (acier à traiter) | D79: kg | I79: ='QUANTITATIF_CHARPENTE'!$I$72 -> 24287.697 | J79: Acier de structure
B80: Protection : peinture (surface) | D80: m² | I80: ='QUANTITATIF_CHARPENTE'!$I$72/1000*'PARAMÈTRES'!$C$60 -> 607.19242 | J80: t × m²/t

Sheet GROS_ŒUVRE
A1: GROS ŒUVRE ET FONDATIONS (BAEL 91 mod. 99 / EC2)
A2: Sol latéritique : remblai en latérite compactée à 95 % OPM. Ciment CPJ 42.5. Aciers : longueurs avec recouvrement de 40 Ø et barres de 12 m.
B4: Désignation | C4: Profilé / section | D4: Unité | E4: Quantité | F4: Long. unitaire (m) | G4: Long. totale (m) | H4: kg/ml ou kg/u | I4: Poids total (kg) | J4: Règle de calcul (aussi en commentaire)
B5: B0. DONNÉES DE CALCUL
B6: Épaisseur du dallage | D6: m | E6: =VALUE(LEFT('PARAMÈTRES'!$C$114,2))/100 -> 0.2 | J6: Liste 15 / 20 cm
B7: Épaisseur du remblai compacté | D7: m | E7: =VALUE(LEFT('PARAMÈTRES'!$C$86,2))/100 -> 0.2 | J7: Liste 20 / 40 cm
B8: Maille du dallage | D8: m | E8: =VALUE(LEFT('PARAMÈTRES'!$C$120,2))/100 -> 0.2 | J8: Liste 15 / 20 / 25 cm
B9: Nappe double (1 = oui) | E9: =IF('PARAMÈTRES'!$C$115="Nappe double",1,0) -> 0
B10: Semelles isolées 1 (poteaux de portique et file centrale) | D10: u | E10: =2*'PRÉDIMENSIONNEMENT'!$C$29+'PRÉDIMENSIONNEMENT'!$C$38 -> 16
B11: Semelles isolées 2 (poteaux de pignon) | D11: u | E11: ='PRÉDIMENSIONNEMENT'!$C$37 -> 6
B12: Longueur de semelle filante | D12: m | E12: =MAX(0,'PRÉDIMENSIONNEMENT'!$C$47-2*'PRÉDIMENSIONNEMENT'!$C$29*'PARAMÈTRES'!$C$89-'PRÉDIMENSIONNEMENT'!$C$37*'PARAMÈTRES'!$C$92) -> 96 | J12: Périmètre − largeur des semelles isolées traversées
B13: Dallage : longueur intérieure (sens X) | D13: m | E13: ='PARAMÈTRES'!$C$10-'PARAMÈTRES'!$C$85 -> 39.85 | J13: L − épaisseur de mur
B14: Dallage : largeur intérieure (sens Y) | D14: m | E14: ='PARAMÈTRES'!$C$9-'PARAMÈTRES'!$C$85 -> 19.85 | J14: B − épaisseur de mur
B15: Surface intérieure | D15: m² | E15: ='GROS_ŒUVRE'!$E$13*'GROS_ŒUVRE'!$E$14 -> 791.0225
B16: Hauteur de maçonnerie d'élévation | D16: m | E16: ='PRÉDIMENSIONNEMENT'!$C$49 -> 0 | J16: selon type de façade
B17: Nombre de chaînages horizontaux | D17: u | E17: =IF('PRÉDIMENSIONNEMENT'!$C$48="Agglos 15 creux",3,IF('PRÉDIMENSIONNEMENT'!$C$48="Mixte",2,0)) -> 0 | J17: Agglos : bas, intermédiaire, haut · Mixte : bas et haut
B18: Panneaux de maçonnerie (travées du périmètre) | D18: u | E18: ='PRÉDIMENSIONNEMENT'!$C$51*(2*'PRÉDIMENSIONNEMENT'!$C$28+2*'PRÉDIMENSIONNEMENT'!$C$35) -> 0
B19: Coût matériaux d'1 m³ de béton armé | D19: FCFA/m³ | E19: ='PARAMÈTRES'!$C$143/'PARAMÈTRES'!$C$145*'PARAMÈTRES'!$C$185+'PARAMÈTRES'!$C$146*'PARAMÈTRES'!$C$186+'PARAMÈTRES'!$C$147*'PARAMÈTRES'!$C$187+'PARAMÈTRES'!$C$148*'PARAMÈTRES'!$C$188 -> 59900
B20: Coût matériaux d'1 m³ de mortier | D20: FCFA/m³ | E20: ='PARAMÈTRES'!$C$144/'PARAMÈTRES'!$C$145*'PARAMÈTRES'!$C$185+'PARAMÈTRES'!$C$149*'PARAMÈTRES'!$C$186 -> 46200
B22: B1. TERRASSEMENTS
B23: Décapage de l'emprise | D23: m² | E23: =('PARAMÈTRES'!$C$9+2*'PARAMÈTRES'!$C$81)*('PARAMÈTRES'!$C$10+2*'PARAMÈTRES'!$C$81) -> 924 | J23: (B + 2 débords) × (L + 2 débords)
B24: Fouilles en puits – semelles isolées 1 | D24: m³ | E24: ='GROS_ŒUVRE'!$E$10*('PARAMÈTRES'!$C$89+2*'PARAMÈTRES'!$C$82)^2*'PARAMÈTRES'!$C$83 -> 37.632 | J24: n × (a + 2 surlargeurs)² × profondeur 1,20 m
B25: Fouilles en puits – semelles isolées 2 | D25: m³ | E25: ='GROS_ŒUVRE'!$E$11*('PARAMÈTRES'!$C$92+2*'PARAMÈTRES'!$C$82)^2*'PARAMÈTRES'!$C$83 -> 7.2 | J25: n × (a + 2 surlargeurs)² × profondeur
B26: Fouilles en rigole – semelles filantes | D26: m³ | E26: ='GROS_ŒUVRE'!$E$12*('PARAMÈTRES'!$C$102+2*'PARAMÈTRES'!$C$82)*'PARAMÈTRES'!$C$83 -> 92.16 | J26: Longueur filante × (b + 2 surlargeurs) × profondeur
B27: Remblai latérite compactée sous dallage (approvisionnement) | D27: m³ | E27: ='GROS_ŒUVRE'!$E$15*'GROS_ŒUVRE'!$E$7*'PARAMÈTRES'!$C$84 -> 197.75563 | J27: Surface intérieure × épaisseur × foisonnement 1,25 (95 % OPM)
B28: Lit de sable de réglage (nid de sable) | D28: m³ | E28: ='GROS_ŒUVRE'!$E$15*'PARAMÈTRES'!$C$87 -> 39.551125 | J28: Surface × 5 cm
B29: Évacuation des déblais | D29: m³ | E29: =('GROS_ŒUVRE'!$E$23*'PARAMÈTRES'!$C$80+'GROS_ŒUVRE'!$E$24+'GROS_ŒUVRE'!$E$25+'GROS_ŒUVRE'!$E$26)*'PARAMÈTRES'!$C$84 -> 402.24 | J29: (décapage + fouilles) × foisonnement
B31: B2. SEMELLES ISOLÉES – POTEAUX DE PORTIQUE (120 × 120)
B32: Béton de propreté (5 cm) | D32: m³ | E32: ='GROS_ŒUVRE'!$E$10*'PARAMÈTRES'!$C$89^2*'PARAMÈTRES'!$C$88 -> 1.152 | J32: n × a² × 5 cm
B33: Béton armé – semelles | D33: m³ | E33: ='GROS_ŒUVRE'!$E$10*'PARAMÈTRES'!$C$89^2*'PARAMÈTRES'!$C$90 -> 9.216 | J33: n × a² × h
B34: Béton armé – fûts (amorces) | D34: m³ | E34: ='GROS_ŒUVRE'!$E$10*'PARAMÈTRES'!$C$91^2*'PARAMÈTRES'!$C$95 -> 3.072 | J34: n × côté² × hauteur du fût (1,20 m)
B35: Coffrage semelles et fûts | D35: m² | E35: ='GROS_ŒUVRE'!$E$10*(4*'PARAMÈTRES'!$C$89*'PARAMÈTRES'!$C$90+4*'PARAMÈTRES'!$C$91*'PARAMÈTRES'!$C$95) -> 61.44 | J35: n × (4 a h + 4 côté × h fût)
B36: Aciers – quadrillage inférieur | C36: ='PARAMÈTRES'!$C$97 -> HA12 | D36: barres | E36: ='GROS_ŒUVRE'!$E$10*2*(ROUNDDOWN(('PARAMÈTRES'!$C$89-2*'PARAMÈTRES'!$C$108)/'PARAMÈTRES'!$C$96,0)+1) -> 256 | F36: ='PARAMÈTRES'!$C$89-2*'PARAMÈTRES'!$C$108+2*'PARAMÈTRES'!$C$109 -> 1.4 | G36: ='GROS_ŒUVRE'!$E$36*'GROS_ŒUVRE'!$F$36 -> 358.4 | H36: =IFERROR(_xlfn.XLOOKUP('PARAMÈTRES'!$C$97,'BASE_ACIERS'!$B$5:$B$20,'BASE_ACIERS'!$D$5:$D$20),IFERROR(INDEX('BASE_ACIERS'!$D$5:$D$20,MATCH('PARAMÈTRES'!$C$97,'BASE_ACIERS'!$B$5:$B$20,0)),0)) -> 0.888 | I36: ='GROS_ŒUVRE'!$G$36*'GROS_ŒUVRE'!$H$36 -> 318.2592 | J36: 2 sens × (ENT((a − 2c) / maille) + 1) barres ; L = a − 2c + 2 retours
B37: Aciers – fûts (barres longitudinales) | C37: ='PARAMÈTRES'!$C$98 -> HA12 | D37: barres | E37: ='GROS_ŒUVRE'!$E$10*'PARAMÈTRES'!$C$99 -> 64 | F37: ='PARAMÈTRES'!$C$95+'PARAMÈTRES'!$C$90-'PARAMÈTRES'!$C$108+'PARAMÈTRES'!$C$109 -> 1.7 | G37: ='GROS_ŒUVRE'!$E$37*'GROS_ŒUVRE'!$F$37 -> 108.8 | H37: =IFERROR(_xlfn.XLOOKUP('PARAMÈTRES'!$C$98,'BASE_ACIERS'!$B$5:$B$20,'BASE_ACIERS'!$D$5:$D$20),IFERROR(INDEX('BASE_ACIERS'!$D$5:$D$20,MATCH('PARAMÈTRES'!$C$98,'BASE_ACIERS'!$B$5:$B$20,0)),0)) -> 0.888 | I37: ='GROS_ŒUVRE'!$G$37*'GROS_ŒUVRE'!$H$37 -> 96.6144 | J37: 4 barres par fût, ancrées dans la semelle
B38: Aciers – cadres des fûts | C38: ='PARAMÈTRES'!$C$100 -> HA6 | D38: barres | E38: ='GROS_ŒUVRE'!$E$10*(ROUNDDOWN('PARAMÈTRES'!$C$95/'PARAMÈTRES'!$C$101,0)+1) -> 144 | F38: =4*('PARAMÈTRES'!$C$91-2*'PARAMÈTRES'!$C$108)+2*'PARAMÈTRES'!$C$110 -> 1.4 | G38: ='GROS_ŒUVRE'!$E$38*'GROS_ŒUVRE'!$F$38 -> 201.6 | H38: =IFERROR(_xlfn.XLOOKUP('PARAMÈTRES'!$C$100,'BASE_ACIERS'!$B$5:$B$20,'BASE_ACIERS'!$D$5:$D$20),IFERROR(INDEX('BASE_ACIERS'!$D$5:$D$20,MATCH('PARAMÈTRES'!$C$100,'BASE_ACIERS'!$B$5:$B$20,0)),0)) -> 0.222 | I38: ='GROS_ŒUVRE'!$G$38*'GROS_ŒUVRE'!$H$38 -> 44.7552 | J38: Cadres tous les 15 cm
B40: B3. SEMELLES ISOLÉES – POTEAUX DE PIGNON (80 × 80)
B41: Béton de propreté (5 cm) | D41: m³ | E41: ='GROS_ŒUVRE'!$E$11*'PARAMÈTRES'!$C$92^2*'PARAMÈTRES'!$C$88 -> 0.192 | J41: n × a² × 5 cm
B42: Béton armé – semelles | D42: m³ | E42: ='GROS_ŒUVRE'!$E$11*'PARAMÈTRES'!$C$92^2*'PARAMÈTRES'!$C$93 -> 1.152 | J42: n × a² × h
B43: Béton armé – fûts (amorces) | D43: m³ | E43: ='GROS_ŒUVRE'!$E$11*'PARAMÈTRES'!$C$94^2*'PARAMÈTRES'!$C$95 -> 0.648 | J43: n × côté² × hauteur du fût (1,20 m)
B44: Coffrage semelles et fûts | D44: m² | E44: ='GROS_ŒUVRE'!$E$11*(4*'PARAMÈTRES'!$C$92*'PARAMÈTRES'!$C$93+4*'PARAMÈTRES'!$C$94*'PARAMÈTRES'!$C$95) -> 14.4 | J44: n × (4 a h + 4 côté × h fût)
B45: Aciers – quadrillage inférieur | C45: ='PARAMÈTRES'!$C$97 -> HA12 | D45: barres | E45: ='GROS_ŒUVRE'!$E$11*2*(ROUNDDOWN(('PARAMÈTRES'!$C$92-2*'PARAMÈTRES'!$C$108)/'PARAMÈTRES'!$C$96,0)+1) -> 60 | F45: ='PARAMÈTRES'!$C$92-2*'PARAMÈTRES'!$C$108+2*'PARAMÈTRES'!$C$109 -> 1 | G45: ='GROS_ŒUVRE'!$E$45*'GROS_ŒUVRE'!$F$45 -> 60 | H45: =IFERROR(_xlfn.XLOOKUP('PARAMÈTRES'!$C$97,'BASE_ACIERS'!$B$5:$B$20,'BASE_ACIERS'!$D$5:$D$20),IFERROR(INDEX('BASE_ACIERS'!$D$5:$D$20,MATCH('PARAMÈTRES'!$C$97,'BASE_ACIERS'!$B$5:$B$20,0)),0)) -> 0.888 | I45: ='GROS_ŒUVRE'!$G$45*'GROS_ŒUVRE'!$H$45 -> 53.28 | J45: 2 sens × (ENT((a − 2c) / maille) + 1) barres ; L = a − 2c + 2 retours
B46: Aciers – fûts (barres longitudinales) | C46: ='PARAMÈTRES'!$C$98 -> HA12 | D46: barres | E46: ='GROS_ŒUVRE'!$E$11*'PARAMÈTRES'!$C$99 -> 24 | F46: ='PARAMÈTRES'!$C$95+'PARAMÈTRES'!$C$93-'PARAMÈTRES'!$C$108+'PARAMÈTRES'!$C$109 -> 1.6 | G46: ='GROS_ŒUVRE'!$E$46*'GROS_ŒUVRE'!$F$46 -> 38.4 | H46: =IFERROR(_xlfn.XLOOKUP('PARAMÈTRES'!$C$98,'BASE_ACIERS'!$B$5:$B$20,'BASE_ACIERS'!$D$5:$D$20),IFERROR(INDEX('BASE_ACIERS'!$D$5:$D$20,MATCH('PARAMÈTRES'!$C$98,'BASE_ACIERS'!$B$5:$B$20,0)),0)) -> 0.888 | I46: ='GROS_ŒUVRE'!$G$46*'GROS_ŒUVRE'!$H$46 -> 34.0992 | J46: 4 barres par fût, ancrées dans la semelle
B47: Aciers – cadres des fûts | C47: ='PARAMÈTRES'!$C$100 -> HA6 | D47: barres | E47: ='GROS_ŒUVRE'!$E$11*(ROUNDDOWN('PARAMÈTRES'!$C$95/'PARAMÈTRES'!$C$101,0)+1) -> 54 | F47: =4*('PARAMÈTRES'!$C$94-2*'PARAMÈTRES'!$C$108)+2*'PARAMÈTRES'!$C$110 -> 1 | G47: ='GROS_ŒUVRE'!$E$47*'GROS_ŒUVRE'!$F$47 -> 54 | H47: =IFERROR(_xlfn.XLOOKUP('PARAMÈTRES'!$C$100,'BASE_ACIERS'!$B$5:$B$20,'BASE_ACIERS'!$D$5:$D$20),IFERROR(INDEX('BASE_ACIERS'!$D$5:$D$20,MATCH('PARAMÈTRES'!$C$100,'BASE_ACIERS'!$B$5:$B$20,0)),0)) -> 0.222 | I47: ='GROS_ŒUVRE'!$G$47*'GROS_ŒUVRE'!$H$47 -> 11.988 | J47: Cadres tous les 15 cm
B49: B4. SEMELLES FILANTES (SOUS MURS)
B50: Béton de propreté (5 cm) | D50: m³ | E50: ='GROS_ŒUVRE'!$E$12*'PARAMÈTRES'!$C$102*'PARAMÈTRES'!$C$88 -> 2.88 | J50: L × b × 5 cm
B51: Béton armé – semelle filante 60 × 20 | D51: m³ | E51: ='GROS_ŒUVRE'!$E$12*'PARAMÈTRES'!$C$102*'PARAMÈTRES'!$C$103 -> 11.52 | J51: L × b × h
B52: Coffrage semelle filante | D52: m² | E52: =2*'GROS_ŒUVRE'!$E$12*'PARAMÈTRES'!$C$103 -> 38.4 | J52: 2 faces × L × h
B53: Aciers filants (4 HA10) | C53: ='PARAMÈTRES'!$C$104 -> HA10 | D53: barres | E53: ='PARAMÈTRES'!$C$105 -> 4 | F53: =('GROS_ŒUVRE'!$E$12+MAX(0,ROUNDUP(('GROS_ŒUVRE'!$E$12)/'PARAMÈTRES'!$C$58,0)-1)*'PARAMÈTRES'!$C$153*IFERROR(_xlfn.XLOOKUP('PARAMÈTRES'!$C$104,'BASE_ACIERS'!$B$5:$B$20,'BASE_ACIERS'!$C$5:$C$20),IFERROR(INDEX('BASE_ACIERS'!$C$5:$C$20,MATCH('PARAMÈTRES'!$C$104,'BASE_ACIERS'!$B$5:$B$20,0)),0))/1000) -> 98.8 | G53: ='GROS_ŒUVRE'!$E$53*'GROS_ŒUVRE'!$F$53 -> 395.2 | H53: =IFERROR(_xlfn.XLOOKUP('PARAMÈTRES'!$C$104,'BASE_ACIERS'!$B$5:$B$20,'BASE_ACIERS'!$D$5:$D$20),IFERROR(INDEX('BASE_ACIERS'!$D$5:$D$20,MATCH('PARAMÈTRES'!$C$104,'BASE_ACIERS'!$B$5:$B$20,0)),0)) -> 0.617 | I53: ='GROS_ŒUVRE'!$G$53*'GROS_ŒUVRE'!$H$53 -> 243.8384 | J53: 4 filants × longueur avec recouvrements de 40 Ø
B54: Aciers de répartition (HA8 e = 20 cm) | C54: ='PARAMÈTRES'!$C$106 -> HA8 | D54: barres | E54: =ROUNDDOWN('GROS_ŒUVRE'!$E$12/'PARAMÈTRES'!$C$107,0)+1 -> 481 | F54: ='PARAMÈTRES'!$C$102-2*'PARAMÈTRES'!$C$108 -> 0.5 | G54: ='GROS_ŒUVRE'!$E$54*'GROS_ŒUVRE'!$F$54 -> 240.5 | H54: =IFERROR(_xlfn.XLOOKUP('PARAMÈTRES'!$C$106,'BASE_ACIERS'!$B$5:$B$20,'BASE_ACIERS'!$D$5:$D$20),IFERROR(INDEX('BASE_ACIERS'!$D$5:$D$20,MATCH('PARAMÈTRES'!$C$106,'BASE_ACIERS'!$B$5:$B$20,0)),0)) -> 0.395 | I54: ='GROS_ŒUVRE'!$G$54*'GROS_ŒUVRE'!$H$54 -> 94.9975 | J54: L / espacement + 1 ; L = b − 2c
B56: B5. MAÇONNERIE DE FONDATION (AGGLOS 15 PLEINS)
B57: Maçonnerie agglos 15 pleins (h = 1,00 m) | D57: m² | E57: ='PRÉDIMENSIONNEMENT'!$C$47*'PARAMÈTRES'!$C$111 -> 120 | J57: Périmètre × 1,00 m
B58: Agglos 15 pleins | D58: u | E58: =ROUNDUP('GROS_ŒUVRE'!$E$57*'PARAMÈTRES'!$C$151*(1+'PARAMÈTRES'!$C$152),0) -> 1575 | J58: 12,5 /m² + 5 % de casse
B59: Mortier de pose | D59: m³ | E59: ='GROS_ŒUVRE'!$E$57*'PARAMÈTRES'!$C$150 -> 1.8 | J59: m² × mortier / m²
B61: B6. DALLAGE INTÉRIEUR
B62: Film polyane | D62: m² | E62: ='GROS_ŒUVRE'!$E$15*(1+'PARAMÈTRES'!$C$126) -> 870.12475 | J62: Surface intérieure × 1,10
B63: Béton du dallage | D63: m³ | E63: ='GROS_ŒUVRE'!$E$15*'GROS_ŒUVRE'!$E$6 -> 158.2045 | J63: Surface × épaisseur (15 ou 20 cm)
B64: Nappe inférieure – sens X | C64: ='PARAMÈTRES'!$C$116 -> HA10 | D64: barres | E64: =ROUNDDOWN('GROS_ŒUVRE'!$E$14/'GROS_ŒUVRE'!$E$8,0)+1 -> 100 | F64: =('GROS_ŒUVRE'!$E$13-2*'PARAMÈTRES'!$C$121+MAX(0,ROUNDUP(('GROS_ŒUVRE'!$E$13-2*'PARAMÈTRES'!$C$121)/'PARAMÈTRES'!$C$58,0)-1)*'PARAMÈTRES'!$C$153*IFERROR(_xlfn.XLOOKUP('PARAMÈTRES'!$C$116,'BASE_ACIERS'!$B$5:$B$20,'BASE_ACIERS'!$C$5:$C$20),IFERROR(INDEX('BASE_ACIERS'!$C$5:$C$20,MATCH('PARAMÈTRES'!$C$116,'BASE_ACIERS'!$B$5:$B$20,0)),0))/1000) -> 40.99 | G64: ='GROS_ŒUVRE'!$E$64*'GROS_ŒUVRE'!$F$64 -> 4099 | H64: =IFERROR(_xlfn.XLOOKUP('PARAMÈTRES'!$C$116,'BASE_ACIERS'!$B$5:$B$20,'BASE_ACIERS'!$D$5:$D$20),IFERROR(INDEX('BASE_ACIERS'!$D$5:$D$20,MATCH('PARAMÈTRES'!$C$116,'BASE_ACIERS'!$B$5:$B$20,0)),0)) -> 0.617 | I64: ='GROS_ŒUVRE'!$G$64*'GROS_ŒUVRE'!$H$64 -> 2529.083 | J64: (côté / maille) + 1 barres ; L avec recouvrements 40 Ø
B65: Nappe inférieure – sens Y | C65: ='PARAMÈTRES'!$C$117 -> HA10 | D65: barres | E65: =ROUNDDOWN('GROS_ŒUVRE'!$E$13/'GROS_ŒUVRE'!$E$8,0)+1 -> 200 | F65: =('GROS_ŒUVRE'!$E$14-2*'PARAMÈTRES'!$C$121+MAX(0,ROUNDUP(('GROS_ŒUVRE'!$E$14-2*'PARAMÈTRES'!$C$121)/'PARAMÈTRES'!$C$58,0)-1)*'PARAMÈTRES'!$C$153*IFERROR(_xlfn.XLOOKUP('PARAMÈTRES'!$C$117,'BASE_ACIERS'!$B$5:$B$20,'BASE_ACIERS'!$C$5:$C$20),IFERROR(INDEX('BASE_ACIERS'!$C$5:$C$20,MATCH('PARAMÈTRES'!$C$117,'BASE_ACIERS'!$B$5:$B$20,0)),0))/1000) -> 20.19 | G65: ='GROS_ŒUVRE'!$E$65*'GROS_ŒUVRE'!$F$65 -> 4038 | H65: =IFERROR(_xlfn.XLOOKUP('PARAMÈTRES'!$C$117,'BASE_ACIERS'!$B$5:$B$20,'BASE_ACIERS'!$D$5:$D$20),IFERROR(INDEX('BASE_ACIERS'!$D$5:$D$20,MATCH('PARAMÈTRES'!$C$117,'BASE_ACIERS'!$B$5:$B$20,0)),0)) -> 0.617 | I65: ='GROS_ŒUVRE'!$G$65*'GROS_ŒUVRE'!$H$65 -> 2491.446 | J65: (côté / maille) + 1 barres
B66: Nappe supérieure – sens X (si nappe double) | C66: ='PARAMÈTRES'!$C$118 -> HA8 | D66: barres | E66: ='GROS_ŒUVRE'!$E$9*(ROUNDDOWN('GROS_ŒUVRE'!$E$14/'GROS_ŒUVRE'!$E$8,0)+1) -> 0 | F66: =('GROS_ŒUVRE'!$E$13-2*'PARAMÈTRES'!$C$121+MAX(0,ROUNDUP(('GROS_ŒUVRE'!$E$13-2*'PARAMÈTRES'!$C$121)/'PARAMÈTRES'!$C$58,0)-1)*'PARAMÈTRES'!$C$153*IFERROR(_xlfn.XLOOKUP('PARAMÈTRES'!$C$118,'BASE_ACIERS'!$B$5:$B$20,'BASE_ACIERS'!$C$5:$C$20),IFERROR(INDEX('BASE_ACIERS'!$C$5:$C$20,MATCH('PARAMÈTRES'!$C$118,'BASE_ACIERS'!$B$5:$B$20,0)),0))/1000) -> 40.75 | G66: ='GROS_ŒUVRE'!$E$66*'GROS_ŒUVRE'!$F$66 -> 0 | H66: =IFERROR(_xlfn.XLOOKUP('PARAMÈTRES'!$C$118,'BASE_ACIERS'!$B$5:$B$20,'BASE_ACIERS'!$D$5:$D$20),IFERROR(INDEX('BASE_ACIERS'!$D$5:$D$20,MATCH('PARAMÈTRES'!$C$118,'BASE_ACIERS'!$B$5:$B$20,0)),0)) -> 0.395 | I66: ='GROS_ŒUVRE'!$G$66*'GROS_ŒUVRE'!$H$66 -> 0 | J66: 0 en nappe simple
B67: Nappe supérieure – sens Y (si nappe double) | C67: ='PARAMÈTRES'!$C$119 -> HA8 | D67: barres | E67: ='GROS_ŒUVRE'!$E$9*(ROUNDDOWN('GROS_ŒUVRE'!$E$13/'GROS_ŒUVRE'!$E$8,0)+1) -> 0 | F67: =('GROS_ŒUVRE'!$E$14-2*'PARAMÈTRES'!$C$121+MAX(0,ROUNDUP(('GROS_ŒUVRE'!$E$14-2*'PARAMÈTRES'!$C$121)/'PARAMÈTRES'!$C$58,0)-1)*'PARAMÈTRES'!$C$153*IFERROR(_xlfn.XLOOKUP('PARAMÈTRES'!$C$119,'BASE_ACIERS'!$B$5:$B$20,'BASE_ACIERS'!$C$5:$C$20),IFERROR(INDEX('BASE_ACIERS'!$C$5:$C$20,MATCH('PARAMÈTRES'!$C$119,'BASE_ACIERS'!$B$5:$B$20,0)),0))/1000) -> 20.11 | G67: ='GROS_ŒUVRE'!$E$67*'GROS_ŒUVRE'!$F$67 -> 0 | H67: =IFERROR(_xlfn.XLOOKUP('PARAMÈTRES'!$C$119,'BASE_ACIERS'!$B$5:$B$20,'BASE_ACIERS'!$D$5:$D$20),IFERROR(INDEX('BASE_ACIERS'!$D$5:$D$20,MATCH('PARAMÈTRES'!$C$119,'BASE_ACIERS'!$B$5:$B$20,0)),0)) -> 0.395 | I67: ='GROS_ŒUVRE'!$G$67*'GROS_ŒUVRE'!$H$67 -> 0 | J67: 0 en nappe simple
B68: Chaises (nappe double, 4 /m²) | C68: ='PARAMÈTRES'!$C$122 -> HA8 | D68: barres | E68: ='GROS_ŒUVRE'!$E$9*ROUNDUP('PARAMÈTRES'!$C$123*'GROS_ŒUVRE'!$E$15,0) -> 0 | F68: ='PARAMÈTRES'!$C$124 -> 0.6 | G68: ='GROS_ŒUVRE'!$E$68*'GROS_ŒUVRE'!$F$68 -> 0 | H68: =IFERROR(_xlfn.XLOOKUP('PARAMÈTRES'!$C$122,'BASE_ACIERS'!$B$5:$B$20,'BASE_ACIERS'!$D$5:$D$20),IFERROR(INDEX('BASE_ACIERS'!$D$5:$D$20,MATCH('PARAMÈTRES'!$C$122,'BASE_ACIERS'!$B$5:$B$20,0)),0)) -> 0.395 | I68: ='GROS_ŒUVRE'!$G$68*'GROS_ŒUVRE'!$H$68 -> 0 | J68: 4 chaises / m² en nappe double
B69: Joints de retrait sciés | D69: ml | E69: =(ROUNDUP('GROS_ŒUVRE'!$E$13/'PARAMÈTRES'!$C$125,0)-1)*'GROS_ŒUVRE'!$E$14+(ROUNDUP('GROS_ŒUVRE'!$E$14/'PARAMÈTRES'!$C$125,0)-1)*'GROS_ŒUVRE'!$E$13 -> 258.5 | J69: Tous les 5 à 6 m dans les 2 sens
B70: Cure du béton | D70: m² | E70: ='GROS_ŒUVRE'!$E$15 -> 791.0225 | J70: Surface du dallage
B72: B7. VARIANTE ÉLÉVATION EN AGGLOS 15 CREUX (selon type de façade)
B73: Surface des murs (− ouvertures, pignons en trapèze) | D73: m² | E73: =MAX(0,'PRÉDIMENSIONNEMENT'!$C$51*('PRÉDIMENSIONNEMENT'!$C$47*'GROS_ŒUVRE'!$E$16+IF('PRÉDIMENSIONNEMENT'!$C$48="Agglos 15 creux",2*'PARAMÈTRES'!$C$12*'PARAMÈTRES'!$C$9^2/4,0))-'PRÉDIMENSIONNEMENT'!$C$58) -> 0 | J73: Périmètre × hauteur + pignons (agglos) − ouvertures
B74: Agglos 15 creux | D74: u | E74: =ROUNDUP('GROS_ŒUVRE'!$E$73*'PARAMÈTRES'!$C$151*(1+'PARAMÈTRES'!$C$152),0) -> 0 | J74: 12,5 /m² + 5 % de casse
B75: Mortier de pose | D75: m³ | E75: ='GROS_ŒUVRE'!$E$73*'PARAMÈTRES'!$C$150 -> 0 | J75: m² × mortier / m²
B76: Chaînages 15 × 20 (bas, intermédiaire, haut + rampants) | D76: ml | E76: ='GROS_ŒUVRE'!$E$17*'PRÉDIMENSIONNEMENT'!$C$47+IF('PRÉDIMENSIONNEMENT'!$C$48="Agglos 15 creux",4*'PRÉDIMENSIONNEMENT'!$C$31,0) -> 0 | J76: Nombre de chaînages × périmètre (+ rampants des pignons)
B77: Béton des chaînages | D77: m³ | E77: ='GROS_ŒUVRE'!$E$76*'PARAMÈTRES'!$C$129*'PARAMÈTRES'!$C$130 -> 0 | J77: ml × 0,15 × 0,20
B78: Coffrage des chaînages | D78: m² | E78: ='GROS_ŒUVRE'!$E$76*2*'PARAMÈTRES'!$C$130 -> 0 | J78: 2 faces
B79: Chaînages – aciers longitudinaux (4 HA10) | C79: ='PARAMÈTRES'!$C$131 -> HA10 | D79: barres | E79: ='PARAMÈTRES'!$C$132 -> 4 | F79: ='GROS_ŒUVRE'!$E$76*(1+'PARAMÈTRES'!$C$153*IFERROR(_xlfn.XLOOKUP('PARAMÈTRES'!$C$131,'BASE_ACIERS'!$B$5:$B$20,'BASE_ACIERS'!$C$5:$C$20),IFERROR(INDEX('BASE_ACIERS'!$C$5:$C$20,MATCH('PARAMÈTRES'!$C$131,'BASE_ACIERS'!$B$5:$B$20,0)),0))/1000/'PARAMÈTRES'!$C$58) -> 0 | G79: ='GROS_ŒUVRE'!$E$79*'GROS_ŒUVRE'!$F$79 -> 0 | H79: =IFERROR(_xlfn.XLOOKUP('PARAMÈTRES'!$C$131,'BASE_ACIERS'!$B$5:$B$20,'BASE_ACIERS'!$D$5:$D$20),IFERROR(INDEX('BASE_ACIERS'!$D$5:$D$20,MATCH('PARAMÈTRES'!$C$131,'BASE_ACIERS'!$B$5:$B$20,0)),0)) -> 0.617 | I79: ='GROS_ŒUVRE'!$G$79*'GROS_ŒUVRE'!$H$79 -> 0 | J79: 4 barres × ml × (1 + 40 Ø / 12 m)
B80: Chaînages – cadres HA6 e = 20 cm | C80: ='PARAMÈTRES'!$C$133 -> HA6 | D80: barres | E80: =ROUNDDOWN('GROS_ŒUVRE'!$E$76/'PARAMÈTRES'!$C$134,0)+'GROS_ŒUVRE'!$E$17 -> 0 | F80: =2*('PARAMÈTRES'!$C$129+'PARAMÈTRES'!$C$130)-8*'PARAMÈTRES'!$C$108+2*'PARAMÈTRES'!$C$110 -> 0.5 | G80: ='GROS_ŒUVRE'!$E$80*'GROS_ŒUVRE'!$F$80 -> 0 | H80: =IFERROR(_xlfn.XLOOKUP('PARAMÈTRES'!$C$133,'BASE_ACIERS'!$B$5:$B$20,'BASE_ACIERS'!$D$5:$D$20),IFERROR(INDEX('BASE_ACIERS'!$D$5:$D$20,MATCH('PARAMÈTRES'!$C$133,'BASE_ACIERS'!$B$5:$B$20,0)),0)) -> 0.222 | I80: ='GROS_ŒUVRE'!$G$80*'GROS_ŒUVRE'!$H$80 -> 0 | J80: ml / 0,20 + 1 par chaînage
B81: Poteaux raidisseurs 15 × 15 (3 par panneau) | D81: u | E81: ='PARAMÈTRES'!$C$136*'GROS_ŒUVRE'!$E$18 -> 0 | J81: 3 × nombre de travées sur le périmètre
B82: Béton des raidisseurs | D82: m³ | E82: ='GROS_ŒUVRE'!$E$81*'PARAMÈTRES'!$C$135^2*'GROS_ŒUVRE'!$E$16 -> 0 | J82: n × 0,15² × hauteur du mur
B83: Coffrage des raidisseurs | D83: m² | E83: ='GROS_ŒUVRE'!$E$81*2*'PARAMÈTRES'!$C$135*'GROS_ŒUVRE'!$E$16 -> 0 | J83: 2 faces coffrées
B84: Raidisseurs – aciers (4 HA10) | C84: ='PARAMÈTRES'!$C$131 -> HA10 | D84: barres | E84: ='GROS_ŒUVRE'!$E$81*'PARAMÈTRES'!$C$132 -> 0 | F84: ='GROS_ŒUVRE'!$E$16+2*'PARAMÈTRES'!$C$109 -> 0.3 | G84: ='GROS_ŒUVRE'!$E$84*'GROS_ŒUVRE'!$F$84 -> 0 | H84: =IFERROR(_xlfn.XLOOKUP('PARAMÈTRES'!$C$131,'BASE_ACIERS'!$B$5:$B$20,'BASE_ACIERS'!$D$5:$D$20),IFERROR(INDEX('BASE_ACIERS'!$D$5:$D$20,MATCH('PARAMÈTRES'!$C$131,'BASE_ACIERS'!$B$5:$B$20,0)),0)) -> 0.617 | I84: ='GROS_ŒUVRE'!$G$84*'GROS_ŒUVRE'!$H$84 -> 0 | J84: 4 barres × (hauteur + 2 retours)
B85: Raidisseurs – cadres HA6 e = 20 cm | C85: ='PARAMÈTRES'!$C$133 -> HA6 | D85: barres | E85: ='GROS_ŒUVRE'!$E$81*(ROUNDDOWN('GROS_ŒUVRE'!$E$16/'PARAMÈTRES'!$C$134,0)+1) -> 0 | F85: =4*'PARAMÈTRES'!$C$135-8*'PARAMÈTRES'!$C$108+2*'PARAMÈTRES'!$C$110 -> 0.4 | G85: ='GROS_ŒUVRE'!$E$85*'GROS_ŒUVRE'!$F$85 -> 0 | H85: =IFERROR(_xlfn.XLOOKUP('PARAMÈTRES'!$C$133,'BASE_ACIERS'!$B$5:$B$20,'BASE_ACIERS'!$D$5:$D$20),IFERROR(INDEX('BASE_ACIERS'!$D$5:$D$20,MATCH('PARAMÈTRES'!$C$133,'BASE_ACIERS'!$B$5:$B$20,0)),0)) -> 0.222 | I85: ='GROS_ŒUVRE'!$G$85*'GROS_ŒUVRE'!$H$85 -> 0 | J85: hauteur / 0,20 + 1 par raidisseur
B86: Linteaux BA au-dessus des baies (appuis 20 cm) | D86: ml | E86: ='PRÉDIMENSIONNEMENT'!$C$51*(IF('PARAMÈTRES'!$C$30<'GROS_ŒUVRE'!$E$16,'PARAMÈTRES'!$C$28*('PARAMÈTRES'!$C$29+2*'PARAMÈTRES'!$C$137),0)+IF('PARAMÈTRES'!$C$34<'GROS_ŒUVRE'!$E$16,'PARAMÈTRES'!$C$32*('PARAMÈTRES'!$C$33+2*'PARAMÈTRES'!$C$137),0)) -> 0 | J86: Baies dans la maçonnerie : largeur + 2 × 0,20 m
B87: Béton des linteaux | D87: m³ | E87: ='GROS_ŒUVRE'!$E$86*'PARAMÈTRES'!$C$129*'PARAMÈTRES'!$C$130 -> 0 | J87: ml × 0,15 × 0,20
B88: Coffrage des linteaux | D88: m² | E88: ='GROS_ŒUVRE'!$E$86*(2*'PARAMÈTRES'!$C$130+'PARAMÈTRES'!$C$129) -> 0 | J88: 2 joues + fond
B89: Linteaux – aciers (4 HA10) | C89: ='PARAMÈTRES'!$C$131 -> HA10 | D89: barres | E89: ='PARAMÈTRES'!$C$132 -> 4 | F89: ='GROS_ŒUVRE'!$E$86 -> 0 | G89: ='GROS_ŒUVRE'!$E$89*'GROS_ŒUVRE'!$F$89 -> 0 | H89: =IFERROR(_xlfn.XLOOKUP('PARAMÈTRES'!$C$131,'BASE_ACIERS'!$B$5:$B$20,'BASE_ACIERS'!$D$5:$D$20),IFERROR(INDEX('BASE_ACIERS'!$D$5:$D$20,MATCH('PARAMÈTRES'!$C$131,'BASE_ACIERS'!$B$5:$B$20,0)),0)) -> 0.617 | I89: ='GROS_ŒUVRE'!$G$89*'GROS_ŒUVRE'!$H$89 -> 0 | J89: 4 barres × ml
B90: Linteaux – cadres HA6 | C90: ='PARAMÈTRES'!$C$133 -> HA6 | D90: barres | E90: =ROUNDDOWN('GROS_ŒUVRE'!$E$86/'PARAMÈTRES'!$C$134,0) -> 0 | F90: =2*('PARAMÈTRES'!$C$129+'PARAMÈTRES'!$C$130)-8*'PARAMÈTRES'!$C$108+2*'PARAMÈTRES'!$C$110 -> 0.5 | G90: ='GROS_ŒUVRE'!$E$90*'GROS_ŒUVRE'!$F$90 -> 0 | H90: =IFERROR(_xlfn.XLOOKUP('PARAMÈTRES'!$C$133,'BASE_ACIERS'!$B$5:$B$20,'BASE_ACIERS'!$D$5:$D$20),IFERROR(INDEX('BASE_ACIERS'!$D$5:$D$20,MATCH('PARAMÈTRES'!$C$133,'BASE_ACIERS'!$B$5:$B$20,0)),0)) -> 0.222 | I90: ='GROS_ŒUVRE'!$G$90*'GROS_ŒUVRE'!$H$90 -> 0 | J90: ml / 0,20
B91: Enduit 2 faces (option) | D91: m² | E91: =IF('PARAMÈTRES'!$C$138="Oui",2*'GROS_ŒUVRE'!$E$73,0) -> 0 | J91: 2 × surface des murs
B92: Mortier d'enduit | D92: m³ | E92: ='GROS_ŒUVRE'!$E$91*'PARAMÈTRES'!$C$139 -> 0 | J92: m² × épaisseur
B94: B8. RÉCAPITULATIF DES MATÉRIAUX DE GROS ŒUVRE
B95: Béton de propreté (150 kg/m³) | D95: m³ | E95: ='GROS_ŒUVRE'!$E$32+'GROS_ŒUVRE'!$E$41+'GROS_ŒUVRE'!$E$50 -> 4.224
B96: Béton armé (350 kg/m³) | D96: m³ | E96: ='GROS_ŒUVRE'!$E$33+'GROS_ŒUVRE'!$E$34+'GROS_ŒUVRE'!$E$42+'GROS_ŒUVRE'!$E$43+'GROS_ŒUVRE'!$E$51+'GROS_ŒUVRE'!$E$63+'GROS_ŒUVRE'!$E$77+'GROS_ŒUVRE'!$E$82+'GROS_ŒUVRE'!$E$87 -> 183.8125
B97: Mortier (300 kg/m³) | D97: m³ | E97: ='GROS_ŒUVRE'!$E$59+'GROS_ŒUVRE'!$E$75+'GROS_ŒUVRE'!$E$92 -> 1.8
B98: Béton total | D98: m³ | E98: ='GROS_ŒUVRE'!$E$95+'GROS_ŒUVRE'!$E$96 -> 188.0365
B99: Ciment CPJ 42.5 | D99: sacs | E99: =ROUNDUP(('GROS_ŒUVRE'!$E$95*'PARAMÈTRES'!$C$142+'GROS_ŒUVRE'!$E$96*'PARAMÈTRES'!$C$143+'GROS_ŒUVRE'!$E$97*'PARAMÈTRES'!$C$144)/'PARAMÈTRES'!$C$145,0) -> 1311 | J99: Σ volumes × dosages / 50 kg
B100: Sable | D100: m³ | E100: ='GROS_ŒUVRE'!$E$98*'PARAMÈTRES'!$C$146+'GROS_ŒUVRE'!$E$97*'PARAMÈTRES'!$C$149+'GROS_ŒUVRE'!$E$28 -> 116.74572 | J100: béton × 0,40 + mortier × 1,10 + lit de sable
B101: Gravier 5/15 | D101: m³ | E101: ='GROS_ŒUVRE'!$E$98*'PARAMÈTRES'!$C$147 -> 56.41095
B102: Gravier 15/25 | D102: m³ | E102: ='GROS_ŒUVRE'!$E$98*'PARAMÈTRES'!$C$148 -> 94.01825
B103: Aciers HA6 (chutes comprises) | D103: kg | E103: =ROUNDUP('GROS_ŒUVRE'!$I$103/(IFERROR(_xlfn.XLOOKUP("HA6",'BASE_ACIERS'!$B$5:$B$20,'BASE_ACIERS'!$D$5:$D$20),IFERROR(INDEX('BASE_ACIERS'!$D$5:$D$20,MATCH("HA6",'BASE_ACIERS'!$B$5:$B$20,0)),0))*'PARAMÈTRES'!$C$58),0) -> 23 | F103: ← barres de 12 m | I103: =(IF('GROS_ŒUVRE'!$C$36="HA6",'GROS_ŒUVRE'!$I$36,0)+IF('GROS_ŒUVRE'!$C$37="HA6",'GROS_ŒUVRE'!$I$37,0)+IF('GROS_ŒUVRE'!$C$38="HA6",'GROS_ŒUVRE'!$I$38,0)+IF('GROS_ŒUVRE'!$C$45="HA6",'GROS_ŒUVRE'!$I$45,0)+IF('GROS_ŒUVRE'!$C$46="HA6",'GROS_ŒUVRE'!$I$46,0)+IF('GROS_ŒUVRE'!$C$47="HA6",'GROS_ŒUVRE'!$I$47,0)+IF('GROS_ŒUVRE'!$C$53="HA6",'GROS_ŒUVRE'!$I$53,0)+IF('GROS_ŒUVRE'!$C$54="HA6",'GROS_ŒUVRE'!$I$54,0)+IF('GROS_ŒUVRE'!$C$64="HA6",'GROS_ŒUVRE'!$I$64,0)+IF('GROS_ŒUVRE'!$C$65="HA6",'GROS_ŒUVRE'!$I$65,0)+IF('GROS_ŒUVRE'!$C$66="HA6",'GROS_ŒUVRE'!$I$66,0)+IF('GROS_ŒUVRE'!$C$67="HA6",'GROS_ŒUVRE'!$I$67,0)+IF('GROS_ŒUVRE'!$C$68="HA6",'GROS_ŒUVRE'!$I$68,0)+IF('GROS_ŒUVRE'!$C$79="HA6",'GROS_ŒUVRE'!$I$79,0)+IF('GROS_ŒUVRE'!$C$80="HA6",'GROS_ŒUVRE'!$I$80,0)+IF('GROS_ŒUVRE'!$C$84="HA6",'GROS_ŒUVRE'!$I$84,0)+IF('GROS_ŒUVRE'!$C$85="HA6",'GROS_ŒUVRE'!$I$85,0)+IF('GROS_ŒUVRE'!$C$89="HA6",'GROS_ŒUVRE'!$I$89,0)+IF('GROS_ŒUVRE'!$C$90="HA6",'GROS_ŒUVRE'!$I$90,0))*(1+'PARAMÈTRES'!$C$154) -> 59.58036 | J103: Somme des lignes de ce diamètre × (1 + chutes)
B104: Aciers HA8 (chutes comprises) | D104: kg | E104: =ROUNDUP('GROS_ŒUVRE'!$I$104/(IFERROR(_xlfn.XLOOKUP("HA8",'BASE_ACIERS'!$B$5:$B$20,'BASE_ACIERS'!$D$5:$D$20),IFERROR(INDEX('BASE_ACIERS'!$D$5:$D$20,MATCH("HA8",'BASE_ACIERS'!$B$5:$B$20,0)),0))*'PARAMÈTRES'!$C$58),0) -> 22 | F104: ← barres de 12 m | I104: =(IF('GROS_ŒUVRE'!$C$36="HA8",'GROS_ŒUVRE'!$I$36,0)+IF('GROS_ŒUVRE'!$C$37="HA8",'GROS_ŒUVRE'!$I$37,0)+IF('GROS_ŒUVRE'!$C$38="HA8",'GROS_ŒUVRE'!$I$38,0)+IF('GROS_ŒUVRE'!$C$45="HA8",'GROS_ŒUVRE'!$I$45,0)+IF('GROS_ŒUVRE'!$C$46="HA8",'GROS_ŒUVRE'!$I$46,0)+IF('GROS_ŒUVRE'!$C$47="HA8",'GROS_ŒUVRE'!$I$47,0)+IF('GROS_ŒUVRE'!$C$53="HA8",'GROS_ŒUVRE'!$I$53,0)+IF('GROS_ŒUVRE'!$C$54="HA8",'GROS_ŒUVRE'!$I$54,0)+IF('GROS_ŒUVRE'!$C$64="HA8",'GROS_ŒUVRE'!$I$64,0)+IF('GROS_ŒUVRE'!$C$65="HA8",'GROS_ŒUVRE'!$I$65,0)+IF('GROS_ŒUVRE'!$C$66="HA8",'GROS_ŒUVRE'!$I$66,0)+IF('GROS_ŒUVRE'!$C$67="HA8",'GROS_ŒUVRE'!$I$67,0)+IF('GROS_ŒUVRE'!$C$68="HA8",'GROS_ŒUVRE'!$I$68,0)+IF('GROS_ŒUVRE'!$C$79="HA8",'GROS_ŒUVRE'!$I$79,0)+IF('GROS_ŒUVRE'!$C$80="HA8",'GROS_ŒUVRE'!$I$80,0)+IF('GROS_ŒUVRE'!$C$84="HA8",'GROS_ŒUVRE'!$I$84,0)+IF('GROS_ŒUVRE'!$C$85="HA8",'GROS_ŒUVRE'!$I$85,0)+IF('GROS_ŒUVRE'!$C$89="HA8",'GROS_ŒUVRE'!$I$89,0)+IF('GROS_ŒUVRE'!$C$90="HA8",'GROS_ŒUVRE'!$I$90,0))*(1+'PARAMÈTRES'!$C$154) -> 99.747375 | J104: Somme des lignes de ce diamètre × (1 + chutes)
B105: Aciers HA10 (chutes comprises) | D105: kg | E105: =ROUNDUP('GROS_ŒUVRE'!$I$105/(IFERROR(_xlfn.XLOOKUP("HA10",'BASE_ACIERS'!$B$5:$B$20,'BASE_ACIERS'!$D$5:$D$20),IFERROR(INDEX('BASE_ACIERS'!$D$5:$D$20,MATCH("HA10",'BASE_ACIERS'!$B$5:$B$20,0)),0))*'PARAMÈTRES'!$C$58),0) -> 747 | F105: ← barres de 12 m | I105: =(IF('GROS_ŒUVRE'!$C$36="HA10",'GROS_ŒUVRE'!$I$36,0)+IF('GROS_ŒUVRE'!$C$37="HA10",'GROS_ŒUVRE'!$I$37,0)+IF('GROS_ŒUVRE'!$C$38="HA10",'GROS_ŒUVRE'!$I$38,0)+IF('GROS_ŒUVRE'!$C$45="HA10",'GROS_ŒUVRE'!$I$45,0)+IF('GROS_ŒUVRE'!$C$46="HA10",'GROS_ŒUVRE'!$I$46,0)+IF('GROS_ŒUVRE'!$C$47="HA10",'GROS_ŒUVRE'!$I$47,0)+IF('GROS_ŒUVRE'!$C$53="HA10",'GROS_ŒUVRE'!$I$53,0)+IF('GROS_ŒUVRE'!$C$54="HA10",'GROS_ŒUVRE'!$I$54,0)+IF('GROS_ŒUVRE'!$C$64="HA10",'GROS_ŒUVRE'!$I$64,0)+IF('GROS_ŒUVRE'!$C$65="HA10",'GROS_ŒUVRE'!$I$65,0)+IF('GROS_ŒUVRE'!$C$66="HA10",'GROS_ŒUVRE'!$I$66,0)+IF('GROS_ŒUVRE'!$C$67="HA10",'GROS_ŒUVRE'!$I$67,0)+IF('GROS_ŒUVRE'!$C$68="HA10",'GROS_ŒUVRE'!$I$68,0)+IF('GROS_ŒUVRE'!$C$79="HA10",'GROS_ŒUVRE'!$I$79,0)+IF('GROS_ŒUVRE'!$C$80="HA10",'GROS_ŒUVRE'!$I$80,0)+IF('GROS_ŒUVRE'!$C$84="HA10",'GROS_ŒUVRE'!$I$84,0)+IF('GROS_ŒUVRE'!$C$85="HA10",'GROS_ŒUVRE'!$I$85,0)+IF('GROS_ŒUVRE'!$C$89="HA10",'GROS_ŒUVRE'!$I$89,0)+IF('GROS_ŒUVRE'!$C$90="HA10",'GROS_ŒUVRE'!$I$90,0))*(1+'PARAMÈTRES'!$C$154) -> 5527.5858 | J105: Somme des lignes de ce diamètre × (1 + chutes)
B106: Aciers HA12 (chutes comprises) | D106: kg | E106: =ROUNDUP('GROS_ŒUVRE'!$I$106/(IFERROR(_xlfn.XLOOKUP("HA12",'BASE_ACIERS'!$B$5:$B$20,'BASE_ACIERS'!$D$5:$D$20),IFERROR(INDEX('BASE_ACIERS'!$D$5:$D$20,MATCH("HA12",'BASE_ACIERS'!$B$5:$B$20,0)),0))*'PARAMÈTRES'!$C$58),0) -> 50 | F106: ← barres de 12 m | I106: =(IF('GROS_ŒUVRE'!$C$36="HA12",'GROS_ŒUVRE'!$I$36,0)+IF('GROS_ŒUVRE'!$C$37="HA12",'GROS_ŒUVRE'!$I$37,0)+IF('GROS_ŒUVRE'!$C$38="HA12",'GROS_ŒUVRE'!$I$38,0)+IF('GROS_ŒUVRE'!$C$45="HA12",'GROS_ŒUVRE'!$I$45,0)+IF('GROS_ŒUVRE'!$C$46="HA12",'GROS_ŒUVRE'!$I$46,0)+IF('GROS_ŒUVRE'!$C$47="HA12",'GROS_ŒUVRE'!$I$47,0)+IF('GROS_ŒUVRE'!$C$53="HA12",'GROS_ŒUVRE'!$I$53,0)+IF('GROS_ŒUVRE'!$C$54="HA12",'GROS_ŒUVRE'!$I$54,0)+IF('GROS_ŒUVRE'!$C$64="HA12",'GROS_ŒUVRE'!$I$64,0)+IF('GROS_ŒUVRE'!$C$65="HA12",'GROS_ŒUVRE'!$I$65,0)+IF('GROS_ŒUVRE'!$C$66="HA12",'GROS_ŒUVRE'!$I$66,0)+IF('GROS_ŒUVRE'!$C$67="HA12",'GROS_ŒUVRE'!$I$67,0)+IF('GROS_ŒUVRE'!$C$68="HA12",'GROS_ŒUVRE'!$I$68,0)+IF('GROS_ŒUVRE'!$C$79="HA12",'GROS_ŒUVRE'!$I$79,0)+IF('GROS_ŒUVRE'!$C$80="HA12",'GROS_ŒUVRE'!$I$80,0)+IF('GROS_ŒUVRE'!$C$84="HA12",'GROS_ŒUVRE'!$I$84,0)+IF('GROS_ŒUVRE'!$C$85="HA12",'GROS_ŒUVRE'!$I$85,0)+IF('GROS_ŒUVRE'!$C$89="HA12",'GROS_ŒUVRE'!$I$89,0)+IF('GROS_ŒUVRE'!$C$90="HA12",'GROS_ŒUVRE'!$I$90,0))*(1+'PARAMÈTRES'!$C$154) -> 527.36544 | J106: Somme des lignes de ce diamètre × (1 + chutes)
B107: Aciers HA14 (chutes comprises) | D107: kg | E107: =ROUNDUP('GROS_ŒUVRE'!$I$107/(IFERROR(_xlfn.XLOOKUP("HA14",'BASE_ACIERS'!$B$5:$B$20,'BASE_ACIERS'!$D$5:$D$20),IFERROR(INDEX('BASE_ACIERS'!$D$5:$D$20,MATCH("HA14",'BASE_ACIERS'!$B$5:$B$20,0)),0))*'PARAMÈTRES'!$C$58),0) -> 0 | F107: ← barres de 12 m | I107: =(IF('GROS_ŒUVRE'!$C$36="HA14",'GROS_ŒUVRE'!$I$36,0)+IF('GROS_ŒUVRE'!$C$37="HA14",'GROS_ŒUVRE'!$I$37,0)+IF('GROS_ŒUVRE'!$C$38="HA14",'GROS_ŒUVRE'!$I$38,0)+IF('GROS_ŒUVRE'!$C$45="HA14",'GROS_ŒUVRE'!$I$45,0)+IF('GROS_ŒUVRE'!$C$46="HA14",'GROS_ŒUVRE'!$I$46,0)+IF('GROS_ŒUVRE'!$C$47="HA14",'GROS_ŒUVRE'!$I$47,0)+IF('GROS_ŒUVRE'!$C$53="HA14",'GROS_ŒUVRE'!$I$53,0)+IF('GROS_ŒUVRE'!$C$54="HA14",'GROS_ŒUVRE'!$I$54,0)+IF('GROS_ŒUVRE'!$C$64="HA14",'GROS_ŒUVRE'!$I$64,0)+IF('GROS_ŒUVRE'!$C$65="HA14",'GROS_ŒUVRE'!$I$65,0)+IF('GROS_ŒUVRE'!$C$66="HA14",'GROS_ŒUVRE'!$I$66,0)+IF('GROS_ŒUVRE'!$C$67="HA14",'GROS_ŒUVRE'!$I$67,0)+IF('GROS_ŒUVRE'!$C$68="HA14",'GROS_ŒUVRE'!$I$68,0)+IF('GROS_ŒUVRE'!$C$79="HA14",'GROS_ŒUVRE'!$I$79,0)+IF('GROS_ŒUVRE'!$C$80="HA14",'GROS_ŒUVRE'!$I$80,0)+IF('GROS_ŒUVRE'!$C$84="HA14",'GROS_ŒUVRE'!$I$84,0)+IF('GROS_ŒUVRE'!$C$85="HA14",'GROS_ŒUVRE'!$I$85,0)+IF('GROS_ŒUVRE'!$C$89="HA14",'GROS_ŒUVRE'!$I$89,0)+IF('GROS_ŒUVRE'!$C$90="HA14",'GROS_ŒUVRE'!$I$90,0))*(1+'PARAMÈTRES'!$C$154) -> 0 | J107: Somme des lignes de ce diamètre × (1 + chutes)
B108: Aciers HA16 (chutes comprises) | D108: kg | E108: =ROUNDUP('GROS_ŒUVRE'!$I$108/(IFERROR(_xlfn.XLOOKUP("HA16",'BASE_ACIERS'!$B$5:$B$20,'BASE_ACIERS'!$D$5:$D$20),IFERROR(INDEX('BASE_ACIERS'!$D$5:$D$20,MATCH("HA16",'BASE_ACIERS'!$B$5:$B$20,0)),0))*'PARAMÈTRES'!$C$58),0) -> 0 | F108: ← barres de 12 m | I108: =(IF('GROS_ŒUVRE'!$C$36="HA16",'GROS_ŒUVRE'!$I$36,0)+IF('GROS_ŒUVRE'!$C$37="HA16",'GROS_ŒUVRE'!$I$37,0)+IF('GROS_ŒUVRE'!$C$38="HA16",'GROS_ŒUVRE'!$I$38,0)+IF('GROS_ŒUVRE'!$C$45="HA16",'GROS_ŒUVRE'!$I$45,0)+IF('GROS_ŒUVRE'!$C$46="HA16",'GROS_ŒUVRE'!$I$46,0)+IF('GROS_ŒUVRE'!$C$47="HA16",'GROS_ŒUVRE'!$I$47,0)+IF('GROS_ŒUVRE'!$C$53="HA16",'GROS_ŒUVRE'!$I$53,0)+IF('GROS_ŒUVRE'!$C$54="HA16",'GROS_ŒUVRE'!$I$54,0)+IF('GROS_ŒUVRE'!$C$64="HA16",'GROS_ŒUVRE'!$I$64,0)+IF('GROS_ŒUVRE'!$C$65="HA16",'GROS_ŒUVRE'!$I$65,0)+IF('GROS_ŒUVRE'!$C$66="HA16",'GROS_ŒUVRE'!$I$66,0)+IF('GROS_ŒUVRE'!$C$67="HA16",'GROS_ŒUVRE'!$I$67,0)+IF('GROS_ŒUVRE'!$C$68="HA16",'GROS_ŒUVRE'!$I$68,0)+IF('GROS_ŒUVRE'!$C$79="HA16",'GROS_ŒUVRE'!$I$79,0)+IF('GROS_ŒUVRE'!$C$80="HA16",'GROS_ŒUVRE'!$I$80,0)+IF('GROS_ŒUVRE'!$C$84="HA16",'GROS_ŒUVRE'!$I$84,0)+IF('GROS_ŒUVRE'!$C$85="HA16",'GROS_ŒUVRE'!$I$85,0)+IF('GROS_ŒUVRE'!$C$89="HA16",'GROS_ŒUVRE'!$I$89,0)+IF('GROS_ŒUVRE'!$C$90="HA16",'GROS_ŒUVRE'!$I$90,0))*(1+'PARAMÈTRES'!$C$154) -> 0 | J108: Somme des lignes de ce diamètre × (1 + chutes)
B109: Aciers HA – total | D109: kg | I109: ='GROS_ŒUVRE'!$I$103+'GROS_ŒUVRE'!$I$104+'GROS_ŒUVRE'!$I$105+'GROS_ŒUVRE'!$I$106+'GROS_ŒUVRE'!$I$107+'GROS_ŒUVRE'!$I$108 -> 6214.2789
...

Sheet DQE_DEVIS
A1: DÉTAIL QUANTITATIF ET ESTIMATIF (DQE) – DEVIS
A2: Montants en FCFA HT. Prix unitaires saisis dans PARAMÈTRES (section 10). TVA 18 %.
B4: N° | C4: Désignation | D4: Unité | E4: Quantité | F4: PU (FCFA) | G4: Montant (FCFA)
B6: LOT 1 – CHARPENTE MÉTALLIQUE
B7: 1.1 | C7: Fourniture et fabrication de la charpente (profilés, platines, boulonnerie, chutes) | D7: kg | E7: ='QUANTITATIF_CHARPENTE'!$I$76 -> 25987.835 | F7: ='PARAMÈTRES'!$C$158 -> 1150 | G7: ='DQE_DEVIS'!$E$7*'DQE_DEVIS'!$F$7 -> 29886011
B8: 1.2 | C8: Transport et montage de la charpente | D8: kg | E8: ='QUANTITATIF_CHARPENTE'!$I$76 -> 25987.835 | F8: ='PARAMÈTRES'!$C$159 -> 250 | G8: ='DQE_DEVIS'!$E$8*'DQE_DEVIS'!$F$8 -> 6496958.9
B9: 1.3 | C9: Protection anticorrosion (galvanisation ou peinture, climat tropical humide) | D9: =IF('PARAMÈTRES'!$C$59="Galvanisation à chaud","kg","m²") -> kg | E9: =IF('PARAMÈTRES'!$C$59="Galvanisation à chaud",'QUANTITATIF_CHARPENTE'!$I$79,'QUANTITATIF_CHARPENTE'!$I$80) -> 24287.697 | F9: =IF('PARAMÈTRES'!$C$59="Galvanisation à chaud",'PARAMÈTRES'!$C$160,'PARAMÈTRES'!$C$161) -> 450 | G9: ='DQE_DEVIS'!$E$9*'DQE_DEVIS'!$F$9 -> 10929464
B10: 1.4 | C10: Tiges d'ancrage avec écrous et rondelles | D10: u | E10: ='QUANTITATIF_CHARPENTE'!$E$64+'QUANTITATIF_CHARPENTE'!$E$65 -> 76 | F10: ='PARAMÈTRES'!$C$162 -> 6000 | G10: ='DQE_DEVIS'!$E$10*'DQE_DEVIS'!$F$10 -> 456000
B11: 1.5 | C11: Gabarits de pose des tiges d'ancrage | D11: u | E11: ='QUANTITATIF_CHARPENTE'!$E$68 -> 22 | F11: ='PARAMÈTRES'!$C$163 -> 7500 | G11: ='DQE_DEVIS'!$E$11*'DQE_DEVIS'!$F$11 -> 165000
C12: Sous-total LOT 1 | G12: ='DQE_DEVIS'!$G$7+'DQE_DEVIS'!$G$8+'DQE_DEVIS'!$G$9+'DQE_DEVIS'!$G$10+'DQE_DEVIS'!$G$11 -> 47933433
B14: LOT 2 – COUVERTURE
B15: 2.1 | C15: Couverture en tôles bac acier | D15: m² | E15: ='QUANTITATIF_CHARPENTE'!$E$36 -> 816.56792 | F15: ='PARAMÈTRES'!$C$164 -> 6500 | G15: ='DQE_DEVIS'!$E$15*'DQE_DEVIS'!$F$15 -> 5307691.5
B16: 2.2 | C16: Panneaux translucides | D16: m² | E16: ='QUANTITATIF_CHARPENTE'!$E$37 -> 82.232792 | F16: ='PARAMÈTRES'!$C$165 -> 12000 | G16: ='DQE_DEVIS'!$E$16*'DQE_DEVIS'!$F$16 -> 986793.5
B17: 2.3 | C17: Faîtières | D17: ml | E17: ='QUANTITATIF_CHARPENTE'!$E$38 -> 40.6 | F17: ='PARAMÈTRES'!$C$166 -> 4500 | G17: ='DQE_DEVIS'!$E$17*'DQE_DEVIS'!$F$17 -> 182700
B18: 2.4 | C18: Rives | D18: ml | E18: ='QUANTITATIF_CHARPENTE'!$E$39 -> 40.508764 | F18: ='PARAMÈTRES'!$C$167 -> 3500 | G18: ='DQE_DEVIS'!$E$18*'DQE_DEVIS'!$F$18 -> 141780.68
B19: 2.5 | C19: Larmiers et bavettes de couverture | D19: ml | E19: ='QUANTITATIF_CHARPENTE'!$E$40 -> 81.2 | F19: ='PARAMÈTRES'!$C$168 -> 3000 | G19: ='DQE_DEVIS'!$E$19*'DQE_DEVIS'!$F$19 -> 243600
B20: 2.6 | C20: Chéneaux d'eau | D20: ml | E20: ='QUANTITATIF_CHARPENTE'!$E$41 -> 80 | F20: ='PARAMÈTRES'!$C$169 -> 15000 | G20: ='DQE_DEVIS'!$E$20*'DQE_DEVIS'!$F$20 -> 1200000
B21: 2.7 | C21: Naissances EP | D21: u | E21: ='QUANTITATIF_CHARPENTE'!$E$42 -> 6 | F21: ='PARAMÈTRES'!$C$170 -> 7500 | G21: ='DQE_DEVIS'!$E$21*'DQE_DEVIS'!$F$21 -> 45000
B22: 2.8 | C22: Descentes EP PVC Ø110 | D22: ml | E22: ='QUANTITATIF_CHARPENTE'!$E$43 -> 36 | F22: ='PARAMÈTRES'!$C$171 -> 6000 | G22: ='DQE_DEVIS'!$E$22*'DQE_DEVIS'!$F$22 -> 216000
B23: 2.9 | C23: Skydomes avec chevêtres | D23: u | E23: ='QUANTITATIF_CHARPENTE'!$E$44 -> 4 | F23: ='PARAMÈTRES'!$C$172 -> 150000 | G23: ='DQE_DEVIS'!$E$23*'DQE_DEVIS'!$F$23 -> 600000
B24: 2.10 | C24: Vis autoforeuses | D24: u | E24: ='QUANTITATIF_CHARPENTE'!$E$69 -> 10093 | F24: ='PARAMÈTRES'!$C$173 -> 75 | G24: ='DQE_DEVIS'!$E$24*'DQE_DEVIS'!$F$24 -> 756975
B25: 2.11 | C25: Rivets de chéneaux | D25: u | E25: ='QUANTITATIF_CHARPENTE'!$E$45 -> 400 | F25: ='PARAMÈTRES'!$C$174 -> 25 | G25: ='DQE_DEVIS'!$E$25*'DQE_DEVIS'!$F$25 -> 10000
C26: Sous-total LOT 2 | G26: ='DQE_DEVIS'!$G$15+'DQE_DEVIS'!$G$16+'DQE_DEVIS'!$G$17+'DQE_DEVIS'!$G$18+'DQE_DEVIS'!$G$19+'DQE_DEVIS'!$G$20+'DQE_DEVIS'!$G$21+'DQE_DEVIS'!$G$22+'DQE_DEVIS'!$G$23+'DQE_DEVIS'!$G$24+'DQE_DEVIS'!$G$25 -> 9690540.7
B28: LOT 3 – BARDAGE ET MENUISERIES MÉTALLIQUES
B29: 3.1 | C29: Bardage en bac acier | D29: m² | E29: ='QUANTITATIF_CHARPENTE'!$E$52 -> 783.2 | F29: ='PARAMÈTRES'!$C$175 -> 6000 | G29: ='DQE_DEVIS'!$E$29*'DQE_DEVIS'!$F$29 -> 4699200
B30: 3.2 | C30: Larmiers de bardage (pied et angles) | D30: ml | E30: ='QUANTITATIF_CHARPENTE'!$E$55 -> 134.5 | F30: ='PARAMÈTRES'!$C$176 -> 3000 | G30: ='DQE_DEVIS'!$E$30*'DQE_DEVIS'!$F$30 -> 403500
B31: 3.3 | C31: Larmiers de portes coulissantes | D31: ml | E31: ='QUANTITATIF_CHARPENTE'!$E$53 -> 4.2 | F31: ='PARAMÈTRES'!$C$177 -> 3500 | G31: ='DQE_DEVIS'!$E$31*'DQE_DEVIS'!$F$31 -> 14700
B32: 3.4 | C32: Rails hauts de portes coulissantes | D32: ml | E32: ='QUANTITATIF_CHARPENTE'!$E$54 -> 8 | F32: ='PARAMÈTRES'!$C$178 -> 15000 | G32: ='DQE_DEVIS'!$E$32*'DQE_DEVIS'!$F$32 -> 120000
B33: 3.5 | C33: Portes coulissantes | D33: m² | E33: ='PARAMÈTRES'!$C$28*'PARAMÈTRES'!$C$29*'PARAMÈTRES'!$C$30 -> 18 | F33: ='PARAMÈTRES'!$C$179 -> 45000 | G33: ='DQE_DEVIS'!$E$33*'DQE_DEVIS'!$F$33 -> 810000
B34: 3.6 | C34: Portillons | D34: m² | E34: ='PARAMÈTRES'!$C$32*'PARAMÈTRES'!$C$33*'PARAMÈTRES'!$C$34 -> 22 | F34: ='PARAMÈTRES'!$C$180 -> 50000 | G34: ='DQE_DEVIS'!$E$34*'DQE_DEVIS'!$F$34 -> 1100000
C35: Sous-total LOT 3 | G35: ='DQE_DEVIS'!$G$29+'DQE_DEVIS'!$G$30+'DQE_DEVIS'!$G$31+'DQE_DEVIS'!$G$32+'DQE_DEVIS'!$G$33+'DQE_DEVIS'!$G$34 -> 7147400
B37: LOT 4 – TERRASSEMENTS
B38: 4.1 | C38: Décapage de l'emprise | D38: m² | E38: ='GROS_ŒUVRE'!$E$23 -> 924 | F38: ='PARAMÈTRES'!$C$181 -> 500 | G38: ='DQE_DEVIS'!$E$38*'DQE_DEVIS'!$F$38 -> 462000
B39: 4.2 | C39: Fouilles en puits et en rigole (profondeur 1,20 m) | D39: m³ | E39: ='GROS_ŒUVRE'!$E$24+'GROS_ŒUVRE'!$E$25+'GROS_ŒUVRE'!$E$26 -> 136.992 | F39: ='PARAMÈTRES'!$C$182 -> 4500 | G39: ='DQE_DEVIS'!$E$39*'DQE_DEVIS'!$F$39 -> 616464
B40: 4.3 | C40: Remblai en latérite compactée à 95 % OPM | D40: m³ | E40: ='GROS_ŒUVRE'!$E$27 -> 197.75563 | F40: ='PARAMÈTRES'!$C$183 -> 9000 | G40: ='DQE_DEVIS'!$E$40*'DQE_DEVIS'!$F$40 -> 1779800.6
B41: 4.4 | C41: Évacuation des déblais | D41: m³ | E41: ='GROS_ŒUVRE'!$E$29 -> 402.24 | F41: ='PARAMÈTRES'!$C$184 -> 3500 | G41: ='DQE_DEVIS'!$E$41*'DQE_DEVIS'!$F$41 -> 1407840
C42: Sous-total LOT 4 | G42: ='DQE_DEVIS'!$G$38+'DQE_DEVIS'!$G$39+'DQE_DEVIS'!$G$40+'DQE_DEVIS'!$G$41 -> 4266104.6
B44: LOT 5 – GROS ŒUVRE (matériaux et main d'œuvre)
B45: 5.1 | C45: Ciment CPJ 42.5 (sacs de 50 kg) | D45: sacs | E45: ='GROS_ŒUVRE'!$E$99 -> 1311 | F45: ='PARAMÈTRES'!$C$185 -> 5500 | G45: ='DQE_DEVIS'!$E$45*'DQE_DEVIS'!$F$45 -> 7210500
B46: 5.2 | C46: Sable | D46: m³ | E46: ='GROS_ŒUVRE'!$E$100 -> 116.74572 | F46: ='PARAMÈTRES'!$C$186 -> 12000 | G46: ='DQE_DEVIS'!$E$46*'DQE_DEVIS'!$F$46 -> 1400948.7
B47: 5.3 | C47: Gravier 5/15 | D47: m³ | E47: ='GROS_ŒUVRE'!$E$101 -> 56.41095 | F47: ='PARAMÈTRES'!$C$187 -> 22000 | G47: ='DQE_DEVIS'!$E$47*'DQE_DEVIS'!$F$47 -> 1241040.9
B48: 5.4 | C48: Gravier 15/25 | D48: m³ | E48: ='GROS_ŒUVRE'!$E$102 -> 94.01825 | F48: ='PARAMÈTRES'!$C$188 -> 20000 | G48: ='DQE_DEVIS'!$E$48*'DQE_DEVIS'!$F$48 -> 1880365
B49: 5.5 | C49: Aciers HA6 | D49: kg | E49: ='GROS_ŒUVRE'!$I$103 -> 59.58036 | F49: ='PARAMÈTRES'!$C$189 -> 800 | G49: ='DQE_DEVIS'!$E$49*'DQE_DEVIS'!$F$49 -> 47664.288
B50: 5.6 | C50: Aciers HA8 | D50: kg | E50: ='GROS_ŒUVRE'!$I$104 -> 99.747375 | F50: ='PARAMÈTRES'!$C$190 -> 750 | G50: ='DQE_DEVIS'!$E$50*'DQE_DEVIS'!$F$50 -> 74810.531
B51: 5.7 | C51: Aciers HA10 | D51: kg | E51: ='GROS_ŒUVRE'!$I$105 -> 5527.5858 | F51: ='PARAMÈTRES'!$C$191 -> 725 | G51: ='DQE_DEVIS'!$E$51*'DQE_DEVIS'!$F$51 -> 4007499.7
B52: 5.8 | C52: Aciers HA12 | D52: kg | E52: ='GROS_ŒUVRE'!$I$106 -> 527.36544 | F52: ='PARAMÈTRES'!$C$192 -> 725 | G52: ='DQE_DEVIS'!$E$52*'DQE_DEVIS'!$F$52 -> 382339.94
B53: 5.9 | C53: Aciers HA14 | D53: kg | E53: ='GROS_ŒUVRE'!$I$107 -> 0 | F53: ='PARAMÈTRES'!$C$193 -> 725 | G53: ='DQE_DEVIS'!$E$53*'DQE_DEVIS'!$F$53 -> 0
B54: 5.10 | C54: Aciers HA16 | D54: kg | E54: ='GROS_ŒUVRE'!$I$108 -> 0 | F54: ='PARAMÈTRES'!$C$194 -> 725 | G54: ='DQE_DEVIS'!$E$54*'DQE_DEVIS'!$F$54 -> 0
B55: 5.11 | C55: Agglos 15 pleins | D55: u | E55: ='GROS_ŒUVRE'!$E$110 -> 1575 | F55: ='PARAMÈTRES'!$C$195 -> 450 | G55: ='DQE_DEVIS'!$E$55*'DQE_DEVIS'!$F$55 -> 708750
B56: 5.12 | C56: Agglos 15 creux | D56: u | E56: ='GROS_ŒUVRE'!$E$111 -> 0 | F56: ='PARAMÈTRES'!$C$196 -> 375 | G56: ='DQE_DEVIS'!$E$56*'DQE_DEVIS'!$F$56 -> 0
B57: 5.13 | C57: Film polyane | D57: m² | E57: ='GROS_ŒUVRE'!$E$112 -> 870.12475 | F57: ='PARAMÈTRES'!$C$197 -> 400 | G57: ='DQE_DEVIS'!$E$57*'DQE_DEVIS'!$F$57 -> 348049.9
B58: 5.14 | C58: Bois de coffrage | D58: m² | E58: ='GROS_ŒUVRE'!$E$113 -> 114.24 | F58: ='PARAMÈTRES'!$C$198 -> 3500 | G58: ='DQE_DEVIS'!$E$58*'DQE_DEVIS'!$F$58 -> 399840
B59: 5.15 | C59: Joints de retrait sciés | D59: ml | E59: ='GROS_ŒUVRE'!$E$69 -> 258.5 | F59: ='PARAMÈTRES'!$C$199 -> 1500 | G59: ='DQE_DEVIS'!$E$59*'DQE_DEVIS'!$F$59 -> 387750
B60: 5.16 | C60: Cure du béton | D60: m² | E60: ='GROS_ŒUVRE'!$E$70 -> 791.0225 | F60: ='PARAMÈTRES'!$C$200 -> 250 | G60: ='DQE_DEVIS'!$E$60*'DQE_DEVIS'!$F$60 -> 197755.62
B61: 5.17 | C61: Main d'œuvre et matériel gros œuvre (% des matériaux du lot 5) | D61: Fft | E61: =1 -> 1 | F61: ='PARAMÈTRES'!$C$155*('DQE_DEVIS'!$G$45+'DQE_DEVIS'!$G$46+'DQE_DEVIS'!$G$47+'DQE_DEVIS'!$G$48+'DQE_DEVIS'!$G$49+'DQE_DEVIS'!$G$50+'DQE_DEVIS'!$G$51+'DQE_DEVIS'!$G$52+'DQE_DEVIS'!$G$53+'DQE_DEVIS'!$G$54+'DQE_DEVIS'!$G$55+'DQE_DEVIS'!$G$56+'DQE_DEVIS'!$G$57+'DQE_DEVIS'!$G$58+'DQE_DEVIS'!$G$59+'DQE_DEVIS'!$G$60) -> 7314925.8 | G61: ='DQE_DEVIS'!$E$61*'DQE_DEVIS'!$F$61 -> 7314925.8
C62: Sous-total LOT 5 | G62: ='DQE_DEVIS'!$G$45+'DQE_DEVIS'!$G$46+'DQE_DEVIS'!$G$47+'DQE_DEVIS'!$G$48+'DQE_DEVIS'!$G$49+'DQE_DEVIS'!$G$50+'DQE_DEVIS'!$G$51+'DQE_DEVIS'!$G$52+'DQE_DEVIS'!$G$53+'DQE_DEVIS'!$G$54+'DQE_DEVIS'!$G$55+'DQE_DEVIS'!$G$56+'DQE_DEVIS'!$G$57+'DQE_DEVIS'!$G$58+'DQE_DEVIS'!$G$59+'DQE_DEVIS'!$G$60+'DQE_DEVIS'!$G$61 -> 25602240
C64: TOTAL HT | G64: ='DQE_DEVIS'!$G$12+'DQE_DEVIS'!$G$26+'DQE_DEVIS'!$G$35+'DQE_DEVIS'!$G$42+'DQE_DEVIS'!$G$62 -> 94639719
C65: TVA 18 % | G65: ='DQE_DEVIS'!$G$64*0.18 -> 17035149
C66: TOTAL TTC | G66: ='DQE_DEVIS'!$G$64+'DQE_DEVIS'!$G$65 -> 1.1167487e+08
C67: Coût HT au m² couvert | G67: ='DQE_DEVIS'!$G$64/'PRÉDIMENSIONNEMENT'!$C$46 -> 118299.65
C68: Coût de la façade bardée (bardage, lisses et liernes, larmiers) | G68: ='QUANTITATIF_CHARPENTE'!$E$52*'PARAMÈTRES'!$C$175+'QUANTITATIF_CHARPENTE'!$E$55*'PARAMÈTRES'!$C$176+('QUANTITATIF_CHARPENTE'!$I$48+'QUANTITATIF_CHARPENTE'!$I$49+'QUANTITATIF_CHARPENTE'!$I$28+'QUANTITATIF_CHARPENTE'!$I$29)*(1+'PARAMÈTRES'!$C$55)*('PARAMÈTRES'!$C$158+'PARAMÈTRES'!$C$159+'PRÉDIMENSIONNEMENT'!$C$65) -> 9270590.1
C69: Coût de la façade maçonnée (agglos, chaînages, raidisseurs, linteaux, enduit) | G69: ='GROS_ŒUVRE'!$I$114 -> 0 | H69: ='DQE_DEVIS'!$G$68+'GROS_ŒUVRE'!$I$114 -> 9270590.1

Sheet RÉCAP_GABARITS
A1: RÉCAPITULATIF COMPARATIF DES 7 GABARITS
A2: Calculé avec les paramètres en vigueur (hauteur, pente, prix…) et les profilés automatiques. Façades : variante bardage bac acier et variante agglos 15 creux.
B4: Gabarit | C4: Système | D4: Surface (m²) | E4: Tonnage acier (t) | F4: kg/m² | G4: Tôles (m²) | H4: Béton (m³) | I4: Aciers HA (kg) | J4: Coût HT (FCFA) | K4: Coût HT / m² | L4: Coût façade bardage | M4: Coût façade agglos
B5: 10 × 30 | C5: ='CALC_GABARITS'!$D$11 -> Portique IPE avec jarrets | D5: ='CALC_GABARITS'!$D$31 -> 300 | E5: ='CALC_GABARITS'!$D$356 -> 10.270178 | F5: ='CALC_GABARITS'!$D$357 -> 34.233927 | G5: ='CALC_GABARITS'!$D$256 -> 304.13205 | H5: ='CALC_GABARITS'!$D$531 -> 79.1485 | I5: ='CALC_GABARITS'!$D$548 -> 2576.5903 | J5: ='CALC_GABARITS'!$D$688 -> 42081885 | K5: ='CALC_GABARITS'!$D$691 -> 140272.95 | L5: ='CALC_GABARITS'!$E$693 -> 5896757.3 | M5: ='CALC_GABARITS'!$F$693 -> 7329355.2
B6: 15 × 20 | C6: ='CALC_GABARITS'!$G$11 -> Portique IPE avec jarrets | D6: ='CALC_GABARITS'!$G$31 -> 300 | E6: ='CALC_GABARITS'!$G$356 -> 11.543299 | F6: ='CALC_GABARITS'!$G$357 -> 38.477663 | G6: ='CALC_GABARITS'!$G$256 -> 307.17021 | H6: ='CALC_GABARITS'!$G$531 -> 76.9025 | I6: ='CALC_GABARITS'!$G$548 -> 2539.4625 | J6: ='CALC_GABARITS'!$G$688 -> 43222389 | K6: ='CALC_GABARITS'!$G$691 -> 144074.63 | L6: ='CALC_GABARITS'!$H$693 -> 5020447 | M6: ='CALC_GABARITS'!$I$693 -> 6780431.7
B7: 15 × 30 | C7: ='CALC_GABARITS'!$J$11 -> Portique IPE avec jarrets | D7: ='CALC_GABARITS'!$J$31 -> 450 | E7: ='CALC_GABARITS'!$J$356 -> 14.307908 | F7: ='CALC_GABARITS'!$J$357 -> 31.795351 | G7: ='CALC_GABARITS'!$J$256 -> 459.07807 | H7: ='CALC_GABARITS'!$J$531 -> 110.9225 | I7: ='CALC_GABARITS'!$J$548 -> 3663.0847 | J7: ='CALC_GABARITS'!$J$688 -> 56330713 | K7: ='CALC_GABARITS'!$J$691 -> 125179.36 | L7: ='CALC_GABARITS'!$K$693 -> 6758131.9 | M7: ='CALC_GABARITS'!$L$693 -> 8434210.9
B8: 20 × 20 | C8: ='CALC_GABARITS'!$M$11 -> Portique IPE avec jarrets | D8: ='CALC_GABARITS'!$M$31 -> 400 | E8: ='CALC_GABARITS'!$M$356 -> 16.051438 | F8: ='CALC_GABARITS'!$M$357 -> 40.128595 | G8: ='CALC_GABARITS'!$M$256 -> 411.48027 | H8: ='CALC_GABARITS'!$M$531 -> 98.6765 | I8: ='CALC_GABARITS'!$M$548 -> 3256.6824 | J8: ='CALC_GABARITS'!$M$688 -> 56397658 | K8: ='CALC_GABARITS'!$M$691 -> 140994.14 | L8: ='CALC_GABARITS'!$N$693 -> 5902975.5 | M8: ='CALC_GABARITS'!$O$693 -> 7916598.7
B9: 20 × 40 | C9: ='CALC_GABARITS'!$P$11 -> Portique IPE avec jarrets | D9: ='CALC_GABARITS'!$P$31 -> 800 | E9: ='CALC_GABARITS'!$P$356 -> 25.987835 | F9: ='CALC_GABARITS'!$P$357 -> 32.484794 | G9: ='CALC_GABARITS'!$P$256 -> 816.56792 | H9: ='CALC_GABARITS'!$P$531 -> 188.0365 | I9: ='CALC_GABARITS'!$P$548 -> 6214.2789 | J9: ='CALC_GABARITS'!$P$688 -> 94639719 | K9: ='CALC_GABARITS'!$P$691 -> 118299.65 | L9: ='CALC_GABARITS'!$Q$693 -> 9270590.1 | M9: ='CALC_GABARITS'!$R$693 -> 11463852
B10: 30 × 40 | C10: ='CALC_GABARITS'!$S$11 -> Portique IPE renforcé | D10: ='CALC_GABARITS'!$S$31 -> 1200 | E10: ='CALC_GABARITS'!$S$356 -> 44.985603 | F10: ='CALC_GABARITS'!$S$357 -> 37.488002 | G10: ='CALC_GABARITS'!$S$256 -> 1227.7319 | H10: ='CALC_GABARITS'!$S$531 -> 271.1605 | I10: ='CALC_GABARITS'!$S$548 -> 8993.1874 | J10: ='CALC_GABARITS'!$S$688 -> 1.466907e+08 | K10: ='CALC_GABARITS'!$S$691 -> 122242.25 | L10: ='CALC_GABARITS'!$T$693 -> 11206036 | M10: ='CALC_GABARITS'!$U$693 -> 13590953
B11: 40 × 40 | C11: ='CALC_GABARITS'!$V$11 -> Ferme treillis | D11: ='CALC_GABARITS'!$V$31 -> 1600 | E11: ='CALC_GABARITS'!$V$356 -> 62.380658 | F11: ='CALC_GABARITS'!$V$357 -> 38.987911 | G11: ='CALC_GABARITS'!$V$256 -> 1638.8958 | H11: ='CALC_GABARITS'!$V$531 -> 354.7085 | I11: ='CALC_GABARITS'!$V$548 -> 11800.033 | J11: ='CALC_GABARITS'!$V$688 -> 1.9767797e+08 | K11: ='CALC_GABARITS'!$V$691 -> 123548.73 | L11: ='CALC_GABARITS'!$W$693 -> 16079603 | M11: ='CALC_GABARITS'!$X$693 -> 18483818
B13: Contrôle de cohérence (gabarit actif) : écart entre le moteur et le DQE | H13: =IFERROR(IF(ABS(INDEX('CALC_GABARITS'!$D$688:$X$688,1,(MATCH('ACCUEIL'!$D$6,'PARAMÈTRES'!$G$5:$G$11,0)-1)*3+1)-'DQE_DEVIS'!$G$64)<1,"OK (écart nul)","ÉCART : vérifier les forçages de profilés"),"PERSONNALISÉ : sans objet") -> OK (écart nul)
B14: Le comparatif utilise les profilés automatiques : un forçage en PRÉDIMENSIONNEMENT ne s'applique qu'au gabarit actif. Coûts façade = bardage + lisses + liernes + larmiers, ou agglos + chaînages + raidisseurs + linteaux (+ enduit), main d'œuvre comprise.

Sheet PLANS
B1: PLANCHE 1 / 7 – VUE EN PLAN – IMPLANTATION
B28: VUE EN PLAN – IMPLANTATION | J28: Planche n° 1 / 7 | L28: Date : | M28: =TODAY() -> 46301
B29: ="Gabarit "&'ACCUEIL'!$D$6&" : portée "&FIXED('PARAMÈTRES'!$C$9,2,TRUE)&" m × longueur "&FIXED('PARAMÈTRES'!$C$10,2,TRUE)&" m – H sablière "&FIXED('PARAMÈTRES'!$C$11,2,TRUE)&" m – pente "&FIXED('PARAMÈTRES'!$C$12*100,1,TRUE)&" % – "&'PRÉDIMENSIONNEMENT'!$C$26&" – façade : "&'PARAMÈTRES'!$C$51 -> Gabarit 20 × 40 : portée 20.00 m × longueur 40.00 m – H sablière 6.00 m – pente 16.0 % – Portique IPE avec jarrets – façade : Bardage bac acier | J29: ESQUISSE NON CONTRACTUELLE
B30: Couleurs : charpente en bleu · contreventements en orange · béton en gris · aciers en rouge · maçonnerie en marron clair · cotes et baies en noir · translucides en bleu clair · remblai en latérite | J30: BON POUR ACCORD
B31: ="Poteaux de portique ■ "&'PRÉDIMENSIONNEMENT'!$E$69&" sur semelles "&'PARAMÈTRES'!$C$89*100&" × "&'PARAMÈTRES'!$C$89*100&" ; poteaux de pignon ● "&'PRÉDIMENSIONNEMENT'!$E$75&" sur semelles "&'PARAMÈTRES'!$C$92*100&" × "&'PARAMÈTRES'!$C$92*100&" ; semelles filantes en pointillés." -> Poteaux de portique ■ IPE 330 sur semelles 120 × 120 ; poteaux de pignon ● IPE 220 sur semelles 80 × 80 ; semelles filantes en pointillés. | J31: Date :
J32: Signature :
B33: Échelle : automatique (même échelle en X et en Y) – cotes en mètres
B37: PLANCHE 2 / 7 – COUPE TRANSVERSALE – PORTIQUE TYPE
B64: COUPE TRANSVERSALE – PORTIQUE TYPE | J64: Planche n° 2 / 7 | L64: Date : | M64: =TODAY() -> 46301
B65: ="Gabarit "&'ACCUEIL'!$D$6&" : portée "&FIXED('PARAMÈTRES'!$C$9,2,TRUE)&" m × longueur "&FIXED('PARAMÈTRES'!$C$10,2,TRUE)&" m – H sablière "&FIXED('PARAMÈTRES'!$C$11,2,TRUE)&" m – pente "&FIXED('PARAMÈTRES'!$C$12*100,1,TRUE)&" % – "&'PRÉDIMENSIONNEMENT'!$C$26&" – façade : "&'PARAMÈTRES'!$C$51 -> Gabarit 20 × 40 : portée 20.00 m × longueur 40.00 m – H sablière 6.00 m – pente 16.0 % – Portique IPE avec jarrets – façade : Bardage bac acier | J65: ESQUISSE NON CONTRACTUELLE
B66: Couleurs : charpente en bleu · contreventements en orange · béton en gris · aciers en rouge · maçonnerie en marron clair · cotes et baies en noir · translucides en bleu clair · remblai en latérite | J66: BON POUR ACCORD
B67: ="Croix de Saint-André dans les travées d'extrémité et une travée sur 5 ("&'PRÉDIMENSIONNEMENT'!$C$44&" travées). "&IF('PRÉDIMENSIONNEMENT'!$C$50=1,"Lisses "&'PRÉDIMENSIONNEMENT'!$E$78&" e = "&FIXED('PARAMÈTRES'!$C$17,2,TRUE)&" m","Façade maçonnée : lisses sans objet")&IF('PRÉDIMENSIONNEMENT'!$C$51=1," ; maçonnerie agglos 15 creux sur "&FIXED('PRÉDIMENSIONNEMENT'!$C$49,2,TRUE)&" m avec chaînages gris.",".") -> Croix de Saint-André dans les travées d'extrémité et une travée sur 5 (3 travées). Lisses C 160 e = 1.80 m. | J67: Date :
J68: Signature :
B69: Échelle : automatique (même échelle en X et en Y) – cotes en mètres
B73: PLANCHE 3 / 7 – ÉLÉVATION LONG-PAN
B100: ÉLÉVATION LONG-PAN | J100: Planche n° 3 / 7 | L100: Date : | M100: =TODAY() -> 46301
B101: ="Gabarit "&'ACCUEIL'!$D$6&" : portée "&FIXED('PARAMÈTRES'!$C$9,2,TRUE)&" m × longueur "&FIXED('PARAMÈTRES'!$C$10,2,TRUE)&" m – H sablière "&FIXED('PARAMÈTRES'!$C$11,2,TRUE)&" m – pente "&FIXED('PARAMÈTRES'!$C$12*100,1,TRUE)&" % – "&'PRÉDIMENSIONNEMENT'!$C$26&" – façade : "&'PARAMÈTRES'!$C$51 -> Gabarit 20 × 40 : portée 20.00 m × longueur 40.00 m – H sablière 6.00 m – pente 16.0 % – Portique IPE avec jarrets – façade : Bardage bac acier | J101: ESQUISSE NON CONTRACTUELLE
B102: Couleurs : charpente en bleu · contreventements en orange · béton en gris · aciers en rouge · maçonnerie en marron clair · cotes et baies en noir · translucides en bleu clair · remblai en latérite | J102: BON POUR ACCORD
B103: ="Croix de Saint-André dans les travées d'extrémité et une travée sur 5 ("&'PRÉDIMENSIONNEMENT'!$C$44&" travées). "&IF('PRÉDIMENSIONNEMENT'!$C$50=1,"Lisses "&'PRÉDIMENSIONNEMENT'!$E$78&" e = "&FIXED('PARAMÈTRES'!$C$17,2,TRUE)&" m","Façade maçonnée : lisses sans objet")&IF('PRÉDIMENSIONNEMENT'!$C$51=1," ; maçonnerie agglos 15 creux sur "&FIXED('PRÉDIMENSIONNEMENT'!$C$49,2,TRUE)&" m avec chaînages gris.",".") -> Croix de Saint-André dans les travées d'extrémité et une travée sur 5 (3 travées). Lisses C 160 e = 1.80 m. | J103: Date :
J104: Signature :
B105: Échelle : automatique (même échelle en X et en Y) – cotes en mètres
B109: PLANCHE 4 / 7 – ÉLÉVATION PIGNON
B136: ÉLÉVATION PIGNON | J136: Planche n° 4 / 7 | L136: Date : | M136: =TODAY() -> 46301
B137: ="Gabarit "&'ACCUEIL'!$D$6&" : portée "&FIXED('PARAMÈTRES'!$C$9,2,TRUE)&" m × longueur "&FIXED('PARAMÈTRES'!$C$10,2,TRUE)&" m – H sablière "&FIXED('PARAMÈTRES'!$C$11,2,TRUE)&" m – pente "&FIXED('PARAMÈTRES'!$C$12*100,1,TRUE)&" % – "&'PRÉDIMENSIONNEMENT'!$C$26&" – façade : "&'PARAMÈTRES'!$C$51 -> Gabarit 20 × 40 : portée 20.00 m × longueur 40.00 m – H sablière 6.00 m – pente 16.0 % – Portique IPE avec jarrets – façade : Bardage bac acier | J137: ESQUISSE NON CONTRACTUELLE
B138: Couleurs : charpente en bleu · contreventements en orange · béton en gris · aciers en rouge · maçonnerie en marron clair · cotes et baies en noir · translucides en bleu clair · remblai en latérite | J138: BON POUR ACCORD
B139: ="Croix de Saint-André dans les travées d'extrémité et une travée sur 5 ("&'PRÉDIMENSIONNEMENT'!$C$44&" travées). "&IF('PRÉDIMENSIONNEMENT'!$C$50=1,"Lisses "&'PRÉDIMENSIONNEMENT'!$E$78&" e = "&FIXED('PARAMÈTRES'!$C$17,2,TRUE)&" m","Façade maçonnée : lisses sans objet")&IF('PRÉDIMENSIONNEMENT'!$C$51=1," ; maçonnerie agglos 15 creux sur "&FIXED('PRÉDIMENSIONNEMENT'!$C$49,2,TRUE)&" m avec chaînages gris.",".") -> Croix de Saint-André dans les travées d'extrémité et une travée sur 5 (3 travées). Lisses C 160 e = 1.80 m. | J139: Date :
J140: Signature :
B141: Échelle : automatique (même échelle en X et en Y) – cotes en mètres
B145: PLANCHE 5 / 7 – VUE EN PLAN TOITURE – CALEPINAGE
B172: VUE EN PLAN TOITURE – CALEPINAGE | J172: Planche n° 5 / 7 | L172: Date : | M172: =TODAY() -> 46301
B173: ="Gabarit "&'ACCUEIL'!$D$6&" : portée "&FIXED('PARAMÈTRES'!$C$9,2,TRUE)&" m × longueur "&FIXED('PARAMÈTRES'!$C$10,2,TRUE)&" m – H sablière "&FIXED('PARAMÈTRES'!$C$11,2,TRUE)&" m – pente "&FIXED('PARAMÈTRES'!$C$12*100,1,TRUE)&" % – "&'PRÉDIMENSIONNEMENT'!$C$26&" – façade : "&'PARAMÈTRES'!$C$51 -> Gabarit 20 × 40 : portée 20.00 m × longueur 40.00 m – H sablière 6.00 m – pente 16.0 % – Portique IPE avec jarrets – façade : Bardage bac acier | J173: ESQUISSE NON CONTRACTUELLE
B174: Couleurs : charpente en bleu · contreventements en orange · béton en gris · aciers en rouge · maçonnerie en marron clair · cotes et baies en noir · translucides en bleu clair · remblai en latérite | J174: BON POUR ACCORD
B175: ="Translucides : "&FIXED('PARAMÈTRES'!$C$45*100,0,TRUE)&" % – skydomes : "&'PARAMÈTRES'!$C$37&" – descentes EP : "&'PRÉDIMENSIONNEMENT'!$C$64&" – poutre au vent : "&'PRÉDIMENSIONNEMENT'!$C$44&" travées – liernes : "&'PRÉDIMENSIONNEMENT'!$C$43&" ligne(s) par travée." -> Translucides : 10 % – skydomes : 4 – descentes EP : 6 – poutre au vent : 3 travées – liernes : 1 ligne(s) par travée. | J175: Date :
J176: Signature :
B177: Échelle : automatique (même échelle en X et en Y) – cotes en mètres
B181: PLANCHE 6 / 7 – COUPE DE FONDATION ET DALLAGE (DÉTAIL)
B208: COUPE DE FONDATION ET DALLAGE (DÉTAIL) | J208: Planche n° 6 / 7 | L208: Date : | M208: =TODAY() -> 46301
B209: ="Gabarit "&'ACCUEIL'!$D$6&" : portée "&FIXED('PARAMÈTRES'!$C$9,2,TRUE)&" m × longueur "&FIXED('PARAMÈTRES'!$C$10,2,TRUE)&" m – H sablière "&FIXED('PARAMÈTRES'!$C$11,2,TRUE)&" m – pente "&FIXED('PARAMÈTRES'!$C$12*100,1,TRUE)&" % – "&'PRÉDIMENSIONNEMENT'!$C$26&" – façade : "&'PARAMÈTRES'!$C$51 -> Gabarit 20 × 40 : portée 20.00 m × longueur 40.00 m – H sablière 6.00 m – pente 16.0 % – Portique IPE avec jarrets – façade : Bardage bac acier | J209: ESQUISSE NON CONTRACTUELLE
B210: Couleurs : charpente en bleu · contreventements en orange · béton en gris · aciers en rouge · maçonnerie en marron clair · cotes et baies en noir · translucides en bleu clair · remblai en latérite | J210: BON POUR ACCORD
B211: ="Légende aciers : semelles isolées "&'PARAMÈTRES'!$C$97&" maille "&'PARAMÈTRES'!$C$96*100&" cm ; fûts "&'PARAMÈTRES'!$C$99&" "&'PARAMÈTRES'!$C$98&" + cadres "&'PARAMÈTRES'!$C$100&" e = "&'PARAMÈTRES'!$C$101*100&" cm ; semelle filante "&'PARAMÈTRES'!$C$105&" "&'PARAMÈTRES'!$C$104&" + "&'PARAMÈTRES'!$C$106&" e = "&'PARAMÈTRES'!$C$107*100&" cm ; dallage "&'PARAMÈTRES'!$C$115&" "&'PARAMÈTRES'!$C$116&" (X) / "&'PARAMÈTRES'!$C$117&" (Y)"&IF('GROS_ŒUVRE'!$E$9=1," + nappe sup. "&'PARAMÈTRES'!$C$118&" / "&'PARAMÈTRES'!$C$119&" + chaises "&'PARAMÈTRES'!$C$122,"")&", maille "&'GROS_ŒUVRE'!$E$8*100&" cm." -> Légende aciers : semelles isolées HA12 maille 15 cm ; fûts 4 HA12 + cadres HA6 e = 15 cm ; semelle filante 4 HA10 + HA8 e = 20 cm ; dallage Nappe simple HA10 (X) / HA10 (Y), maille 20 cm. | J211: Date :
J212: Signature :
B213: Échelle : automatique (même échelle en X et en Y) – cotes en mètres
B217: PLANCHE 7 / 7 – ÉLÉVATION MUR AGGLOS – PANNEAU TYPE
B244: ÉLÉVATION MUR AGGLOS – PANNEAU TYPE | J244: Planche n° 7 / 7 | L244: Date : | M244: =TODAY() -> 46301
B245: ="Gabarit "&'ACCUEIL'!$D$6&" : portée "&FIXED('PARAMÈTRES'!$C$9,2,TRUE)&" m × longueur "&FIXED('PARAMÈTRES'!$C$10,2,TRUE)&" m – H sablière "&FIXED('PARAMÈTRES'!$C$11,2,TRUE)&" m – pente "&FIXED('PARAMÈTRES'!$C$12*100,1,TRUE)&" % – "&'PRÉDIMENSIONNEMENT'!$C$26&" – façade : "&'PARAMÈTRES'!$C$51 -> Gabarit 20 × 40 : portée 20.00 m × longueur 40.00 m – H sablière 6.00 m – pente 16.0 % – Portique IPE avec jarrets – façade : Bardage bac acier | J245: ESQUISSE NON CONTRACTUELLE
B246: Couleurs : charpente en bleu · contreventements en orange · béton en gris · aciers en rouge · maçonnerie en marron clair · cotes et baies en noir · translucides en bleu clair · remblai en latérite | J246: BON POUR ACCORD
B247: ="Sections : chaînages "&'PARAMÈTRES'!$C$129*100&" × "&'PARAMÈTRES'!$C$130*100&" cm et raidisseurs "&'PARAMÈTRES'!$C$135*100&" × "&'PARAMÈTRES'!$C$135*100&" cm – "&'PARAMÈTRES'!$C$132&" "&'PARAMÈTRES'!$C$131&" + cadres "&'PARAMÈTRES'!$C$133&" e = "&'PARAMÈTRES'!$C$134*100&" cm ; linteaux idem avec appuis de "&'PARAMÈTRES'!$C$137*100&" cm." -> Sections : chaînages 15 × 20 cm et raidisseurs 15 × 15 cm – 4 HA10 + cadres HA6 e = 20 cm ; linteaux idem avec appuis de 20 cm. | J247: Date :
J248: Signature :
B249: Échelle : automatique (même échelle en X et en Y) – cotes en mètres

Sheet COORD_PLANS
A1: COORDONNÉES DES ESQUISSES (feuille masquée, calculée) – les #N/A sont des ruptures de trait volontaires
G3: P1 – Axes des files | I3: P1 – Semelles filantes | K3: P1 – Semelles isolées | M3: P1 – Poteaux de portique | O3: P1 – Poteaux de pignon | Q3: P1 – Baies | S3: P1 – étiquette | U3: P1 – étiquette | W3: P1 – étiquette | Y3: P1 – étiquette | AA3: P1 – étiquette | AC3: P1 – étiquette | AE3: P1 – étiquette | AG3: P1 – étiquette | AI3: P1 – cote | AK3: P1 – cote | AM3: P1 – cote | AO3: P1 – étiquette | AQ3: P1 – étiquette | AS3: P1 – étiquette | AU3: P1 – étiquette | AW3: P1 – étiquette | AY3: P1 – étiquette | BA3: P1 – étiquette | BC3: P1 – étiquette | BE3: P1 – étiquette | BG3: P1 – étiquette | BI3: P1 – étiquette | BK3: P1 – étiquette | BM3: P1 – étiquette | BO3: P1 – étiquette | BQ3: P1 – étiquette | BS3: P1 – étiquette | BU3: P1 – étiquette | BW3: P1 – étiquette | BY3: P1 – étiquette | CA3: P1 – étiquette | CC3: P1 – étiquette | CE3: P1 – étiquette | CG3: P1 – étiquette | CI3: P1 – étiquette | CK3: P1 – étiquette | CM3: P1 – étiquette | CO3: P1 – étiquette | CQ3: P1 – étiquette | CS3: P1 – étiquette | CU3: P1 – étiquette | CW3: P1 – étiquette | CY3: P1 – étiquette | DA3: P1 – étiquette | DC3: P1 – étiquette | DE3: P1 – étiquette | DG3: P1 – étiquette | DI3: P1 – étiquette | DK3: P1 – étiquette | DM3: P1 – étiquette | DO3: P1 – étiquette | DQ3: P1 – étiquette | DS3: P1 – étiquette | DU3: P1 – étiquette | DW3: P2 – Sol / dallage | DY3: P2 – Ossature | EA3: P2 – Treillis | EC3: P2 – Jarrets | EE3: P2 – Pannes | EG3: P2 – Faîtage | EI3: P2 – Chéneaux | EK3: P2 – Fondations | EM3: P2 – cote | EO3: P2 – cote | EQ3: P2 – cote | ES3: P2 – étiquette | EU3: P2 – étiquette | EW3: P2 – étiquette | EY3: P3 – Sol | FA3: P3 – Poteaux et sablière | FC3: P3 – Lisses | FE3: P3 – Maçonnerie agglos | FG3: P3 – Chaînages | FI3: P3 – Croix de contreventement | FK3: P3 – Potelets et linteaux | FM3: P3 – Baies et larmiers | FO3: P3 – étiquette | FQ3: P3 – étiquette | FS3: P3 – étiquette | FU3: P3 – étiquette | FW3: P3 – cote | FY3: P3 – cote | GA3: P3 – cote | GC3: P4 – Sol | GE3: P4 – Poteaux de pignon et rampants | GG3: P4 – Lisses | GI3: P4 – Maçonnerie agglos | GK3: P4 – Chaînages | GM3: P4 – Potelets et linteaux | GO3: P4 – Baies et larmiers | GQ3: P4 – étiquette | GS3: P4 – étiquette | GU3: P4 – étiquette | GW3: P4 – étiquette | GY3: P4 – cote | HA3: P4 – cote | HC3: P4 – cote | HE3: P4 – étiquette | HG3: P5 – Rives et égouts | HI3: P5 – Pannes | HK3: P5 – Fermes / traverses | HM3: P5 – Liernes | HO3: P5 – Faîtière | HQ3: P5 – Poutre au vent | HS3: P5 – Translucides (hachurés) | HU3: P5 – Skydomes et chevêtres | HW3: P5 – Descentes EP | HY3: P5 – cote | IA3: P5 – cote | IC3: P5 – étiquette | IE3: P5 – étiquette | IG3: P5 – étiquette | II3: P6 – Terrain naturel | IK3: P6 – Béton | IM3: P6 – Maçonnerie | IO3: P6 – Remblai latérite | IQ3: P6 – Polyane | IS3: P6 – Lit de sable | IU3: P6 – Aciers | IW3: P6 – Aciers (sections) | IY3: P6 – Platine et poteau | JA3: P6 – cote | JC3: P6 – cote | JE3: P6 – cote | JG3: P6 – étiquette | JI3: P6 – étiquette | JK3: P6 – étiquette | JM3: P6 – étiquette | JO3: P6 – étiquette | JQ3: P6 – étiquette | JS3: P6 – étiquette | JU3: P6 – étiquette | JW3: P6 – Repères | JY3: P6 – étiquette | KA3: P6 – étiquette | KC3: P7 – Sol | KE3: P7 – Poteaux métalliques | KG3: P7 – Béton (chaînages, raidisseurs) | KI3: P7 – Agglos 15 creux | KK3: P7 – Aciers | KM3: P7 – cote | KO3: P7 – cote | KQ3: P7 – étiquette | KS3: P7 – étiquette | KU3: P7 – étiquette | KW3: P7 – étiquette | KY3: P7 – étiquette
A4: Grandeur | B4: Valeur | D4: Texte | E4: Contenu | G4: X | H4: Y | I4: X | J4: Y | K4: X | L4: Y | M4: X | N4: Y | O4: X | P4: Y | Q4: X | R4: Y | S4: X | T4: Y | U4: X | V4: Y | W4: X | X4: Y | Y4: X | Z4: Y | AA4: X | AB4: Y | AC4: X | AD4: Y | AE4: X | AF4: Y | AG4: X | AH4: Y | AI4: X | AJ4: Y | AK4: X | AL4: Y | AM4: X | AN4: Y | AO4: X | AP4: Y | AQ4: X | AR4: Y | AS4: X | AT4: Y | AU4: X | AV4: Y | AW4: X | AX4: Y | AY4: X | AZ4: Y | BA4: X | BB4: Y | BC4: X | BD4: Y | BE4: X | BF4: Y | BG4: X | BH4: Y | BI4: X | BJ4: Y | BK4: X | BL4: Y | BM4: X | BN4: Y | BO4: X | BP4: Y | BQ4: X | BR4: Y | BS4: X | BT4: Y | BU4: X | BV4: Y | BW4: X | BX4: Y | BY4: X | BZ4: Y | CA4: X | CB4: Y | CC4: X | CD4: Y | CE4: X | CF4: Y | CG4: X | CH4: Y | CI4: X | CJ4: Y | CK4: X | CL4: Y | CM4: X | CN4: Y | CO4: X | CP4: Y | CQ4: X | CR4: Y | CS4: X | CT4: Y | CU4: X | CV4: Y | CW4: X | CX4: Y | CY4: X | CZ4: Y | DA4: X | DB4: Y | DC4: X | DD4: Y | DE4: X | DF4: Y | DG4: X | DH4: Y | DI4: X | DJ4: Y | DK4: X | DL4: Y | DM4: X | DN4: Y | DO4: X | DP4: Y | DQ4: X | DR4: Y | DS4: X | DT4: Y | DU4: X | DV4: Y | DW4: X | DX4: Y | DY4: X | DZ4: Y | EA4: X | EB4: Y | EC4: X | ED4: Y | EE4: X | EF4: Y | EG4: X | EH4: Y | EI4: X | EJ4: Y | EK4: X | EL4: Y | EM4: X | EN4: Y | EO4: X | EP4: Y | EQ4: X | ER4: Y | ES4: X | ET4: Y | EU4: X | EV4: Y | EW4: X | EX4: Y | EY4: X | EZ4: Y | FA4: X | FB4: Y | FC4: X | FD4: Y | FE4: X | FF4: Y | FG4: X | FH4: Y | FI4: X | FJ4: Y | FK4: X | FL4: Y | FM4: X | FN4: Y | FO4: X | FP4: Y | FQ4: X | FR4: Y | FS4: X | FT4: Y | FU4: X | FV4: Y | FW4: X | FX4: Y | FY4: X | FZ4: Y | GA4: X | GB4: Y | GC4: X | GD4: Y | GE4: X | GF4: Y | GG4: X | GH4: Y | GI4: X | GJ4: Y | GK4: X | GL4: Y | GM4: X | GN4: Y | GO4: X | GP4: Y | GQ4: X | GR4: Y | GS4: X | GT4: Y | GU4: X | GV4: Y | GW4: X | GX4: Y | GY4: X | GZ4: Y | HA4: X | HB4: Y | HC4: X | HD4: Y | HE4: X | HF4: Y | HG4: X | HH4: Y | HI4: X | HJ4: Y | HK4: X | HL4: Y | HM4: X | HN4: Y | HO4: X | HP4: Y | HQ4: X | HR4: Y | HS4: X | HT4: Y | HU4: X | HV4: Y | HW4: X | HX4: Y | HY4: X | HZ4: Y | IA4: X | IB4: Y | IC4: X | ID4: Y | IE4: X | IF4: Y | IG4: X | IH4: Y | II4: X | IJ4: Y | IK4: X | IL4: Y | IM4: X | IN4: Y | IO4: X | IP4: Y | IQ4: X | IR4: Y | IS4: X | IT4: Y | IU4: X | IV4: Y | IW4: X | IX4: Y | IY4: X | IZ4: Y | JA4: X | JB4: Y | JC4: X | JD4: Y | JE4: X | JF4: Y | JG4: X | JH4: Y | JI4: X | JJ4: Y | JK4: X | JL4: Y | JM4: X | JN4: Y | JO4: X | JP4: Y | JQ4: X | JR4: Y | JS4: X | JT4: Y | JU4: X | JV4: Y | JW4: X | JX4: Y | JY4: X | JZ4: Y | KA4: X | KB4: Y | KC4: X | KD4: Y | KE4: X | KF4: Y | KG4: X | KH4: Y | KI4: X | KJ4: Y | KK4: X | KL4: Y | KM4: X | KN4: Y | KO4: X | KP4: Y | KQ4: X | KR4: Y | KS4: X | KT4: Y | KU4: X | KV4: Y | KW4: X | KX4: Y | KY4: X | KZ4: Y
A5: B | B5: ='PARAMÈTRES'!$C$9 -> 20 | D5: LP_txt1 | E5: =IF(1<=$B$68,"Porte coul. ","Portillon ")&FIXED($B$72,2,TRUE)&" × "&FIXED($B$73,2,TRUE) -> Portillon 5.50 × 4.00 | G5: =IF(0<=$B$12,$B$133+$B$132*($B$13*0),NA()) -> 31.591 | H5: =IF(0<=$B$12,$B$134+$B$132*(-4*$B$135),NA()) -> 12 | I5: =$B$133+$B$132*(-$B$31/2) -> 30.571 | J5: =$B$134+$B$132*(-$B$31/2) -> 14.98 | K5: =IF(0<=$B$12,$B$133+$B$132*($B$13*0-$B$27/2),NA()) -> 29.551 | L5: =IF(0<=$B$12,$B$134+$B$132*(0-$B$27/2),NA()) -> 13.96 | M5: =IF(0<=$B$12,$B$133+$B$132*($B$13*0),NA()) -> 31.591 | N5: =IF(0<=$B$12,$B$134+$B$132*(0),NA()) -> 16 | O5: =IF(1<=$B$14-1,$B$133+$B$132*(0),NA()) -> 31.591 | P5: =IF(1<=$B$14-1,$B$134+$B$132*(1*$B$15),NA()) -> 33 | Q5: =IF($B$71=1,$B$133+$B$132*($B$76),NA()) -> 90.241 | R5: =IF($B$71=1,$B$134+$B$132*(-2.5*$B$135),NA()) -> 13.5 | S5: =IF($B$71=1,$B$133+$B$132*($B$75),NA()) -> 99.591 | T5: =IF($B$71=1,$B$134+$B$132*(-2.5*$B$135),NA()) -> 13.5 | U5: =IF($B$78=1,$B$133+$B$132*($B$82),NA()) -> #N/A | V5: =IF($B$78=1,$B$134+$B$132*(-2.5*$B$135),NA()) -> #N/A | W5: =IF($B$85=1,$B$133+$B$132*($B$89),NA()) -> #N/A | X5: =IF($B$85=1,$B$134+$B$132*(-2.5*$B$135),NA()) -> #N/A | Y5: =IF($B$92=1,$B$133+$B$132*($B$96),NA()) -> #N/A | Z5: =IF($B$92=1,$B$134+$B$132*(-2.5*$B$135),NA()) -> #N/A | AA5: =IF($B$102=1,$B$133+$B$132*(-2.5*$B$135),NA()) -> 29.091 | AB5: =IF($B$102=1,$B$134+$B$132*($B$106),NA()) -> 41.5 | AC5: =IF($B$109=1,$B$133+$B$132*(-2.5*$B$135),NA()) -> #N/A | AD5: =IF($B$109=1,$B$134+$B$132*($B$113),NA()) -> #N/A | AE5: =IF($B$116=1,$B$133+$B$132*(-2.5*$B$135),NA()) -> #N/A | AF5: =IF($B$116=1,$B$134+$B$132*($B$120),NA()) -> #N/A | AG5: =IF($B$123=1,$B$133+$B$132*(-2.5*$B$135),NA()) -> #N/A | AH5: =IF($B$123=1,$B$134+$B$132*($B$127),NA()) -> #N/A | AI5: =$B$133+$B$132*(0) -> 31.591 | AJ5: =$B$134+$B$132*(-11*$B$135+1.2*$B$135) -> 6.2 | AK5: =$B$133+$B$132*(-12*$B$135+1.2*$B$135) -> 20.791 | AL5: =$B$134+$B$132*(0) -> 16 | AM5: =$B$133+$B$132*(0) -> 31.591 | AN5: =$B$134+$B$132*($B$5+6*$B$135+1.2*$B$135) -> 91.2 | AO5: =IF(0<=$B$12,$B$133+$B$132*($B$13*0),NA()) -> 31.591 | AP5: =IF(0<=$B$12,$B$134+$B$132*($B$5+11*$B$135),NA()) -> 95 | AQ5: =IF(1<=$B$12,$B$133+$B$132*($B$13*1),NA()) -> 51.019571 | AR5: =IF(1<=$B$12,$B$134+$B$132*($B$5+11*$B$135),NA()) -> 95 | AS5: =IF(2<=$B$12,$B$133+$B$132*($B$13*2),NA()) -> 70.448143 | AT5: =IF(2<=$B$12,$B$134+$B$132*($B$5+11*$B$135),NA()) -> 95 | AU5: =IF(3<=$B$12,$B$133+$B$132*($B$13*3),NA()) -> 89.876714 | AV5: =IF(3<=$B$12,$B$134+$B$132*($B$5+11*$B$135),NA()) -> 95 | AW5: =IF(4<=$B$12,$B$133+$B$132*($B$13*4),NA()) -> 109.30529 | AX5: =IF(4<=$B$12,$B$134+$B$132*($B$5+11*$B$135),NA()) -> 95 | AY5: =IF(5<=$B$12,$B$133+$B$132*($B$13*5),NA()) -> 128.73386 | AZ5: =IF(5<=$B$12,$B$134+$B$132*($B$5+11*$B$135),NA()) -> 95 | BA5: =IF(6<=$B$12,$B$133+$B$132*($B$13*6),NA()) -> 148.16243 | BB5: =IF(6<=$B$12,$B$134+$B$132*($B$5+11*$B$135),NA()) -> 95 | BC5: =IF(7<=$B$12,$B$133+$B$132*($B$13*7),NA()) -> 167.591 | BD5: =IF(7<=$B$12,$B$134+$B$132*($B$5+11*$B$135),NA()) -> 95 | BE5: =IF(8<=$B$12,$B$133+$B$132*($B$13*8),NA()) -> #N/A | BF5: =IF(8<=$B$12,$B$134+$B$132*($B$5+11*$B$135),NA()) -> #N/A | BG5: =IF(9<=$B$12,$B$133+$B$132*($B$13*9),NA()) -> #N/A | BH5: =IF(9<=$B$12,$B$134+$B$132*($B$5+11*$B$135),NA()) -> #N/A | BI5: =IF(10<=$B$12,$B$133+$B$132*($B$13*10),NA()) -> #N/A | BJ5: =IF(10<=$B$12,$B$134+$B$132*($B$5+11*$B$135),NA()) -> #N/A | BK5: =IF(11<=$B$12,$B$133+$B$132*($B$13*11),NA()) -> #N/A | BL5: =IF(11<=$B$12,$B$134+$B$132*($B$5+11*$B$135),NA()) -> #N/A | BM5: =IF(12<=$B$12,$B$133+$B$132*($B$13*12),NA()) -> #N/A | BN5: =IF(12<=$B$12,$B$134+$B$132*($B$5+11*$B$135),NA()) -> #N/A | BO5: =IF(13<=$B$12,$B$133+$B$132*($B$13*13),NA()) -> #N/A | BP5: =IF(13<=$B$12,$B$134+$B$132*($B$5+11*$B$135),NA()) -> #N/A | BQ5: =IF(14<=$B$12,$B$133+$B$132*($B$13*14),NA()) -> #N/A | BR5: =IF(14<=$B$12,$B$134+$B$132*($B$5+11*$B$135),NA()) -> #N/A | BS5: =IF(15<=$B$12,$B$133+$B$132*($B$13*15),NA()) -> #N/A | BT5: =IF(15<=$B$12,$B$134+$B$132*($B$5+11*$B$135),NA()) -> #N/A | BU5: =IF(16<=$B$12,$B$133+$B$132*($B$13*16),NA()) -> #N/A | BV5: =IF(16<=$B$12,$B$134+$B$132*($B$5+11*$B$135),NA()) -> #N/A | BW5: =IF(17<=$B$12,$B$133+$B$132*($B$13*17),NA()) -> #N/A | BX5: =IF(17<=$B$12,$B$134+$B$132*($B$5+11*$B$135),NA()) -> #N/A | BY5: =IF(18<=$B$12,$B$133+$B$132*($B$13*18),NA()) -> #N/A | BZ5: =IF(18<=$B$12,$B$134+$B$132*($B$5+11*$B$135),NA()) -> #N/A | CA5: =IF(19<=$B$12,$B$133+$B$132*($B$13*19),NA()) -> #N/A | CB5: =IF(19<=$B$12,$B$134+$B$132*($B$5+11*$B$135),NA()) -> #N/A | CC5: =IF(20<=$B$12,$B$133+$B$132*($B$13*20),NA()) -> #N/A | CD5: =IF(20<=$B$12,$B$134+$B$132*($B$5+11*$B$135),NA()) -> #N/A | CE5: =IF(21<=$B$12,$B$133+$B$132*($B$13*21),NA()) -> #N/A | CF5: =IF(21<=$B$12,$B$134+$B$132*($B$5+11*$B$135),NA()) -> #N/A | CG5: =IF(22<=$B$12,$B$133+$B$132*($B$13*22),NA()) -> #N/A | CH5: =IF(22<=$B$12,$B$134+$B$132*($B$5+11*$B$135),NA()) -> #N/A | CI5: =IF(23<=$B$12,$B$133+$B$132*($B$13*23),NA()) -> #N/A | CJ5: =IF(23<=$B$12,$B$134+$B$132*($B$5+11*$B$135),NA()) -> #N/A | CK5: =IF(24<=$B$12,$B$133+$B$132*($B$13*24),NA()) -> #N/A | CL5: =IF(24<=$B$12,$B$134+$B$132*($B$5+11*$B$135),NA()) -> #N/A | CM5: =IF(25<=$B$12,$B$133+$B$132*($B$13*25),NA()) -> #N/A | CN5: =IF(25<=$B$12,$B$134+$B$132*($B$5+11*$B$135),NA()) -> #N/A | CO5: =IF(26<=$B$12,$B$133+$B$132*($B$13*26),NA()) -> #N/A | CP5: =IF(26<=$B$12,$B$134+$B$132*($B$5+11*$B$135),NA()) -> #N/A | CQ5: =IF(27<=$B$12,$B$133+$B$132*($B$13*27),NA()) -> #N/A | CR5: =IF(27<=$B$12,$B$134+$B$132*($B$5+11*$B$135),NA()) -> #N/A | CS5: =IF(28<=$B$12,$B$133+$B$132*($B$13*28),NA()) -> #N/A | CT5: =IF(28<=$B$12,$B$134+$B$132*($B$5+11*$B$135),NA()) -> #N/A | CU5: =IF(29<=$B$12,$B$133+$B$132*($B$13*29),NA()) -> #N/A | CV5: =IF(29<=$B$12,$B$134+$B$132*($B$5+11*$B$135),NA()) -> #N/A | CW5: =IF(30<=$B$12,$B$133+$B$132*($B$13*30),NA()) -> #N/A | CX5: =IF(30<=$B$12,$B$134+$B$132*($B$5+11*$B$135),NA()) -> #N/A | CY5: =IF(31<=$B$12,$B$133+$B$132*($B$13*31),NA()) -> #N/A | CZ5: =IF(31<=$B$12,$B$134+$B$132*($B$5+11*$B$135),NA()) -> #N/A | DA5: =IF(32<=$B$12,$B$133+$B$132*($B$13*32),NA()) -> #N/A | DB5: =IF(32<=$B$12,$B$134+$B$132*($B$5+11*$B$135),NA()) -> #N/A | DC5: =IF(33<=$B$12,$B$133+$B$132*($B$13*33),NA()) -> #N/A | DD5: =IF(33<=$B$12,$B$134+$B$132*($B$5+11*$B$135),NA()) -> #N/A | DE5: =IF(34<=$B$12,$B$133+$B$132*($B$13*34),NA()) -> #N/A | DF5: =IF(34<=$B$12,$B$134+$B$132*($B$5+11*$B$135),NA()) -> #N/A | DG5: =IF(35<=$B$12,$B$133+$B$132*($B$13*35),NA()) -> #N/A | DH5: =IF(35<=$B$12,$B$134+$B$132*($B$5+11*$B$135),NA()) -> #N/A | DI5: =IF(36<=$B$12,$B$133+$B$132*($B$13*36),NA()) -> #N/A | DJ5: =IF(36<=$B$12,$B$134+$B$132*($B$5+11*$B$135),NA()) -> #N/A | DK5: =IF(37<=$B$12,$B$133+$B$132*($B$13*37),NA()) -> #N/A | DL5: =IF(37<=$B$12,$B$134+$B$132*($B$5+11*$B$135),NA()) -> #N/A | DM5: =IF(38<=$B$12,$B$133+$B$132*($B$13*38),NA()) -> #N/A | DN5: =IF(38<=$B$12,$B$134+$B$132*($B$5+11*$B$135),NA()) -> #N/A | DO5: =IF(39<=$B$12,$B$133+$B$132*($B$13*39),NA()) -> #N/A | DP5: =IF(39<=$B$12,$B$134+$B$132*($B$5+11*$B$135),NA()) -> #N/A | DQ5: =IF(40<=$B$12,$B$133+$B$132*($B$13*40),NA()) -> #N/A | DR5: =IF(40<=$B$12,$B$134+$B$132*($B$5+11*$B$135),NA()) -> #N/A | DS5: =$B$133+$B$132*($B$6+6*$B$135) -> 173.591 | DT5: =$B$134+$B$132*(0) -> 16 | DU5: =$B$133+$B$132*($B$6+6*$B$135) -> 173.591 | DV5: =$B$134+$B$132*($B$5) -> 84 | DW5: =$B$139+$B$138*(-6*$B$141) -> 14 | DX5: =$B$140+$B$138*(0) -> 27.873835 | DY5: =$B$139+$B$138*(0) -> 20 | DZ5: =$B$140+$B$138*(0) -> 27.873835 | EA5: =IF(AND($B$18=1,1<=$B$26-1),$B$139+$B$138*(1*($B$5/MAX(1,$B$26))),NA()) -> #N/A | EB5: =IF(AND($B$18=1,1<=$B$26-1),$B$140+$B$138*($B$7),NA()) -> #N/A | EC5: =IF($B$18=0,$B$139+$B$138*(0),NA()) -> 20 | ED5: =IF($B$18=0,$B$140+$B$138*($B$7-$B$54),NA()) -> 71.530705 | EE5: =IF(0<=$B$16-1,$B$139+$B$138*(0*($B$5/2)/MAX(1,$B$16-1)),NA()) -> 20 | EF5: =IF(0<=$B$16-1,$B$140+$B$138*($B$9+$B$8*0*($B$5/2)/MAX(1,$B$16-1)+1.2*$B$141),NA()) -> 75.028435 | EG5: =$B$139+$B$138*($B$5/2) -> 96.591 | EH5: =$B$140+$B$138*($B$10+3*$B$141) -> 89.082995 | EI5: =$B$139+$B$138*(-3.5*$B$141) -> 16.5 | EJ5: =$B$140+$B$138*($B$9+1.5*$B$141) -> 75.328435 | EK5: =$B$139+$B$138*(0-$B$27/2) -> 15.40454 | EL5: =$B$140+$B$138*((-$B$33+$B$34)) -> 19.06587 | EM5: =$B$139+$B$138*(-9*$B$141+1.2*$B$141) -> 12.2 | EN5: =$B$140+$B$138*(0) -> 27.873835 | EO5: =$B$139+$B$138*($B$5+9*$B$141+1.2*$B$141) -> 183.382 | EP5: =$B$140+$B$138*(0) -> 27.873835 | EQ5: =$B$139+$B$138*(0) -> 20 | ER5: =$B$140+$B$138*(-$B$33-4*$B$141+1.2*$B$141) -> 15.882915 | ES5: =$B$139+$B$138*($B$5/4) -> 58.2955 | ET5: =$B$140+$B$138*($B$9+$B$8*$B$5/4+5*$B$141) -> 84.955715 | EU5: =$B$139+$B$138*($B$5/2) -> 96.591 | EV5: =$B$140+$B$138*($B$7/2) -> 50.851135 | EW5: =$B$139+$B$138*($B$5/2) -> 96.591 | EX5: =$B$140+$B$138*($B$10+7*$B$141) -> 93.082995 | EY5: =$B$145+$B$144*(-5*$B$147) -> 15 | EZ5: =$B$146+$B$144*(0) -> 38.76135 | FA5: =IF(0<=$B$12,$B$145+$B$144*($B$13*0),NA()) -> 20 | FB5: =IF(0<=$B$12,$B$146+$B$144*(0),NA()) -> 38.76135 | FC5: =IF(0<$B$22,$B$145+$B$144*(0),NA()) -> 20 | FD5: =IF(0<$B$22,$B$146+$B$144*(($B$19+0*$B$64)),NA()) -> 38.76135 | FE5: =IF(AND($B$21=1,(1*$B$66)<$B$62),$B$145+$B$144*(0),NA()) -> #N/A | FF5: =IF(AND($B$21=1,(1*$B$66)<$B$62),$B$146+$B$144*((1*$B$66)),NA()) -> #N/A | FG5: =IF($B$21=1,$B$145+$B$144*(0),NA()) -> #N/A | FH5: =IF($B$21=1,$B$146+$B$144*($B$59/2),NA()) -> #N/A | FI5: =IF(1<=$B$23,$B$145+$B$144*((IF(1=1,1,IF(1=$B$23,$B$12,5*(1-1)))-1)*$B$13),NA()) -> 20 | FJ5: =IF(1<=$B$23,$B$146+$B$144*(0),NA()) -> 38.76135 | FK5: =IF($B$71=1,$B$145+$B$144*($B$76),NA()) -> 90.372237 | FL5: =IF($B$71=1,$B$146+$B$144*(0),NA()) -> 38.76135 | FM5: =IF($B$71=1,$B$145+$B$144*($B$76),NA()) -> 90.372237 | FN5: =IF($B$71=1,$B$146+$B$144*(0),NA()) -> 38.76135 | FO5: =IF($B$71=1,$B$145+$B$144*($B$75),NA()) -> 101.591 | FP5: =IF($B$71=1,$B$146+$B$144*($B$73+0.15),NA()) -> 55.691482 | FQ5: =IF($B$78=1,$B$145+$B$144*($B$82),NA()) -> #N/A | FR5: =IF($B$78=1,$B$146+$B$144*($B$80+0.15),NA()) -> #N/A | FS5: =IF($B$85=1,$B$145+$B$144*($B$89),NA()) -> #N/A | FT5: =IF($B$85=1,$B$146+$B$144*($B$87+0.15),NA()) -> #N/A | FU5: =IF($B$92=1,$B$145+$B$144*($B$96),NA()) -> #N/A | FV5: =IF($B$92=1,$B$146+$B$144*($B$94+0.15),NA()) -> #N/A | FW5: =$B$145+$B$144*(0) -> 20 | FX5: =$B$146+$B$144*(-6*$B$147+1.2*$B$147) -> 33.96135 | FY5: =$B$145+$B$144*(-9*$B$147+1.2*$B$147) -> 12.2 | FZ5: =$B$146+$B$144*(0) -> 38.76135 | GA5: =$B$145+$B$144*(0) -> 20 | GB5: =$B$146+$B$144*($B$9+$B$53+4*$B$147+1.2*$B$147) -> 68.43865 | GC5: =$B$151+$B$150*(-5*$B$153) -> 15 | GD5: =$B$152+$B$150*(0) -> 23.89542 | GE5: =$B$151+$B$150*(0) -> 20 | GF5: =$B$152+$B$150*(0) -> 23.89542 | GG5: =IF(AND($B$20=1,($B$19+0*$B$64)<$B$10-0.3),$B$151+$B$150*(IF(($B$19+0*$B$64)<=$B$9,0,(($B$19+0*$B$64)-$B$9)/$B$8)),NA()) -> 20 | GH5: =IF(AND($B$20=1,($B$19+0*$B$64)<$B$10-0.3),$B$152+$B$150*(($B$19+0*$B$64)),NA()) -> 23.89542 | GI5: =IF(AND($B$21=1,(1*$B$66)<IF($B$63=1,$B$10-0.2,$B$62)),$B$151+$B$150*(IF((1*$B$66)<=$B$9,0,((1*$B$66)-$B$9)/$B$8)),NA()) -> #N/A | GJ5: =IF(AND($B$21=1,(1*$B$66)<IF($B$63=1,$B$10-0.2,$B$62)),$B$152+$B$150*((1*$B$66)),NA()) -> #N/A | GK5: =IF($B$21=1,$B$151+$B$150*(0),NA()) -> #N/A | GL5: =IF($B$21=1,$B$152+$B$150*($B$59/2),NA()) -> #N/A | GM5: =IF($B$102=1,$B$151+$B$150*($B$107),NA()) -> 62.12505 | GN5: =IF($B$102=1,$B$152+$B$150*(0),NA()) -> 23.89542 | GO5: =IF($B$102=1,$B$151+$B$150*($B$107),NA()) -> 62.12505 | GP5: =IF($B$102=1,$B$152+$B$150*(0),NA()) -> 23.89542 | GQ5: =IF($B$102=1,$B$151+$B$150*($B$106),NA()) -> 77.44325 | GR5: =IF($B$102=1,$B$152+$B$150*($B$104+0.15),NA()) -> 59.510235 | GS5: =IF($B$109=1,$B$151+$B$150*($B$113),NA()) -> #N/A | GT5: =IF($B$109=1,$B$152+$B$150*($B$111+0.15),NA()) -> #N/A | GU5: =IF($B$116=1,$B$151+$B$150*($B$120),NA()) -> #N/A | GV5: =IF($B$116=1,$B$152+$B$150*($B$118+0.15),NA()) -> #N/A | GW5: =IF($B$123=1,$B$151+$B$150*($B$127),NA()) -> #N/A | GX5: =IF($B$123=1,$B$152+$B$150*($B$125+0.15),NA()) -> #N/A | GY5: =$B$151+$B$150*(0) -> 20 | GZ5: =$B$152+$B$150*(-6*$B$153+1.2*$B$153) -> 19.09542 | HA5: =$B$151+$B$150*(-9*$B$153+1.2*$B$153) -> 12.2 | HB5: =$B$152+$B$150*(0) -> 23.89542 | HC5: =$B$151+$B$150*($B$5+9*$B$153+1.2*$B$153) -> 183.382 | HD5: =$B$152+$B$150*(0) -> 23.89542 | HE5: =$B$151+$B$150*($B$5/2) -> 96.591 | HF5: =$B$152+$B$150*($B$10+3*$B$153) -> 85.10458 | HG5: =$B$157+$B$156*(-$B$46) -> 21.451 | HH5: =$B$158+$B$156*(0) -> 14 | HI5: =IF(0<=$B$16-1,$B$157+$B$156*(-$B$46),NA()) -> 21.451 | HJ5: =IF(0<=$B$16-1,$B$158+$B$156*(0*($B$5/2)/MAX(1,$B$16-1)),NA()) -> 14 | HK5: =IF(0<=$B$12,$B$157+$B$156*($B$13*0),NA()) -> 22.591 | HL5: =IF(0<=$B$12,$B$158+$B$156*(0),NA()) -> 14 | HM5: =IF(AND(1<=$B$12,1<=$B$25),$B$157+$B$156*((1-1)*$B$13+1*$B$13/($B$25+1)),NA()) -> 33.448143 | HN5: =IF(AND(1<=$B$12,1<=$B$25),$B$158+$B$156*(0),NA()) -> 14 | HO5: =$B$157+$B$156*(-$B$46) -> 21.451 | HP5: =$B$158+$B$156*($B$5/2) -> 52 | HQ5: =IF(AND(1<=$B$23,1<=$B$24),$B$157+$B$156*((IF(1=1,1,IF(1=$B$23,$B$12,5*(1-1)))-1)*$B$13),NA()) -> 22.591 | HR5: =IF(AND(1<=$B$23,1<=$B$24),$B$158+$B$156*((0*$B$5/2+(1-1)*($B$5/2)/$B$24)),NA()) -> 14 | HS5: =IF(AND(1<=$B$12,$B$51>0),$B$157+$B$156*(((1-0.5)*$B$13)-($B$51*$B$13)/2),NA()) -> 32.362429 | HT5: =IF(AND(1<=$B$12,$B$51>0),$B$158+$B$156*((0*$B$5/2+0.6*$B$159)),NA()) -> 14.6 | HU5: =IF(1<=$B$47,$B$157+$B$156*(((MAX(1,MIN($B$12,ROUND(1*$B$12/($B$47+1),0)))-1)*$B$13+0.25*$B$13)-$B$48/2),NA()) -> 25.739571 | HV5: =IF(1<=$B$47,$B$158+$B$156*(IF(MOD(1,2)=1,$B$5/4,3*$B$5/4)-$B$49/2),NA()) -> 30.72 | HW5: =IF(1<=$B$50/2,$B$157+$B$156*((1-0.5)*$B$6/MAX(1,$B$50/2)),NA()) -> 47.924333 | HX5: =IF(1<=$B$50/2,$B$158+$B$156*(0),NA()) -> 14 | HY5: =$B$157+$B$156*(0) -> 22.591 | HZ5: =$B$158+$B$156*(-7*$B$159+1.2*$B$159) -> 8.2 | IA5: =$B$157+$B$156*(-$B$46-9*$B$159+1.2*$B$159) -> 13.651 | IB5: =$B$158+$B$156*(0) -> 14 | IC5: =$B$157+$B$156*($B$6+$B$46+2*$B$159) -> 177.731 | ID5: =$B$158+$B$156*($B$5/2) -> 52 | IE5: =$B$157+$B$156*($B$6+$B$46+2*$B$159) -> 177.731 | IF5: =$B$158+$B$156*($B$5/4) -> 33 | IG5: =$B$157+$B$156*($B$6/2) -> 98.591 | IH5: =$B$158+$B$156*(-2.5*$B$159) -> 11.5 | II5: =$B$174+$B$173*(-$B$31/2-0.3) -> 16 | IJ5: =$B$175+$B$173*(0) -> 51.3601 | IK5: =$B$174+$B$173*(-$B$31/2-0.05) -> 22.399 | IL5: =$B$175+$B$173*($B$160) -> 20.6449 | IM5: =$B$174+$B$173*(-0.075) -> 29.4379 | IN5: =$B$175+$B$173*($B$162) -> 27.0439 | IO5: =$B$174+$B$173*(0.075) -> 33.2773 | IP5: =$B$175+$B$173*($B$164) -> 56.4793 | IQ5: =$B$174+$B$173*(0.075) -> 33.2773 | IR5: =$B$175+$B$173*($B$165+0.005) -> 57.88708 | IS5: =$B$174+$B$173*(0.075) -> 33.2773 | IT5: =$B$175+$B$173*($B$164+$B$39/2) -> 57.1192 | IU5: =$B$174+$B$173*(-$B$31/2+$B$41) -> 24.9586 | IV5: =$B$175+$B$173*($B$161+$B$41) -> 23.2045 | IW5: =$B$174+$B$173*(-$B$31/2+$B$41+0*($B$31-2*$B$41)/3) -> 24.9586 | IX5: =$B$175+$B$173*($B$161+$B$41+0.02) -> 23.71642 | IY5: =$B$174+$B$173*($B$169-'PARAMÈTRES'!$H$18/2) -> 89.5885 | IZ5: =$B$175+$B$173*($B$168+0.025) -> 63.5182 | JA5: =$B$174+$B$173*(-$B$31/2-0.18+1.2*$B$176) -> 20.27152 | JB5: =$B$175+$B$173*($B$160) -> 20.6449 | JC5: =$B$174+$B$173*(-$B$31/2) -> 23.6788 | JD5: =$B$175+$B$173*($B$160-0.06+1.2*$B$176) -> 20.30914 | JE5: =$B$174+$B$173*($B$169-$B$27/2) -> 79.99 | JF5: =$B$175+$B$173*($B$160-0.06+1.2*$B$176) -> 20.30914 | JG5: =$B$174+$B$173*($B$170+5*$B$176) -> 136.182 | JH5: =$B$175+$B$173*((MAX($B$166,$B$168)+0.75)-0*6.5*$B$176) -> 82.0753 | JI5: =$B$174+$B$173*($B$170+5*$B$176) -> 136.182 | JJ5: =$B$175+$B$173*((MAX($B$166,$B$168)+0.75)-1*6.5*$B$176) -> 75.5753 | JK5: =$B$174+$B$173*($B$170+5*$B$176) -> 136.182 | JL5: =$B$175+$B$173*((MAX($B$166,$B$168)+0.75)-2*6.5*$B$176) -> 69.0753 | JM5: =$B$174+$B$173*($B$170+5*$B$176) -> 136.182 | JN5: =$B$175+$B$173*((MAX($B$166,$B$168)+0.75)-3*6.5*$B$176) -> 62.5753 | JO5: =$B$174+$B$173*($B$170+5*$B$176) -> 136.182 | JP5: =$B$175+$B$173*((MAX($B$166,$B$168)+0.75)-4*6.5*$B$176) -> 56.0753 | JQ5: =$B$174+$B$173*($B$170+5*$B$176) -> 136.182 | JR5: =$B$175+$B$173*((MAX($B$166,$B$168)+0.75)-5*6.5*$B$176) -> 49.5753 | JS5: =$B$174+$B$173*($B$170+5*$B$176) -> 136.182 | JT5: =$B$175+$B$173*((MAX($B$166,$B$168)+0.75)-6*6.5*$B$176) -> 43.0753 | JU5: =$B$174+$B$173*($B$170+5*$B$176) -> 136.182 | JV5: =$B$175+$B$173*((MAX($B$166,$B$168)+0.75)-7*6.5*$B$176) -> 36.5753 | JW5: =$B$174+$B$173*($B$169+$B$29/2-0.10) -> 97.9072 | JX5: =$B$175+$B$173*($B$168+0.06) -> 64.41406 | JY5: =$B$174+$B$173*(-0.075) -> 29.4379 | JZ5: =$B$175+$B$173*(($B$162+$B$163)/2) -> 39.8419 | KA5: =$B$174+$B$173*(0) -> 31.3576 | KB5: =$B$175+$B$173*($B$160-0.30) -> 12.9661 | KC5: =IF($B$21=1,$B$182+$B$181*(-3*$B$184),NA()) -> #N/A | KD5: =IF($B$21=1,$B$183+$B$181*(0),NA()) -> #N/A | KE5: =IF($B$21=1,$B$182+$B$181*(0),NA()) -> #N/A | KF5: =IF($B$21=1,$B$183+$B$181*(0),NA()) -> #N/A | KG5: =IF($B$21=1,$B$182+$B$181*(0),NA()) -> #N/A | KH5: =IF($B$21=1,$B$183+$B$181*(0),NA()) -> #N/A | KI5: =IF(AND($B$21=1,1*$B$67>$B$59,1*$B$67<$B$178-$B$59,OR($B$63=0,ABS(1*$B$67-$B$178/2)>$B$59/2)),$B$182+$B$181*(0),NA()) -> #N/A | KJ5: =IF(AND($B$21=1,1*$B$67>$B$59,1*$B$67<$B$178-$B$59,OR($B$63=0,ABS(1*$B$67-$B$178/2)>$B$59/2)),$B$183+$B$181*(1*$B$67),NA()) -> #N/A | KK5: =IF($B$21=1,$B$182+$B$181*(0),NA()) -> #N/A | KL5: =IF($B$21=1,$B$183+$B$181*($B$59/2-($B$59/2-$B$41*0.6)),NA()) -> #N/A | KM5: =IF($B$21=1,$B$182+$B$181*(0),NA()) -> #N/A | KN5: =IF($B$21=1,$B$183+$B$181*(-6*$B$184+1.2*$B$184),NA()) -> #N/A | KO5: =IF($B$21=1,$B$182+$B$181*(-6*$B$184+1.2*$B$184),NA()) -> #N/A | KP5: =IF($B$21=1,$B$183+$B$181*(0),NA()) -> #N/A | KQ5: =IF($B$21=1,$B$182+$B$181*($B$177+4*$B$184),NA()) -> #N/A | KR5: =IF($B$21=1,$B$183+$B$181*($B$178-$B$59/2),NA()) -> #N/A | KS5: =IF(AND($B$21=1,$B$63=1),$B$182+$B$181*($B$177+4*$B$184),NA()) -> #N/A | KT5: =IF(AND($B$21=1,$B$63=1),$B$183+$B$181*($B$178/2),NA()) -> #N/A | KU5: =IF($B$21=1,$B$182+$B$181*($B$177+4*$B$184),NA()) -> #N/A | KV5: =IF($B$21=1,$B$183+$B$181*($B$59/2),NA()) -> #N/A | KW5: =IF($B$21=1,$B$182+$B$181*($B$177/2),NA()) -> #N/A | KX5: =IF($B$21=1,$B$183+$B$181*($B$178+3*$B$184),NA()) -> #N/A | KY5: =IF($B$21=0,$B$182+$B$181*($B$177/2),NA()) -> 75.591 | KZ5: =IF($B$21=0,$B$183+$B$181*($B$178/2),NA()) -> 46.785787
A6: L | B6: ='PARAMÈTRES'!$C$10 -> 40 | D6: LP_txt2 | E6: =IF(2<=$B$68,"Porte coul. ","Portillon ")&FIXED($B$79,2,TRUE)&" × "&FIXED($B$80,2,TRUE) -> Portillon 5.50 × 0.00 | G6: =IF(0<=$B$12,$B$133+$B$132*($B$13*0),NA()) -> 31.591 | H6: =IF(0<=$B$12,$B$134+$B$132*($B$5+4*$B$135),NA()) -> 88 | I6: =$B$133+$B$132*($B$6+$B$31/2) -> 168.611 | J6: =$B$134+$B$132*(-$B$31/2) -> 14.98 | K6: =IF(0<=$B$12,$B$133+$B$132*($B$13*0+$B$27/2),NA()) -> 33.631 | L6: =IF(0<=$B$12,$B$134+$B$132*(0-$B$27/2),NA()) -> 13.96 | M6: =IF(0<=$B$12,$B$133+$B$132*($B$13*0),NA()) -> 31.591 | N6: =IF(0<=$B$12,$B$134+$B$132*($B$5),NA()) -> 84 | O6: =IF(1<=$B$14-1,$B$133+$B$132*($B$6),NA()) -> 167.591 | P6: =IF(1<=$B$14-1,$B$134+$B$132*(1*$B$15),NA()) -> 33 | Q6: =IF($B$71=1,$B$133+$B$132*($B$77),NA()) -> 108.941 | R6: =IF($B$71=1,$B$134+$B$132*(-2.5*$B$135),NA()) -> 13.5 | AI6: =$B$133+$B$132*(0) -> 31.591 | AJ6: =$B$134+$B$132*(-11*$B$135-1.2*$B$135) -> 3.8 | AK6: =$B$133+$B$132*(-12*$B$135-1.2*$B$135) -> 18.391 | AL6: =$B$134+$B$132*(0) -> 16 | AM6: =$B$133+$B$132*(0) -> 31.591 | AN6: =$B$134+$B$132*($B$5+6*$B$135-1.2*$B$135) -> 88.8 | DW6: =$B$139+$B$138*($B$5+6*$B$141) -> 179.182 | DX6: =$B$140+$B$138*(0) -> 27.873835 | DY6: =$B$139+$B$138*(0) -> 20 | DZ6: =$B$140+$B$138*($B$9) -> 73.828435 | EA6: =IF(AND($B$18=1,1<=$B$26-1),$B$139+$B$138*(1*($B$5/MAX(1,$B$26))),NA()) -> #N/A | EB6: =IF(AND($B$18=1,1<=$B$26-1),$B$140+$B$138*(($B$9+$B$8*MIN(1*($B$5/MAX(1,$B$26)),$B$5-(1*($B$5/MAX(1,$B$26)))))),NA()) -> #N/A | EC6: =IF($B$18=0,$B$139+$B$138*($B$55),NA()) -> 35.3182 | ED6: =IF($B$18=0,$B$140+$B$138*($B$7+$B$8*$B$55),NA()) -> 76.279347 | EE6: =IF(0<=$B$16-1,$B$139+$B$138*($B$5-0*($B$5/2)/MAX(1,$B$16-1)),NA()) -> 173.182 | EF6: =IF(0<=$B$16-1,$B$140+$B$138*($B$9+$B$8*0*($B$5/2)/MAX(1,$B$16-1)+1.2*$B$141),NA()) -> 75.028435 | EI6: =$B$139+$B$138*(-3.5*$B$141) -> 16.5 | EJ6: =$B$140+$B$138*($B$9-0.8*$B$141) -> 73.028435 | EK6: =$B$139+$B$138*(0+$B$27/2) -> 24.59546 | EL6: =$B$140+$B$138*((-$B$33+$B$34)) -> 19.06587 | EM6: =$B$139+$B$138*(-9*$B$141-1.2*$B$141) -> 9.8 | EN6: =$B$140+$B$138*(0) -> 27.873835 | EO6: =$B$139+$B$138*($B$5+9*$B$141-1.2*$B$141) -> 180.982 | EP6: =$B$140+$B$138*(0) -> 27.873835 | EQ6: =$B$139+$B$138*(0) -> 20 | ER6: =$B$140+$B$138*(-$B$33-4*$B$141-1.2*$B$141) -> 13.482915 | EY6: =$B$145+$B$144*($B$6+5*$B$147) -> 188.182 | EZ6: =$B$146+$B$144*(0) -> 38.76135 | FA6: =IF(0<=$B$12,$B$145+$B$144*($B$13*0),NA()) -> 20 | FB6: =IF(0<=$B$12,$B$146+$B$144*($B$9),NA()) -> 63.23865 | FC6: =IF(0<$B$22,$B$145+$B$144*(IF(($B$19+0*$B$64)<$B$73,$B$76,$B$75)),NA()) -> 90.372237 | FD6: =IF(0<$B$22,$B$146+$B$144*(($B$19+0*$B$64)),NA()) -> 38.76135 | FE6: =IF(AND($B$21=1,(1*$B$66)<$B$62),$B$145+$B$144*(IF((1*$B$66)<$B$73,$B$76,$B$75)),NA()) -> #N/A | FF6: =IF(AND($B$21=1,(1*$B$66)<$B$62),$B$146+$B$144*((1*$B$66)),NA()) -> #N/A | FG6: =IF($B$21=1,$B$145+$B$144*($B$6),NA()) -> #N/A | FH6: =IF($B$21=1,$B$146+$B$144*($B$59/2),NA()) -> #N/A | FI6: =IF(1<=$B$23,$B$145+$B$144*(IF(1=1,1,IF(1=$B$23,$B$12,5*(1-1)))*$B$13),NA()) -> 43.311714 | FJ6: =IF(1<=$B$23,$B$146+$B$144*($B$9),NA()) -> 63.23865 | FK6: =IF($B$71=1,$B$145+$B$144*($B$76),NA()) -> 90.372237 | FL6: =IF($B$71=1,$B$146+$B$144*($B$9),NA()) -> 63.23865 | FM6: =IF($B$71=1,$B$145+$B$144*($B$77),NA()) -> 112.80976 | FN6: =IF($B$71=1,$B$146+$B$144*($B$73),NA()) -> 55.07955 | FW6: =$B$145+$B$144*(0) -> 20 | FX6: =$B$146+$B$144*(-6*$B$147-1.2*$B$147) -> 31.56135 | FY6: =$B$145+$B$144*(-9*$B$147-1.2*$B$147) -> 9.8 | FZ6: =$B$146+$B$144*(0) -> 38.76135 | GA6: =$B$145+$B$144*(0) -> 20 | GB6: =$B$146+$B$144*($B$9+$B$53+4*$B$147-1.2*$B$147) -> 66.03865 | GC6: =$B$151+$B$150*($B$5+5*$B$153) -> 178.182 | GD6: =$B$152+$B$150*(0) -> 23.89542 | GE6: =$B$151+$B$150*(0) -> 20 | GF6: =$B$152+$B$150*($B$9) -> 69.85002 | GG6: =IF(AND($B$20=1,($B$19+0*$B$64)<$B$10-0.3),$B$151+$B$150*(MAX(IF(($B$19+0*$B$64)<=$B$9,0,(($B$19+0*$B$64)-$B$9)/$B$8),MIN(($B$5-IF(($B$19+0*$B$64)<=$B$9,0,(($B$19+0*$B$64)-$B$9)/$B$8)),IF(($B$19+0*$B$64)<$B$104,$B$107,$B$106)))),NA()) -> 62.12505 | GH6: =IF(AND($B$20=1,($B$19+0*$B$64)<$B$10-0.3),$B$152+$B$150*(($B$19+0*$B$64)),NA()) -> 23.89542 | GI6: =IF(AND($B$21=1,(1*$B$66)<IF($B$63=1,$B$10-0.2,$B$62)),$B$151+$B$150*(MAX(IF((1*$B$66)<=$B$9,0,((1*$B$66)-$B$9)/$B$8),MIN(($B$5-IF((1*$B$66)<=$B$9,0,((1*$B$66)-$B$9)/$B$8)),IF((1*$B$66)<$B$104,$B$107,$B$106)))),NA()) -> #N/A | GJ6: =IF(AND($B$21=1,(1*$B$66)<IF($B$63=1,$B$10-0.2,$B$62)),$B$152+$B$150*((1*$B$66)),NA()) -> #N/A | GK6: =IF($B$21=1,$B$151+$B$150*($B$5),NA()) -> #N/A | GL6: =IF($B$21=1,$B$152+$B$150*($B$59/2),NA()) -> #N/A | GM6: =IF($B$102=1,$B$151+$B$150*($B$107),NA()) -> 62.12505 | GN6: =IF($B$102=1,$B$152+$B$150*(MIN($B$9,$B$104+$B$64)),NA()) -> 69.85002 | GO6: =IF($B$102=1,$B$151+$B$150*($B$108),NA()) -> 92.76145 | GP6: =IF($B$102=1,$B$152+$B$150*($B$104),NA()) -> 58.36137 | GY6: =$B$151+$B$150*(0) -> 20 | GZ6: =$B$152+$B$150*(-6*$B$153-1.2*$B$153) -> 16.69542 | HA6: =$B$151+$B$150*(-9*$B$153-1.2*$B$153) -> 9.8 | HB6: =$B$152+$B$150*(0) -> 23.89542 | HC6: =$B$151+$B$150*($B$5+9*$B$153-1.2*$B$153) -> 180.982 | HD6: =$B$152+$B$150*(0) -> 23.89542 | HG6: =$B$157+$B$156*($B$6+$B$46) -> 175.731 | HH6: =$B$158+$B$156*(0) -> 14 | HI6: =IF(0<=$B$16-1,$B$157+$B$156*($B$6+$B$46),NA()) -> 175.731 | HJ6: =IF(0<=$B$16-1,$B$158+$B$156*(0*($B$5/2)/MAX(1,$B$16-1)),NA()) -> 14 | HK6: =IF(0<=$B$12,$B$157+$B$156*($B$13*0),NA()) -> 22.591 | HL6: =IF(0<=$B$12,$B$158+$B$156*($B$5),NA()) -> 90 | HM6: =IF(AND(1<=$B$12,1<=$B$25),$B$157+$B$156*((1-1)*$B$13+1*$B$13/($B$25+1)),NA()) -> 33.448143 | HN6: =IF(AND(1<=$B$12,1<=$B$25),$B$158+$B$156*($B$5),NA()) -> 90 | HO6: =$B$157+$B$156*($B$6+$B$46) -> 175.731 | HP6: =$B$158+$B$156*($B$5/2) -> 52 | HQ6: =IF(AND(1<=$B$23,1<=$B$24),$B$157+$B$156*(IF(1=1,1,IF(1=$B$23,$B$12,5*(1-1)))*$B$13),NA()) -> 44.305286 | HR6: =IF(AND(1<=$B$23,1<=$B$24),$B$158+$B$156*((0*$B$5/2+1*($B$5/2)/$B$24)),NA()) -> 33 | HS6: =IF(AND(1<=$B$12,$B$51>0),$B$157+$B$156*(((1-0.5)*$B$13)+($B$51*$B$13)/2),NA()) -> 34.533857 | HT6: =IF(AND(1<=$B$12,$B$51>0),$B$158+$B$156*((0*$B$5/2+0.6*$B$159)),NA()) -> 14.6 | HU6: =IF(1<=$B$47,$B$157+$B$156*(((MAX(1,MIN($B$12,ROUND(1*$B$12/($B$47+1),0)))-1)*$B$13+0.25*$B$13)+$B$48/2),NA()) -> 30.299571 | HV6: =IF(1<=$B$47,$B$158+$B$156*(IF(MOD(1,2)=1,$B$5/4,3*$B$5/4)-$B$49/2),NA()) -> 30.72 | HW6: =IF(1<=$B$50/2,$B$157+$B$156*((1-0.5)*$B$6/MAX(1,$B$50/2)),NA()) -> 47.924333 | HX6: =IF(1<=$B$50/2,$B$158+$B$156*($B$5),NA()) -> 90 | HY6: =$B$157+$B$156*(0) -> 22.591 | HZ6: =$B$158+$B$156*(-7*$B$159-1.2*$B$159) -> 5.8 | IA6: =$B$157+$B$156*(-$B$46-9*$B$159-1.2*$B$159) -> 11.251 | IB6: =$B$158+$B$156*(0) -> 14 | II6: =$B$174+$B$173*(-0.075) -> 29.4379 | IJ6: =$B$175+$B$173*(0) -> 51.3601 | IK6: =$B$174+$B$173*($B$31/2+0.05) -> 40.3162 | IL6: =$B$175+$B$173*($B$160) -> 20.6449 | IM6: =$B$174+$B$173*(0.075) -> 33.2773 | IN6: =$B$175+$B$173*($B$162) -> 27.0439 | IO6: =$B$174+$B$173*($B$169-$B$29/2) -> 90.2284 | IP6: =$B$175+$B$173*($B$164) -> 56.4793 | IQ6: =$B$174+$B$173*($B$170) -> 131.182 | IR6: =$B$175+$B$173*($B$165+0.005) -> 57.88708 | IS6: =$B$174+$B$173*($B$170) -> 131.182 | IT6: =$B$175+$B$173*($B$164+$B$39/2) -> 57.1192 | IU6: =$B$174+$B$173*($B$31/2-$B$41) -> 37.7566 | IV6: =$B$175+$B$173*($B$161+$B$41) -> 23.2045 | IW6: =$B$174+$B$173*(-$B$31/2+$B$41+1*($B$31-2*$B$41)/3) -> 29.2246 | IX6: =$B$175+$B$173*($B$161+$B$41+0.02) -> 23.71642 | IY6: =$B$174+$B$173*($B$169+'PARAMÈTRES'!$H$18/2) -> 101.1067 | IZ6: =$B$175+$B$173*($B$168+0.025) -> 63.5182 | JA6: =$B$174+$B$173*(-$B$31/2-0.18-1.2*$B$176) -> 17.87152 | JB6: =$B$175+$B$173*($B$160) -> 20.6449 | JC6: =$B$174+$B$173*(-$B$31/2) -> 23.6788 | JD6: =$B$175+$B$173*($B$160-0.06-1.2*$B$176) -> 17.90914 | JE6: =$B$174+$B$173*($B$169-$B$27/2) -> 79.99 | JF6: =$B$175+$B$173*($B$160-0.06-1.2*$B$176) -> 17.90914 | JW6: =$B$174+$B$173*($B$170+1*$B$176) -> 132.182 | JX6: =$B$175+$B$173*($B$168+0.06) -> 64.41406 | KC6: =IF($B$21=1,$B$182+$B$181*($B$177+3*$B$184),NA()) -> #N/A | KD6: =IF($B$21=1,$B$183+$B$181*(0),NA()) -> #N/A | KE6: =IF($B$21=1,$B$182+$B$181*(0),NA()) -> #N/A | KF6: =IF($B$21=1,$B$183+$B$181*($B$178+0.4),NA()) -> #N/A | KG6: =IF($B$21=1,$B$182+$B$181*($B$177),NA()) -> #N/A | KH6: =IF($B$21=1,$B$183+$B$181*(0),NA()) -> #N/A | KI6: =IF(AND($B$21=1,1*$B$67>$B$59,1*$B$67<$B$178-$B$59,OR($B$63=0,ABS(1*$B$67-$B$178/2)>$B$59/2)),$B$182+$B$181*($B$177*1/4-$B$60/2),NA()) -> #N/A | KJ6: =IF(AND($B$21=1,1*$B$67>$B$59,1*$B$67<$B$178-$B$59,OR($B$63=0,ABS(1*$B$67-$B$178/2)>$B$59/2)),$B$183+$B$181*(1*$B$67),NA()) -> #N/A | KK6: =IF($B$21=1,$B$182+$B$181*($B$177),NA()) -> #N/A | KL6: =IF($B$21=1,$B$183+$B$181*($B$59/2-($B$59/2-$B$41*0.6)),NA()) -> #N/A | KM6: =IF($B$21=1,$B$182+$B$181*(0),NA()) -> #N/A | KN6: =IF($B$21=1,$B$183+$B$181*(-6*$B$184-1.2*$B$184),NA()) -> #N/A | KO6: =IF($B$21=1,$B$182+$B$181*(-6*$B$184-1.2*$B$184),NA()) -> #N/A | KP6: =IF($B$21=1,$B$183+$B$181*(0),NA()) -> #N/A
A7: H | B7: ='PARAMÈTRES'!$C$11 -> 6 | D7: LP_txt3 | E7: =IF(3<=$B$68,"Porte coul. ","Portillon ")&FIXED($B$86,2,TRUE)&" × "&FIXED($B$87,2,TRUE) -> Portillon 5.50 × 0.00 | G7: =NA() -> #N/A | H7: =NA() -> #N/A | I7: =$B$133+$B$132*($B$6+$B$31/2) -> 168.611 | J7: =$B$134+$B$132*($B$5+$B$31/2) -> 85.02 | K7: =IF(0<=$B$12,$B$133+$B$132*($B$13*0+$B$27/2),NA()) -> 33.631 | L7: =IF(0<=$B$12,$B$134+$B$132*(0+$B$27/2),NA()) -> 18.04 | M7: =IF(AND(0<=$B$12,$B$45=1),$B$133+$B$132*($B$13*0),NA()) -> #N/A | N7: =IF(AND(0<=$B$12,$B$45=1),$B$134+$B$132*($B$5/2),NA()) -> #N/A | O7: =IF(2<=$B$14-1,$B$133+$B$132*(0),NA()) -> 31.591 | P7: =IF(2<=$B$14-1,$B$134+$B$132*(2*$B$15),NA()) -> 50 | Q7: =NA() -> #N/A | R7: =NA() -> #N/A | AI7: =$B$133+$B$132*(0) -> 31.591 | AJ7: =$B$134+$B$132*(-11*$B$135) -> 5 | AK7: =$B$133+$B$132*(-12*$B$135) -> 19.591 | AL7: =$B$134+$B$132*(0) -> 16 | AM7: =$B$133+$B$132*(0) -> 31.591 | AN7: =$B$134+$B$132*($B$5+6*$B$135) -> 90 | DW7: =NA() -> #N/A | DX7: =NA() -> #N/A | DY7: =NA() -> #N/A | DZ7: =NA() -> #N/A | EA7: =NA() -> #N/A | EB7: =NA() -> #N/A | EC7: =NA() -> #N/A | ED7: =NA() -> #N/A | EE7: =IF(1<=$B$16-1,$B$139+$B$138*(1*($B$5/2)/MAX(1,$B$16-1)),NA()) -> 29.573875 | EF7: =IF(1<=$B$16-1,$B$140+$B$138*($B$9+$B$8*1*($B$5/2)/MAX(1,$B$16-1)+1.2*$B$141),NA()) -> 76.560255 | EI7: =$B$139+$B$138*(-0.3*$B$141) -> 19.7 | EJ7: =$B$140+$B$138*($B$9-0.8*$B$141) -> 73.028435 | EK7: =$B$139+$B$138*(0+$B$27/2) -> 24.59546 | EL7: =$B$140+$B$138*((-$B$33+$B$34)+$B$35) -> 22.12951 | EM7: =$B$139+$B$138*(-9*$B$141) -> 11 | EN7: =$B$140+$B$138*(0) -> 27.873835 | EO7: =$B$139+$B$138*($B$5+9*$B$141) -> 182.182 | EP7: =$B$140+$B$138*(0) -> 27.873835 | EQ7: =$B$139+$B$138*(0) -> 20 | ER7: =$B$140+$B$138*(-$B$33-4*$B$141) -> 14.682915 | EY7: =NA() -> #N/A | EZ7: =NA() -> #N/A | FA7: =NA() -> #N/A | FB7: =NA() -> #N/A | FC7: =IF(AND(0<$B$22,($B$19+0*$B$64)>=$B$73),$B$145+$B$144*($B$75),NA()) -> #N/A | FD7: =IF(AND(0<$B$22,($B$19+0*$B$64)>=$B$73),$B$146+$B$144*(($B$19+0*$B$64)),NA()) -> #N/A | FE7: =IF(AND(AND($B$21=1,(1*$B$66)<$B$62),(1*$B$66)>=$B$73),$B$145+$B$144*($B$75),NA()) -> #N/A | FF7: =IF(AND(AND($B$21=1,(1*$B$66)<$B$62),(1*$B$66)>=$B$73),$B$146+$B$144*((1*$B$66)),NA()) -> #N/A | FG7: =NA() -> #N/A | FH7: =NA() -> #N/A | FI7: =NA() -> #N/A | FJ7: =NA() -> #N/A | FK7: =NA() -> #N/A | FL7: =NA() -> #N/A | FM7: =NA() -> #N/A | FN7: =NA() -> #N/A | FW7: =$B$145+$B$144*(0) -> 20 | FX7: =$B$146+$B$144*(-6*$B$147) -> 32.76135 | FY7: =$B$145+$B$144*(-9*$B$147) -> 11 | FZ7: =$B$146+$B$144*(0) -> 38.76135 | GA7: =$B$145+$B$144*(0) -> 20 | GB7: =$B$146+$B$144*($B$9+$B$53+4*$B$147) -> 67.23865 | GC7: =NA() -> #N/A | GD7: =NA() -> #N/A | GE7: =$B$151+$B$150*($B$5/2) -> 96.591 | GF7: =$B$152+$B$150*($B$10) -> 82.10458 | GG7: =IF(AND(AND($B$20=1,($B$19+0*$B$64)<$B$10-0.3),($B$19+0*$B$64)>=$B$104),$B$151+$B$150*(MAX(IF(($B$19+0*$B$64)<=$B$9,0,(($B$19+0*$B$64)-$B$9)/$B$8),MIN(($B$5-IF(($B$19+0*$B$64)<=$B$9,0,(($B$19+0*$B$64)-$B$9)/$B$8)),$B$106))),NA()) -> #N/A | GH7: =IF(AND(AND($B$20=1,($B$19+0*$B$64)<$B$10-0.3),($B$19+0*$B$64)>=$B$104),$B$152+$B$150*(($B$19+0*$B$64)),NA()) -> #N/A | GI7: =IF(AND(AND($B$21=1,(1*$B$66)<IF($B$63=1,$B$10-0.2,$B$62)),(1*$B$66)>=$B$104),$B$151+$B$150*(MAX(IF((1*$B$66)<=$B$9,0,((1*$B$66)-$B$9)/$B$8),MIN(($B$5-IF((1*$B$66)<=$B$9,0,((1*$B$66)-$B$9)/$B$8)),$B$106))),NA()) -> #N/A | GJ7: =IF(AND(AND($B$21=1,(1*$B$66)<IF($B$63=1,$B$10-0.2,$B$62)),(1*$B$66)>=$B$104),$B$152+$B$150*((1*$B$66)),NA()) -> #N/A | GK7: =NA() -> #N/A | GL7: =NA() -> #N/A | GM7: =NA() -> #N/A | GN7: =NA() -> #N/A | GO7: =NA() -> #N/A | GP7: =NA() -> #N/A | GY7: =$B$151+$B$150*(0) -> 20 | GZ7: =$B$152+$B$150*(-6*$B$153) -> 17.89542 | HA7: =$B$151+$B$150*(-9*$B$153) -> 11 | HB7: =$B$152+$B$150*(0) -> 23.89542 | HC7: =$B$151+$B$150*($B$5+9*$B$153) -> 182.182 | HD7: =$B$152+$B$150*(0) -> 23.89542 | HG7: =$B$157+$B$156*($B$6+$B$46) -> 175.731 | HH7: =$B$158+$B$156*($B$5) -> 90 | HI7: =NA() -> #N/A | HJ7: =NA() -> #N/A | HK7: =NA() -> #N/A | HL7: =NA() -> #N/A | HM7: =NA() -> #N/A | HN7: =NA() -> #N/A | HO7: =NA() -> #N/A | HP7: =NA() -> #N/A | ... HR7: =NA() -> #N/A | HS7: =IF(AND(1<=$B$12,$B$51>0),$B$157+$B$156*(((1-0.5)*$B$13)+($B$51*$B$13)/2),NA()) -> 34.533857 | HT7: =IF(AND(1<=$B$12,$B$51>0),$B$158+$B$156*((0*$B$5/2+$B$5/2-0.6*$B$159)),NA()) -> 51.4 | HU7: =IF(1<=$B$47,$B$157+$B$156*(((MAX(1,MIN($B$12,ROUND(1*$B$12/($B$47+1),0)))-1)*$B$13+0.25*$B$13)+$B$48/2),NA()) -> 30.299571 | HV7: =IF(1<=$B$47,$B$158+$B$156*(IF(MOD(1,2)=1,$B$5/4,3*$B$5/4)+$B$49/2),NA()) -> 35.28 | HW7: =IF(2<=$B$50/2,$B$157+$B$156*((2-0.5)*$B$6/MAX(1,$B$50/2)),NA()) -> 98.591 | HX7: =IF(2<=$B$50/2,$B$158+$B$156*(0),NA()) -> 14 | HY7: =$B$157+$B$156*(0) -> 22.591 | HZ7: =$B$158+$B$156*(-7*$B$159) -> 7 | IA7: =$B$157+$B$156*(-$B$46-9*$B$159) -> 12.451 | IB7: =$B$158+$B$156*(0) -> 14 | II7: =NA() -> #N/A | IJ7: =NA() -> #N/A | IK7: =$B$174+$B$173*($B$31/2+0.05) -> 40.3162 | IL7: =$B$175+$B$173*($B$161) -> 21.9247 | IM7: =$B$174+$B$173*(0.075) -> 33.2773 | IN7: =$B$175+$B$173*($B$163) -> 52.6399 | IO7: =NA() -> #N/A | IP7: =NA() -> #N/A | IQ7: =NA() -> #N/A | IR7: =NA() -> #N/A | IS7: =NA() -> #N/A | IT7: =NA() -> #N/A | IU7: =NA() -> #N/A | IV7: =NA() -> #N/A | IW7: =$B$174+$B$173*(-$B$31/2+$B$41+2*($B$31-2*$B$41)/3) -> 33.4906 | IX7: =$B$175+$B$173*($B$161+$B$41+0.02) -> 23.71642 | IY7: =NA() -> #N/A | IZ7: =NA() -> #N/A | JA7: =$B$174+$B$173*(-$B$31/2-0.18) -> 19.07152 | JB7: =$B$175+$B$173*($B$160) -> 20.6449 | JC7: =$B$174+$B$173*(-$B$31/2) -> 23.6788 | JD7: =$B$175+$B$173*($B$160-0.06) -> 19.10914 | JE7: =$B$174+$B$173*($B$169-$B$27/2) -> 79.99 | JF7: =$B$175+$B$173*($B$160-0.06) -> 19.10914 | JW7: =$B$174+$B$173*($B$170+4*$B$176) -> 135.182 | JX7: =$B$175+$B$173*((MAX($B$166,$B$168)+0.75)-0*6.5*$B$176) -> 82.0753 | KC7: =NA() -> #N/A | KD7: =NA() -> #N/A | KE7: =NA() -> #N/A | KF7: =NA() -> #N/A | KG7: =IF($B$21=1,$B$182+$B$181*($B$177),NA()) -> #N/A | KH7: =IF($B$21=1,$B$183+$B$181*($B$59),NA()) -> #N/A | KI7: =NA() -> #N/A | KJ7: =NA() -> #N/A | KK7: =NA() -> #N/A | KL7: =NA() -> #N/A | KM7: =IF($B$21=1,$B$182+$B$181*(0),NA()) -> #N/A | KN7: =IF($B$21=1,$B$183+$B$181*(-6*$B$184),NA()) -> #N/A | KO7: =IF($B$21=1,$B$182+$B$181*(-6*$B$184),NA()) -> #N/A | KP7: =IF($B$21=1,$B$183+$B$181*(0),NA()) -> #N/A
A8: p | B8: =MAX(0.001,'PARAMÈTRES'!$C$12) -> 0.16 | D8: LP_txt4 | E8: =IF(4<=$B$68,"Porte coul. ","Portillon ")&FIXED($B$93,2,TRUE)&" × "&FIXED($B$94,2,TRUE) -> Portillon 5.50 × 0.00 | G8: =IF(1<=$B$12,$B$133+$B$132*($B$13*1),NA()) -> 51.019571 | H8: =IF(1<=$B$12,$B$134+$B$132*(-4*$B$135),NA()) -> 12 | I8: =$B$133+$B$132*(-$B$31/2) -> 30.571 | J8: =$B$134+$B$132*($B$5+$B$31/2) -> 85.02 | K8: =IF(0<=$B$12,$B$133+$B$132*($B$13*0-$B$27/2),NA()) -> 29.551 | L8: =IF(0<=$B$12,$B$134+$B$132*(0+$B$27/2),NA()) -> 18.04 | M8: =IF(1<=$B$12,$B$133+$B$132*($B$13*1),NA()) -> 51.019571 | N8: =IF(1<=$B$12,$B$134+$B$132*(0),NA()) -> 16 | O8: =IF(2<=$B$14-1,$B$133+$B$132*($B$6),NA()) -> 167.591 | P8: =IF(2<=$B$14-1,$B$134+$B$132*(2*$B$15),NA()) -> 50 | Q8: =IF($B$78=1,$B$133+$B$132*($B$83),NA()) -> #N/A | R8: =IF($B$78=1,$B$134+$B$132*(-2.5*$B$135),NA()) -> #N/A | AI8: =$B$133+$B$132*(((0)+($B$6))/2) -> 99.591 | AJ8: =$B$134+$B$132*(-11*$B$135) -> 5 | AK8: =$B$133+$B$132*(-12*$B$135) -> 19.591 | AL8: =$B$134+$B$132*(((0)+($B$5))/2) -> 50 | AM8: =$B$133+$B$132*(((0)+($B$13))/2) -> 41.305286 | AN8: =$B$134+$B$132*($B$5+6*$B$135) -> 90 | DY8: =$B$139+$B$138*($B$5) -> 173.182 | DZ8: =$B$140+$B$138*(0) -> 27.873835 | EA8: =IF(AND($B$18=1,2<=$B$26-1),$B$139+$B$138*(2*($B$5/MAX(1,$B$26))),NA()) -> #N/A | EB8: =IF(AND($B$18=1,2<=$B$26-1),$B$140+$B$138*($B$7),NA()) -> #N/A | EC8: =IF($B$18=0,$B$139+$B$138*($B$5),NA()) -> 173.182 | ED8: =IF($B$18=0,$B$140+$B$138*($B$7-$B$54),NA()) -> 71.530705 | EE8: =IF(1<=$B$16-1,$B$139+$B$138*($B$5-1*($B$5/2)/MAX(1,$B$16-1)),NA()) -> 163.60813 | EF8: =IF(1<=$B$16-1,$B$140+$B$138*($B$9+$B$8*1*($B$5/2)/MAX(1,$B$16-1)+1.2*$B$141),NA()) -> 76.560255 | EI8: =$B$139+$B$138*(-0.3*$B$141) -> 19.7 | EJ8: =$B$140+$B$138*($B$9+1.5*$B$141) -> 75.328435 | EK8: =$B$139+$B$138*(0-$B$27/2) -> 15.40454 | EL8: =$B$140+$B$138*((-$B$33+$B$34)+$B$35) -> 22.12951 | EM8: =$B$139+$B$138*(-9*$B$141) -> 11 | EN8: =$B$140+$B$138*(((0)+($B$7))/2) -> 50.851135 | EO8: =$B$139+$B$138*($B$5+9*$B$141) -> 182.182 | EP8: =$B$140+$B$138*(((0)+($B$10))/2) -> 56.978415 | EQ8: =$B$139+$B$138*(((0)+($B$5))/2) -> 96.591 | ER8: =$B$140+$B$138*(-$B$33-4*$B$141) -> 14.682915 | FA8: =IF(1<=$B$12,$B$145+$B$144*($B$13*1),NA()) -> 43.311714 | FB8: =IF(1<=$B$12,$B$146+$B$144*(0),NA()) -> 38.76135 | FC8: =IF(0<$B$22,$B$145+$B$144*(IF(($B$19+0*$B$64)<$B$73,$B$77,$B$75)),NA()) -> 112.80976 | FD8: =IF(0<$B$22,$B$146+$B$144*(($B$19+0*$B$64)),NA()) -> 38.76135 | FE8: =IF(AND($B$21=1,(1*$B$66)<$B$62),$B$145+$B$144*(IF((1*$B$66)<$B$73,$B$77,$B$75)),NA()) -> #N/A | FF8: =IF(AND($B$21=1,(1*$B$66)<$B$62),$B$146+$B$144*((1*$B$66)),NA()) -> #N/A | FG8: =IF($B$63=1,$B$145+$B$144*(0),NA()) -> #N/A | FH8: =IF($B$63=1,$B$146+$B$144*($B$62/2),NA()) -> #N/A | FI8: =IF(1<=$B$23,$B$145+$B$144*(IF(1=1,1,IF(1=$B$23,$B$12,5*(1-1)))*$B$13),NA()) -> 43.311714 | FJ8: =IF(1<=$B$23,$B$146+$B$144*(0),NA()) -> 38.76135 | FK8: =IF($B$71=1,$B$145+$B$144*($B$77),NA()) -> 112.80976 | FL8: =IF($B$71=1,$B$146+$B$144*(0),NA()) -> 38.76135 | FM8: =IF($B$71=1,$B$145+$B$144*($B$77),NA()) -> 112.80976 | FN8: =IF($B$71=1,$B$146+$B$144*(0),NA()) -> 38.76135 | FW8: =$B$145+$B$144*(((0)+($B$6))/2) -> 101.591 | FX8: =$B$146+$B$144*(-6*$B$147) -> 32.76135 | FY8: =$B$145+$B$144*(-9*$B$147) -> 11 | FZ8: =$B$146+$B$144*(((0)+($B$9))/2) -> 51 | GA8: =$B$145+$B$144*(((0)+($B$13))/2) -> 31.655857 | GB8: =$B$146+$B$144*($B$9+$B$53+4*$B$147) -> 67.23865 | GE8: =$B$151+$B$150*($B$5) -> 173.182 | GF8: =$B$152+$B$150*($B$9) -> 69.85002 | GG8: =IF(AND($B$20=1,($B$19+0*$B$64)<$B$10-0.3),$B$151+$B$150*(MAX(IF(($B$19+0*$B$64)<=$B$9,0,(($B$19+0*$B$64)-$B$9)/$B$8),MIN(($B$5-IF(($B$19+0*$B$64)<=$B$9,0,(($B$19+0*$B$64)-$B$9)/$B$8)),IF(($B$19+0*$B$64)<$B$104,$B$108,$B$106)))),NA()) -> 92.76145 | GH8: =IF(AND($B$20=1,($B$19+0*$B$64)<$B$10-0.3),$B$152+$B$150*(($B$19+0*$B$64)),NA()) -> 23.89542 | GI8: =IF(AND($B$21=1,(1*$B$66)<IF($B$63=1,$B$10-0.2,$B$62)),$B$151+$B$150*(MAX(IF((1*$B$66)<=$B$9,0,((1*$B$66)-$B$9)/$B$8),MIN(($B$5-IF((1*$B$66)<=$B$9,0,((1*$B$66)-$B$9)/$B$8)),IF((1*$B$66)<$B$104,$B$108,$B$106)))),NA()) -> #N/A | GJ8: =IF(AND($B$21=1,(1*$B$66)<IF($B$63=1,$B$10-0.2,$B$62)),$B$152+$B$150*((1*$B$66)),NA()) -> #N/A | GK8: =IF($B$63=1,$B$151+$B$150*(0),NA()) -> #N/A | GL8: =IF($B$63=1,$B$152+$B$150*($B$62/2),NA()) -> #N/A | GM8: =IF($B$102=1,$B$151+$B$150*($B$108),NA()) -> 92.76145 | GN8: =IF($B$102=1,$B$152+$B$150*(0),NA()) -> 23.89542 | GO8: =IF($B$102=1,$B$151+$B$150*($B$108),NA()) -> 92.76145 | GP8: =IF($B$102=1,$B$152+$B$150*(0),NA()) -> 23.89542 | GY8: =$B$151+$B$150*(((0)+($B$5))/2) -> 96.591 | GZ8: =$B$152+$B$150*(-6*$B$153) -> 17.89542 | HA8: =$B$151+$B$150*(-9*$B$153) -> 11 | HB8: =$B$152+$B$150*(((0)+($B$9))/2) -> 46.87272 | HC8: =$B$151+$B$150*($B$5+9*$B$153) -> 182.182 | HD8: =$B$152+$B$150*(((0)+($B$10))/2) -> 53 | HG8: =$B$157+$B$156*(-$B$46) -> 21.451 | HH8: =$B$158+$B$156*($B$5) -> 90 | HI8: =IF(0<=$B$16-1,$B$157+$B$156*(-$B$46),NA()) -> 21.451 | HJ8: =IF(0<=$B$16-1,$B$158+$B$156*($B$5-0*($B$5/2)/MAX(1,$B$16-1)),NA()) -> 90 | HK8: =IF(1<=$B$12,$B$157+$B$156*($B$13*1),NA()) -> 44.305286 | HL8: =IF(1<=$B$12,$B$158+$B$156*(0),NA()) -> 14 | HM8: =IF(AND(1<=$B$12,2<=$B$25),$B$157+$B$156*((1-1)*$B$13+2*$B$13/($B$25+1)),NA()) -> #N/A | HN8: =IF(AND(1<=$B$12,2<=$B$25),$B$158+$B$156*(0),NA()) -> #N/A | HQ8: =IF(AND(1<=$B$23,1<=$B$24),$B$157+$B$156*((IF(1=1,1,IF(1=$B$23,$B$12,5*(1-1)))-1)*$B$13),NA()) -> 22.591 | HR8: =IF(AND(1<=$B$23,1<=$B$24),$B$158+$B$156*((0*$B$5/2+1*($B$5/2)/$B$24)),NA()) -> 33 | HS8: =IF(AND(1<=$B$12,$B$51>0),$B$157+$B$156*(((1-0.5)*$B$13)-($B$51*$B$13)/2),NA()) -> 32.362429 | HT8: =IF(AND(1<=$B$12,$B$51>0),$B$158+$B$156*((0*$B$5/2+$B$5/2-0.6*$B$159)),NA()) -> 51.4 | HU8: =IF(1<=$B$47,$B$157+$B$156*(((MAX(1,MIN($B$12,ROUND(1*$B$12/($B$47+1),0)))-1)*$B$13+0.25*$B$13)-$B$48/2),NA()) -> 25.739571 | HV8: =IF(1<=$B$47,$B$158+$B$156*(IF(MOD(1,2)=1,$B$5/4,3*$B$5/4)+$B$49/2),NA()) -> 35.28 | HW8: =IF(2<=$B$50/2,$B$157+$B$156*((2-0.5)*$B$6/MAX(1,$B$50/2)),NA()) -> 98.591 | HX8: =IF(2<=$B$50/2,$B$158+$B$156*($B$5),NA()) -> 90 | HY8: =$B$157+$B$156*(((0)+($B$6))/2) -> 98.591 | HZ8: =$B$158+$B$156*(-7*$B$159) -> 7 | IA8: =$B$157+$B$156*(-$B$46-9*$B$159) -> 12.451 | IB8: =$B$158+$B$156*(((0)+($B$5))/2) -> 52 | IK8: =$B$174+$B$173*(-$B$31/2-0.05) -> 22.399 | IL8: =$B$175+$B$173*($B$161) -> 21.9247 | IM8: =$B$174+$B$173*(-0.075) -> 29.4379 | IN8: =$B$175+$B$173*($B$163) -> 52.6399 | IO8: =$B$174+$B$173*($B$169+$B$29/2) -> 100.4668 | IP8: =$B$175+$B$173*($B$164) -> 56.4793 | IU8: =$B$174+$B$173*($B$169-$B$27/2+$B$41) -> 81.2698 | IV8: =$B$175+$B$173*($B$161+$B$41+0.15) -> 27.0439 | IW8: =$B$174+$B$173*(-$B$31/2+$B$41+3*($B$31-2*$B$41)/3) -> 37.7566 | IX8: =$B$175+$B$173*($B$161+$B$41+0.02) -> 23.71642 | IY8: =$B$174+$B$173*($B$169-$B$56/2) -> 91.12426 | IZ8: =$B$175+$B$173*($B$168+0.05) -> 64.1581 | JA8: =$B$174+$B$173*(-$B$31/2-0.18) -> 19.07152 | JB8: =$B$175+$B$173*((($B$160)+(0))/2) -> 36.0025 | JC8: =$B$174+$B$173*(((-$B$31/2)+($B$31/2))/2) -> 31.3576 | JD8: =$B$175+$B$173*($B$160-0.06) -> 19.10914 | JE8: =$B$174+$B$173*((($B$169-$B$27/2)+($B$169+$B$27/2))/2) -> 95.3476 | JF8: =$B$175+$B$173*($B$160-0.06) -> 19.10914 | JW8: =NA() -> #N/A | JX8: =NA() -> #N/A | KE8: =IF($B$21=1,$B$182+$B$181*($B$177),NA()) -> #N/A | KF8: =IF($B$21=1,$B$183+$B$181*(0),NA()) -> #N/A | KG8: =IF($B$21=1,$B$182+$B$181*(0),NA()) -> #N/A | KH8: =IF($B$21=1,$B$183+$B$181*($B$59),NA()) -> #N/A | KI8: =IF(AND($B$21=1,1*$B$67>$B$59,1*$B$67<$B$178-$B$59,OR($B$63=0,ABS(1*$B$67-$B$178/2)>$B$59/2)),$B$182+$B$181*($B$177*1/4+$B$60/2),NA()) -> #N/A | KJ8: =IF(AND($B$21=1,1*$B$67>$B$59,1*$B$67<$B$178-$B$59,OR($B$63=0,ABS(1*$B$67-$B$178/2)>$B$59/2)),$B$183+$B$181*(1*$B$67),NA()) -> #N/A | KK8: =IF($B$21=1,$B$182+$B$181*(0),NA()) -> #N/A | KL8: =IF($B$21=1,$B$183+$B$181*($B$59/2+($B$59/2-$B$41*0.6)),NA()) -> #N/A | KM8: =IF($B$21=1,$B$182+$B$181*(((0)+($B$177))/2),NA()) -> #N/A | KN8: =IF($B$21=1,$B$183+$B$181*(-6*$B$184),NA()) -> #N/A | KO8: =IF($B$21=1,$B$182+$B$181*(-6*$B$184),NA()) -> #N/A | KP8: =IF($B$21=1,$B$183+$B$181*(((0)+($B$178))/2),NA()) -> #N/A
A9: Hm | B9: ='PRÉDIMENSIONNEMENT'!$C$33 -> 6 | D9: PG_txt1 | E9: =IF(1<=$B$99,"Porte coul. ","Portillon ")&FIXED($B$103,2,TRUE)&" × "&FIXED($B$104,2,TRUE) -> Porte coul. 4.00 × 4.50 | G9: =IF(1<=$B$12,$B$133+$B$132*($B$13*1),NA()) -> 51.019571 | H9: =IF(1<=$B$12,$B$134+$B$132*($B$5+4*$B$135),NA()) -> 88 | I9: =$B$133+$B$132*(-$B$31/2) -> 30.571 | J9: =$B$134+$B$132*(-$B$31/2) -> 14.98 | K9: =IF(0<=$B$12,$B$133+$B$132*($B$13*0-$B$27/2),NA()) -> 29.551 | L9: =IF(0<=$B$12,$B$134+$B$132*(0-$B$27/2),NA()) -> 13.96 | M9: =IF(1<=$B$12,$B$133+$B$132*($B$13*1),NA()) -> 51.019571 | N9: =IF(1<=$B$12,$B$134+$B$132*($B$5),NA()) -> 84 | O9: =IF(3<=$B$14-1,$B$133+$B$132*(0),NA()) -> 31.591 | P9: =IF(3<=$B$14-1,$B$134+$B$132*(3*$B$15),NA()) -> 67 | Q9: =IF($B$78=1,$B$133+$B$132*($B$84),NA()) -> #N/A | R9: =IF($B$78=1,$B$134+$B$132*(-2.5*$B$135),NA()) -> #N/A | AI9: =$B$133+$B$132*($B$6) -> 167.591 | AJ9: =$B$134+$B$132*(-11*$B$135) -> 5 | AK9: =$B$133+$B$132*(-12*$B$135) -> 19.591 | AL9: =$B$134+$B$132*($B$5) -> 84 | AM9: =$B$133+$B$132*($B$13) -> 51.019571 | AN9: =$B$134+$B$132*($B$5+6*$B$135) -> 90 | DY9: =$B$139+$B$138*($B$5) -> 173.182 | DZ9: =$B$140+$B$138*($B$9) -> 73.828435 | EA9: =IF(AND($B$18=1,2<=$B$26-1),$B$139+$B$138*(2*($B$5/MAX(1,$B$26))),NA()) -> #N/A | EB9: =IF(AND($B$18=1,2<=$B$26-1),$B$140+$B$138*(($B$9+$B$8*MIN(2*($B$5/MAX(1,$B$26)),$B$5-(2*($B$5/MAX(1,$B$26)))))),NA()) -> #N/A | EC9: =IF($B$18=0,$B$139+$B$138*($B$5-$B$55),NA()) -> 157.8638 | ED9: =IF($B$18=0,$B$140+$B$138*($B$7+$B$8*$B$55),NA()) -> 76.279347 | EE9: =IF(2<=$B$16-1,$B$139+$B$138*(2*($B$5/2)/MAX(1,$B$16-1)),NA()) -> 39.14775 | EF9: =IF(2<=$B$16-1,$B$140+$B$138*($B$9+$B$8*2*($B$5/2)/MAX(1,$B$16-1)+1.2*$B$141),NA()) -> 78.092075 | EI9: =NA() -> #N/A | EJ9: =NA() -> #N/A | EK9: =$B$139+$B$138*(0-$B$27/2) -> 15.40454 | EL9: =$B$140+$B$138*((-$B$33+$B$34)) -> 19.06587 | EM9: =$B$139+$B$138*(-9*$B$141) -> 11 | EN9: =$B$140+$B$138*($B$7) -> 73.828435 | EO9: =$B$139+$B$138*($B$5+9*$B$141) -> 182.182 | EP9: =$B$140+$B$138*($B$10) -> 86.082995 | EQ9: =$B$139+$B$138*($B$5) -> 173.182 | ER9: =$B$140+$B$138*(-$B$33-4*$B$141) -> 14.682915 | FA9: =IF(1<=$B$12,$B$145+$B$144*($B$13*1),NA()) -> 43.311714 | FB9: =IF(1<=$B$12,$B$146+$B$144*($B$9),NA()) -> 63.23865 | FC9: =IF(0<$B$22,$B$145+$B$144*(IF(($B$19+0*$B$64)<$B$80,$B$83,$B$82)),NA()) -> 183.182 | FD9: =IF(0<$B$22,$B$146+$B$144*(($B$19+0*$B$64)),NA()) -> 38.76135 | FE9: =IF(AND($B$21=1,(1*$B$66)<$B$62),$B$145+$B$144*(IF((1*$B$66)<$B$80,$B$83,$B$82)),NA()) -> #N/A | FF9: =IF(AND($B$21=1,(1*$B$66)<$B$62),$B$146+$B$144*((1*$B$66)),NA()) -> #N/A | FG9: =IF($B$63=1,$B$145+$B$144*($B$6),NA()) -> #N/A | FH9: =IF($B$63=1,$B$146+$B$144*($B$62/2),NA()) -> #N/A | FI9: =IF(1<=$B$23,$B$145+$B$144*((IF(1=1,1,IF(1=$B$23,$B$12,5*(1-1)))-1)*$B$13),NA()) -> 20 | FJ9: =IF(1<=$B$23,$B$146+$B$144*($B$9),NA()) -> 63.23865 | FK9: =IF($B$71=1,$B$145+$B$144*($B$77),NA()) -> 112.80976 | FL9: =IF($B$71=1,$B$146+$B$144*($B$9),NA()) -> 63.23865 | FM9: =IF($B$71=1,$B$145+$B$144*($B$76),NA()) -> 90.372237 | FN9: =IF($B$71=1,$B$146+$B$144*($B$73),NA()) -> 55.07955 | FW9: =$B$145+$B$144*($B$6) -> 183.182 | FX9: =$B$146+$B$144*(-6*$B$147) -> 32.76135 | FY9: =$B$145+$B$144*(-9*$B$147) -> 11 | FZ9: =$B$146+$B$144*($B$9) -> 63.23865 | GA9: =$B$145+$B$144*($B$13) -> 43.311714 | GB9: =$B$146+$B$144*($B$9+$B$53+4*$B$147) -> 67.23865 | GE9: =$B$151+$B$150*($B$5) -> 173.182 | GF9: =$B$152+$B$150*(0) -> 23.89542 | GG9: =IF(AND($B$20=1,($B$19+0*$B$64)<$B$10-0.3),$B$151+$B$150*(MAX(IF(($B$19+0*$B$64)<=$B$9,0,(($B$19+0*$B$64)-$B$9)/$B$8),MIN(($B$5-IF(($B$19+0*$B$64)<=$B$9,0,(($B$19+0*$B$64)-$B$9)/$B$8)),IF(($B$19+0*$B$64)<$B$111,$B$114,$B$113)))),NA()) -> 173.182 | GH9: =IF(AND($B$20=1,($B$19+0*$B$64)<$B$10-0.3),$B$152+$B$150*(($B$19+0*$B$64)),NA()) -> 23.89542 | GI9: =IF(AND($B$21=1,(1*$B$66)<IF($B$63=1,$B$10-0.2,$B$62)),$B$151+$B$150*(MAX(IF((1*$B$66)<=$B$9,0,((1*$B$66)-$B$9)/$B$8),MIN(($B$5-IF((1*$B$66)<=$B$9,0,((1*$B$66)-$B$9)/$B$8)),IF((1*$B$66)<$B$111,$B$114,$B$113)))),NA()) -> #N/A | GJ9: =IF(AND($B$21=1,(1*$B$66)<IF($B$63=1,$B$10-0.2,$B$62)),$B$152+$B$150*((1*$B$66)),NA()) -> #N/A | GK9: =IF($B$63=1,$B$151+$B$150*($B$5),NA()) -> #N/A | GL9: =IF($B$63=1,$B$152+$B$150*($B$62/2),NA()) -> #N/A | GM9: =IF($B$102=1,$B$151+$B$150*($B$108),NA()) -> 92.76145 | GN9: =IF($B$102=1,$B$152+$B$150*(MIN($B$9,$B$104+$B$64)),NA()) -> 69.85002 | GO9: =IF($B$102=1,$B$151+$B$150*($B$107),NA()) -> 62.12505 | GP9: =IF($B$102=1,$B$152+$B$150*($B$104),NA()) -> 58.36137 | GY9: =$B$151+$B$150*($B$5) -> 173.182 | GZ9: =$B$152+$B$150*(-6*$B$153) -> 17.89542 | HA9: =$B$151+$B$150*(-9*$B$153) -> 11 | HB9: =$B$152+$B$150*($B$9) -> 69.85002 | HC9: =$B$151+$B$150*($B$5+9*$B$153) -> 182.182 | HD9: =$B$152+$B$150*($B$10) -> 82.10458 | HG9: =$B$157+$B$156*(-$B$46) -> 21.451 | HH9: =$B$158+$B$156*(0) -> 14 | HI9: =IF(0<=$B$16-1,$B$157+$B$156*($B$6+$B$46),NA()) -> 175.731 | HJ9: =IF(0<=$B$16-1,$B$158+$B$156*($B$5-0*($B$5/2)/MAX(1,$B$16-1)),NA()) -> 90 | HK9: =IF(1<=$B$12,$B$157+$B$156*($B$13*1),NA()) -> 44.305286 | HL9: =IF(1<=$B$12,$B$158+$B$156*($B$5),NA()) -> 90 | HM9: =IF(AND(1<=$B$12,2<=$B$25),$B$157+$B$156*((1-1)*$B$13+2*$B$13/($B$25+1)),NA()) -> #N/A | HN9: =IF(AND(1<=$B$12,2<=$B$25),$B$158+$B$156*($B$5),NA()) -> #N/A | HQ9: =IF(AND(1<=$B$23,1<=$B$24),$B$157+$B$156*(IF(1=1,1,IF(1=$B$23,$B$12,5*(1-1)))*$B$13),NA()) -> 44.305286 | HR9: =IF(AND(1<=$B$23,1<=$B$24),$B$158+$B$156*((0*$B$5/2+(1-1)*($B$5/2)/$B$24)),NA()) -> 14 | HS9: =IF(AND(1<=$B$12,$B$51>0),$B$157+$B$156*(((1-0.5)*$B$13)-($B$51*$B$13)/2),NA()) -> 32.362429 | HT9: =IF(AND(1<=$B$12,$B$51>0),$B$158+$B$156*((0*$B$5/2+0.6*$B$159)),NA()) -> 14.6 | HU9: =IF(1<=$B$47,$B$157+$B$156*(((MAX(1,MIN($B$12,ROUND(1*$B$12/($B$47+1),0)))-1)*$B$13+0.25*$B$13)-$B$48/2),NA()) -> 25.739571 | HV9: =IF(1<=$B$47,$B$158+$B$156*(IF(MOD(1,2)=1,$B$5/4,3*$B$5/4)-$B$49/2),NA()) -> 30.72 | HW9: =IF(3<=$B$50/2,$B$157+$B$156*((3-0.5)*$B$6/MAX(1,$B$50/2)),NA()) -> 149.25767 | HX9: =IF(3<=$B$50/2,$B$158+$B$156*(0),NA()) -> 14 | HY9: =$B$157+$B$156*($B$6) -> 174.591 | HZ9: =$B$158+$B$156*(-7*$B$159) -> 7 | IA9: =$B$157+$B$156*(-$B$46-9*$B$159) -> 12.451 | IB9: =$B$158+$B$156*($B$5) -> 90 | IK9: =$B$174+$B$173*(-$B$31/2-0.05) -> 22.399 | IL9: =$B$175+$B$173*($B$160) -> 20.6449 | IM9: =$B$174+$B$173*(-0.075) -> 29.4379 | IN9: =$B$175+$B$173*($B$162) -> 27.0439 | IO9: =$B$174+$B$173*($B$170) -> 131.182 | IP9: =$B$175+$B$173*($B$164) -> 56.4793 | IU9: =$B$174+$B$173*($B$169-$B$27/2+$B$41) -> 81.2698 | IV9: =$B$175+$B$173*($B$161+$B$41) -> 23.2045 | IW9: =IF(0<=ROUNDDOWN(($B$27-2*$B$41)/'PARAMÈTRES'!$C$96,0),$B$174+$B$173*($B$169-$B$27/2+$B$41+0*'PARAMÈTRES'!$C$96),NA()) -> 81.2698 | IX9: =IF(0<=ROUNDDOWN(($B$27-2*$B$41)/'PARAMÈTRES'!$C$96,0),$B$175+$B$173*($B$161+$B$41+0.02),NA()) -> 23.71642 | IY9: =$B$174+$B$173*($B$169-$B$56/2) -> 91.12426 | IZ9: =$B$175+$B$173*($B$168+0.85) -> 84.6349 | JA9: =$B$174+$B$173*(-$B$31/2-0.18) -> 19.07152 | JB9: =$B$175+$B$173*(0) -> 51.3601 | JC9: =$B$174+$B$173*($B$31/2) -> 39.0364 | JD9: =$B$175+$B$173*($B$160-0.06) -> 19.10914 | JE9: =$B$174+$B$173*($B$169+$B$27/2) -> 110.7052 | JF9: =$B$175+$B$173*($B$160-0.06) -> 19.10914 | JW9: =$B$174+$B$173*($B$170) -> 131.182 | JX9: =$B$175+$B$173*(($B$165+$B$166)/2) -> 60.3187 | KE9: =IF($B$21=1,$B$182+$B$181*($B$177),NA()) -> #N/A | KF9: =IF($B$21=1,$B$183+$B$181*($B$178+0.4),NA()) -> #N/A | KG9: =IF($B$21=1,$B$182+$B$181*(0),NA()) -> #N/A | KH9: =IF($B$21=1,$B$183+$B$181*(0),NA()) -> #N/A | KI9: =IF(AND($B$21=1,1*$B$67>$B$59,1*$B$67<$B$178-$B$59,OR($B$63=0,ABS(1*$B$67-$B$178/2)>$B$59/2)),$B$182+$B$181*($B$177*2/4-$B$60/2),NA()) -> #N/A | KJ9: =IF(AND($B$21=1,1*$B$67>$B$59,1*$B$67<$B$178-$B$59,OR($B$63=0,ABS(1*$B$67-$B$178/2)>$B$59/2)),$B$183+$B$181*(1*$B$67),NA()) -> #N/A | KK9: =IF($B$21=1,$B$182+$B$181*($B$177),NA()) -> #N/A | KL9: =IF($B$21=1,$B$183+$B$181*($B$59/2+($B$59/2-$B$41*0.6)),NA()) -> #N/A | KM9: =IF($B$21=1,$B$182+$B$181*($B$177),NA()) -> #N/A | KN9: =IF($B$21=1,$B$183+$B$181*(-6*$B$184),NA()) -> #N/A | KO9: =IF($B$21=1,$B$182+$B$181*(-6*$B$184),NA()) -> #N/A | KP9: =IF($B$21=1,$B$183+$B$181*($B$178),NA()) -> #N/A
A10: Hf | B10: ='PRÉDIMENSIONNEMENT'!$C$34 -> 7.6 | D10: PG_txt2 | E10: =IF(2<=$B$99,"Porte coul. ","Portillon ")&FIXED($B$110,2,TRUE)&" × "&FIXED($B$111,2,TRUE) -> Portillon 5.50 × 0.00 | G10: =NA() -> #N/A | H10: =NA() -> #N/A | I10: =NA() -> #N/A | J10: =NA() -> #N/A | K10: =NA() -> #N/A | L10: =NA() -> #N/A | M10: =IF(AND(1<=$B$12,$B$45=1),$B$133+$B$132*($B$13*1),NA()) -> #N/A | N10: =IF(AND(1<=$B$12,$B$45=1),$B$134+$B$132*($B$5/2),NA()) -> #N/A | O10: =IF(3<=$B$14-1,$B$133+$B$132*($B$6),NA()) -> 167.591 | P10: =IF(3<=$B$14-1,$B$134+$B$132*(3*$B$15),NA()) -> 67 | Q10: =NA() -> #N/A | R10: =NA() -> #N/A | AI10: =$B$133+$B$132*($B$6) -> 167.591 | AJ10: =$B$134+$B$132*(-11*$B$135+1.2*$B$135) -> 6.2 | AK10: =$B$133+$B$132*(-12*$B$135+1.2*$B$135) -> 20.791 | AL10: =$B$134+$B$132*($B$5) -> 84 | AM10: =$B$133+$B$132*($B$13) -> 51.019571 | AN10: =$B$134+$B$132*($B$5+6*$B$135+1.2*$B$135) -> 91.2 | DY10: =NA() -> #N/A | DZ10: =NA() -> #N/A | EA10: =NA() -> #N/A | EB10: =NA() -> #N/A | EC10: =NA() -> #N/A | ED10: =NA() -> #N/A | EE10: =IF(2<=$B$16-1,$B$139+$B$138*($B$5-2*($B$5/2)/MAX(1,$B$16-1)),NA()) -> 154.03425 | EF10: =IF(2<=$B$16-1,$B$140+$B$138*($B$9+$B$8*2*($B$5/2)/MAX(1,$B$16-1)+1.2*$B$141),NA()) -> 78.092075 | EI10: =$B$139+$B$138*($B$5+3.5*$B$141) -> 176.682 | EJ10: =$B$140+$B$138*($B$9+1.5*$B$141) -> 75.328435 | EK10: =NA() -> #N/A | EL10: =NA() -> #N/A | EM10: =$B$139+$B$138*(-9*$B$141+1.2*$B$141) -> 12.2 | EN10: =$B$140+$B$138*($B$7) -> 73.828435 | EO10: =$B$139+$B$138*($B$5+9*$B$141+1.2*$B$141) -> 183.382 | EP10: =$B$140+$B$138*($B$10) -> 86.082995 | EQ10: =$B$139+$B$138*($B$5) -> 173.182 | ER10: =$B$140+$B$138*(-$B$33-4*$B$141+1.2*$B$141) -> 15.882915 | FA10: =NA() -> #N/A | FB10: =NA() -> #N/A | FC10: =IF(AND(0<$B$22,($B$19+0*$B$64)>=$B$80),$B$145+$B$144*($B$82),NA()) -> 183.182 | FD10: =IF(AND(0<$B$22,($B$19+0*$B$64)>=$B$80),$B$146+$B$144*(($B$19+0*$B$64)),NA()) -> 38.76135 | FE10: =IF(AND(AND($B$21=1,(1*$B$66)<$B$62),(1*$B$66)>=$B$80),$B$145+$B$144*($B$82),NA()) -> #N/A | FF10: =IF(AND(AND($B$21=1,(1*$B$66)<$B$62),(1*$B$66)>=$B$80),$B$146+$B$144*((1*$B$66)),NA()) -> #N/A | FG10: =NA() -> #N/A | FH10: =NA() -> #N/A | FI10: =NA() -> #N/A | FJ10: =NA() -> #N/A | FK10: =NA() -> #N/A | FL10: =NA() -> #N/A | FM10: =NA() -> #N/A | FN10: =NA() -> #N/A | FW10: =$B$145+$B$144*($B$6) -> 183.182 | FX10: =$B$146+$B$144*(-6*$B$147+1.2*$B$147) -> 33.96135 | FY10: =$B$145+$B$144*(-9*$B$147+1.2*$B$147) -> 12.2 | FZ10: =$B$146+$B$144*($B$9) -> 63.23865 | GA10: =$B$145+$B$144*($B$13) -> 43.311714 | GB10: =$B$146+$B$144*($B$9+$B$53+4*$B$147+1.2*$B$147) -> 68.43865 | GE10: =NA() -> #N/A | GF10: =NA() -> #N/A | GG10: =IF(AND(AND($B$20=1,($B$19+0*$B$64)<$B$10-0.3),($B$19+0*$B$64)>=$B$111),$B$151+$B$150*(MAX(IF(($B$19+0*$B$64)<=$B$9,0,(($B$19+0*$B$64)-$B$9)/$B$8),MIN(($B$5-IF(($B$19+0*$B$64)<=$B$9,0,(($B$19+0*$B$64)-$B$9)/$B$8)),$B$113))),NA()) -> 173.182 | GH10: =IF(AND(AND($B$20=1,($B$19+0*$B$64)<$B$10-0.3),($B$19+0*$B$64)>=$B$111),$B$152+$B$150*(($B$19+0*$B$64)),NA()) -> 23.89542 | GI10: =IF(AND(AND($B$21=1,(1*$B$66)<IF($B$63=1,$B$10-0.2,$B$62)),(1*$B$66)>=$B$111),$B$151+$B$150*(MAX(IF((1*$B$66)<=$B$9,0,((1*$B$66)-$B$9)/$B$8),MIN(($B$5-IF((1*$B$66)<=$B$9,0,((1*$B$66)-$B$9)/$B$8)),$B$113))),NA()) -> #N/A | GJ10: =IF(AND(AND($B$21=1,(1*$B$66)<IF($B$63=1,$B$10-0.2,$B$62)),(1*$B$66)>=$B$111),$B$152+$B$150*((1*$B$66)),NA()) -> #N/A | GK10: =NA() -> #N/A | GL10: =NA() -> #N/A | GM10: =NA() -> #N/A | GN10: =NA() -> #N/A | GO10: =NA() -> #N/A | GP10: =NA() -> #N/A | GY10: =$B$151+$B$150*($B$5) -> 173.182 | GZ10: =$B$152+$B$150*(-6*$B$153+1.2*$B$153) -> 19.09542 | HA10: =$B$151+$B$150*(-9*$B$153+1.2*$B$153) -> 12.2 | HB10: =$B$152+$B$150*($B$9) -> 69.85002 | HC10: =$B$151+$B$150*($B$5+9*$B$153+1.2*$B$153) -> 183.382 | HD10: =$B$152+$B$150*($B$10) -> 82.10458 | HG10: =NA() -> #N/A | HH10: =NA() -> #N/A | HI10: =NA() -> #N/A | HJ10: =NA() -> #N/A | HK10: =NA() -> #N/A | HL10: =NA() -> #N/A | HM10: =NA() -> #N/A | HN10: =NA() -> #N/A | HQ10: =NA() -> #N/A | HR10: =NA() -> #N/A | HS10: =NA() -> #N/A | HT10: =NA() -> #N/A | HU10: =NA() -> #N/A | HV10: =NA() -> #N/A | HW10: =IF(3<=$B$50/2,$B$157+$B$156*((3-0.5)*$B$6/MAX(1,$B$50/2)),NA()) -> 149.25767 | HX10: =IF(3<=$B$50/2,$B$158+$B$156*($B$5),NA()) -> 90 | HY10: =$B$157+$B$156*($B$6) -> 174.591 | HZ10: =$B$158+$B$156*(-7*$B$159+1.2*$B$159) -> 8.2 | IA10: =$B$157+$B$156*(-$B$46-9*$B$159+1.2*$B$159) -> 13.651 | IB10: =$B$158+$B$156*($B$5) -> 90 | IK10: =NA() -> #N/A | IL10: =NA() -> #N/A | IM10: =NA() -> #N/A | IN10: =NA() -> #N/A | IO10: =NA() -> #N/A | IP10: =NA() -> #N/A | IU10: =$B$174+$B$173*($B$169+$B$27/2-$B$41) -> 109.4254 | IV10: =$B$175+$B$173*($B$161+$B$41) -> 23.2045 | IW10: =IF(1<=ROUNDDOWN(($B$27-2*$B$41)/'PARAMÈTRES'!$C$96,0),$B$174+$B$173*($B$169-$B$27/2+$B$41+1*'PARAMÈTRES'!$C$96),NA()) -> 85.1092 | IX10: =IF(1<=ROUNDDOWN(($B$27-2*$B$41)/'PARAMÈTRES'!$C$96,0),$B$175+$B$173*($B$161+$B$41+0.02),NA()) -> 23.71642 | IY10: =NA() -> #N/A | IZ10: =NA() -> #N/A | JA10: =$B$174+$B$173*(-$B$31/2-0.18+1.2*$B$176) -> 20.27152 | JB10: =$B$175+$B$173*(0) -> 51.3601 | JC10: =$B$174+$B$173*($B$31/2) -> 39.0364 | JD10: =$B$175+$B$173*($B$160-0.06+1.2*$B$176) -> 20.30914 | JE10: =$B$174+$B$173*($B$169+$B$27/2) -> 110.7052 | JF10: =$B$175+$B$173*($B$160-0.06+1.2*$B$176) -> 20.30914 | JW10: =$B$174+$B$173*($B$170+1*$B$176) -> 132.182 | JX10: =$B$175+$B$173*(($B$165+$B$166)/2) -> 60.3187 | KE10: =NA() -> #N/A | KF10: =NA() -> #N/A | KG10: =NA() -> #N/A | KH10: =NA() -> #N/A | KI10: =NA() -> #N/A | KJ10: =NA() -> #N/A | KK10: =NA() -> #N/A | KL10: =NA() -> #N/A | KM10: =IF($B$21=1,$B$182+$B$181*($B$177),NA()) -> #N/A | KN10: =IF($B$21=1,$B$183+$B$181*(-6*$B$184+1.2*$B$184),NA()) -> #N/A | KO10: =IF($B$21=1,$B$182+$B$181*(-6*$B$184+1.2*$B$184),NA()) -> #N/A | KP10: =IF($B$21=1,$B$183+$B$181*($B$178),NA()) -> #N/A
A11: h0 | B11: ='PRÉDIMENSIONNEMENT'!$C$32 -> 0 | D11: PG_txt3 | E11: =IF(3<=$B$99,"Porte coul. ","Portillon ")&FIXED($B$117,2,TRUE)&" × "&FIXED($B$118,2,TRUE) -> Portillon 5.50 × 0.00 | G11: =IF(2<=$B$12,$B$133+$B$132*($B$13*2),NA()) -> 70.448143 | H11: =IF(2<=$B$12,$B$134+$B$132*(-4*$B$135),NA()) -> 12 | I11: =$B$133+$B$132*($B$31/2) -> 32.611 | J11: =$B$134+$B$132*($B$31/2) -> 17.02 | K11: =IF(0<=$B$12,$B$133+$B$132*($B$13*0-$B$27/2),NA()) -> 29.551 | L11: =IF(0<=$B$12,$B$134+$B$132*($B$5-$B$27/2),NA()) -> 81.96 | M11: =IF(2<=$B$12,$B$133+$B$132*($B$13*2),NA()) -> 70.448143 | N11: =IF(2<=$B$12,$B$134+$B$132*(0),NA()) -> 16 | O11: =IF(4<=$B$14-1,$B$133+$B$132*(0),NA()) -> #N/A | P11: =IF(4<=$B$14-1,$B$134+$B$132*(4*$B$15),NA()) -> #N/A | Q11: =IF($B$85=1,$B$133+$B$132*($B$90),NA()) -> #N/A | R11: =IF($B$85=1,$B$134+$B$132*(-2.5*$B$135),NA()) -> #N/A | AI11: =$B$133+$B$132*($B$6) -> 167.591 | AJ11: =$B$134+$B$132*(-11*$B$135-1.2*$B$135) -> 3.8 | AK11: =$B$133+$B$132*(-12*$B$135-1.2*$B$135) -> 18.391 | AL11: =$B$134+$B$132*($B$5) -> 84 | AM11: =$B$133+$B$132*($B$13) -> 51.019571 | AN11: =$B$134+$B$132*($B$5+6*$B$135-1.2*$B$135) -> 88.8 | DY11: =$B$139+$B$138*(0) -> 20 | DZ11: =$B$140+$B$138*($B$9) -> 73.828435 | EA11: =IF(AND($B$18=1,3<=$B$26-1),$B$139+$B$138*(3*($B$5/MAX(1,$B$26))),NA()) -> #N/A | EB11: =IF(AND($B$18=1,3<=$B$26-1),$B$140+$B$138*($B$7),NA()) -> #N/A | EC11: =IF($B$18=0,$B$139+$B$138*($B$5/2-$B$55/2),NA()) -> 88.9319 | ED11: =IF($B$18=0,$B$140+$B$138*($B$10-$B$8*$B$55/2),NA()) -> 84.857539 | EE11: =IF(3<=$B$16-1,$B$139+$B$138*(3*($B$5/2)/MAX(1,$B$16-1)),NA()) -> 48.721625 | EF11: =IF(3<=$B$16-1,$B$140+$B$138*($B$9+$B$8*3*($B$5/2)/MAX(1,$B$16-1)+1.2*$B$141),NA()) -> 79.623895 | EI11: =$B$139+$B$138*($B$5+3.5*$B$141) -> 176.682 | EJ11: =$B$140+$B$138*($B$9-0.8*$B$141) -> 73.028435 | EK11: =$B$139+$B$138*(0-$B$29/2) -> 18.46818 | EL11: =$B$140+$B$138*((-$B$33+$B$34)+$B$35) -> 22.12951 | EM11: =$B$139+$B$138*(-9*$B$141-1.2*$B$141) -> 9.8 | EN11: =$B$140+$B$138*($B$7) -> 73.828435 | EO11: =$B$139+$B$138*($B$5+9*$B$141-1.2*$B$141) -> 180.982 | EP11: =$B$140+$B$138*($B$10) -> 86.082995 | EQ11: =$B$139+$B$138*($B$5) -> 173.182 | ER11: =$B$140+$B$138*(-$B$33-4*$B$141-1.2*$B$141) -> 13.482915 | FA11: =IF(2<=$B$12,$B$145+$B$144*($B$13*2),NA()) -> 66.623429 | FB11: =IF(2<=$B$12,$B$146+$B$144*(0),NA()) -> 38.76135 | FC11: =IF(0<$B$22,$B$145+$B$144*(IF(($B$19+0*$B$64)<$B$80,$B$84,$B$82)),NA()) -> 183.182 | FD11: =IF(0<$B$22,$B$146+$B$144*(($B$19+0*$B$64)),NA()) -> 38.76135 | FE11: =IF(AND($B$21=1,(1*$B$66)<$B$62),$B$145+$B$144*(IF((1*$B$66)<$B$80,$B$84,$B$82)),NA()) -> #N/A | FF11: =IF(AND($B$21=1,(1*$B$66)<$B$62),$B$146+$B$144*((1*$B$66)),NA()) -> #N/A | FG11: =IF($B$21=1,$B$145+$B$144*(0),NA()) -> #N/A | FH11: =IF($B$21=1,$B$146+$B$144*($B$62-$B$59/2),NA()) -> #N/A | FI11: =IF(2<=$B$23,$B$145+$B$144*((IF(2=1,1,IF(2=$B$23,$B$12,5*(2-1)))-1)*$B$13),NA()) -> 113.24686 | FJ11: =IF(2<=$B$23,$B$146+$B$144*(0),NA()) -> 38.76135 | FK11: =IF($B$71=1,$B$145+$B$144*($B$76),NA()) -> 90.372237 | FL11: =IF($B$71=1,$B$146+$B$144*($B$73),NA()) -> 55.07955 | FM11: =IF(AND($B$71=1,1<=$B$68),$B$145+$B$144*($B$76-0.1),NA()) -> #N/A | FN11: =IF(AND($B$71=1,1<=$B$68),$B$146+$B$144*($B$73+0.15),NA()) -> #N/A | FW11: =$B$145+$B$144*($B$6) -> 183.182 | FX11: =$B$146+$B$144*(-6*$B$147-1.2*$B$147) -> 31.56135 | FY11: =$B$145+$B$144*(-9*$B$147-1.2*$B$147) -> 9.8 | FZ11: =$B$146+$B$144*($B$9) -> 63.23865 | GA11: =$B$145+$B$144*($B$13) -> 43.311714 | GB11: =$B$146+$B$144*($B$9+$B$53+4*$B$147-1.2*$B$147) -> 66.03865 | GE11: =IF(1<=$B$14-1,$B$151+$B$150*(1*$B$15),NA()) -> 58.2955 | GF11: =IF(1<=$B$14-1,$B$152+$B$150*(0),NA()) -> 23.89542 | GG11: =IF(AND($B$20=1,($B$19+0*$B$64)<$B$10-0.3),$B$151+$B$150*(MAX(IF(($B$19+0*$B$64)<=$B$9,0,(($B$19+0*$B$64)-$B$9)/$B$8),MIN(($B$5-IF(($B$19+0*$B$64)<=$B$9,0,(($B$19+0*$B$64)-$B$9)/$B$8)),IF(($B$19+0*$B$64)<$B$111,$B$115,$B$113)))),NA()) -> 173.182 | GH11: =IF(AND($B$20=1,($B$19+0*$B$64)<$B$10-0.3),$B$152+$B$150*(($B$19+0*$B$64)),NA()) -> 23.89542 | GI11: =IF(AND($B$21=1,(1*$B$66)<IF($B$63=1,$B$10-0.2,$B$62)),$B$151+$B$150*(MAX(IF((1*$B$66)<=$B$9,0,((1*$B$66)-$B$9)/$B$8),MIN(($B$5-IF((1*$B$66)<=$B$9,0,((1*$B$66)-$B$9)/$B$8)),IF((1*$B$66)<$B$111,$B$115,$B$113)))),NA()) -> #N/A | GJ11: =IF(AND($B$21=1,(1*$B$66)<IF($B$63=1,$B$10-0.2,$B$62)),$B$152+$B$150*((1*$B$66)),NA()) -> #N/A | GK11: =IF($B$21=1,$B$151+$B$150*(0),NA()) -> #N/A | GL11: =IF($B$21=1,$B$152+$B$150*($B$62-$B$59/2),NA()) -> #N/A | GM11: =IF($B$102=1,$B$151+$B$150*($B$107),NA()) -> 62.12505 | GN11: =IF($B$102=1,$B$152+$B$150*($B$104),NA()) -> 58.36137 | GO11: =IF(AND($B$102=1,1<=$B$99),$B$151+$B$150*($B$107-0.1),NA()) -> 61.35914 | GP11: =IF(AND($B$102=1,1<=$B$99),$B$152+$B$150*($B$104+0.15),NA()) -> 59.510235 | GY11: =$B$151+$B$150*($B$5) -> 173.182 | GZ11: =$B$152+$B$150*(-6*$B$153-1.2*$B$153) -> 16.69542 | HA11: =$B$151+$B$150*(-9*$B$153-1.2*$B$153) -> 9.8 | HB11: =$B$152+$B$150*($B$9) -> 69.85002 | HC11: =$B$151+$B$150*($B$5+9*$B$153-1.2*$B$153) -> 180.982 | HD11: =$B$152+$B$150*($B$10) -> 82.10458 | HI11: =IF(1<=$B$16-1,$B$157+$B$156*(-$B$46),NA()) -> 21.451 | HJ11: =IF(1<=$B$16-1,$B$158+$B$156*(1*($B$5/2)/MAX(1,$B$16-1)),NA()) -> 18.75 | HK11: =IF(2<=$B$12,$B$157+$B$156*($B$13*2),NA()) -> 66.019571 | HL11: =IF(2<=$B$12,$B$158+$B$156*(0),NA()) -> 14 | HM11: =IF(AND(2<=$B$12,1<=$B$25),$B$157+$B$156*((2-1)*$B$13+1*$B$13/($B$25+1)),NA()) -> 55.162429 | HN11: =IF(AND(2<=$B$12,1<=$B$25),$B$158+$B$156*(0),NA()) -> 14 | HQ11: =IF(AND(1<=$B$23,2<=$B$24),$B$157+$B$156*((IF(1=1,1,IF(1=$B$23,$B$12,5*(1-1)))-1)*$B$13),NA()) -> 22.591 | HR11: =IF(AND(1<=$B$23,2<=$B$24),$B$158+$B$156*((0*$B$5/2+(2-1)*($B$5/2)/$B$24)),NA()) -> 33 | HS11: =IF(AND(1<=$B$12,$B$51>0),$B$157+$B$156*(((1-0.5)*$B$13)-($B$51*$B$13)/2),NA()) -> 32.362429 | HT11: =IF(AND(1<=$B$12,$B$51>0),$B$158+$B$156*((0*$B$5/2+0.6*$B$159)),NA()) -> 14.6 | HU11: =IF(1<=$B$47,$B$157+$B$156*(((MAX(1,MIN($B$12,ROUND(1*$B$12/($B$47+1),0)))-1)*$B$13+0.25*$B$13)-$B$48/2-0.2),NA()) -> 24.979571 | HV11: =IF(1<=$B$47,$B$158+$B$156*(IF(MOD(1,2)=1,$B$5/4,3*$B$5/4)-$B$49/2-0.2),NA()) -> 29.96 | HW11: =IF(4<=$B$50/2,$B$157+$B$156*((4-0.5)*$B$6/MAX(1,$B$50/2)),NA()) -> #N/A | HX11: =IF(4<=$B$50/2,$B$158+$B$156*(0),NA()) -> #N/A | HY11: =$B$157+$B$156*($B$6) -> 174.591 | HZ11: =$B$158+$B$156*(-7*$B$159-1.2*$B$159) -> 5.8 | IA11: =$B$157+$B$156*(-$B$46-9*$B$159-1.2*$B$159) -> 11.251 | IB11: =$B$158+$B$156*($B$5) -> 90 | IK11: =$B$174+$B$173*(-$B$31/2) -> 23.6788 | IL11: =$B$175+$B$173*($B$161) -> 21.9247 | IM11: =IF($B$162+1*$B$67<$B$163,$B$174+$B$173*(-0.075),NA()) -> 29.4379 | IN11: =IF($B$162+1*$B$67<$B$163,$B$175+$B$173*($B$162+1*$B$67),NA()) -> 32.1631 | IO11: =$B$174+$B$173*(0.075+0*($B$170-0.075)/12) -> 33.2773 | IP11: =$B$175+$B$173*(0) -> 51.3601 | IU11: =$B$174+$B$173*($B$169+$B$27/2-$B$41) -> 109.4254 | IV11: =$B$175+$B$173*($B$161+$B$41+0.15) -> 27.0439 | IW11: =IF(2<=ROUNDDOWN(($B$27-2*$B$41)/'PARAMÈTRES'!$C$96,0),$B$174+$B$173*($B$169-$B$27/2+$B$41+2*'PARAMÈTRES'!$C$96),NA()) -> 88.9486 | IX11: =IF(2<=ROUNDDOWN(($B$27-2*$B$41)/'PARAMÈTRES'!$C$96,0),$B$175+$B$173*($B$161+$B$41+0.02),NA()) -> 23.71642 | IY11: =$B$174+$B$173*($B$169+$B$56/2) -> 99.57094 | IZ11: =$B$175+$B$173*($B$168+0.05) -> 64.1581 | JA11: =$B$174+$B$173*(-$B$31/2-0.18-1.2*$B$176) -> 17.87152 | JB11: =$B$175+$B$173*(0) -> 51.3601 | JC11: =$B$174+$B$173*($B$31/2) -> 39.0364 | JD11: =$B$175+$B$173*($B$160-0.06-1.2*$B$176) -> 17.90914 | JE11: =$B$174+$B$173*($B$169+$B$27/2) -> 110.7052 | JF11: =$B$175+$B$173*($B$160-0.06-1.2*$B$176) -> 17.90914 | JW11: =$B$174+$B$173*($B$170+4*$B$176) -> 135.182 | JX11: =$B$175+$B$173*((MAX($B$166,$B$168)+0.75)-1*6.5*$B$176) -> 75.5753 | KG11: =IF($B$21=1,$B$182+$B$181*(0),NA()) -> #N/A | KH11: =IF($B$21=1,$B$183+$B$181*($B$178-$B$59),NA()) -> #N/A | KI11: =IF(AND($B$21=1,1*$B$67>$B$59,1*$B$67<$B$178-$B$59,OR($B$63=0,ABS(1*$B$67-$B$178/2)>$B$59/2)),$B$182+$B$181*($B$177*2/4+$B$60/2),NA()) -> #N/A | KJ11: =IF(AND($B$21=1,1*$B$67>$B$59,1*$B$67<$B$178-$B$59,OR($B$63=0,ABS(1*$B$67-$B$178/2)>$B$59/2)),$B$183+$B$181*(1*$B$67),NA()) -> #N/A | KK11: =IF($B$21=1,$B$182+$B$181*(0),NA()) -> #N/A | KL11: =IF($B$21=1,$B$183+$B$181*($B$178-$B$59/2-($B$59/2-$B$41*0.6)),NA()) -> #N/A | KM11: =IF($B$21=1,$B$182+$B$181*($B$177),NA()) -> #N/A | KN11: =IF($B$21=1,$B$183+$B$181*(-6*$B$184-1.2*$B$184),NA()) -> #N/A | KO11: =IF($B$21=1,$B$182+$B$181*(-6*$B$184-1.2*$B$184),NA()) -> #N/A | KP11: =IF($B$21=1,$B$183+$B$181*($B$178),NA()) -> #N/A
A12: nt | B12: ='PRÉDIMENSIONNEMENT'!$C$28 -> 7 | D12: PG_txt4 | E12: =IF(4<=$B$99,"Porte coul. ","Portillon ")&FIXED($B$124,2,TRUE)&" × "&FIXED($B$125,2,TRUE) -> Portillon 5.50 × 0.00 | G12: =IF(2<=$B$12,$B$133+$B$132*($B$13*2),NA()) -> 70.448143 | H12: =IF(2<=$B$12,$B$134+$B$132*($B$5+4*$B$135),NA()) -> 88 | I12: =$B$133+$B$132*($B$6-$B$31/2) -> 166.571 | J12: =$B$134+$B$132*($B$31/2) -> 17.02 | K12: =IF(0<=$B$12,$B$133+$B$132*($B$13*0+$B$27/2),NA()) -> 33.631 | L12: =IF(0<=$B$12,$B$134+$B$132*($B$5-$B$27/2),NA()) -> 81.96 | M12: =IF(2<=$B$12,$B$133+$B$132*($B$13*2),NA()) -> 70.448143 | N12: =IF(2<=$B$12,$B$134+$B$132*($B$5),NA()) -> 84 | O12: =IF(4<=$B$14-1,$B$133+$B$132*($B$6),NA()) -> #N/A | P12: =IF(4<=$B$14-1,$B$134+$B$132*(4*$B$15),NA()) -> #N/A | Q12: =IF($B$85=1,$B$133+$B$132*($B$91),NA()) -> #N/A | R12: =IF($B$85=1,$B$134+$B$132*(-2.5*$B$135),NA()) -> #N/A | DY12: =$B$139+$B$138*($B$5/2) -> 96.591 | DZ12: =$B$140+$B$138*($B$10) -> 86.082995 | EA12: =IF(AND($B$18=1,3<=$B$26-1),$B$139+$B$138*(3*($B$5/MAX(1,$B$26))),NA()) -> #N/A | EB12: =IF(AND($B$18=1,3<=$B$26-1),$B$140+$B$138*(($B$9+$B$8*MIN(3*($B$5/MAX(1,$B$26)),$B$5-(3*($B$5/MAX(1,$B$26)))))),NA()) -> #N/A | EC12: =IF($B$18=0,$B$139+$B$138*($B$5/2),NA()) -> 96.591 | ED12: =IF($B$18=0,$B$140+$B$138*($B$10-$B$54),NA()) -> 83.785265 | EE12: =IF(3<=$B$16-1,$B$139+$B$138*($B$5-3*($B$5/2)/MAX(1,$B$16-1)),NA()) -> 144.46037 | EF12: =IF(3<=$B$16-1,$B$140+$B$138*($B$9+$B$8*3*($B$5/2)/MAX(1,$B$16-1)+1.2*$B$141),NA()) -> 79.623895 | EI12: =$B$139+$B$138*($B$5+0.3*$B$141) -> 173.482 | EJ12: =$B$140+$B$138*($B$9-0.8*$B$141) -> 73.028435 | EK12: =$B$139+$B$138*(0-$B$29/2) -> 18.46818 | EL12: =$B$140+$B$138*(0) -> 27.873835 | FA12: =IF(2<=$B$12,$B$145+$B$144*($B$13*2),NA()) -> 66.623429 | FB12: =IF(2<=$B$12,$B$146+$B$144*($B$9),NA()) -> 63.23865 | FC12: =IF(0<$B$22,$B$145+$B$144*(IF(($B$19+0*$B$64)<$B$87,$B$90,$B$89)),NA()) -> 183.182 | FD12: =IF(0<$B$22,$B$146+$B$144*(($B$19+0*$B$64)),NA()) -> 38.76135 | FE12: =IF(AND($B$21=1,(1*$B$66)<$B$62),$B$145+$B$144*(IF((1*$B$66)<$B$87,$B$90,$B$89)),NA()) -> #N/A | FF12: =IF(AND($B$21=1,(1*$B$66)<$B$62),$B$146+$B$144*((1*$B$66)),NA()) -> #N/A | FG12: =IF($B$21=1,$B$145+$B$144*($B$6),NA()) -> #N/A | FH12: =IF($B$21=1,$B$146+$B$144*($B$62-$B$59/2),NA()) -> #N/A | FI12: =IF(2<=$B$23,$B$145+$B$144*(IF(2=1,1,IF(2=$B$23,$B$12,5*(2-1)))*$B$13),NA()) -> 136.55857 | FJ12: =IF(2<=$B$23,$B$146+$B$144*($B$9),NA()) -> 63.23865 | FK12: =IF($B$71=1,$B$145+$B$144*($B$77),NA()) -> 112.80976 | FL12: =IF($B$71=1,$B$146+$B$144*($B$73),NA()) -> 55.07955 | FM12: =IF(AND($B$71=1,1<=$B$68),$B$145+$B$144*($B$77+0.1),NA()) -> #N/A | FN12: =IF(AND($B$71=1,1<=$B$68),$B$146+$B$144*($B$73+0.15),NA()) -> #N/A | GE12: =IF(1<=$B$14-1,$B$151+$B$150*(1*$B$15),NA()) -> 58.2955 | GF12: =IF(1<=$B$14-1,$B$152+$B$150*($B$9+$B$8*MIN(1*$B$15,$B$5-1*$B$15)),NA()) -> 75.9773 | GG12: =IF(AND($B$20=1,($B$19+0*$B$64)<$B$10-0.3),$B$151+$B$150*(MAX(IF(($B$19+0*$B$64)<=$B$9,0,(($B$19+0*$B$64)-$B$9)/$B$8),MIN(($B$5-IF(($B$19+0*$B$64)<=$B$9,0,(($B$19+0*$B$64)-$B$9)/$B$8)),IF(($B$19+0*$B$64)<$B$118,$B$121,$B$120)))),NA()) -> 173.182 | GH12: =IF(AND($B$20=1,($B$19+0*$B$64)<$B$10-0.3),$B$152+$B$150*(($B$19+0*$B$64)),NA()) -> 23.89542 | GI12: =IF(AND($B$21=1,(1*$B$66)<IF($B$63=1,$B$10-0.2,$B$62)),$B$151+$B$150*(MAX(IF((1*$B$66)<=$B$9,0,((1*$B$66)-$B$9)/$B$8),MIN(($B$5-IF((1*$B$66)<=$B$9,0,((1*$B$66)-$B$9)/$B$8)),IF((1*$B$66)<$B$118,$B$121,$B$120)))),NA()) -> #N/A | GJ12: =IF(AND($B$21=1,(1*$B$66)<IF($B$63=1,$B$10-0.2,$B$62)),$B$152+$B$150*((1*$B$66)),NA()) -> #N/A | GK12: =IF($B$21=1,$B$151+$B$150*($B$5),NA()) -> #N/A | GL12: =IF($B$21=1,$B$152+$B$150*($B$62-$B$59/2),NA()) -> #N/A | GM12: =IF($B$102=1,$B$151+$B$150*($B$108),NA()) -> 92.76145 | GN12: =IF($B$102=1,$B$152+$B$150*($B$104),NA()) -> 58.36137 | GO12: =IF(AND($B$102=1,1<=$B$99),$B$151+$B$150*($B$108+0.1),NA()) -> 93.52736 | GP12: =IF(AND($B$102=1,1<=$B$99),$B$152+$B$150*($B$104+0.15),NA()) -> 59.510235 | HI12: =IF(1<=$B$16-1,$B$157+$B$156*($B$6+$B$46),NA()) -> 175.731 | HJ12: =IF(1<=$B$16-1,$B$158+$B$156*(1*($B$5/2)/MAX(1,$B$16-1)),NA()) -> 18.75 | HK12: =IF(2<=$B$12,$B$157+$B$156*($B$13*2),NA()) -> 66.019571 | HL12: =IF(2<=$B$12,$B$158+$B$156*($B$5),NA()) -> 90 | HM12: =IF(AND(2<=$B$12,1<=$B$25),$B$157+$B$156*((2-1)*$B$13+1*$B$13/($B$25+1)),NA()) -> 55.162429 | HN12: =IF(AND(2<=$B$12,1<=$B$25),$B$158+$B$156*($B$5),NA()) -> 90 | HQ12: =IF(AND(1<=$B$23,2<=$B$24),$B$157+$B$156*(IF(1=1,1,IF(1=$B$23,$B$12,5*(1-1)))*$B$13),NA()) -> 44.305286 | HR12: =IF(AND(1<=$B$23,2<=$B$24),$B$158+$B$156*((0*$B$5/2+2*($B$5/2)/$B$24)),NA()) -> 52 | HS12: =IF(AND(1<=$B$12,$B$51>0),$B$157+$B$156*(((1-0.5)*$B$13)+($B$51*$B$13)/2),NA()) -> 34.533857 | HT12: =IF(AND(1<=$B$12,$B$51>0),$B$158+$B$156*((0*$B$5/2+0.6*$B$159)+(((0*$B$5/2+$B$5/2-0.6*$B$159))-((0*$B$5/2+0.6*$B$159)))/4),NA()) -> 23.8 | HU12: =IF(1<=$B$47,$B$157+$B$156*(((MAX(1,MIN($B$12,ROUND(1*$B$12/($B$47+1),0)))-1)*$B$13+0.25*$B$13)+$B$48/2+0.2),NA()) -> 31.059571 | HV12: =IF(1<=$B$47,$B$158+$B$156*(IF(MOD(1,2)=1,$B$5/4,3*$B$5/4)-$B$49/2-0.2),NA()) -> 29.96 | HW12: =IF(4<=$B$50/2,$B$157+$B$156*((4-0.5)*$B$6/MAX(1,$B$50/2)),NA()) -> #N/A | HX12: =IF(4<=$B$50/2,$B$158+$B$156*($B$5),NA()) -> #N/A | IK12: =$B$174+$B$173*($B$31/2) -> 39.0364 | IL12: =$B$175+$B$173*($B$161) -> 21.9247 | IM12: =IF($B$162+1*$B$67<$B$163,$B$174+$B$173*(0.075),NA()) -> 33.2773 | IN12: =IF($B$162+1*$B$67<$B$163,$B$175+$B$173*($B$162+1*$B$67),NA()) -> 32.1631 | IO12: =$B$174+$B$173*(0.075+(0+0.5)*($B$170-0.075)/12) -> 37.356662 | IP12: =$B$175+$B$173*($B$164) -> 56.4793 | IU12: =NA() -> #N/A | IV12: =NA() -> #N/A | IW12: =IF(3<=ROUNDDOWN(($B$27-2*$B$41)/'PARAMÈTRES'!$C$96,0),$B$174+$B$173*($B$169-$B$27/2+$B$41+3*'PARAMÈTRES'!$C$96),NA()) -> 92.788 | IX12: =IF(3<=ROUNDDOWN(($B$27-2*$B$41)/'PARAMÈTRES'!$C$96,0),$B$175+$B$173*($B$161+$B$41+0.02),NA()) -> 23.71642 | IY12: =$B$174+$B$173*($B$169+$B$56/2) -> 99.57094 | IZ12: =$B$175+$B$173*($B$168+0.85) -> 84.6349 | JW12: =NA() -> #N/A | JX12: =NA() -> #N/A | KG12: =IF($B$21=1,$B$182+$B$181*($B$177),NA()) -> #N/A | KH12: =IF($B$21=1,$B$183+$B$181*($B$178-$B$59),NA()) -> #N/A | KI12: =IF(AND($B$21=1,1*$B$67>$B$59,1*$B$67<$B$178-$B$59,OR($B$63=0,ABS(1*$B$67-$B$178/2)>$B$59/2)),$B$182+$B$181*($B$177*3/4-$B$60/2),NA()) -> #N/A | KJ12: =IF(AND($B$21=1,1*$B$67>$B$59,1*$B$67<$B$178-$B$59,OR($B$63=0,ABS(1*$B$67-$B$178/2)>$B$59/2)),$B$183+$B$181*(1*$B$67),NA()) -> #N/A | KK12: =IF($B$21=1,$B$182+$B$181*($B$177),NA()) -> #N/A | KL12: =IF($B$21=1,$B$183+$B$181*($B$178-$B$59/2-($B$59/2-$B$41*0.6)),NA()) -> #N/A
