Workbook
Name p_L: 'Paramètres'!$C$6
Name p_B: 'Paramètres'!$C$7
Name p_ESP: 'Paramètres'!$C$8
Name p_PENTE: 'Paramètres'!$C$9
Name p_H: 'Paramètres'!$C$10
Name p_HFOND: 'Paramètres'!$C$11
Name p_EP: 'Paramètres'!$C$12
Name p_PL: 'Paramètres'!$C$13
Name p_PH: 'Paramètres'!$C$14
Name p_NPIL: 'Paramètres'!$C$15
Name p_APO: 'Paramètres'!$C$16
Name p_NPO: 'Paramètres'!$C$17
Name p_BIPE: 'Paramètres'!$C$18
Name p_BPIL: 'Paramètres'!$C$19
Name p_BCH: 'Paramètres'!$C$20
Name p_HCH: 'Paramètres'!$C$21
Name p_ZCHI: 'Paramètres'!$C$22
Name p_LINH: 'Paramètres'!$C$23
Name p_FRL: 'Paramètres'!$C$25
Name p_FRH: 'Paramètres'!$C$26
Name p_PROP: 'Paramètres'!$C$27
Name p_SFB: 'Paramètres'!$C$28
Name p_SFH: 'Paramètres'!$C$29
Name p_SIA: 'Paramètres'!$C$30
Name p_SIH: 'Paramètres'!$C$31
Name p_FPA: 'Paramètres'!$C$32
Name p_ESI: 'Paramètres'!$C$33
Name p_AFUT: 'Paramètres'!$C$34
Name p_NTIG: 'Paramètres'!$C$35
Name p_FOIS: 'Paramètres'!$C$36
Name p_EPDAL: 'Paramètres'!$C$38
Name p_EDAL: 'Paramètres'!$C$39
Name p_NNAP: 'Paramètres'!$C$40
Name p_RDAL: 'Paramètres'!$C$41
Name p_NCHA: 'Paramètres'!$C$42
Name p_EPLAT: 'Paramètres'!$C$43
Name p_COUCHE: 'Paramètres'!$C$44
Name p_KGIPE: 'Paramètres'!$C$46
Name p_KGPLA: 'Paramètres'!$C$47
Name p_KGCOR: 'Paramètres'!$C$48
Name p_NPAL: 'Paramètres'!$C$49
Name p_NPV: 'Paramètres'!$C$50
Name p_GOUS: 'Paramètres'!$C$51
Name p_KG6: 'Paramètres'!$C$53
Name p_KG10: 'Paramètres'!$C$54
Name p_KG12: 'Paramètres'!$C$55
Name p_CHUTES: 'Paramètres'!$C$56
Name p_RCH: 'Paramètres'!$C$58
Name p_EPAN: 'Paramètres'!$C$59
Name p_KGZ: 'Paramètres'!$C$60
Name p_DEB: 'Paramètres'!$C$61
Name p_PO: 'Paramètres'!$C$63
Name p_FC: 'Paramètres'!$C$64
Name p_FG: 'Paramètres'!$C$65
Name p_ALEA: 'Paramètres'!$C$66
Name p_BEN: 'Paramètres'!$C$67
Name p_TVA: 'Paramètres'!$C$68
Name p_K: 'Paramètres'!$C$69
Name p_P: 'Paramètres'!$C$71
Name p_FL: 'Paramètres'!$C$72

Sheet Lisez-moi
A1: ASSEYA SILVER CONSTRUCTION - Construction métallique et bâtiment - Bouaké - Tél : 07 08 39 02 66 / 05 05 10 76 82 - Email : asseyasilver@gmail.com
A2: Notice du classeur - Bâtiment industriel 30,00 x 10,00 m - 04/10/2026 - établi par Moulo Jean Claude, Technicien Génie Civil BTP - BAEL 91 mod. 99 / EC2
B4: ENTREPRISE
B5: Raison sociale | C5: ASSEYA SILVER CONSTRUCTION (ASC) - Construction métallique et bâtiment
B6: Siège | C6: Bouaké
B7: Téléphone | C7: 07 08 39 02 66 / 05 05 10 76 82
B8: Email | C8: asseyasilver@gmail.com
B9: N° CC / RCCM | C9: 2245191 D / CI-BKE-01-2022-B13-00153
B10: Banque | C10: Bank of Africa - compte n° 004619070000
B11: Régime fiscal | C11: TEE - Bouaké 1
B13: Objet | C13: Métré, déboursé sec et devis quantitatif et estimatif (DQE) d'un bâtiment industriel 30 x 10 m, murs en agglos 15 pleins, piliers IPE 220 tous les 5 m encadrés de 2 poteaux BA, contreventements en cornières 50x50x5, entrée 6 m, toiture 2 versants à 20 %, dallage BA 20 cm double nappe HA10, semelles isolées 80 x 80 x 30 en HA12 avec tiges d'ancrage.
B14: Auteur | C14: Moulo Jean Claude - Technicien Génie Civil BTP - Abidjan
B15: Date | C15: 04/10/2026 - prix du marché d'Abidjan à confirmer par cotations fournisseurs
B17: COMMENT MODIFIER
B18: Cellules bleues sur fond jaune | C18: Données modifiables : dimensions, épaisseurs, prix unitaires, rendements, coefficients. Tout le reste se recalcule automatiquement.
B19: Texte noir | C19: Formules - ne pas écraser.
B20: Sol de bonne portance | C20: Feuille « Paramètres » : mettre p_EPLAT = 0,20 (une seule couche de latérite) au lieu de 0,40.
B21: Changer un prix | C21: Feuille « Prix » colonne D : la modification se répercute sur tous les sous-détails, le DS et le DQE.
B22: Changer un rendement | C22: Feuille « Sous-détails » colonne F (quantité par unité d'ouvrage).
B24: FEUILLES
B25: Paramètres | C25: Dimensions, hypothèses, coefficients K et TVA, grandeurs calculées (noms p_...).
B26: Prix | C26: Prix de base : matériaux, main-d'œuvre (h.j), matériel (noms px_...).
B27: Aciers | C27: Nomenclature des aciers HA6 / HA10 / HA12 par lot, nombre de barres de 12 m.
B28: Métré | C28: Avant-métré : formule de chaque quantité (noms q_...).
B29: Sous-détails | C29: Décomposition matériaux / main-d'œuvre / matériel de chaque prix unitaire.
B30: Déboursé sec | C30: Déboursé sec par article et par lot, répartition par nature.
B31: DQE | C31: Devis quantitatif et estimatif : PU = DS x K arrondi à 5 FCFA, récapitulatif HT / TVA 18 % / TTC.
B32: Matériaux et MO | C32: Liste de commande des matériaux et besoins en main-d'œuvre et matériel.
B34: HYPOTHÈSES CLÉS
B35: Piliers | C35: 17 piliers en IPE 220 (S235) de ±0,00 à +6,00 sur platine 15 mm et 4 tiges d'ancrage M20 ; 2 poteaux BA 15x15 (4 HA10, cadres HA6 e = 15) de part et d'autre de chaque IPE.
B36: Contreventements | C36: Cornières 50x50x5 : 4 palées verticales en croix (travées d'extrémité des long pans) et poutre au vent dans 2 travées de toiture.
B37: Semelles isolées | C37: 80 x 80 x 30 cm, fond de fouille à -1,20 m, nappe HA12 e = 15 cm dans les 2 sens, fût BA 40 x 40 (4 HA12) jusqu'à ±0,00 recevant les 4 tiges d'ancrage M20 de la platine de l'IPE.
B38: Dallage | C38: 20 cm, béton dosé à 350 kg/m³, double nappe HA10 e = 20 cm, chaises HA10, polyane, joints sciés maille 5 m.
B39: Forme | C39: Purge et rechargement en latérite par couches de 20 cm compactées à 95 % OPM : 40 cm si mauvaise portance (valeur par défaut), 20 cm sinon.
B40: Options | C40: Lots 6 à 8 (enduits, fermes + pannes Z 120x2 + tôles bacs 5 ondes, portail) chiffrés séparément.

Sheet Paramètres
A1: ASSEYA SILVER CONSTRUCTION - Construction métallique et bâtiment - Bouaké - Tél : 07 08 39 02 66 / 05 05 10 76 82 - Email : asseyasilver@gmail.com
A2: Paramètres et hypothèses - Bâtiment industriel 30,00 x 10,00 m - 04/10/2026 - établi par Moulo Jean Claude, Technicien Génie Civil BTP - BAEL 91 mod. 99 / EC2
A4: Nom | B4: Désignation | C4: Valeur | D4: Unité | E4: Commentaire / source
A5: GÉOMÉTRIE
A6: p_L | B6: Longueur du bâtiment entre axes | C6: 30 | D6: m | E6: Donnée du maître d'ouvrage
A7: p_B | B7: Largeur du bâtiment entre axes | C7: 10 | D7: m | E7: Donnée du maître d'ouvrage
A8: p_ESP | B8: Espacement des piliers | C8: 5 | D8: m | E8: Donnée du maître d'ouvrage
A9: p_PENTE | B9: Pente de la toiture (2 versants) | C9: 0.2 | D9: - | E9: Donnée : 20 %
A10: p_H | B10: Hauteur élévation (TN → dessus chaînage haut) | C10: 6 | D10: m | E10: Donnée : 6 m
A11: p_HFOND | B11: Hauteur maçonnerie agglos en fondation | C11: 1 | D11: m | E11: Donnée : 1 m
A12: p_EP | B12: Épaisseur des murs (agglos 15 pleins) | C12: 0.15 | D12: m | E12: Donnée
A13: p_PL | B13: Largeur de l'entrée | C13: 6 | D13: m | E13: Donnée : 6 m
A14: p_PH | B14: Hauteur du portail | C14: 4.5 | D14: m | E14: Hypothèse
A15: p_NPIL | B15: Nombre de piliers IPE 220 | C15: =2*(p_L/p_ESP+1)+3 -> 17 | D15: u | E15: 7 par long pan + 1 pignon Ouest + 2 encadrement entrée
A16: p_APO | B16: Poteaux BA de part et d'autre des IPE : côté | C16: 0.15 | D16: m | E16: 2 poteaux 15x15 par pilier
A17: p_NPO | B17: Nombre de poteaux BA par pilier | C17: 2 | D17: u | E17: Donnée : deux poteaux autour de chaque pilier
A18: p_BIPE | B18: Largeur d'aile IPE 220 | C18: 0.11 | D18: m | E18: IPE 220 : h = 220 mm, b = 110 mm
A19: p_BPIL | B19: Emprise d'un pilier dans le mur (poteau + IPE + poteau) | C19: =p_NPO*p_APO+p_BIPE -> 0.41 | D19: m
A20: p_BCH | B20: Chaînages : largeur | C20: 0.15 | D20: m
A21: p_HCH | B21: Chaînages : hauteur | C21: 0.2 | D21: m | E21: Chaînages bas, intermédiaire et haut 15x20
A22: p_ZCHI | B22: Niveau du chaînage intermédiaire | C22: 3 | D22: m | E22: Hypothèse : mi-hauteur
A23: p_LINH | B23: Hauteur du linteau d'entrée | C23: 0.4 | D23: m | E23: Linteau 15x40
A24: FONDATIONS
A25: p_FRL | B25: Largeur des fouilles en rigole | C25: 0.6 | D25: m
A26: p_FRH | B26: Profondeur des fouilles (rigoles et puits) | C26: 1.2 | D26: m | E26: Donnée : 120 cm
A27: p_PROP | B27: Épaisseur béton de propreté | C27: 0.05 | D27: m
A28: p_SFB | B28: Semelle filante : largeur | C28: 0.4 | D28: m
A29: p_SFH | B29: Semelle filante : hauteur | C29: 0.15 | D29: m
A30: p_SIA | B30: Semelle isolée : côté | C30: 0.8 | D30: m | E30: Donnée : 80 x 80 cm
A31: p_SIH | B31: Semelle isolée : hauteur | C31: 0.3 | D31: m | E31: Hypothèse (≥ (A-a)/4 = 0,16 m)
A32: p_FPA | B32: Fouille en puits : côté | C32: =p_SIA+0.20 -> 1 | D32: m | E32: 10 cm de jeu de chaque côté
A33: p_ESI | B33: Semelle isolée : espacement des HA12 | C33: 0.15 | D33: m
A34: p_AFUT | B34: Fût BA sous platine : côté | C34: 0.4 | D34: m | E34: Fût 40x40 de -0,85 à ±0,00, 4 HA12
A35: p_NTIG | B35: Tiges d'ancrage M20 par pilier | C35: 4 | D35: u | E35: L = 600 mm coudées, écrous + rondelles
A36: p_FOIS | B36: Coefficient de foisonnement des terres | C36: 1.25 | D36: -
A37: DALLAGE
A38: p_EPDAL | B38: Épaisseur du dallage | C38: 0.2 | D38: m | E38: Donnée : 20 cm
A39: p_EDAL | B39: Maille des armatures du dallage | C39: 0.2 | D39: m | E39: HA10 e = 20 cm dans les 2 sens
A40: p_NNAP | B40: Nombre de nappes | C40: 2 | D40: u | E40: Donnée : double nappe HA10
A41: p_RDAL | B41: Majoration recouvrements dallage | C41: 1.1 | D41: -
A42: p_NCHA | B42: Chaises (distanciers) HA10 par m² | C42: 1 | D42: u/m² | E42: L = 0,80 m par chaise
A43: p_EPLAT | B43: Épaisseur de latérite (purge + rechargement) | C43: 0.4 | D43: m | E43: Mettre 0,20 si le sol a une bonne portance ; 0,40 sinon
A44: p_COUCHE | B44: Épaisseur d'une couche compactée | C44: 0.2 | D44: m | E44: Compactage à 95 % OPM
A45: STRUCTURE MÉTALLIQUE
A46: p_KGIPE | B46: Poids IPE 220 | C46: 26.2 | D46: kg/m | E46: Catalogue profilés
A47: p_KGPLA | B47: Platines (pied 320x220x15 + tête) et raidisseurs par pilier | C47: 15 | D47: kg/u | E47: Estimation
A48: p_KGCOR | B48: Poids cornière 50x50x5 | C48: 3.77 | D48: kg/m | E48: Catalogue profilés
A49: p_NPAL | B49: Palées verticales (croix de St-André) en long pan | C49: 4 | D49: u | E49: 2 par long pan, travées d'extrémité
A50: p_NPV | B50: Travées de poutre au vent en toiture | C50: 2 | D50: u | E50: Travées d'extrémité, 2 versants
A51: p_GOUS | B51: Majoration goussets et boulonnerie | C51: 1.1 | D51: - | E51: 10 %
A52: ACIERS
A53: p_KG6 | B53: Poids HA6 | C53: 0.222 | D53: kg/m
A54: p_KG10 | B54: Poids HA10 | C54: 0.617 | D54: kg/m
A55: p_KG12 | B55: Poids HA12 | C55: 0.888 | D55: kg/m
A56: p_CHUTES | B56: Majoration pour chutes | C56: 1.05 | D56: - | E56: 5 %
A57: OPTIONS
A58: p_RCH | B58: Ratio fermes / traverses de toiture | C58: 8 | D58: kg/m² | E58: Hors piliers IPE, pannes et contreventements - à confirmer par note de calcul
A59: p_EPAN | B59: Entraxe maximal des pannes | C59: 1.2 | D59: m | E59: Pour bac 5 ondes - vérifier la fiche du fabricant
A60: p_KGZ | B60: Poids panne Z 120 x 2 mm | C60: 3.9 | D60: kg/m | E60: Z 120 x 50 x 2 (développé ≈ 250 mm)
A61: p_DEB | B61: Débord de toiture | C61: 0.5 | D61: m
A62: COEFFICIENTS
A63: p_PO | B63: Petit outillage (% de la main-d'œuvre) | C63: 0.03 | D63: %
A64: p_FC | B64: Frais de chantier | C64: 0.05 | D64: %
A65: p_FG | B65: Frais généraux | C65: 0.08 | D65: %
A66: p_ALEA | B66: Aléas | C66: 0.02 | D66: %
A67: p_BEN | B67: Bénéfice | C67: 0.1 | D67: %
A68: p_TVA | B68: TVA (Côte d'Ivoire) | C68: 0.18 | D68: %
A69: p_K | B69: Coefficient de vente K | C69: =(1+p_FC)/(1-(p_FG+p_ALEA+p_BEN)) -> 1.3125 | D69: - | E69: PV = DS x K
A70: CALCULÉ
A71: p_P | B71: Périmètre à l'axe des murs | C71: =2*(p_L+p_B) -> 80 | D71: m
A72: p_FL | B72: Flèche de toiture | C72: =p_B/2*p_PENTE -> 1 | D72: m
A73: p_RAMP | B73: Longueur d'un rampant | C73: =SQRT(p_B/2*p_B/2+p_FL*p_FL) -> 5.0990195 | D73: m
A74: p_LNET | B74: Longueur nette de murs (hors piliers) | C74: =p_P-p_NPIL*p_BPIL -> 73.03 | D74: m
A75: p_LCHI | B75: Longueur nette hors piliers et entrée | C75: =p_LNET-p_PL -> 67.03 | D75: m
A76: p_SINT | B76: Surface intérieure (dallage) | C76: =(p_L-p_EP)*(p_B-p_EP) -> 294.0225 | D76: m²
A77: p_HENT | B77: Hauteur dessus semelle → TN (fût) | C77: =p_FRH-p_PROP-p_SIH -> 0.85 | D77: m
A78: p_HPO | B78: Hauteur totale des poteaux BA | C78: =p_H+p_HENT -> 6.85 | D78: m
A79: p_LIPE | B79: Longueur totale d'IPE 220 | C79: =p_NPIL*p_H+p_FL -> 103 | D79: m | E79: Platine à ±0,00, tête à +6,00 (+1,00 pilier de pignon)
A80: p_NPAN | B80: Nombre de lignes de pannes (2 versants) | C80: =2*(ROUNDUP(p_RAMP/p_EPAN,0)+1) -> 12 | D80: u
A81: p_LCOR | B81: Longueur totale de cornières | C81: =p_NPAL*2*SQRT(p_ESP*p_ESP+p_H*p_H)+p_NPV*2*2*SQRT(p_ESP*p_ESP+p_RAMP*p_RAMP) -> 119.61342 | D81: m
A82: p_HM | B82: Hauteur nette d'agglos en élévation | C82: =p_H-3*p_HCH -> 5.4 | D82: m
A83: p_PIGN | B83: Agglos net par pignon triangulaire | C83: =0.5*p_B*p_FL-2*p_RAMP*p_BCH-p_BPIL*0.5 -> 3.2652941 | D83: m²
A84: p_NCOU | B84: Nombre de couches de latérite | C84: =p_EPLAT/p_COUCHE -> 2 | D84: u
A85: p_VRIG | B85: Volume fouilles en rigole | C85: =p_P*p_FRL*p_FRH -> 57.6 | D85: m³
A86: p_VPUI | B86: Volume fouilles en puits (complément) | C86: =p_NPIL*(p_FPA*p_FPA-p_FRL*p_FPA)*p_FRH -> 8.16 | D86: m³
A87: p_VPROP | B87: Volume béton de propreté | C87: =(p_P-p_NPIL*p_FPA)*p_FRL*p_PROP+p_NPIL*p_FPA*p_FPA*p_PROP -> 2.74 | D87: m³
A88: p_VSI | B88: Volume semelles isolées | C88: =p_NPIL*p_SIA*p_SIA*p_SIH -> 3.264 | D88: m³
A89: p_VSF | B89: Volume semelle filante | C89: =(p_P-p_NPIL*p_SIA)*p_SFB*p_SFH -> 3.984 | D89: m³
A90: p_VENT | B90: Volume des ouvrages enterrés | C90: =p_VPROP+p_VSI+p_VSF+p_LNET*p_HFOND*p_EP+p_NPIL*(p_AFUT*p_AFUT+p_NPO*p_APO*p_APO)*p_HENT -> 23.90475 | D90: m³

Sheet Prix
A1: ASSEYA SILVER CONSTRUCTION - Construction métallique et bâtiment - Bouaké - Tél : 07 08 39 02 66 / 05 05 10 76 82 - Email : asseyasilver@gmail.com
A2: Prix de base - Bâtiment industriel 30,00 x 10,00 m - 04/10/2026 - établi par Moulo Jean Claude, Technicien Génie Civil BTP - BAEL 91 mod. 99 / EC2
A4: Code | B4: Désignation | C4: Unité | D4: Prix unitaire (FCFA) | E4: Catégorie
A5: MATÉRIAUX
A6: ciment | B6: Ciment CPJ 42,5 (sac 50 kg) | C6: sac | D6: 5800 | E6: Matériaux
A7: sable | B7: Sable lavé | C7: m³ | D7: 12000 | E7: Matériaux
A8: gravier | B8: Gravier concassé 5/15 - 15/25 | C8: m³ | D8: 25000 | E8: Matériaux
A9: eau | B9: Eau | C9: m³ | D9: 1000 | E9: Matériaux
A10: agglo | B10: Agglo 15 plein 40x20x15 rendu chantier | C10: u | D10: 500 | E10: Matériaux
A11: ha6 | B11: Acier HA6 FeE500 (barre 12 m = 2,66 kg à 2 300) | C11: kg | D11: 865 | E11: Matériaux
A12: ha10 | B12: Acier HA10 FeE500 (barre 12 m = 7,40 kg à 6 000) | C12: kg | D12: 810 | E12: Matériaux
A13: ha12 | B13: Acier HA12 FeE500 (barre 12 m = 10,66 kg à 8 500) | C13: kg | D13: 800 | E13: Matériaux
A14: fil | B14: Fil recuit | C14: kg | D14: 1500 | E14: Matériaux
A15: bois | B15: Bois de coffrage (amorti 3 emplois) | C15: m² | D15: 1800 | E15: Matériaux
A16: pointes | B16: Pointes | C16: kg | D16: 1500 | E16: Matériaux
A17: huile | B17: Huile de décoffrage | C17: L | D17: 1000 | E17: Matériaux
... A36: ff_portail | B36: Portail : tubes, tôle 15/10, rail, roulettes, peinture | C36: ft | D36: 1600000 | E36: Matériaux
A37: MAIN-D'ŒUVRE
A38: mo_macon | B38: Maçon | C38: h.j | D38: 10000 | E38: Main-d'œuvre
A39: mo_ferr | B39: Ferrailleur | C39: h.j | D39: 10000 | E39: Main-d'œuvre
A40: mo_coff | B40: Coffreur | C40: h.j | D40: 10000 | E40: Main-d'œuvre
A41: mo_soud | B41: Soudeur / couvreur | C41: h.j | D41: 15000 | E41: Main-d'œuvre
A42: mo_tech | B42: Technicien | C42: h.j | D42: 15000 | E42: Main-d'œuvre
A43: mo_man | B43: Manœuvre | C43: h.j | D43: 5000 | E43: Main-d'œuvre
A44: MATÉRIEL
A45: mt_bet | B45: Bétonnière 350 L (location) | C45: j | D45: 25000 | E45: Matériel
A46: mt_vib | B46: Vibreur (location) | C46: j | D46: 15000 | E46: Matériel
A47: mt_dame | B47: Dame sauteuse (location) | C47: j | D47: 20000 | E47: Matériel
A48: mt_plaque | B48: Compacteur à plaque vibrante / rouleau 1 t (location) | C48: j | D48: 60000 | E48: Matériel
A49: mt_cam | B49: Camion benne 10 m³ | C49: voyage | D49: 25000 | E49: Matériel
A50: mt_scie | B50: Scie à sol (location) | C50: j | D50: 30000 | E50: Matériel
A51: mt_niveau | B51: Niveau / théodolite (location) | C51: j | D51: 15000 | E51: Matériel
A52: mt_branch | B52: Branchements provisoires eau et électricité | C52: ft | D52: 100000 | E52: Matériel
A53: mt_ch | B53: Poste à souder, meuleuse, levage (charpente) | C53: kg | D53: 100 | E53: Matériel
A54: mt_echaf | B54: Échafaudage (location) | C54: m² | D54: 150 | E54: Matériel
A55: mt_portail | B55: Poste à souder, meuleuse (portail) | C55: ft | D55: 150000 | E55: Matériel
B57: Source : estimation du marché d'Abidjan, octobre 2026 - à actualiser avec les cotations des fournisseurs.

Sheet Aciers
A1: ASSEYA SILVER CONSTRUCTION - Construction métallique et bâtiment - Bouaké - Tél : 07 08 39 02 66 / 05 05 10 76 82 - Email : asseyasilver@gmail.com
A2: Nomenclature des aciers - Bâtiment industriel 30,00 x 10,00 m - 04/10/2026 - établi par Moulo Jean Claude, Technicien Génie Civil BTP - BAEL 91 mod. 99 / EC2
A4: Lot | B4: Élément | C4: Nuance | D4: Longueur (m) | E4: kg/m | F4: Poids (kg)
A5: 2 | B5: Semelles isolées 80x80 : 2 sens x n HA12 e=15 (L = A - 0,10 + 2 retours 0,20) | C5: HA12 | D5: =p_NPIL*2*(ROUNDUP((p_SIA-0.10)/p_ESI,0)+1)*(p_SIA-0.10+2*0.20) -> 224.4 | E5: =p_KG12 -> 0.888 | F5: =D5*E5 -> 199.2672
A6: 2 | B6: Fûts 40x40 sous platines : 4 HA12 en L (hauteur + retour 0,40) | C6: HA12 | D6: =p_NPIL*4*(p_HENT+0.40) -> 85 | E6: =p_KG12 -> 0.888 | F6: =D6*E6 -> 75.48
A7: 2 | B7: Fûts 40x40 : cadres HA6 e=15 (L = 1,40 m) | C7: HA6 | D7: =p_NPIL*(ROUNDUP(p_HENT/0.15,0)+1)*1.40 -> 166.6 | E7: =p_KG6 -> 0.222 | F7: =D7*E7 -> 36.9852
A8: 2 | B8: Semelle filante : 4 HA10 filants (x1,05 recouvrements) | C8: HA10 | D8: =4*p_P*1.05 -> 336 | E8: =p_KG10 -> 0.617 | F8: =D8*E8 -> 207.312
A9: 2 | B9: Semelle filante : répartiteurs HA6 e=20 | C9: HA6 | D9: =p_P/0.20*(p_SFB+0.05) -> 180 | E9: =p_KG6 -> 0.222 | F9: =D9*E9 -> 39.96
A10: 2 | B10: Chaînage bas : 4 HA10 (x1,10 recouvrements et angles) | C10: HA10 | D10: =4*p_P*1.10 -> 352 | E10: =p_KG10 -> 0.617 | F10: =D10*E10 -> 217.184
A11: 2 | B11: Chaînage bas : cadres HA6 15x20 e=20 (L = 0,60 m) | C11: HA6 | D11: =p_P/0.20*0.60 -> 240 | E11: =p_KG6 -> 0.222 | F11: =D11*E11 -> 53.28
A12: 3 | B12: Poteaux BA 15x15 (2 par pilier) : 4 HA10 (retour 0,30 en semelle + ancrage 0,40) | C12: HA10 | D12: =p_NPIL*p_NPO*4*(p_HPO+0.70)+p_NPO*4*p_FL -> 1034.8 | E12: =p_KG10 -> 0.617 | F12: =D12*E12 -> 638.4716
A13: 3 | B13: Poteaux BA 15x15 : cadres HA6 e=15 (L = 0,50 m) | C13: HA6 | D13: =p_NPIL*p_NPO*(ROUNDUP(p_HPO/0.15,0)+1)*0.50 -> 799 | E13: =p_KG6 -> 0.222 | F13: =D13*E13 -> 177.378
A14: 3 | B14: Chaînage intermédiaire : 4 HA10 (interrompu à l'entrée) | C14: HA10 | D14: =4*(p_P-p_PL)*1.10 -> 325.6 | E14: =p_KG10 -> 0.617 | F14: =D14*E14 -> 200.8952
A15: 3 | B15: Chaînage intermédiaire : cadres HA6 e=20 | C15: HA6 | D15: =(p_P-p_PL)/0.20*0.60 -> 222 | E15: =p_KG6 -> 0.222 | F15: =D15*E15 -> 49.284
A16: 3 | B16: Chaînage haut : 4 HA10 | C16: HA10 | D16: =4*p_P*1.10 -> 352 | E16: =p_KG10 -> 0.617 | F16: =D16*E16 -> 217.184
A17: 3 | B17: Chaînage haut : cadres HA6 e=20 | C17: HA6 | D17: =p_P/0.20*0.60 -> 240 | E17: =p_KG6 -> 0.222 | F17: =D17*E17 -> 53.28
A18: 3 | B18: Linteau 15x40 : 2 lits 3 HA10 + 2 HA10 haut | C18: HA10 | D18: =8*(p_PL+0.80) -> 54.4 | E18: =p_KG10 -> 0.617 | F18: =D18*E18 -> 33.5648
A19: 3 | B19: Linteau : cadres HA6 15x40 e=15 (L = 1,00 m) | C19: HA6 | D19: =ROUNDUP((p_PL+0.80)/0.15,0)*1.00 -> 46 | E19: =p_KG6 -> 0.222 | F19: =D19*E19 -> 10.212
A20: 3 | B20: Chaînages rampants 15x15 : 4 HA10 | C20: HA10 | D20: =16*p_RAMP*1.10 -> 89.742743 | E20: =p_KG10 -> 0.617 | F20: =D20*E20 -> 55.371273
A21: 3 | B21: Chaînages rampants : cadres HA6 e=20 (L = 0,50 m) | C21: HA6 | D21: =4*p_RAMP/0.20*0.50 -> 50.990195 | E21: =p_KG6 -> 0.222 | F21: =D21*E21 -> 11.319823
A22: 5 | B22: Dallage : double nappe HA10 e=20 dans les 2 sens | C22: HA10 | D22: =p_SINT*p_NNAP*2/p_EDAL*p_RDAL -> 6468.495 | E22: =p_KG10 -> 0.617 | F22: =D22*E22 -> 3991.0614
A23: 5 | B23: Dallage : chaises HA10 (L = 0,80 m) | C23: HA10 | D23: =p_SINT*p_NCHA*0.80 -> 235.218 | E23: =p_KG10 -> 0.617 | F23: =D23*E23 -> 145.12951
A25: Lot | B25: Récapitulatif | C25: Nuance | D25: Poids net (kg) | E25: Chutes | F25: Poids à commander (kg) | G25: Barres de 12 m
A26: 2 | B26: Lot 2 | C26: HA12 | D26: =SUMIFS('Aciers'!$F$5:$F$23,'Aciers'!$A$5:$A$23,A26,'Aciers'!$C$5:$C$23,C26) -> 274.7472 | E26: =p_CHUTES -> 1.05 | F26: =D26*E26 -> 288.48456 | G26: =ROUNDUP(F26/(12*p_KG12),0) -> 28
A27: 2 | B27: Lot 2 | C27: HA10 | D27: =SUMIFS('Aciers'!$F$5:$F$23,'Aciers'!$A$5:$A$23,A27,'Aciers'!$C$5:$C$23,C27) -> 424.496 | E27: =p_CHUTES -> 1.05 | F27: =D27*E27 -> 445.7208 | G27: =ROUNDUP(F27/(12*p_KG10),0) -> 61
A28: 2 | B28: Lot 2 | C28: HA6 | D28: =SUMIFS('Aciers'!$F$5:$F$23,'Aciers'!$A$5:$A$23,A28,'Aciers'!$C$5:$C$23,C28) -> 130.2252 | E28: =p_CHUTES -> 1.05 | F28: =D28*E28 -> 136.73646 | G28: =ROUNDUP(F28/(12*p_KG6),0) -> 52
A29: 3 | B29: Lot 3 | C29: HA10 | D29: =SUMIFS('Aciers'!$F$5:$F$23,'Aciers'!$A$5:$A$23,A29,'Aciers'!$C$5:$C$23,C29) -> 1145.4869 | E29: =p_CHUTES -> 1.05 | F29: =D29*E29 -> 1202.7612 | G29: =ROUNDUP(F29/(12*p_KG10),0) -> 163
A30: 3 | B30: Lot 3 | C30: HA6 | D30: =SUMIFS('Aciers'!$F$5:$F$23,'Aciers'!$A$5:$A$23,A30,'Aciers'!$C$5:$C$23,C30) -> 301.47382 | E30: =p_CHUTES -> 1.05 | F30: =D30*E30 -> 316.54751 | G30: =ROUNDUP(F30/(12*p_KG6),0) -> 119
A31: 5 | B31: Lot 5 | C31: HA10 | D31: =SUMIFS('Aciers'!$F$5:$F$23,'Aciers'!$A$5:$A$23,A31,'Aciers'!$C$5:$C$23,C31) -> 4136.1909 | E31: =p_CHUTES -> 1.05 | F31: =D31*E31 -> 4343.0005 | G31: =ROUNDUP(F31/(12*p_KG10),0) -> 587
B32: TOTAL HA12 | C32: HA12 | D32: =SUMIFS('Aciers'!$F$5:$F$23,'Aciers'!$C$5:$C$23,C32) -> 274.7472 | E32: =p_CHUTES -> 1.05 | F32: =D32*E32 -> 288.48456 | G32: =ROUNDUP(F32/(12*p_KG12),0) -> 28
B33: TOTAL HA10 | C33: HA10 | D33: =SUMIFS('Aciers'!$F$5:$F$23,'Aciers'!$C$5:$C$23,C33) -> 5706.1738 | E33: =p_CHUTES -> 1.05 | F33: =D33*E33 -> 5991.4825 | G33: =ROUNDUP(F33/(12*p_KG10),0) -> 810
B34: TOTAL HA6 | C34: HA6 | D34: =SUMIFS('Aciers'!$F$5:$F$23,'Aciers'!$C$5:$C$23,C34) -> 431.69902 | E34: =p_CHUTES -> 1.05 | F34: =D34*E34 -> 453.28397 | G34: =ROUNDUP(F34/(12*p_KG6),0) -> 171

Sheet Métré
A1: ASSEYA SILVER CONSTRUCTION - Construction métallique et bâtiment - Bouaké - Tél : 07 08 39 02 66 / 05 05 10 76 82 - Email : asseyasilver@gmail.com
A2: Avant-métré - Bâtiment industriel 30,00 x 10,00 m - 04/10/2026 - établi par Moulo Jean Claude, Technicien Génie Civil BTP - BAEL 91 mod. 99 / EC2
A4: N° | B4: Lot | C4: Désignation | D4: U | E4: Formule (noms de la feuille Paramètres) | F4: Quantité
A5: LOT 0 | C5: INSTALLATION DE CHANTIER ET TRAVAUX PRÉPARATOIRES
A6: 0.1 | B6: 0 | C6: Installation et repli de chantier (magasin, clôture provisoire, eau, électricité, panneau) | D6: ft | E6: 1 | F6: =1 -> 1
A7: 0.2 | B7: 0 | C7: Débroussaillage et décapage de la terre végétale ép. 10 cm | D7: m² | E7: (p_L+4)*(p_B+4) | F7: =(p_L+4)*(p_B+4) -> 476
A8: 0.3 | B8: 0 | C8: Implantation du bâtiment (chaises, cordeaux, axes et niveaux) | D8: ft | E8: 1 | F8: =1 -> 1
A9: LOT 1 | C9: TERRASSEMENTS
A10: 1.1 | B10: 1 | C10: Fouilles en rigole 0,60 x 1,20 m en terrain latéritique | D10: m³ | E10: p_VRIG | F10: =p_VRIG -> 57.6
A11: 1.2 | B11: 1 | C11: Fouilles en puits 1,00 x 1,00 x 1,20 m pour semelles isolées 80x80 (complément) | D11: m³ | E11: p_VPUI | F11: =p_VPUI -> 8.16
A12: 1.3 | B12: 1 | C12: Remblai des fouilles avec les terres extraites, compacté par couches de 20 cm | D12: m³ | E12: p_VRIG+p_VPUI-p_VENT | F12: =p_VRIG+p_VPUI-p_VENT -> 41.85525
A13: 1.4 | B13: 1 | C13: Évacuation des terres excédentaires des fouilles | D13: m³ | E13: p_VENT*p_FOIS | F13: =p_VENT*p_FOIS -> 29.880938
A14: 1.5 | B14: 1 | C14: Traitement anti-termites des fonds de fouilles | D14: m² | E14: p_P*p_FRL+p_NPIL*(p_FPA*p_FPA-p_FRL*p_FPA) | F14: =p_P*p_FRL+p_NPIL*(p_FPA*p_FPA-p_FRL*p_FPA) -> 54.8
A15: LOT 2 | C15: FONDATIONS
A16: 2.1 | B16: 2 | C16: Béton de propreté dosé à 150 kg/m³, ép. 5 cm | D16: m³ | E16: p_VPROP | F16: =p_VPROP -> 2.74
A17: 2.2 | B17: 2 | C17: Béton armé dosé à 350 kg/m³ pour semelles isolées 0,80 x 0,80 x 0,30 | D17: m³ | E17: p_VSI | F17: =p_VSI -> 3.264
A18: 2.3 | B18: 2 | C18: Béton armé dosé à 350 kg/m³ pour fûts 40 x 40 sous platines des IPE (de -0,85 à ±0,00) | D18: m³ | E18: p_NPIL*p_AFUT*p_AFUT*p_HENT | F18: =p_NPIL*p_AFUT*p_AFUT*p_HENT -> 2.312
A19: 2.4 | B19: 2 | C19: Fourniture et scellement des tiges d'ancrage M20 des IPE (gabarit de pose, 4 par pilier) | D19: u | E19: p_NPIL*p_NTIG | F19: =p_NPIL*p_NTIG -> 68
A20: 2.5 | B20: 2 | C20: Béton armé dosé à 350 kg/m³ pour semelle filante 0,40 x 0,15 | D20: m³ | E20: p_VSF | F20: =p_VSF -> 3.984
A21: 2.6 | B21: 2 | C21: Maçonnerie d'agglos 15 pleins en fondation h = 1,00 m, mortier dosé à 300 kg/m³ | D21: m² | E21: p_LNET*p_HFOND | F21: =p_LNET*p_HFOND -> 73.03
A22: 2.7 | B22: 2 | C22: Béton armé dosé à 350 kg/m³ pour chaînage bas 15 x 20 | D22: m³ | E22: p_LNET*p_BCH*p_HCH | F22: =p_LNET*p_BCH*p_HCH -> 2.1909
A23: 2.8 | B23: 2 | C23: Chape d'arase étanche (mortier dosé à 400 kg/m³ + hydrofuge) ép. 3 cm | D23: m² | E23: p_LNET*p_EP | F23: =p_LNET*p_EP -> 10.9545
A24: 2.9 | B24: 2 | C24: Coffrage en bois ordinaire (semelles isolées, fûts, chaînage bas) | D24: m² | E24: p_NPIL*4*(p_SIA*p_SIH+p_AFUT*p_HENT)+2*p_HCH*p_LNET | F24: =p_NPIL*4*(p_SIA*p_SIH+p_AFUT*p_HENT)+2*p_HCH*p_LNET -> 68.652
A25: 2.10 | B25: 2 | C25: Armatures HA12 FeE500 - semelles isolées 80x80 et fûts | D25: kg | E25: Nomenclature des aciers - lot 2 - HA12 (y compris chutes) | F25: ='Aciers'!$F$26 -> 288.48456
A26: 2.11 | B26: 2 | C26: Armatures HA10 FeE500 - fondations | D26: kg | E26: Nomenclature des aciers - lot 2 - HA10 (y compris chutes) | F26: ='Aciers'!$F$27 -> 445.7208
A27: 2.12 | B27: 2 | C27: Armatures HA6 FeE500 - fondations | D27: kg | E27: Nomenclature des aciers - lot 2 - HA6 (y compris chutes) | F27: ='Aciers'!$F$28 -> 136.73646
A28: LOT 3 | C28: ÉLÉVATION (MAÇONNERIE ET BÉTON ARMÉ)
A29: 3.1 | B29: 3 | C29: Maçonnerie d'agglos 15 pleins en élévation, mortier dosé à 300 kg/m³ (y compris pignons) | D29: m² | E29: p_LCHI*p_HM+p_PL*((p_H-p_HCH)-(p_PH+p_LINH))+2*p_PIGN | F29: =p_LCHI*p_HM+p_PL*((p_H-p_HCH)-(p_PH+p_LINH))+2*p_PIGN -> 373.89259
A30: 3.2 | B30: 3 | C30: Béton armé dosé à 350 kg/m³ pour poteaux 15 x 15 (2 par pilier IPE), de -0,85 à +6,00 | D30: m³ | E30: p_NPIL*p_NPO*p_APO*p_APO*p_HPO+p_NPO*p_APO*p_APO*p_FL | F30: =p_NPIL*p_NPO*p_APO*p_APO*p_HPO+p_NPO*p_APO*p_APO*p_FL -> 5.28525
A31: 3.3 | B31: 3 | C31: Béton armé dosé à 350 kg/m³ pour chaînage intermédiaire 15 x 20 à +3,00 | D31: m³ | E31: p_LCHI*p_BCH*p_HCH | F31: =p_LCHI*p_BCH*p_HCH -> 2.0109
A32: 3.4 | B32: 3 | C32: Béton armé dosé à 350 kg/m³ pour chaînage haut 15 x 20 | D32: m³ | E32: p_LNET*p_BCH*p_HCH | F32: =p_LNET*p_BCH*p_HCH -> 2.1909
A33: 3.5 | B33: 3 | C33: Béton armé dosé à 350 kg/m³ pour linteau de l'entrée 15 x 40 | D33: m³ | E33: p_PL*p_BCH*p_LINH | F33: =p_PL*p_BCH*p_LINH -> 0.36
A34: 3.6 | B34: 3 | C34: Béton armé dosé à 350 kg/m³ pour chaînages rampants 15 x 15 (pente 20 %) | D34: m³ | E34: 4*(p_RAMP-0.20)*0.15*0.15 | F34: =4*(p_RAMP-0.20)*0.15*0.15 -> 0.44091176
A35: 3.7 | B35: 3 | C35: Coffrage en bois ordinaire (poteaux, chaînages, linteau, rampants) | D35: m² | E35: 3*p_APO*p_NPO*(p_NPIL*p_HPO+p_FL)+2*p_HCH*(p_LCHI+p_LNET)+(2*p_LINH+p_BCH)*p_PL+2*0.15*4*(p_RAMP-0.20) | F35: =3*p_APO*p_NPO*(p_NPIL*p_HPO+p_FL)+2*p_HCH*(p_LCHI+p_LNET)+(2*p_LINH+p_BCH)*p_PL+2*0.15*4*(p_RAMP-0.20) -> 173.30782
A36: 3.8 | B36: 3 | C36: Armatures HA10 FeE500 - élévation | D36: kg | E36: Nomenclature des aciers - lot 3 - HA10 (y compris chutes) | F36: ='Aciers'!$F$29 -> 1202.7612
A37: 3.9 | B37: 3 | C37: Armatures HA6 FeE500 - élévation | D37: kg | E37: Nomenclature des aciers - lot 3 - HA6 (y compris chutes) | F37: ='Aciers'!$F$30 -> 316.54751
A38: LOT 4 | C38: STRUCTURE MÉTALLIQUE : PILIERS IPE 220 ET CONTREVENTEMENTS
A39: 4.1 | B39: 4 | C39: Piliers en IPE 220 (S235) de ±0,00 à +6,00, fournis, fabriqués, peints et posés | D39: kg | E39: p_LIPE*p_KGIPE | F39: =p_LIPE*p_KGIPE -> 2698.6
A40: 4.2 | B40: 4 | C40: Platines de pied et de tête 15 mm + raidisseurs, soudées | D40: kg | E40: p_NPIL*p_KGPLA | F40: =p_NPIL*p_KGPLA -> 255
A41: 4.3 | B41: 4 | C41: Calage et scellement des platines au mortier sans retrait | D41: u | E41: p_NPIL | F41: =p_NPIL -> 17
A42: 4.4 | B42: 4 | C42: Contreventements en cornières 50x50x5 : palées verticales en long pan et poutre au vent en toiture (goussets et boulons compris) | D42: kg | E42: p_LCOR*p_KGCOR*p_GOUS | F42: =p_LCOR*p_KGCOR*p_GOUS -> 496.03687
A43: LOT 5 | C43: FORME EN LATÉRITE ET DALLAGE BA 20 cm
A44: 5.1 | B44: 5 | C44: Décaissement / purge intérieure du sol de mauvaise portance (ép. = épaisseur de latérite) et évacuation | D44: m³ | E44: p_SINT*p_EPLAT | F44: =p_SINT*p_EPLAT -> 117.609
A45: 5.2 | B45: 5 | C45: Rechargement en latérite d'emprunt à l'intérieur, mis en œuvre par couches de 20 cm, arrosé et compacté à 95 % OPM | D45: m³ | E45: p_SINT*p_EPLAT | F45: =p_SINT*p_EPLAT -> 117.609
A46: 5.3 | B46: 5 | C46: Essais de contrôle (Proctor modifié, densités in situ par couche, éprouvettes béton) | D46: ft | E46: 1 | F46: =1 -> 1
A47: 5.4 | B47: 5 | C47: Traitement anti-termites sous dallage | D47: m² | E47: p_SINT | F47: =p_SINT -> 294.0225
A48: 5.5 | B48: 5 | C48: Film polyane 150 µ sous dallage (recouvrements 10 %) | D48: m² | E48: p_SINT*1.10 | F48: =p_SINT*1.10 -> 323.42475
A49: 5.6 | B49: 5 | C49: Armatures HA10 FeE500 - dallage double nappe e = 20 cm + chaises | D49: kg | E49: Nomenclature des aciers - lot 5 - HA10 (y compris chutes) | F49: ='Aciers'!$F$31 -> 4343.0005
A50: 5.7 | B50: 5 | C50: Béton armé dosé à 350 kg/m³ pour dallage ép. 20 cm, vibré et surfacé | D50: m³ | E50: p_SINT*p_EPDAL | F50: =p_SINT*p_EPDAL -> 58.8045
A51: 5.8 | B51: 5 | C51: Joints de retrait sciés (maille 5 m) et joint périphérique | D51: ml | E51: (p_L/p_ESP-1)*(p_B-p_EP)+(ROUNDUP(p_B/p_ESP,0)-1)*(p_L-p_EP)+2*(p_L+p_B-2*p_EP) | F51: =(p_L/p_ESP-1)*(p_B-p_EP)+(ROUNDUP(p_B/p_ESP,0)-1)*(p_L-p_EP)+2*(p_L+p_B-2*p_EP) -> 158.5
A52: LOT 6 | C52: ENDUITS (OPTION)
A53: 6.1 | B53: 6 | C53: Enduit au mortier dosé à 300 kg/m³ ép. 2 cm, intérieur et extérieur | D53: m² | E53: 2*(p_L+p_B+2*p_EP)*(p_H+0.20)+p_B*p_FL-p_PL*p_PH+2*(p_L+p_B-2*p_EP)*(p_H-p_EPDAL)+p_B*p_FL-p_PL*p_PH | F53: =2*(p_L+p_B+2*p_EP)*(p_H+0.20)+p_B*p_FL-p_PL*p_PH+2*(p_L+p_B-2*p_EP)*(p_H-p_EPDAL)+p_B*p_FL-p_PL*p_PH -> 926.24
A54: LOT 7 | C54: CHARPENTE DE TOITURE ET COUVERTURE - PENTE 20 % (OPTION)
A55: 7.1 | B55: 7 | C55: Fermes / traverses de toiture sur têtes d'IPE 220 (hors pannes) - ratio à confirmer par note de calcul | D55: kg | E55: p_RCH*(p_L+1)*(p_B+1) | F55: =p_RCH*(p_L+1)*(p_B+1) -> 2728
A56: 7.2 | B56: 7 | C56: Pannes en Z 120 x 2 mm, entraxe ≤ 1,20 m, y compris échantignoles et boulonnerie | D56: kg | E56: p_NPAN*(p_L+1)*1.05*p_KGZ | F56: =p_NPAN*(p_L+1)*1.05*p_KGZ -> 1523.34
A57: 7.3 | B57: 7 | C57: Couverture en tôles bacs 5 ondulations sur pannes Z, pente 20 %, débords 0,50 m | D57: m² | E57: 2*(p_RAMP+p_DEB)*(p_L+1) | F57: =2*(p_RAMP+p_DEB)*(p_L+1) -> 347.13921
A58: 7.4 | B58: 7 | C58: Faîtière | D58: ml | E58: p_L+1 | F58: =p_L+1 -> 31
A59: LOT 8 | C59: MENUISERIE MÉTALLIQUE (OPTION)
A60: 8.1 | B60: 8 | C60: Portail métallique coulissant 6,00 x 4,50 m | D60: u | E60: 1 | F60: =1 -> 1

Sheet Sous-détails
A1: ASSEYA SILVER CONSTRUCTION - Construction métallique et bâtiment - Bouaké - Tél : 07 08 39 02 66 / 05 05 10 76 82 - Email : asseyasilver@gmail.com
A2: Sous-détails de prix (déboursé sec unitaire) - Bâtiment industriel 30,00 x 10,00 m - 04/10/2026 - établi par Moulo Jean Claude, Technicien Génie Civil BTP - BAEL 91 mod. 99 / EC2
A4: N° | B4: Nature | C4: Composante | D4: Code prix | E4: U | F4: Qté / unité | G4: P.U. (FCFA) | H4: Montant / unité | I4: Qté ouvrage | J4: Qté totale | K4: Option
B5: Article 0.1 - Installation et repli de chantier (magasin, clôture provisoire, eau, électricité, panneau) (unité : ft)
A6: Art. 0.1 | B6: Matériaux | C6: Magasin, clôture provisoire, panneau de chantier | D6: ff_install | E6: ft | F6: =1 -> 1 | G6: =px_ff_install -> 300000 | H6: =F6*G6 -> 300000 | I6: =q_0_1 -> 1 | J6: =F6*I6 -> 1 | K6: NON
A7: Art. 0.1 | B7: Main-d'œuvre | C7: Manœuvres (montage / repli) | D7: mo_man | E7: h.j | F7: =20 -> 20 | G7: =px_mo_man -> 5000 | H7: =F7*G7 -> 100000 | I7: =q_0_1 -> 1 | J7: =F7*I7 -> 20 | K7: NON
A8: Art. 0.1 | B8: Matériel | C8: Branchements provisoires eau et électricité | D8: mt_branch | E8: ft | F8: =1 -> 1 | G8: =px_mt_branch -> 100000 | H8: =F8*G8 -> 100000 | I8: =q_0_1 -> 1 | J8: =F8*I8 -> 1 | K8: NON
A9: Art. 0.1 | B9: Matériel | C9: Petit outillage (% de la main-d'œuvre) | E9: % | F9: =p_PO -> 0.03 | G9: =SUMIFS(H6:H8,B6:B8,"Main-d'œuvre") -> 100000 | H9: =F9*G9 -> 3000
C10: DÉBOURSÉ SEC UNITAIRE / ft | H10: =SUM(H6:H9) -> 503000
B12: Article 0.2 - Débroussaillage et décapage de la terre végétale ép. 10 cm (unité : m²)
A13: Art. 0.2 | B13: Main-d'œuvre | C13: Manœuvre (60 m²/j) | D13: mo_man | E13: h.j | F13: =1/60 -> 0.016666667 | G13: =px_mo_man -> 5000 | H13: =F13*G13 -> 83.333333 | I13: =q_0_2 -> 476 | J13: =F13*I13 -> 7.9333333 | K13: NON
A14: Art. 0.2 | B14: Matériel | C14: Petit outillage (% de la main-d'œuvre) | E14: % | F14: =p_PO -> 0.03 | G14: =SUMIFS(H13:H13,B13:B13,"Main-d'œuvre") -> 83.333333 | H14: =F14*G14 -> 2.5
C15: DÉBOURSÉ SEC UNITAIRE / m² | H15: =SUM(H13:H14) -> 85.833333
B17: Article 0.3 - Implantation du bâtiment (chaises, cordeaux, axes et niveaux) (unité : ft)
A18: Art. 0.3 | B18: Matériaux | C18: Bois de chaises, cordeau, peinture | D18: ff_implant | E18: ft | F18: =1 -> 1 | G18: =px_ff_implant -> 40000 | H18: =F18*G18 -> 40000 | I18: =q_0_3 -> 1 | J18: =F18*I18 -> 1 | K18: NON
A19: Art. 0.3 | B19: Main-d'œuvre | C19: Technicien | D19: mo_tech | E19: h.j | F19: =2 -> 2 | G19: =px_mo_tech -> 15000 | H19: =F19*G19 -> 30000 | I19: =q_0_3 -> 1 | J19: =F19*I19 -> 2 | K19: NON
A20: Art. 0.3 | B20: Main-d'œuvre | C20: Manœuvre | D20: mo_man | E20: h.j | F20: =4 -> 4 | G20: =px_mo_man -> 5000 | H20: =F20*G20 -> 20000 | I20: =q_0_3 -> 1 | J20: =F20*I20 -> 4 | K20: NON
A21: Art. 0.3 | B21: Matériel | C21: Niveau / théodolite (location) | D21: mt_niveau | E21: j | F21: =2 -> 2 | G21: =px_mt_niveau -> 15000 | H21: =F21*G21 -> 30000 | I21: =q_0_3 -> 1 | J21: =F21*I21 -> 2 | K21: NON
A22: Art. 0.3 | B22: Matériel | C22: Petit outillage (% de la main-d'œuvre) | E22: % | F22: =p_PO -> 0.03 | G22: =SUMIFS(H18:H21,B18:B21,"Main-d'œuvre") -> 50000 | H22: =F22*G22 -> 1500
C23: DÉBOURSÉ SEC UNITAIRE / ft | H23: =SUM(H18:H22) -> 121500
B25: Article 1.1 - Fouilles en rigole 0,60 x 1,20 m en terrain latéritique (unité : m³)
A26: Art. 1.1 | B26: Main-d'œuvre | C26: Manœuvre (1,5 m³/j en latérite compacte) | D26: mo_man | E26: h.j | F26: =1/1.5 -> 0.66666667 | G26: =px_mo_man -> 5000 | H26: =F26*G26 -> 3333.3333 | I26: =q_1_1 -> 57.6 | J26: =F26*I26 -> 38.4 | K26: NON
A27: Art. 1.1 | B27: Matériel | C27: Petit outillage (% de la main-d'œuvre) | E27: % | F27: =p_PO -> 0.03 | G27: =SUMIFS(H26:H26,B26:B26,"Main-d'œuvre") -> 3333.3333 | H27: =F27*G27 -> 100
C28: DÉBOURSÉ SEC UNITAIRE / m³ | H28: =SUM(H26:H27) -> 3433.3333
B30: Article 1.2 - Fouilles en puits 1,00 x 1,00 x 1,20 m pour semelles isolées 80x80 (complément) (unité : m³)
A31: Art. 1.2 | B31: Main-d'œuvre | C31: Manœuvre (1,5 m³/j) | D31: mo_man | E31: h.j | F31: =1/1.5 -> 0.66666667 | G31: =px_mo_man -> 5000 | H31: =F31*G31 -> 3333.3333 | I31: =q_1_2 -> 8.16 | J31: =F31*I31 -> 5.44 | K31: NON
A32: Art. 1.2 | B32: Matériel | C32: Petit outillage (% de la main-d'œuvre) | E32: % | F32: =p_PO -> 0.03 | G32: =SUMIFS(H31:H31,B31:B31,"Main-d'œuvre") -> 3333.3333 | H32: =F32*G32 -> 100
C33: DÉBOURSÉ SEC UNITAIRE / m³ | H33: =SUM(H31:H32) -> 3433.3333
B35: Article 1.3 - Remblai des fouilles avec les terres extraites, compacté par couches de 20 cm (unité : m³)
A36: Art. 1.3 | B36: Main-d'œuvre | C36: Manœuvre (4 m³/j) | D36: mo_man | E36: h.j | F36: =1/4 -> 0.25 | G36: =px_mo_man -> 5000 | H36: =F36*G36 -> 1250 | I36: =q_1_3 -> 41.85525 | J36: =F36*I36 -> 10.463812 | K36: NON
A37: Art. 1.3 | B37: Matériel | C37: Dame sauteuse (20 m³/j) | D37: mt_dame | E37: j | F37: =1/20 -> 0.05 | G37: =px_mt_dame -> 20000 | H37: =F37*G37 -> 1000 | I37: =q_1_3 -> 41.85525 | J37: =F37*I37 -> 2.0927625 | K37: NON
A38: Art. 1.3 | B38: Matériel | C38: Petit outillage (% de la main-d'œuvre) | E38: % | F38: =p_PO -> 0.03 | G38: =SUMIFS(H36:H37,B36:B37,"Main-d'œuvre") -> 1250 | H38: =F38*G38 -> 37.5
C39: DÉBOURSÉ SEC UNITAIRE / m³ | H39: =SUM(H36:H38) -> 2287.5
B41: Article 1.4 - Évacuation des terres excédentaires des fouilles (unité : m³)
A42: Art. 1.4 | B42: Main-d'œuvre | C42: Manœuvre - chargement (5 m³/j) | D42: mo_man | E42: h.j | F42: =1/5 -> 0.2 | G42: =px_mo_man -> 5000 | H42: =F42*G42 -> 1000 | I42: =q_1_4 -> 29.880938 | J42: =F42*I42 -> 5.9761875 | K42: NON
A43: Art. 1.4 | B43: Matériel | C43: Camion benne 10 m³ (voyage) | D43: mt_cam | E43: voyage | F43: =1/10 -> 0.1 | G43: =px_mt_cam -> 25000 | H43: =F43*G43 -> 2500 | I43: =q_1_4 -> 29.880938 | J43: =F43*I43 -> 2.9880938 | K43: NON
A44: Art. 1.4 | B44: Matériel | C44: Petit outillage (% de la main-d'œuvre) | E44: % | F44: =p_PO -> 0.03 | G44: =SUMIFS(H42:H43,B42:B43,"Main-d'œuvre") -> 1000 | H44: =F44*G44 -> 30
C45: DÉBOURSÉ SEC UNITAIRE / m³ | H45: =SUM(H42:H44) -> 3530
B47: Article 1.5 - Traitement anti-termites des fonds de fouilles (unité : m²)
A48: Art. 1.5 | B48: Matériaux | C48: Produit anti-termites (dilué) | D48: termite | E48: m² | F48: =1 -> 1 | G48: =px_termite -> 1200 | H48: =F48*G48 -> 1200 | I48: =q_1_5 -> 54.8 | J48: =F48*I48 -> 54.8 | K48: NON
A49: Art. 1.5 | B49: Main-d'œuvre | C49: Manœuvre (25 m²/j) | D49: mo_man | E49: h.j | F49: =1/25 -> 0.04 | G49: =px_mo_man -> 5000 | H49: =F49*G49 -> 200 | I49: =q_1_5 -> 54.8 | J49: =F49*I49 -> 2.192 | K49: NON
A50: Art. 1.5 | B50: Matériel | C50: Petit outillage (% de la main-d'œuvre) | E50: % | F50: =p_PO -> 0.03 | G50: =SUMIFS(H48:H49,B48:B49,"Main-d'œuvre") -> 200 | H50: =F50*G50 -> 6
C51: DÉBOURSÉ SEC UNITAIRE / m² | H51: =SUM(H48:H50) -> 1406
B53: Article 2.1 - Béton de propreté dosé à 150 kg/m³, ép. 5 cm (unité : m³)
A54: Art. 2.1 | B54: Matériaux | C54: Ciment CPJ 42,5 (sac 50 kg) | D54: ciment | E54: sac | F54: =150/50 -> 3 | G54: =px_ciment -> 5800 | H54: =F54*G54 -> 17400 | I54: =q_2_1 -> 2.74 | J54: =F54*I54 -> 8.22 | K54: NON
A55: Art. 2.1 | B55: Matériaux | C55: Sable lavé | D55: sable | E55: m³ | F55: =0.45 -> 0.45 | G55: =px_sable -> 12000 | H55: =F55*G55 -> 5400 | I55: =q_2_1 -> 2.74 | J55: =F55*I55 -> 1.233 | K55: NON
A56: Art. 2.1 | B56: Matériaux | C56: Gravier concassé 5/15 - 15/25 | D56: gravier | E56: m³ | F56: =0.85 -> 0.85 | G56: =px_gravier -> 25000 | H56: =F56*G56 -> 21250 | I56: =q_2_1 -> 2.74 | J56: =F56*I56 -> 2.329 | K56: NON
A57: Art. 2.1 | B57: Matériaux | C57: Eau | D57: eau | E57: m³ | F57: =0.20 -> 0.2 | G57: =px_eau -> 1000 | H57: =F57*G57 -> 200 | I57: =q_2_1 -> 2.74 | J57: =F57*I57 -> 0.548 | K57: NON
A58: Art. 2.1 | B58: Main-d'œuvre | C58: Maçon (équipe 1 maçon + 6 manœuvres : 8 m³/j) | D58: mo_macon | E58: h.j | F58: =1/8 -> 0.125 | G58: =px_mo_macon -> 10000 | H58: =F58*G58 -> 1250 | I58: =q_2_1 -> 2.74 | J58: =F58*I58 -> 0.3425 | K58: NON
A59: Art. 2.1 | B59: Main-d'œuvre | C59: Manœuvres (6 par équipe) | D59: mo_man | E59: h.j | F59: =6/8 -> 0.75 | G59: =px_mo_man -> 5000 | H59: =F59*G59 -> 3750 | I59: =q_2_1 -> 2.74 | J59: =F59*I59 -> 2.055 | K59: NON
A60: Art. 2.1 | B60: Matériel | C60: Bétonnière 350 L (location) | D60: mt_bet | E60: j | F60: =1/8 -> 0.125 | G60: =px_mt_bet -> 25000 | H60: =F60*G60 -> 3125 | I60: =q_2_1 -> 2.74 | J60: =F60*I60 -> 0.3425 | K60: NON
A61: Art. 2.1 | B61: Matériel | C61: Vibreur (location) | D61: mt_vib | E61: j | F61: =1/8 -> 0.125 | G61: =px_mt_vib -> 15000 | H61: =F61*G61 -> 1875 | I61: =q_2_1 -> 2.74 | J61: =F61*I61 -> 0.3425 | K61: NON
A62: Art. 2.1 | B62: Matériel | C62: Petit outillage (% de la main-d'œuvre) | E62: % | F62: =p_PO -> 0.03 | G62: =SUMIFS(H54:H61,B54:B61,"Main-d'œuvre") -> 5000 | H62: =F62*G62 -> 150
C63: DÉBOURSÉ SEC UNITAIRE / m³ | H63: =SUM(H54:H62) -> 54400
B65: Article 2.2 - Béton armé dosé à 350 kg/m³ pour semelles isolées 0,80 x 0,80 x 0,30 (unité : m³)
A66: Art. 2.2 | B66: Matériaux | C66: Ciment CPJ 42,5 (sac 50 kg) | D66: ciment | E66: sac | F66: =350/50 -> 7 | G66: =px_ciment -> 5800 | H66: =F66*G66 -> 40600 | I66: =q_2_2 -> 3.264 | J66: =F66*I66 -> 22.848 | K66: NON
A67: Art. 2.2 | B67: Matériaux | C67: Sable lavé | D67: sable | E67: m³ | F67: =0.45 -> 0.45 | G67: =px_sable -> 12000 | H67: =F67*G67 -> 5400 | I67: =q_2_2 -> 3.264 | J67: =F67*I67 -> 1.4688 | K67: NON
A68: Art. 2.2 | B68: Matériaux | C68: Gravier concassé 5/15 - 15/25 | D68: gravier | E68: m³ | F68: =0.85 -> 0.85 | G68: =px_gravier -> 25000 | H68: =F68*G68 -> 21250 | I68: =q_2_2 -> 3.264 | J68: =F68*I68 -> 2.7744 | K68: NON
A69: Art. 2.2 | B69: Matériaux | C69: Eau | D69: eau | E69: m³ | F69: =0.20 -> 0.2 | G69: =px_eau -> 1000 | H69: =F69*G69 -> 200 | I69: =q_2_2 -> 3.264 | J69: =F69*I69 -> 0.6528 | K69: NON
A70: Art. 2.2 | B70: Main-d'œuvre | C70: Maçon (équipe 1 maçon + 6 manœuvres : 5 m³/j) | D70: mo_macon | E70: h.j | F70: =1/5 -> 0.2 | G70: =px_mo_macon -> 10000 | H70: =F70*G70 -> 2000 | I70: =q_2_2 -> 3.264 | J70: =F70*I70 -> 0.6528 | K70: NON
A71: Art. 2.2 | B71: Main-d'œuvre | C71: Manœuvres (6 par équipe) | D71: mo_man | E71: h.j | F71: =6/5 -> 1.2 | G71: =px_mo_man -> 5000 | H71: =F71*G71 -> 6000 | I71: =q_2_2 -> 3.264 | J71: =F71*I71 -> 3.9168 | K71: NON
A72: Art. 2.2 | B72: Matériel | C72: Bétonnière 350 L (location) | D72: mt_bet | E72: j | F72: =1/5 -> 0.2 | G72: =px_mt_bet -> 25000 | H72: =F72*G72 -> 5000 | I72: =q_2_2 -> 3.264 | J72: =F72*I72 -> 0.6528 | K72: NON
A73: Art. 2.2 | B73: Matériel | C73: Vibreur (location) | D73: mt_vib | E73: j | F73: =1/5 -> 0.2 | G73: =px_mt_vib -> 15000 | H73: =F73*G73 -> 3000 | I73: =q_2_2 -> 3.264 | J73: =F73*I73 -> 0.6528 | K73: NON
A74: Art. 2.2 | B74: Matériel | C74: Petit outillage (% de la main-d'œuvre) | E74: % | F74: =p_PO -> 0.03 | G74: =SUMIFS(H66:H73,B66:B73,"Main-d'œuvre") -> 8000 | H74: =F74*G74 -> 240
C75: DÉBOURSÉ SEC UNITAIRE / m³ | H75: =SUM(H66:H74) -> 83690
B77: Article 2.3 - Béton armé dosé à 350 kg/m³ pour fûts 40 x 40 sous platines des IPE (de -0,85 à ±0,00) (unité : m³)
A78: Art. 2.3 | B78: Matériaux | C78: Ciment CPJ 42,5 (sac 50 kg) | D78: ciment | E78: sac | F78: =350/50 -> 7 | G78: =px_ciment -> 5800 | H78: =F78*G78 -> 40600 | I78: =q_2_3 -> 2.312 | J78: =F78*I78 -> 16.184 | K78: NON
A79: Art. 2.3 | B79: Matériaux | C79: Sable lavé | D79: sable | E79: m³ | F79: =0.45 -> 0.45 | G79: =px_sable -> 12000 | H79: =F79*G79 -> 5400 | I79: =q_2_3 -> 2.312 | J79: =F79*I79 -> 1.0404 | K79: NON
A80: Art. 2.3 | B80: Matériaux | C80: Gravier concassé 5/15 - 15/25 | D80: gravier | E80: m³ | F80: =0.85 -> 0.85 | G80: =px_gravier -> 25000 | H80: =F80*G80 -> 21250 | I80: =q_2_3 -> 2.312 | J80: =F80*I80 -> 1.9652 | K80: NON
A81: Art. 2.3 | B81: Matériaux | C81: Eau | D81: eau | E81: m³ | F81: =0.20 -> 0.2 | G81: =px_eau -> 1000 | H81: =F81*G81 -> 200 | I81: =q_2_3 -> 2.312 | J81: =F81*I81 -> 0.4624 | K81: NON
A82: Art. 2.3 | B82: Main-d'œuvre | C82: Maçon (équipe 1 maçon + 6 manœuvres : 4 m³/j) | D82: mo_macon | E82: h.j | F82: =1/4 -> 0.25 | G82: =px_mo_macon -> 10000 | H82: =F82*G82 -> 2500 | I82: =q_2_3 -> 2.312 | J82: =F82*I82 -> 0.578 | K82: NON
A83: Art. 2.3 | B83: Main-d'œuvre | C83: Manœuvres (6 par équipe) | D83: mo_man | E83: h.j | F83: =6/4 -> 1.5 | G83: =px_mo_man -> 5000 | H83: =F83*G83 -> 7500 | I83: =q_2_3 -> 2.312 | J83: =F83*I83 -> 3.468 | K83: NON
A84: Art. 2.3 | B84: Matériel | C84: Bétonnière 350 L (location) | D84: mt_bet | E84: j | F84: =1/4 -> 0.25 | G84: =px_mt_bet -> 25000 | H84: =F84*G84 -> 6250 | I84: =q_2_3 -> 2.312 | J84: =F84*I84 -> 0.578 | K84: NON
A85: Art. 2.3 | B85: Matériel | C85: Vibreur (location) | D85: mt_vib | E85: j | F85: =1/4 -> 0.25 | G85: =px_mt_vib -> 15000 | H85: =F85*G85 -> 3750 | I85: =q_2_3 -> 2.312 | J85: =F85*I85 -> 0.578 | K85: NON
A86: Art. 2.3 | B86: Matériel | C86: Petit outillage (% de la main-d'œuvre) | E86: % | F86: =p_PO -> 0.03 | G86: =SUMIFS(H78:H85,B78:B85,"Main-d'œuvre") -> 10000 | H86: =F86*G86 -> 300
C87: DÉBOURSÉ SEC UNITAIRE / m³ | H87: =SUM(H78:H86) -> 87750
B89: Article 2.4 - Fourniture et scellement des tiges d'ancrage M20 des IPE (gabarit de pose, 4 par pilier) (unité : u)
A90: Art. 2.4 | B90: Matériaux | C90: Tige d'ancrage M20 L = 600 coudée + 2 écrous + rondelle | D90: tige | E90: u | F90: =1 -> 1 | G90: =px_tige -> 6000 | H90: =F90*G90 -> 6000 | I90: =q_2_4 -> 68 | J90: =F90*I90 -> 68 | K90: NON
A91: Art. 2.4 | B91: Matériaux | C91: Gabarit de pose (contreplaqué) | D91: bois | E91: m² | F91: =0.10 -> 0.1 | G91: =px_bois -> 1800 | H91: =F91*G91 -> 180 | I91: =q_2_4 -> 68 | J91: =F91*I91 -> 6.8 | K91: NON
A92: Art. 2.4 | B92: Main-d'œuvre | C92: Monteur (16 tiges/j) | D92: mo_soud | E92: h.j | F92: =1/16 -> 0.0625 | G92: =px_mo_soud -> 15000 | H92: =F92*G92 -> 937.5 | I92: =q_2_4 -> 68 | J92: =F92*I92 -> 4.25 | K92: NON
A93: Art. 2.4 | B93: Main-d'œuvre | C93: Manœuvre (16 tiges/j) | D93: mo_man | E93: h.j | F93: =1/16 -> 0.0625 | G93: =px_mo_man -> 5000 | H93: =F93*G93 -> 312.5 | I93: =q_2_4 -> 68 | J93: =F93*I93 -> 4.25 | K93: NON
A94: Art. 2.4 | B94: Matériel | C94: Petit outillage (% de la main-d'œuvre) | E94: % | F94: =p_PO -> 0.03 | G94: =SUMIFS(H90:H93,B90:B93,"Main-d'œuvre") -> 1250 | H94: =F94*G94 -> 37.5
C95: DÉBOURSÉ SEC UNITAIRE / u | H95: =SUM(H90:H94) -> 7467.5
B97: Article 2.5 - Béton armé dosé à 350 kg/m³ pour semelle filante 0,40 x 0,15 (unité : m³)
A98: Art. 2.5 | B98: Matériaux | C98: Ciment CPJ 42,5 (sac 50 kg) | D98: ciment | E98: sac | F98: =350/50 -> 7 | G98: =px_ciment -> 5800 | H98: =F98*G98 -> 40600 | I98: =q_2_5 -> 3.984 | J98: =F98*I98 -> 27.888 | K98: NON
A99: Art. 2.5 | B99: Matériaux | C99: Sable lavé | D99: sable | E99: m³ | F99: =0.45 -> 0.45 | G99: =px_sable -> 12000 | H99: =F99*G99 -> 5400 | I99: =q_2_5 -> 3.984 | J99: =F99*I99 -> 1.7928 | K99: NON
A100: Art. 2.5 | B100: Matériaux | C100: Gravier concassé 5/15 - 15/25 | D100: gravier | E100: m³ | F100: =0.85 -> 0.85 | G100: =px_gravier -> 25000 | H100: =F100*G100 -> 21250 | I100: =q_2_5 -> 3.984 | J100: =F100*I100 -> 3.3864 | K100: NON
A101: Art. 2.5 | B101: Matériaux | C101: Eau | D101: eau | E101: m³ | F101: =0.20 -> 0.2 | G101: =px_eau -> 1000 | H101: =F101*G101 -> 200 | I101: =q_2_5 -> 3.984 | J101: =F101*I101 -> 0.7968 | K101: NON
A102: Art. 2.5 | B102: Main-d'œuvre | C102: Maçon (équipe 1 maçon + 6 manœuvres : 6 m³/j) | D102: mo_macon | E102: h.j | F102: =1/6 -> 0.16666667 | G102: =px_mo_macon -> 10000 | H102: =F102*G102 -> 1666.6667 | I102: =q_2_5 -> 3.984 | J102: =F102*I102 -> 0.664 | K102: NON
A103: Art. 2.5 | B103: Main-d'œuvre | C103: Manœuvres (6 par équipe) | D103: mo_man | E103: h.j | F103: =6/6 -> 1 | G103: =px_mo_man -> 5000 | H103: =F103*G103 -> 5000 | I103: =q_2_5 -> 3.984 | J103: =F103*I103 -> 3.984 | K103: NON
A104: Art. 2.5 | B104: Matériel | C104: Bétonnière 350 L (location) | D104: mt_bet | E104: j | F104: =1/6 -> 0.16666667 | G104: =px_mt_bet -> 25000 | H104: =F104*G104 -> 4166.6667 | I104: =q_2_5 -> 3.984 | J104: =F104*I104 -> 0.664 | K104: NON
A105: Art. 2.5 | B105: Matériel | C105: Vibreur (location) | D105: mt_vib | E105: j | F105: =1/6 -> 0.16666667 | G105: =px_mt_vib -> 15000 | H105: =F105*G105 -> 2500 | I105: =q_2_5 -> 3.984 | J105: =F105*I105 -> 0.664 | K105: NON
A106: Art. 2.5 | B106: Matériel | C106: Petit outillage (% de la main-d'œuvre) | E106: % | F106: =p_PO -> 0.03 | G106: =SUMIFS(H98:H105,B98:B105,"Main-d'œuvre") -> 6666.6667 | H106: =F106*G106 -> 200
C107: DÉBOURSÉ SEC UNITAIRE / m³ | H107: =SUM(H98:H106) -> 80983.333
B109: Article 2.6 - Maçonnerie d'agglos 15 pleins en fondation h = 1,00 m, mortier dosé à 300 kg/m³ (unité : m²)
A110: Art. 2.6 | B110: Matériaux | C110: Agglos 15 pleins (12,5 u/m² + 5 % casse) | D110: agglo | E110: u | F110: =12.5*1.05 -> 13.125 | G110: =px_agglo -> 500 | H110: =F110*G110 -> 6562.5 | I110: =q_2_6 -> 73.03 | J110: =F110*I110 -> 958.51875 | K110: NON
A111: Art. 2.6 | B111: Matériaux | C111: Ciment CPJ 42,5 (sac 50 kg) | D111: ciment | E111: sac | F111: =0.15 -> 0.15 | G111: =px_ciment -> 5800 | H111: =F111*G111 -> 870 | I111: =q_2_6 -> 73.03 | J111: =F111*I111 -> 10.9545 | K111: NON
A112: Art. 2.6 | B112: Matériaux | C112: Sable lavé | D112: sable | E112: m³ | F112: =0.03 -> 0.03 | G112: =px_sable -> 12000 | H112: =F112*G112 -> 360 | I112: =q_2_6 -> 73.03 | J112: =F112*I112 -> 2.1909 | K112: NON
A113: Art. 2.6 | B113: Matériaux | C113: Eau | D113: eau | E113: m³ | F113: =0.01 -> 0.01 | G113: =px_eau -> 1000 | H113: =F113*G113 -> 10 | I113: =q_2_6 -> 73.03 | J113: =F113*I113 -> 0.7303 | K113: NON
A114: Art. 2.6 | B114: Main-d'œuvre | C114: Maçon (10 m²/j) | D114: mo_macon | E114: h.j | F114: =1/10 -> 0.1 | G114: =px_mo_macon -> 10000 | H114: =F114*G114 -> 1000 | I114: =q_2_6 -> 73.03 | J114: =F114*I114 -> 7.303 | K114: NON
...

Sheet Déboursé sec
A1: ASSEYA SILVER CONSTRUCTION - Construction métallique et bâtiment - Bouaké - Tél : 07 08 39 02 66 / 05 05 10 76 82 - Email : asseyasilver@gmail.com
A2: Déboursé sec - Bâtiment industriel 30,00 x 10,00 m - 04/10/2026 - établi par Moulo Jean Claude, Technicien Génie Civil BTP - BAEL 91 mod. 99 / EC2
A4: N° | B4: Désignation | C4: U | D4: Quantité | E4: Matériaux / u | F4: Main-d'œuvre / u | G4: Matériel / u | H4: DS unitaire | I4: Matériaux total | J4: Main-d'œuvre total | K4: Matériel total | L4: DS total (FCFA) | M4: Option
A5: LOT 0 | B5: INSTALLATION DE CHANTIER ET TRAVAUX PRÉPARATOIRES
A6: 0.1 | B6: Installation et repli de chantier (magasin, clôture provisoire, eau, électricité, panneau) | C6: ft | D6: =q_0_1 -> 1 | E6: =SUMIFS('Sous-détails'!$H$5:$H$407,'Sous-détails'!$A$5:$A$407,"Art. "&$A6,'Sous-détails'!$B$5:$B$407,"Matériaux") -> 300000 | F6: =SUMIFS('Sous-détails'!$H$5:$H$407,'Sous-détails'!$A$5:$A$407,"Art. "&$A6,'Sous-détails'!$B$5:$B$407,"Main-d'œuvre") -> 100000 | G6: =SUMIFS('Sous-détails'!$H$5:$H$407,'Sous-détails'!$A$5:$A$407,"Art. "&$A6,'Sous-détails'!$B$5:$B$407,"Matériel") -> 103000 | H6: =E6+F6+G6 -> 503000 | I6: =$D6*E6 -> 300000 | J6: =$D6*F6 -> 100000 | K6: =$D6*G6 -> 103000 | L6: =$D6*H6 -> 503000 | M6: NON
A7: 0.2 | B7: Débroussaillage et décapage de la terre végétale ép. 10 cm | C7: m² | D7: =q_0_2 -> 476 | E7: =SUMIFS('Sous-détails'!$H$5:$H$407,'Sous-détails'!$A$5:$A$407,"Art. "&$A7,'Sous-détails'!$B$5:$B$407,"Matériaux") -> 0 | F7: =SUMIFS('Sous-détails'!$H$5:$H$407,'Sous-détails'!$A$5:$A$407,"Art. "&$A7,'Sous-détails'!$B$5:$B$407,"Main-d'œuvre") -> 83.333333 | G7: =SUMIFS('Sous-détails'!$H$5:$H$407,'Sous-détails'!$A$5:$A$407,"Art. "&$A7,'Sous-détails'!$B$5:$B$407,"Matériel") -> 2.5 | H7: =E7+F7+G7 -> 85.833333 | I7: =$D7*E7 -> 0 | J7: =$D7*F7 -> 39666.667 | K7: =$D7*G7 -> 1190 | L7: =$D7*H7 -> 40856.667 | M7: NON
A8: 0.3 | B8: Implantation du bâtiment (chaises, cordeaux, axes et niveaux) | C8: ft | D8: =q_0_3 -> 1 | E8: =SUMIFS('Sous-détails'!$H$5:$H$407,'Sous-détails'!$A$5:$A$407,"Art. "&$A8,'Sous-détails'!$B$5:$B$407,"Matériaux") -> 40000 | F8: =SUMIFS('Sous-détails'!$H$5:$H$407,'Sous-détails'!$A$5:$A$407,"Art. "&$A8,'Sous-détails'!$B$5:$B$407,"Main-d'œuvre") -> 50000 | G8: =SUMIFS('Sous-détails'!$H$5:$H$407,'Sous-détails'!$A$5:$A$407,"Art. "&$A8,'Sous-détails'!$B$5:$B$407,"Matériel") -> 31500 | H8: =E8+F8+G8 -> 121500 | I8: =$D8*E8 -> 40000 | J8: =$D8*F8 -> 50000 | K8: =$D8*G8 -> 31500 | L8: =$D8*H8 -> 121500 | M8: NON
B9: Sous-total déboursé sec lot 0 | I9: =SUM(I6:I8) -> 340000 | J9: =SUM(J6:J8) -> 189666.67 | K9: =SUM(K6:K8) -> 135690 | L9: =SUM(L6:L8) -> 665356.67
A11: LOT 1 | B11: TERRASSEMENTS
A12: 1.1 | B12: Fouilles en rigole 0,60 x 1,20 m en terrain latéritique | C12: m³ | D12: =q_1_1 -> 57.6 | E12: =SUMIFS('Sous-détails'!$H$5:$H$407,'Sous-détails'!$A$5:$A$407,"Art. "&$A12,'Sous-détails'!$B$5:$B$407,"Matériaux") -> 0 | F12: =SUMIFS('Sous-détails'!$H$5:$H$407,'Sous-détails'!$A$5:$A$407,"Art. "&$A12,'Sous-détails'!$B$5:$B$407,"Main-d'œuvre") -> 3333.3333 | G12: =SUMIFS('Sous-détails'!$H$5:$H$407,'Sous-détails'!$A$5:$A$407,"Art. "&$A12,'Sous-détails'!$B$5:$B$407,"Matériel") -> 100 | H12: =E12+F12+G12 -> 3433.3333 | I12: =$D12*E12 -> 0 | J12: =$D12*F12 -> 192000 | K12: =$D12*G12 -> 5760 | L12: =$D12*H12 -> 197760 | M12: NON
A13: 1.2 | B13: Fouilles en puits 1,00 x 1,00 x 1,20 m pour semelles isolées 80x80 (complément) | C13: m³ | D13: =q_1_2 -> 8.16 | E13: =SUMIFS('Sous-détails'!$H$5:$H$407,'Sous-détails'!$A$5:$A$407,"Art. "&$A13,'Sous-détails'!$B$5:$B$407,"Matériaux") -> 0 | F13: =SUMIFS('Sous-détails'!$H$5:$H$407,'Sous-détails'!$A$5:$A$407,"Art. "&$A13,'Sous-détails'!$B$5:$B$407,"Main-d'œuvre") -> 3333.3333 | G13: =SUMIFS('Sous-détails'!$H$5:$H$407,'Sous-détails'!$A$5:$A$407,"Art. "&$A13,'Sous-détails'!$B$5:$B$407,"Matériel") -> 100 | H13: =E13+F13+G13 -> 3433.3333 | I13: =$D13*E13 -> 0 | J13: =$D13*F13 -> 27200 | K13: =$D13*G13 -> 816 | L13: =$D13*H13 -> 28016 | M13: NON
A14: 1.3 | B14: Remblai des fouilles avec les terres extraites, compacté par couches de 20 cm | C14: m³ | D14: =q_1_3 -> 41.85525 | E14: =SUMIFS('Sous-détails'!$H$5:$H$407,'Sous-détails'!$A$5:$A$407,"Art. "&$A14,'Sous-détails'!$B$5:$B$407,"Matériaux") -> 0 | F14: =SUMIFS('Sous-détails'!$H$5:$H$407,'Sous-détails'!$A$5:$A$407,"Art. "&$A14,'Sous-détails'!$B$5:$B$407,"Main-d'œuvre") -> 1250 | G14: =SUMIFS('Sous-détails'!$H$5:$H$407,'Sous-détails'!$A$5:$A$407,"Art. "&$A14,'Sous-détails'!$B$5:$B$407,"Matériel") -> 1037.5 | H14: =E14+F14+G14 -> 2287.5 | I14: =$D14*E14 -> 0 | J14: =$D14*F14 -> 52319.062 | K14: =$D14*G14 -> 43424.822 | L14: =$D14*H14 -> 95743.884 | M14: NON
A15: 1.4 | B15: Évacuation des terres excédentaires des fouilles | C15: m³ | D15: =q_1_4 -> 29.880938 | E15: =SUMIFS('Sous-détails'!$H$5:$H$407,'Sous-détails'!$A$5:$A$407,"Art. "&$A15,'Sous-détails'!$B$5:$B$407,"Matériaux") -> 0 | F15: =SUMIFS('Sous-détails'!$H$5:$H$407,'Sous-détails'!$A$5:$A$407,"Art. "&$A15,'Sous-détails'!$B$5:$B$407,"Main-d'œuvre") -> 1000 | G15: =SUMIFS('Sous-détails'!$H$5:$H$407,'Sous-détails'!$A$5:$A$407,"Art. "&$A15,'Sous-détails'!$B$5:$B$407,"Matériel") -> 2530 | H15: =E15+F15+G15 -> 3530 | I15: =$D15*E15 -> 0 | J15: =$D15*F15 -> 29880.938 | K15: =$D15*G15 -> 75598.772 | L15: =$D15*H15 -> 105479.71 | M15: NON
A16: 1.5 | B16: Traitement anti-termites des fonds de fouilles | C16: m² | D16: =q_1_5 -> 54.8 | E16: =SUMIFS('Sous-détails'!$H$5:$H$407,'Sous-détails'!$A$5:$A$407,"Art. "&$A16,'Sous-détails'!$B$5:$B$407,"Matériaux") -> 1200 | F16: =SUMIFS('Sous-détails'!$H$5:$H$407,'Sous-détails'!$A$5:$A$407,"Art. "&$A16,'Sous-détails'!$B$5:$B$407,"Main-d'œuvre") -> 200 | G16: =SUMIFS('Sous-détails'!$H$5:$H$407,'Sous-détails'!$A$5:$A$407,"Art. "&$A16,'Sous-détails'!$B$5:$B$407,"Matériel") -> 6 | H16: =E16+F16+G16 -> 1406 | I16: =$D16*E16 -> 65760 | J16: =$D16*F16 -> 10960 | K16: =$D16*G16 -> 328.8 | L16: =$D16*H16 -> 77048.8 | M16: NON
B17: Sous-total déboursé sec lot 1 | I17: =SUM(I12:I16) -> 65760 | J17: =SUM(J12:J16) -> 312360 | K17: =SUM(K12:K16) -> 125928.39 | L17: =SUM(L12:L16) -> 504048.39
A19: LOT 2 | B19: FONDATIONS
A20: 2.1 | B20: Béton de propreté dosé à 150 kg/m³, ép. 5 cm | C20: m³ | D20: =q_2_1 -> 2.74 | E20: =SUMIFS('Sous-détails'!$H$5:$H$407,'Sous-détails'!$A$5:$A$407,"Art. "&$A20,'Sous-détails'!$B$5:$B$407,"Matériaux") -> 44250 | F20: =SUMIFS('Sous-détails'!$H$5:$H$407,'Sous-détails'!$A$5:$A$407,"Art. "&$A20,'Sous-détails'!$B$5:$B$407,"Main-d'œuvre") -> 5000 | G20: =SUMIFS('Sous-détails'!$H$5:$H$407,'Sous-détails'!$A$5:$A$407,"Art. "&$A20,'Sous-détails'!$B$5:$B$407,"Matériel") -> 5150 | H20: =E20+F20+G20 -> 54400 | I20: =$D20*E20 -> 121245 | J20: =$D20*F20 -> 13700 | K20: =$D20*G20 -> 14111 | L20: =$D20*H20 -> 149056 | M20: NON
A21: 2.2 | B21: Béton armé dosé à 350 kg/m³ pour semelles isolées 0,80 x 0,80 x 0,30 | C21: m³ | D21: =q_2_2 -> 3.264 | E21: =SUMIFS('Sous-détails'!$H$5:$H$407,'Sous-détails'!$A$5:$A$407,"Art. "&$A21,'Sous-détails'!$B$5:$B$407,"Matériaux") -> 67450 | F21: =SUMIFS('Sous-détails'!$H$5:$H$407,'Sous-détails'!$A$5:$A$407,"Art. "&$A21,'Sous-détails'!$B$5:$B$407,"Main-d'œuvre") -> 8000 | G21: =SUMIFS('Sous-détails'!$H$5:$H$407,'Sous-détails'!$A$5:$A$407,"Art. "&$A21,'Sous-détails'!$B$5:$B$407,"Matériel") -> 8240 | H21: =E21+F21+G21 -> 83690 | I21: =$D21*E21 -> 220156.8 | J21: =$D21*F21 -> 26112 | K21: =$D21*G21 -> 26895.36 | L21: =$D21*H21 -> 273164.16 | M21: NON
A22: 2.3 | B22: Béton armé dosé à 350 kg/m³ pour fûts 40 x 40 sous platines des IPE (de -0,85 à ±0,00) | C22: m³ | D22: =q_2_3 -> 2.312 | E22: =SUMIFS('Sous-détails'!$H$5:$H$407,'Sous-détails'!$A$5:$A$407,"Art. "&$A22,'Sous-détails'!$B$5:$B$407,"Matériaux") -> 67450 | F22: =SUMIFS('Sous-détails'!$H$5:$H$407,'Sous-détails'!$A$5:$A$407,"Art. "&$A22,'Sous-détails'!$B$5:$B$407,"Main-d'œuvre") -> 10000 | G22: =SUMIFS('Sous-détails'!$H$5:$H$407,'Sous-détails'!$A$5:$A$407,"Art. "&$A22,'Sous-détails'!$B$5:$B$407,"Matériel") -> 10300 | H22: =E22+F22+G22 -> 87750 | I22: =$D22*E22 -> 155944.4 | J22: =$D22*F22 -> 23120 | K22: =$D22*G22 -> 23813.6 | L22: =$D22*H22 -> 202878 | M22: NON
A23: 2.4 | B23: Fourniture et scellement des tiges d'ancrage M20 des IPE (gabarit de pose, 4 par pilier) | C23: u | D23: =q_2_4 -> 68 | E23: =SUMIFS('Sous-détails'!$H$5:$H$407,'Sous-détails'!$A$5:$A$407,"Art. "&$A23,'Sous-détails'!$B$5:$B$407,"Matériaux") -> 6180 | F23: =SUMIFS('Sous-détails'!$H$5:$H$407,'Sous-détails'!$A$5:$A$407,"Art. "&$A23,'Sous-détails'!$B$5:$B$407,"Main-d'œuvre") -> 1250 | G23: =SUMIFS('Sous-détails'!$H$5:$H$407,'Sous-détails'!$A$5:$A$407,"Art. "&$A23,'Sous-détails'!$B$5:$B$407,"Matériel") -> 37.5 | H23: =E23+F23+G23 -> 7467.5 | I23: =$D23*E23 -> 420240 | J23: =$D23*F23 -> 85000 | K23: =$D23*G23 -> 2550 | L23: =$D23*H23 -> 507790 | M23: NON
A24: 2.5 | B24: Béton armé dosé à 350 kg/m³ pour semelle filante 0,40 x 0,15 | C24: m³ | D24: =q_2_5 -> 3.984 | E24: =SUMIFS('Sous-détails'!$H$5:$H$407,'Sous-détails'!$A$5:$A$407,"Art. "&$A24,'Sous-détails'!$B$5:$B$407,"Matériaux") -> 67450 | F24: =SUMIFS('Sous-détails'!$H$5:$H$407,'Sous-détails'!$A$5:$A$407,"Art. "&$A24,'Sous-détails'!$B$5:$B$407,"Main-d'œuvre") -> 6666.6667 | G24: =SUMIFS('Sous-détails'!$H$5:$H$407,'Sous-détails'!$A$5:$A$407,"Art. "&$A24,'Sous-détails'!$B$5:$B$407,"Matériel") -> 6866.6667 | H24: =E24+F24+G24 -> 80983.333 | I24: =$D24*E24 -> 268720.8 | J24: =$D24*F24 -> 26560 | K24: =$D24*G24 -> 27356.8 | L24: =$D24*H24 -> 322637.6 | M24: NON
A25: 2.6 | B25: Maçonnerie d'agglos 15 pleins en fondation h = 1,00 m, mortier dosé à 300 kg/m³ | C25: m² | D25: =q_2_6 -> 73.03 | E25: =SUMIFS('Sous-détails'!$H$5:$H$407,'Sous-détails'!$A$5:$A$407,"Art. "&$A25,'Sous-détails'!$B$5:$B$407,"Matériaux") -> 7802.5 | F25: =SUMIFS('Sous-détails'!$H$5:$H$407,'Sous-détails'!$A$5:$A$407,"Art. "&$A25,'Sous-détails'!$B$5:$B$407,"Main-d'œuvre") -> 1500 | G25: =SUMIFS('Sous-détails'!$H$5:$H$407,'Sous-détails'!$A$5:$A$407,"Art. "&$A25,'Sous-détails'!$B$5:$B$407,"Matériel") -> 45 | H25: =E25+F25+G25 -> 9347.5 | I25: =$D25*E25 -> 569816.57 | J25: =$D25*F25 -> 109545 | K25: =$D25*G25 -> 3286.35 | L25: =$D25*H25 -> 682647.93 | M25: NON
A26: 2.7 | B26: Béton armé dosé à 350 kg/m³ pour chaînage bas 15 x 20 | C26: m³ | D26: =q_2_7 -> 2.1909 | E26: =SUMIFS('Sous-détails'!$H$5:$H$407,'Sous-détails'!$A$5:$A$407,"Art. "&$A26,'Sous-détails'!$B$5:$B$407,"Matériaux") -> 67450 | F26: =SUMIFS('Sous-détails'!$H$5:$H$407,'Sous-détails'!$A$5:$A$407,"Art. "&$A26,'Sous-détails'!$B$5:$B$407,"Main-d'œuvre") -> 6666.6667 | G26: =SUMIFS('Sous-détails'!$H$5:$H$407,'Sous-détails'!$A$5:$A$407,"Art. "&$A26,'Sous-détails'!$B$5:$B$407,"Matériel") -> 6866.6667 | H26: =E26+F26+G26 -> 80983.333 | I26: =$D26*E26 -> 147776.21 | J26: =$D26*F26 -> 14606 | K26: =$D26*G26 -> 15044.18 | L26: =$D26*H26 -> 177426.39 | M26: NON
A27: 2.8 | B27: Chape d'arase étanche (mortier dosé à 400 kg/m³ + hydrofuge) ép. 3 cm | C27: m² | D27: =q_2_8 -> 10.9545 | E27: =SUMIFS('Sous-détails'!$H$5:$H$407,'Sous-détails'!$A$5:$A$407,"Art. "&$A27,'Sous-détails'!$B$5:$B$407,"Matériaux") -> 2824 | F27: =SUMIFS('Sous-détails'!$H$5:$H$407,'Sous-détails'!$A$5:$A$407,"Art. "&$A27,'Sous-détails'!$B$5:$B$407,"Main-d'œuvre") -> 1000 | G27: =SUMIFS('Sous-détails'!$H$5:$H$407,'Sous-détails'!$A$5:$A$407,"Art. "&$A27,'Sous-détails'!$B$5:$B$407,"Matériel") -> 30 | H27: =E27+F27+G27 -> 3854 | I27: =$D27*E27 -> 30935.508 | J27: =$D27*F27 -> 10954.5 | K27: =$D27*G27 -> 328.635 | L27: =$D27*H27 -> 42218.643 | M27: NON
A28: 2.9 | B28: Coffrage en bois ordinaire (semelles isolées, fûts, chaînage bas) | C28: m² | D28: =q_2_9 -> 68.652 | E28: =SUMIFS('Sous-détails'!$H$5:$H$407,'Sous-détails'!$A$5:$A$407,"Art. "&$A28,'Sous-détails'!$B$5:$B$407,"Matériaux") -> 2125 | F28: =SUMIFS('Sous-détails'!$H$5:$H$407,'Sous-détails'!$A$5:$A$407,"Art. "&$A28,'Sous-détails'!$B$5:$B$407,"Main-d'œuvre") -> 1875 | G28: =SUMIFS('Sous-détails'!$H$5:$H$407,'Sous-détails'!$A$5:$A$407,"Art. "&$A28,'Sous-détails'!$B$5:$B$407,"Matériel") -> 56.25 | H28: =E28+F28+G28 -> 4056.25 | I28: =$D28*E28 -> 145885.5 | J28: =$D28*F28 -> 128722.5 | K28: =$D28*G28 -> 3861.675 | L28: =$D28*H28 -> 278469.67 | M28: NON
A29: 2.10 | B29: Armatures HA12 FeE500 - semelles isolées 80x80 et fûts | C29: kg | D29: =q_2_10 -> 288.48456 | E29: =SUMIFS('Sous-détails'!$H$5:$H$407,'Sous-détails'!$A$5:$A$407,"Art. "&$A29,'Sous-détails'!$B$5:$B$407,"Matériaux") -> 822.5 | F29: =SUMIFS('Sous-détails'!$H$5:$H$407,'Sous-détails'!$A$5:$A$407,"Art. "&$A29,'Sous-détails'!$B$5:$B$407,"Main-d'œuvre") -> 100 | G29: =SUMIFS('Sous-détails'!$H$5:$H$407,'Sous-détails'!$A$5:$A$407,"Art. "&$A29,'Sous-détails'!$B$5:$B$407,"Matériel") -> 3 | H29: =E29+F29+G29 -> 925.5 | I29: =$D29*E29 -> 237278.55 | J29: =$D29*F29 -> 28848.456 | K29: =$D29*G29 -> 865.45368 | L29: =$D29*H29 -> 266992.46 | M29: NON
A30: 2.11 | B30: Armatures HA10 FeE500 - fondations | C30: kg | D30: =q_2_11 -> 445.7208 | E30: =SUMIFS('Sous-détails'!$H$5:$H$407,'Sous-détails'!$A$5:$A$407,"Art. "&$A30,'Sous-détails'!$B$5:$B$407,"Matériaux") -> 832.5 | F30: =SUMIFS('Sous-détails'!$H$5:$H$407,'Sous-détails'!$A$5:$A$407,"Art. "&$A30,'Sous-détails'!$B$5:$B$407,"Main-d'œuvre") -> 100 | G30: =SUMIFS('Sous-détails'!$H$5:$H$407,'Sous-détails'!$A$5:$A$407,"Art. "&$A30,'Sous-détails'!$B$5:$B$407,"Matériel") -> 3 | H30: =E30+F30+G30 -> 935.5 | I30: =$D30*E30 -> 371062.57 | J30: =$D30*F30 -> 44572.08 | K30: =$D30*G30 -> 1337.1624 | L30: =$D30*H30 -> 416971.81 | M30: NON
A31: 2.12 | B31: Armatures HA6 FeE500 - fondations | C31: kg | D31: =q_2_12 -> 136.73646 | E31: =SUMIFS('Sous-détails'!$H$5:$H$407,'Sous-détails'!$A$5:$A$407,"Art. "&$A31,'Sous-détails'!$B$5:$B$407,"Matériaux") -> 887.5 | F31: =SUMIFS('Sous-détails'!$H$5:$H$407,'Sous-détails'!$A$5:$A$407,"Art. "&$A31,'Sous-détails'!$B$5:$B$407,"Main-d'œuvre") -> 100 | G31: =SUMIFS('Sous-détails'!$H$5:$H$407,'Sous-détails'!$A$5:$A$407,"Art. "&$A31,'Sous-détails'!$B$5:$B$407,"Matériel") -> 3 | H31: =E31+F31+G31 -> 990.5 | I31: =$D31*E31 -> 121353.61 | J31: =$D31*F31 -> 13673.646 | K31: =$D31*G31 -> 410.20938 | L31: =$D31*H31 -> 135437.46 | M31: NON
B32: Sous-total déboursé sec lot 2 | I32: =SUM(I20:I31) -> 2810415.5 | J32: =SUM(J20:J31) -> 525414.18 | K32: =SUM(K20:K31) -> 119860.43 | L32: =SUM(L20:L31) -> 3455690.1
A34: LOT 3 | B34: ÉLÉVATION (MAÇONNERIE ET BÉTON ARMÉ)
A35: 3.1 | B35: Maçonnerie d'agglos 15 pleins en élévation, mortier dosé à 300 kg/m³ (y compris pignons) | C35: m² | D35: =q_3_1 -> 373.89259 | E35: =SUMIFS('Sous-détails'!$H$5:$H$407,'Sous-détails'!$A$5:$A$407,"Art. "&$A35,'Sous-détails'!$B$5:$B$407,"Matériaux") -> 7802.5 | F35: =SUMIFS('Sous-détails'!$H$5:$H$407,'Sous-détails'!$A$5:$A$407,"Art. "&$A35,'Sous-détails'!$B$5:$B$407,"Main-d'œuvre") -> 1500 | G35: =SUMIFS('Sous-détails'!$H$5:$H$407,'Sous-détails'!$A$5:$A$407,"Art. "&$A35,'Sous-détails'!$B$5:$B$407,"Matériel") -> 45 | H35: =E35+F35+G35 -> 9347.5 | I35: =$D35*E35 -> 2917296.9 | J35: =$D35*F35 -> 560838.88 | K35: =$D35*G35 -> 16825.166 | L35: =$D35*H35 -> 3494961 | M35: NON
A36: 3.2 | B36: Béton armé dosé à 350 kg/m³ pour poteaux 15 x 15 (2 par pilier IPE), de -0,85 à +6,00 | C36: m³ | D36: =q_3_2 -> 5.28525 | E36: =SUMIFS('Sous-détails'!$H$5:$H$407,'Sous-détails'!$A$5:$A$407,"Art. "&$A36,'Sous-détails'!$B$5:$B$407,"Matériaux") -> 67450 | F36: =SUMIFS('Sous-détails'!$H$5:$H$407,'Sous-détails'!$A$5:$A$407,"Art. "&$A36,'Sous-détails'!$B$5:$B$407,"Main-d'œuvre") -> 10000 | G36: =SUMIFS('Sous-détails'!$H$5:$H$407,'Sous-détails'!$A$5:$A$407,"Art. "&$A36,'Sous-détails'!$B$5:$B$407,"Matériel") -> 10300 | H36: =E36+F36+G36 -> 87750 | I36: =$D36*E36 -> 356490.11 | J36: =$D36*F36 -> 52852.5 | K36: =$D36*G36 -> 54438.075 | L36: =$D36*H36 -> 463780.69 | M36: NON
A37: 3.3 | B37: Béton armé dosé à 350 kg/m³ pour chaînage intermédiaire 15 x 20 à +3,00 | C37: m³ | D37: =q_3_3 -> 2.0109 | E37: =SUMIFS('Sous-détails'!$H$5:$H$407,'Sous-détails'!$A$5:$A$407,"Art. "&$A37,'Sous-détails'!$B$5:$B$407,"Matériaux") -> 67450 | F37: =SUMIFS('Sous-détails'!$H$5:$H$407,'Sous-détails'!$A$5:$A$407,"Art. "&$A37,'Sous-détails'!$B$5:$B$407,"Main-d'œuvre") -> 8000 | G37: =SUMIFS('Sous-détails'!$H$5:$H$407,'Sous-détails'!$A$5:$A$407,"Art. "&$A37,'Sous-détails'!$B$5:$B$407,"Matériel") -> 8240 | H37: =E37+F37+G37 -> 83690 | I37: =$D37*E37 -> 135635.2 | J37: =$D37*F37 -> 16087.2 | K37: =$D37*G37 -> 16569.816 | L37: =$D37*H37 -> 168292.22 | M37: NON
A38: 3.4 | B38: Béton armé dosé à 350 kg/m³ pour chaînage haut 15 x 20 | C38: m³ | D38: =q_3_4 -> 2.1909 | E38: =SUMIFS('Sous-détails'!$H$5:$H$407,'Sous-détails'!$A$5:$A$407,"Art. "&$A38,'Sous-détails'!$B$5:$B$407,"Matériaux") -> 67450 | F38: =SUMIFS('Sous-détails'!$H$5:$H$407,'Sous-détails'!$A$5:$A$407,"Art. "&$A38,'Sous-détails'!$B$5:$B$407,"Main-d'œuvre") -> 8000 | G38: =SUMIFS('Sous-détails'!$H$5:$H$407,'Sous-détails'!$A$5:$A$407,"Art. "&$A38,'Sous-détails'!$B$5:$B$407,"Matériel") -> 8240 | H38: =E38+F38+G38 -> 83690 | I38: =$D38*E38 -> 147776.21 | J38: =$D38*F38 -> 17527.2 | K38: =$D38*G38 -> 18053.016 | L38: =$D38*H38 -> 183356.42 | M38: NON
A39: 3.5 | B39: Béton armé dosé à 350 kg/m³ pour linteau de l'entrée 15 x 40 | C39: m³ | D39: =q_3_5 -> 0.36 | E39: =SUMIFS('Sous-détails'!$H$5:$H$407,'Sous-détails'!$A$5:$A$407,"Art. "&$A39,'Sous-détails'!$B$5:$B$407,"Matériaux") -> 67450 | F39: =SUMIFS('Sous-détails'!$H$5:$H$407,'Sous-détails'!$A$5:$A$407,"Art. "&$A39,'Sous-détails'!$B$5:$B$407,"Main-d'œuvre") -> 10000 | G39: =SUMIFS('Sous-détails'!$H$5:$H$407,'Sous-détails'!$A$5:$A$407,"Art. "&$A39,'Sous-détails'!$B$5:$B$407,"Matériel") -> 10300 | H39: =E39+F39+G39 -> 87750 | I39: =$D39*E39 -> 24282 | J39: =$D39*F39 -> 3600 | K39: =$D39*G39 -> 3708 | L39: =$D39*H39 -> 31590 | M39: NON
A40: 3.6 | B40: Béton armé dosé à 350 kg/m³ pour chaînages rampants 15 x 15 (pente 20 %) | C40: m³ | D40: =q_3_6 -> 0.44091176 | E40: =SUMIFS('Sous-détails'!$H$5:$H$407,'Sous-détails'!$A$5:$A$407,"Art. "&$A40,'Sous-détails'!$B$5:$B$407,"Matériaux") -> 67450 | F40: =SUMIFS('Sous-détails'!$H$5:$H$407,'Sous-détails'!$A$5:$A$407,"Art. "&$A40,'Sous-détails'!$B$5:$B$407,"Main-d'œuvre") -> 10000 | G40: =SUMIFS('Sous-détails'!$H$5:$H$407,'Sous-détails'!$A$5:$A$407,"Art. "&$A40,'Sous-détails'!$B$5:$B$407,"Matériel") -> 10300 | H40: =E40+F40+G40 -> 87750 | I40: =$D40*E40 -> 29739.498 | J40: =$D40*F40 -> 4409.1176 | K40: =$D40*G40 -> 4541.3911 | L40: =$D40*H40 -> 38690.007 | M40: NON
A41: 3.7 | B41: Coffrage en bois ordinaire (poteaux, chaînages, linteau, rampants) | C41: m² | D41: =q_3_7 -> 173.30782 | E41: =SUMIFS('Sous-détails'!$H$5:$H$407,'Sous-détails'!$A$5:$A$407,"Art. "&$A41,'Sous-détails'!$B$5:$B$407,"Matériaux") -> 2125 | F41: =SUMIFS('Sous-détails'!$H$5:$H$407,'Sous-détails'!$A$5:$A$407,"Art. "&$A41,'Sous-détails'!$B$5:$B$407,"Main-d'œuvre") -> 1875 | G41: =SUMIFS('Sous-détails'!$H$5:$H$407,'Sous-détails'!$A$5:$A$407,"Art. "&$A41,'Sous-détails'!$B$5:$B$407,"Matériel") -> 56.25 | H41: =E41+F41+G41 -> 4056.25 | I41: =$D41*E41 -> 368279.12 | J41: =$D41*F41 -> 324952.17 | K41: =$D41*G41 -> 9748.5651 | L41: =$D41*H41 -> 702979.86 | M41: NON
A42: 3.8 | B42: Armatures HA10 FeE500 - élévation | C42: kg | D42: =q_3_8 -> 1202.7612 | E42: =SUMIFS('Sous-détails'!$H$5:$H$407,'Sous-détails'!$A$5:$A$407,"Art. "&$A42,'Sous-détails'!$B$5:$B$407,"Matériaux") -> 832.5 | F42: =SUMIFS('Sous-détails'!$H$5:$H$407,'Sous-détails'!$A$5:$A$407,"Art. "&$A42,'Sous-détails'!$B$5:$B$407,"Main-d'œuvre") -> 100 | G42: =SUMIFS('Sous-détails'!$H$5:$H$407,'Sous-détails'!$A$5:$A$407,"Art. "&$A42,'Sous-détails'!$B$5:$B$407,"Matériel") -> 3 | H42: =E42+F42+G42 -> 935.5 | I42: =$D42*E42 -> 1001298.7 | J42: =$D42*F42 -> 120276.12 | K42: =$D42*G42 -> 3608.2836 | L42: =$D42*H42 -> 1125183.1 | M42: NON
A43: 3.9 | B43: Armatures HA6 FeE500 - élévation | C43: kg | D43: =q_3_9 -> 316.54751 | E43: =SUMIFS('Sous-détails'!$H$5:$H$407,'Sous-détails'!$A$5:$A$407,"Art. "&$A43,'Sous-détails'!$B$5:$B$407,"Matériaux") -> 887.5 | F43: =SUMIFS('Sous-détails'!$H$5:$H$407,'Sous-détails'!$A$5:$A$407,"Art. "&$A43,'Sous-détails'!$B$5:$B$407,"Main-d'œuvre") -> 100 | G43: =SUMIFS('Sous-détails'!$H$5:$H$407,'Sous-détails'!$A$5:$A$407,"Art. "&$A43,'Sous-détails'!$B$5:$B$407,"Matériel") -> 3 | H43: =E43+F43+G43 -> 990.5 | I43: =$D43*E43 -> 280935.92 | J43: =$D43*F43 -> 31654.751 | K43: =$D43*G43 -> 949.64254 | L43: =$D43*H43 -> 313540.31 | M43: NON
B44: Sous-total déboursé sec lot 3 | I44: =SUM(I35:I43) -> 5261733.7 | J44: =SUM(J35:J43) -> 1132197.9 | K44: =SUM(K35:K43) -> 128441.96 | L44: =SUM(L35:L43) -> 6522373.6
A46: LOT 4 | B46: STRUCTURE MÉTALLIQUE : PILIERS IPE 220 ET CONTREVENTEMENTS
A47: 4.1 | B47: Piliers en IPE 220 (S235) de ±0,00 à +6,00, fournis, fabriqués, peints et posés | C47: kg | D47: =q_4_1 -> 2698.6 | E47: =SUMIFS('Sous-détails'!$H$5:$H$407,'Sous-détails'!$A$5:$A$407,"Art. "&$A47,'Sous-détails'!$B$5:$B$407,"Matériaux") -> 1097.5 | F47: =SUMIFS('Sous-détails'!$H$5:$H$407,'Sous-détails'!$A$5:$A$407,"Art. "&$A47,'Sous-détails'!$B$5:$B$407,"Main-d'œuvre") -> 250 | G47: =SUMIFS('Sous-détails'!$H$5:$H$407,'Sous-détails'!$A$5:$A$407,"Art. "&$A47,'Sous-détails'!$B$5:$B$407,"Matériel") -> 107.5 | H47: =E47+F47+G47 -> 1455 | I47: =$D47*E47 -> 2961713.5 | J47: =$D47*F47 -> 674650 | K47: =$D47*G47 -> 290099.5 | L47: =$D47*H47 -> 3926463 | M47: NON
A48: 4.2 | B48: Platines de pied et de tête 15 mm + raidisseurs, soudées | C48: kg | D48: =q_4_2 -> 255 | E48: =SUMIFS('Sous-détails'!$H$5:$H$407,'Sous-détails'!$A$5:$A$407,"Art. "&$A48,'Sous-détails'!$B$5:$B$407,"Matériaux") -> 1045 | F48: =SUMIFS('Sous-détails'!$H$5:$H$407,'Sous-détails'!$A$5:$A$407,"Art. "&$A48,'Sous-détails'!$B$5:$B$407,"Main-d'œuvre") -> 625 | G48: =SUMIFS('Sous-détails'!$H$5:$H$407,'Sous-détails'!$A$5:$A$407,"Art. "&$A48,'Sous-détails'!$B$5:$B$407,"Matériel") -> 118.75 | H48: =E48+F48+G48 -> 1788.75 | I48: =$D48*E48 -> 266475 | J48: =$D48*F48 -> 159375 | K48: =$D48*G48 -> 30281.25 | L48: =$D48*H48 -> 456131.25 | M48: NON
A49: 4.3 | B49: Calage et scellement des platines au mortier sans retrait | C49: u | D49: =q_4_3 -> 17 | E49: =SUMIFS('Sous-détails'!$H$5:$H$407,'Sous-détails'!$A$5:$A$407,"Art. "&$A49,'Sous-détails'!$B$5:$B$407,"Matériaux") -> 4500 | F49: =SUMIFS('Sous-détails'!$H$5:$H$407,'Sous-détails'!$A$5:$A$407,"Art. "&$A49,'Sous-détails'!$B$5:$B$407,"Main-d'œuvre") -> 1875 | G49: =SUMIFS('Sous-détails'!$H$5:$H$407,'Sous-détails'!$A$5:$A$407,"Art. "&$A49,'Sous-détails'!$B$5:$B$407,"Matériel") -> 56.25 | H49: =E49+F49+G49 -> 6431.25 | I49: =$D49*E49 -> 76500 | J49: =$D49*F49 -> 31875 | K49: =$D49*G49 -> 956.25 | L49: =$D49*H49 -> 109331.25 | M49: NON
A50: 4.4 | B50: Contreventements en cornières 50x50x5 : palées verticales en long pan et poutre au vent en toiture (goussets et boulons compris) | C50: kg | D50: =q_4_4 -> 496.03687 | E50: =SUMIFS('Sous-détails'!$H$5:$H$407,'Sous-détails'!$A$5:$A$407,"Art. "&$A50,'Sous-détails'!$B$5:$B$407,"Matériaux") -> 1045 | F50: =SUMIFS('Sous-détails'!$H$5:$H$407,'Sous-détails'!$A$5:$A$407,"Art. "&$A50,'Sous-détails'!$B$5:$B$407,"Main-d'œuvre") -> 416.66667 | G50: =SUMIFS('Sous-détails'!$H$5:$H$407,'Sous-détails'!$A$5:$A$407,"Art. "&$A50,'Sous-détails'!$B$5:$B$407,"Matériel") -> 112.5 | H50: =E50+F50+G50 -> 1574.1667 | I50: =$D50*E50 -> 518358.53 | J50: =$D50*F50 -> 206682.03 | K50: =$D50*G50 -> 55804.148 | L50: =$D50*H50 -> 780844.71 | M50: NON
B51: Sous-total déboursé sec lot 4 | I51: =SUM(I47:I50) -> 3823047 | J51: =SUM(J47:J50) -> 1072582 | K51: =SUM(K47:K50) -> 377141.15 | L51: =SUM(L47:L50) -> 5272770.2
A53: LOT 5 | B53: FORME EN LATÉRITE ET DALLAGE BA 20 cm
A54: 5.1 | B54: Décaissement / purge intérieure du sol de mauvaise portance (ép. = épaisseur de latérite) et évacuation | C54: m³ | D54: =q_5_1 -> 117.609 | E54: =SUMIFS('Sous-détails'!$H$5:$H$407,'Sous-détails'!$A$5:$A$407,"Art. "&$A54,'Sous-détails'!$B$5:$B$407,"Matériaux") -> 0 | F54: =SUMIFS('Sous-détails'!$H$5:$H$407,'Sous-détails'!$A$5:$A$407,"Art. "&$A54,'Sous-détails'!$B$5:$B$407,"Main-d'œuvre") -> 2500 | G54: =SUMIFS('Sous-détails'!$H$5:$H$407,'Sous-détails'!$A$5:$A$407,"Art. "&$A54,'Sous-détails'!$B$5:$B$407,"Matériel") -> 3200 | H54: =E54+F54+G54 -> 5700 | I54: =$D54*E54 -> 0 | J54: =$D54*F54 -> 294022.5 | K54: =$D54*G54 -> 376348.8 | L54: =$D54*H54 -> 670371.3 | M54: NON
A55: 5.2 | B55: Rechargement en latérite d'emprunt à l'intérieur, mis en œuvre par couches de 20 cm, arrosé et compacté à 95 % OPM | C55: m³ | D55: =q_5_2 -> 117.609 | E55: =SUMIFS('Sous-détails'!$H$5:$H$407,'Sous-détails'!$A$5:$A$407,"Art. "&$A55,'Sous-détails'!$B$5:$B$407,"Matériaux") -> 7900 | F55: =SUMIFS('Sous-détails'!$H$5:$H$407,'Sous-détails'!$A$5:$A$407,"Art. "&$A55,'Sous-détails'!$B$5:$B$407,"Main-d'œuvre") -> 833.33333 | G55: =SUMIFS('Sous-détails'!$H$5:$H$407,'Sous-détails'!$A$5:$A$407,"Art. "&$A55,'Sous-détails'!$B$5:$B$407,"Matériel") -> 1525 | H55: =E55+F55+G55 -> 10258.333 | I55: =$D55*E55 -> 929111.1 | J55: =$D55*F55 -> 98007.5 | K55: =$D55*G55 -> 179353.73 | L55: =$D55*H55 -> 1206472.3 | M55: NON
A56: 5.3 | B56: Essais de contrôle (Proctor modifié, densités in situ par couche, éprouvettes béton) | C56: ft | D56: =q_5_3 -> 1 | E56: =SUMIFS('Sous-détails'!$H$5:$H$407,'Sous-détails'!$A$5:$A$407,"Art. "&$A56,'Sous-détails'!$B$5:$B$407,"Matériaux") -> 250000 | F56: =SUMIFS('Sous-détails'!$H$5:$H$407,'Sous-détails'!$A$5:$A$407,"Art. "&$A56,'Sous-détails'!$B$5:$B$407,"Main-d'œuvre") -> 0 | G56: =SUMIFS('Sous-détails'!$H$5:$H$407,'Sous-détails'!$A$5:$A$407,"Art. "&$A56,'Sous-détails'!$B$5:$B$407,"Matériel") -> 0 | H56: =E56+F56+G56 -> 250000 | I56: =$D56*E56 -> 250000 | J56: =$D56*F56 -> 0 | K56: =$D56*G56 -> 0 | L56: =$D56*H56 -> 250000 | M56: NON
A57: 5.4 | B57: Traitement anti-termites sous dallage | C57: m² | D57: =q_5_4 -> 294.0225 | E57: =SUMIFS('Sous-détails'!$H$5:$H$407,'Sous-détails'!$A$5:$A$407,"Art. "&$A57,'Sous-détails'!$B$5:$B$407,"Matériaux") -> 1200 | F57: =SUMIFS('Sous-détails'!$H$5:$H$407,'Sous-détails'!$A$5:$A$407,"Art. "&$A57,'Sous-détails'!$B$5:$B$407,"Main-d'œuvre") -> 100 | G57: =SUMIFS('Sous-détails'!$H$5:$H$407,'Sous-détails'!$A$5:$A$407,"Art. "&$A57,'Sous-détails'!$B$5:$B$407,"Matériel") -> 3 | H57: =E57+F57+G57 -> 1303 | I57: =$D57*E57 -> 352827 | J57: =$D57*F57 -> 29402.25 | K57: =$D57*G57 -> 882.0675 | L57: =$D57*H57 -> 383111.32 | M57: NON
A58: 5.5 | B58: Film polyane 150 µ sous dallage (recouvrements 10 %) | C58: m² | D58: =q_5_5 -> 323.42475 | E58: =SUMIFS('Sous-détails'!$H$5:$H$407,'Sous-détails'!$A$5:$A$407,"Art. "&$A58,'Sous-détails'!$B$5:$B$407,"Matériaux") -> 400 | F58: =SUMIFS('Sous-détails'!$H$5:$H$407,'Sous-détails'!$A$5:$A$407,"Art. "&$A58,'Sous-détails'!$B$5:$B$407,"Main-d'œuvre") -> 33.333333 | G58: =SUMIFS('Sous-détails'!$H$5:$H$407,'Sous-détails'!$A$5:$A$407,"Art. "&$A58,'Sous-détails'!$B$5:$B$407,"Matériel") -> 1 | H58: =E58+F58+G58 -> 434.33333 | I58: =$D58*E58 -> 129369.9 | J58: =$D58*F58 -> 10780.825 | K58: =$D58*G58 -> 323.42475 | L58: =$D58*H58 -> 140474.15 | M58: NON
A59: 5.6 | B59: Armatures HA10 FeE500 - dallage double nappe e = 20 cm + chaises | C59: kg | D59: =q_5_6 -> 4343.0005 | E59: =SUMIFS('Sous-détails'!$H$5:$H$407,'Sous-détails'!$A$5:$A$407,"Art. "&$A59,'Sous-détails'!$B$5:$B$407,"Matériaux") -> 832.5 | F59: =SUMIFS('Sous-détails'!$H$5:$H$407,'Sous-détails'!$A$5:$A$407,"Art. "&$A59,'Sous-détails'!$B$5:$B$407,"Main-d'œuvre") -> 75 | G59: =SUMIFS('Sous-détails'!$H$5:$H$407,'Sous-détails'!$A$5:$A$407,"Art. "&$A59,'Sous-détails'!$B$5:$B$407,"Matériel") -> 2.25 | H59: =E59+F59+G59 -> 909.75 | I59: =$D59*E59 -> 3615547.9 | J59: =$D59*F59 -> 325725.04 | K59: =$D59*G59 -> 9771.7511 | L59: =$D59*H59 -> 3951044.7 | M59: NON
A60: 5.7 | B60: Béton armé dosé à 350 kg/m³ pour dallage ép. 20 cm, vibré et surfacé | C60: m³ | D60: =q_5_7 -> 58.8045 | E60: =SUMIFS('Sous-détails'!$H$5:$H$407,'Sous-détails'!$A$5:$A$407,"Art. "&$A60,'Sous-détails'!$B$5:$B$407,"Matériaux") -> 67450 | F60: =SUMIFS('Sous-détails'!$H$5:$H$407,'Sous-détails'!$A$5:$A$407,"Art. "&$A60,'Sous-détails'!$B$5:$B$407,"Main-d'œuvre") -> 5000 | G60: =SUMIFS('Sous-détails'!$H$5:$H$407,'Sous-détails'!$A$5:$A$407,"Art. "&$A60,'Sous-détails'!$B$5:$B$407,"Matériel") -> 5150 | H60: =E60+F60+G60 -> 77600 | I60: =$D60*E60 -> 3966363.5 | J60: =$D60*F60 -> 294022.5 | K60: =$D60*G60 -> 302843.17 | L60: =$D60*H60 -> 4563229.2 | M60: NON
A61: 5.8 | B61: Joints de retrait sciés (maille 5 m) et joint périphérique | C61: ml | D61: =q_5_8 -> 158.5 | E61: =SUMIFS('Sous-détails'!$H$5:$H$407,'Sous-détails'!$A$5:$A$407,"Art. "&$A61,'Sous-détails'!$B$5:$B$407,"Matériaux") -> 800 | F61: =SUMIFS('Sous-détails'!$H$5:$H$407,'Sous-détails'!$A$5:$A$407,"Art. "&$A61,'Sous-détails'!$B$5:$B$407,"Main-d'œuvre") -> 166.66667 | G61: =SUMIFS('Sous-détails'!$H$5:$H$407,'Sous-détails'!$A$5:$A$407,"Art. "&$A61,'Sous-détails'!$B$5:$B$407,"Matériel") -> 255 | H61: =E61+F61+G61 -> 1221.6667 | I61: =$D61*E61 -> 126800 | J61: =$D61*F61 -> 26416.667 | K61: =$D61*G61 -> 40417.5 | L61: =$D61*H61 -> 193634.17 | M61: NON
B62: Sous-total déboursé sec lot 5 | I62: =SUM(I54:I61) -> 9370019.4 | J62: =SUM(J54:J61) -> 1078377.3 | K62: =SUM(K54:K61) -> 909940.44 | L62: =SUM(L54:L61) -> 11358337
A64: LOT 6 | B64: ENDUITS (OPTION)
A65: 6.1 | B65: Enduit au mortier dosé à 300 kg/m³ ép. 2 cm, intérieur et extérieur | C65: m² | D65: =q_6_1 -> 926.24 | E65: =SUMIFS('Sous-détails'!$H$5:$H$407,'Sous-détails'!$A$5:$A$407,"Art. "&$A65,'Sous-détails'!$B$5:$B$407,"Matériaux") -> 1064 | F65: =SUMIFS('Sous-détails'!$H$5:$H$407,'Sous-détails'!$A$5:$A$407,"Art. "&$A65,'Sous-détails'!$B$5:$B$407,"Main-d'œuvre") -> 1250 | G65: =SUMIFS('Sous-détails'!$H$5:$H$407,'Sous-détails'!$A$5:$A$407,"Art. "&$A65,'Sous-détails'!$B$5:$B$407,"Matériel") -> 187.5 | H65: =E65+F65+G65 -> 2501.5 | I65: =$D65*E65 -> 985519.36 | J65: =$D65*F65 -> 1157800 | K65: =$D65*G65 -> 173670 | L65: =$D65*H65 -> 2316989.4 | M65: OUI
B66: Sous-total déboursé sec lot 6 | I66: =SUM(I65:I65) -> 985519.36 | J66: =SUM(J65:J65) -> 1157800 | K66: =SUM(K65:K65) -> 173670 | L66: =SUM(L65:L65) -> 2316989.4
A68: LOT 7 | B68: CHARPENTE DE TOITURE ET COUVERTURE - PENTE 20 % (OPTION)
A69: 7.1 | B69: Fermes / traverses de toiture sur têtes d'IPE 220 (hors pannes) - ratio à confirmer par note de calcul | C69: kg | D69: =q_7_1 -> 2728 | E69: =SUMIFS('Sous-détails'!$H$5:$H$407,'Sous-détails'!$A$5:$A$407,"Art. "&$A69,'Sous-détails'!$B$5:$B$407,"Matériaux") -> 997.5 | F69: =SUMIFS('Sous-détails'!$H$5:$H$407,'Sous-détails'!$A$5:$A$407,"Art. "&$A69,'Sous-détails'!$B$5:$B$407,"Main-d'œuvre") -> 333.33333 | G69: =SUMIFS('Sous-détails'!$H$5:$H$407,'Sous-détails'!$A$5:$A$407,"Art. "&$A69,'Sous-détails'!$B$5:$B$407,"Matériel") -> 110 | H69: =E69+F69+G69 -> 1440.8333 | I69: =$D69*E69 -> 2721180 | J69: =$D69*F69 -> 909333.33 | K69: =$D69*G69 -> 300080 | L69: =$D69*H69 -> 3930593.3 | M69: OUI
A70: 7.2 | B70: Pannes en Z 120 x 2 mm, entraxe ≤ 1,20 m, y compris échantignoles et boulonnerie | C70: kg | D70: =q_7_2 -> 1523.34 | E70: =SUMIFS('Sous-détails'!$H$5:$H$407,'Sous-détails'!$A$5:$A$407,"Art. "&$A70,'Sous-détails'!$B$5:$B$407,"Matériaux") -> 1000 | F70: =SUMIFS('Sous-détails'!$H$5:$H$407,'Sous-détails'!$A$5:$A$407,"Art. "&$A70,'Sous-détails'!$B$5:$B$407,"Main-d'œuvre") -> 166.66667 | G70: =SUMIFS('Sous-détails'!$H$5:$H$407,'Sous-détails'!$A$5:$A$407,"Art. "&$A70,'Sous-détails'!$B$5:$B$407,"Matériel") -> 55 | H70: =E70+F70+G70 -> 1221.6667 | I70: =$D70*E70 -> 1523340 | J70: =$D70*F70 -> 253890 | K70: =$D70*G70 -> 83783.7 | L70: =$D70*H70 -> 1861013.7 | M70: OUI
A71: 7.3 | B71: Couverture en tôles bacs 5 ondulations sur pannes Z, pente 20 %, débords 0,50 m | C71: m² | D71: =q_7_3 -> 347.13921 | E71: =SUMIFS('Sous-détails'!$H$5:$H$407,'Sous-détails'!$A$5:$A$407,"Art. "&$A71,'Sous-détails'!$B$5:$B$407,"Matériaux") -> 4950 | F71: =SUMIFS('Sous-détails'!$H$5:$H$407,'Sous-détails'!$A$5:$A$407,"Art. "&$A71,'Sous-détails'!$B$5:$B$407,"Main-d'œuvre") -> 500 | G71: =SUMIFS('Sous-détails'!$H$5:$H$407,'Sous-détails'!$A$5:$A$407,"Art. "&$A71,'Sous-détails'!$B$5:$B$407,"Matériel") -> 15 | H71: =E71+F71+G71 -> 5465 | I71: =$D71*E71 -> 1718339.1 | J71: =$D71*F71 -> 173569.6 | K71: =$D71*G71 -> 5207.0881 | L71: =$D71*H71 -> 1897115.8 | M71: OUI
A72: 7.4 | B72: Faîtière | C72: ml | D72: =q_7_4 -> 31 | E72: =SUMIFS('Sous-détails'!$H$5:$H$407,'Sous-détails'!$A$5:$A$407,"Art. "&$A72,'Sous-détails'!$B$5:$B$407,"Matériaux") -> 3675 | F72: =SUMIFS('Sous-détails'!$H$5:$H$407,'Sous-détails'!$A$5:$A$407,"Art. "&$A72,'Sous-détails'!$B$5:$B$407,"Main-d'œuvre") -> 500 | G72: =SUMIFS('Sous-détails'!$H$5:$H$407,'Sous-détails'!$A$5:$A$407,"Art. "&$A72,'Sous-détails'!$B$5:$B$407,"Matériel") -> 15 | H72: =E72+F72+G72 -> 4190 | I72: =$D72*E72 -> 113925 | J72: =$D72*F72 -> 15500 | K72: =$D72*G72 -> 465 | L72: =$D72*H72 -> 129890 | M72: OUI
B73: Sous-total déboursé sec lot 7 | I73: =SUM(I69:I72) -> 6076784.1 | J73: =SUM(J69:J72) -> 1352292.9 | K73: =SUM(K69:K72) -> 389535.79 | L73: =SUM(L69:L72) -> 7818612.8
A75: LOT 8 | B75: MENUISERIE MÉTALLIQUE (OPTION)
A76: 8.1 | B76: Portail métallique coulissant 6,00 x 4,50 m | C76: u | D76: =q_8_1 -> 1 | E76: =SUMIFS('Sous-détails'!$H$5:$H$407,'Sous-détails'!$A$5:$A$407,"Art. "&$A76,'Sous-détails'!$B$5:$B$407,"Matériaux") -> 1600000 | F76: =SUMIFS('Sous-détails'!$H$5:$H$407,'Sous-détails'!$A$5:$A$407,"Art. "&$A76,'Sous-détails'!$B$5:$B$407,"Main-d'œuvre") -> 300000 | G76: =SUMIFS('Sous-détails'!$H$5:$H$407,'Sous-détails'!$A$5:$A$407,"Art. "&$A76,'Sous-détails'!$B$5:$B$407,"Matériel") -> 159000 | H76: =E76+F76+G76 -> 2059000 | I76: =$D76*E76 -> 1600000 | J76: =$D76*F76 -> 300000 | K76: =$D76*G76 -> 159000 | L76: =$D76*H76 -> 2059000 | M76: OUI
B77: Sous-total déboursé sec lot 8 | I77: =SUM(I76:I76) -> 1600000 | J77: =SUM(J76:J76) -> 300000 | K77: =SUM(K76:K76) -> 159000 | L77: =SUM(L76:L76) -> 2059000
B79: DÉBOURSÉ SEC GROS ŒUVRE ET STRUCTURE (lots 0 à 5) | I79: =SUMIFS(I5:I78,$M$5:$M$78,"NON") -> 21670976 | J79: =SUMIFS(J5:J78,$M$5:$M$78,"NON") -> 4310598.1 | K79: =SUMIFS(K5:K78,$M$5:$M$78,"NON") -> 1797002.4 | L79: =SUMIFS(L5:L78,$M$5:$M$78,"NON") -> 27778576
B80: DÉBOURSÉ SEC OPTIONS (lots 6 à 8) | I80: =SUMIFS(I5:I78,$M$5:$M$78,"OUI") -> 8662303.4 | J80: =SUMIFS(J5:J78,$M$5:$M$78,"OUI") -> 2810092.9 | K80: =SUMIFS(K5:K78,$M$5:$M$78,"OUI") -> 722205.79 | L80: =SUMIFS(L5:L78,$M$5:$M$78,"OUI") -> 12194602
B81: DÉBOURSÉ SEC TOTAL | I81: =I79+I80 -> 30333279 | J81: =J79+J80 -> 7120691 | K81: =K79+K80 -> 2519208.2 | L81: =L79+L80 -> 39973178
B82: Répartition gros œuvre (%) | I82: =IF($L$79=0,0,I79/$L$79) -> 0.7801327 | J82: =IF($L$79=0,0,J79/$L$79) -> 0.15517707 | K82: =IF($L$79=0,0,K79/$L$79) -> 0.064690226 | L82: =IF($L$79=0,0,L79/$L$79) -> 1

Sheet DQE
A1: ASSEYA SILVER CONSTRUCTION - Construction métallique et bâtiment - Bouaké - Tél : 07 08 39 02 66 / 05 05 10 76 82 - Email : asseyasilver@gmail.com
A2: Devis quantitatif et estimatif - Bâtiment industriel 30,00 x 10,00 m - 04/10/2026 - établi par Moulo Jean Claude, Technicien Génie Civil BTP - BAEL 91 mod. 99 / EC2
A4: N° | B4: Désignation | C4: U | D4: Quantité | E4: P.U. HT (FCFA) | F4: Montant HT (FCFA) | G4: Option
A5: LOT 0 | B5: INSTALLATION DE CHANTIER ET TRAVAUX PRÉPARATOIRES
A6: 0.1 | B6: Installation et repli de chantier (magasin, clôture provisoire, eau, électricité, panneau) | C6: ft | D6: =q_0_1 -> 1 | E6: =ROUND('Déboursé sec'!H6*p_K/5,0)*5 -> 660190 | F6: =D6*E6 -> 660190 | G6: NON
A7: 0.2 | B7: Débroussaillage et décapage de la terre végétale ép. 10 cm | C7: m² | D7: =q_0_2 -> 476 | E7: =ROUND('Déboursé sec'!H7*p_K/5,0)*5 -> 115 | F7: =D7*E7 -> 54740 | G7: NON
A8: 0.3 | B8: Implantation du bâtiment (chaises, cordeaux, axes et niveaux) | C8: ft | D8: =q_0_3 -> 1 | E8: =ROUND('Déboursé sec'!H8*p_K/5,0)*5 -> 159470 | F8: =D8*E8 -> 159470 | G8: NON
B9: Sous-total lot 0 | F9: =SUM(F6:F8) -> 874400
A11: LOT 1 | B11: TERRASSEMENTS
A12: 1.1 | B12: Fouilles en rigole 0,60 x 1,20 m en terrain latéritique | C12: m³ | D12: =q_1_1 -> 57.6 | E12: =ROUND('Déboursé sec'!H12*p_K/5,0)*5 -> 4505 | F12: =D12*E12 -> 259488 | G12: NON
A13: 1.2 | B13: Fouilles en puits 1,00 x 1,00 x 1,20 m pour semelles isolées 80x80 (complément) | C13: m³ | D13: =q_1_2 -> 8.16 | E13: =ROUND('Déboursé sec'!H13*p_K/5,0)*5 -> 4505 | F13: =D13*E13 -> 36760.8 | G13: NON
A14: 1.3 | B14: Remblai des fouilles avec les terres extraites, compacté par couches de 20 cm | C14: m³ | D14: =q_1_3 -> 41.85525 | E14: =ROUND('Déboursé sec'!H14*p_K/5,0)*5 -> 3000 | F14: =D14*E14 -> 125565.75 | G14: NON
A15: 1.4 | B15: Évacuation des terres excédentaires des fouilles | C15: m³ | D15: =q_1_4 -> 29.880938 | E15: =ROUND('Déboursé sec'!H15*p_K/5,0)*5 -> 4635 | F15: =D15*E15 -> 138498.15 | G15: NON
A16: 1.5 | B16: Traitement anti-termites des fonds de fouilles | C16: m² | D16: =q_1_5 -> 54.8 | E16: =ROUND('Déboursé sec'!H16*p_K/5,0)*5 -> 1845 | F16: =D16*E16 -> 101106 | G16: NON
B17: Sous-total lot 1 | F17: =SUM(F12:F16) -> 661418.7
A19: LOT 2 | B19: FONDATIONS
A20: 2.1 | B20: Béton de propreté dosé à 150 kg/m³, ép. 5 cm | C20: m³ | D20: =q_2_1 -> 2.74 | E20: =ROUND('Déboursé sec'!H20*p_K/5,0)*5 -> 71400 | F20: =D20*E20 -> 195636 | G20: NON
A21: 2.2 | B21: Béton armé dosé à 350 kg/m³ pour semelles isolées 0,80 x 0,80 x 0,30 | C21: m³ | D21: =q_2_2 -> 3.264 | E21: =ROUND('Déboursé sec'!H21*p_K/5,0)*5 -> 109845 | F21: =D21*E21 -> 358534.08 | G21: NON
A22: 2.3 | B22: Béton armé dosé à 350 kg/m³ pour fûts 40 x 40 sous platines des IPE (de -0,85 à ±0,00) | C22: m³ | D22: =q_2_3 -> 2.312 | E22: =ROUND('Déboursé sec'!H22*p_K/5,0)*5 -> 115170 | F22: =D22*E22 -> 266273.04 | G22: NON
A23: 2.4 | B23: Fourniture et scellement des tiges d'ancrage M20 des IPE (gabarit de pose, 4 par pilier) | C23: u | D23: =q_2_4 -> 68 | E23: =ROUND('Déboursé sec'!H23*p_K/5,0)*5 -> 9800 | F23: =D23*E23 -> 666400 | G23: NON
A24: 2.5 | B24: Béton armé dosé à 350 kg/m³ pour semelle filante 0,40 x 0,15 | C24: m³ | D24: =q_2_5 -> 3.984 | E24: =ROUND('Déboursé sec'!H24*p_K/5,0)*5 -> 106290 | F24: =D24*E24 -> 423459.36 | G24: NON
A25: 2.6 | B25: Maçonnerie d'agglos 15 pleins en fondation h = 1,00 m, mortier dosé à 300 kg/m³ | C25: m² | D25: =q_2_6 -> 73.03 | E25: =ROUND('Déboursé sec'!H25*p_K/5,0)*5 -> 12270 | F25: =D25*E25 -> 896078.1 | G25: NON
A26: 2.7 | B26: Béton armé dosé à 350 kg/m³ pour chaînage bas 15 x 20 | C26: m³ | D26: =q_2_7 -> 2.1909 | E26: =ROUND('Déboursé sec'!H26*p_K/5,0)*5 -> 106290 | F26: =D26*E26 -> 232870.76 | G26: NON
A27: 2.8 | B27: Chape d'arase étanche (mortier dosé à 400 kg/m³ + hydrofuge) ép. 3 cm | C27: m² | D27: =q_2_8 -> 10.9545 | E27: =ROUND('Déboursé sec'!H27*p_K/5,0)*5 -> 5060 | F27: =D27*E27 -> 55429.77 | G27: NON
A28: 2.9 | B28: Coffrage en bois ordinaire (semelles isolées, fûts, chaînage bas) | C28: m² | D28: =q_2_9 -> 68.652 | E28: =ROUND('Déboursé sec'!H28*p_K/5,0)*5 -> 5325 | F28: =D28*E28 -> 365571.9 | G28: NON
A29: 2.10 | B29: Armatures HA12 FeE500 - semelles isolées 80x80 et fûts | C29: kg | D29: =q_2_10 -> 288.48456 | E29: =ROUND('Déboursé sec'!H29*p_K/5,0)*5 -> 1215 | F29: =D29*E29 -> 350508.74 | G29: NON
A30: 2.11 | B30: Armatures HA10 FeE500 - fondations | C30: kg | D30: =q_2_11 -> 445.7208 | E30: =ROUND('Déboursé sec'!H30*p_K/5,0)*5 -> 1230 | F30: =D30*E30 -> 548236.58 | G30: NON
A31: 2.12 | B31: Armatures HA6 FeE500 - fondations | C31: kg | D31: =q_2_12 -> 136.73646 | E31: =ROUND('Déboursé sec'!H31*p_K/5,0)*5 -> 1300 | F31: =D31*E31 -> 177757.4 | G31: NON
B32: Sous-total lot 2 | F32: =SUM(F20:F31) -> 4536755.7
A34: LOT 3 | B34: ÉLÉVATION (MAÇONNERIE ET BÉTON ARMÉ)
A35: 3.1 | B35: Maçonnerie d'agglos 15 pleins en élévation, mortier dosé à 300 kg/m³ (y compris pignons) | C35: m² | D35: =q_3_1 -> 373.89259 | E35: =ROUND('Déboursé sec'!H35*p_K/5,0)*5 -> 12270 | F35: =D35*E35 -> 4587662.1 | G35: NON
A36: 3.2 | B36: Béton armé dosé à 350 kg/m³ pour poteaux 15 x 15 (2 par pilier IPE), de -0,85 à +6,00 | C36: m³ | D36: =q_3_2 -> 5.28525 | E36: =ROUND('Déboursé sec'!H36*p_K/5,0)*5 -> 115170 | F36: =D36*E36 -> 608702.24 | G36: NON
A37: 3.3 | B37: Béton armé dosé à 350 kg/m³ pour chaînage intermédiaire 15 x 20 à +3,00 | C37: m³ | D37: =q_3_3 -> 2.0109 | E37: =ROUND('Déboursé sec'!H37*p_K/5,0)*5 -> 109845 | F37: =D37*E37 -> 220887.31 | G37: NON
A38: 3.4 | B38: Béton armé dosé à 350 kg/m³ pour chaînage haut 15 x 20 | C38: m³ | D38: =q_3_4 -> 2.1909 | E38: =ROUND('Déboursé sec'!H38*p_K/5,0)*5 -> 109845 | F38: =D38*E38 -> 240659.41 | G38: NON
A39: 3.5 | B39: Béton armé dosé à 350 kg/m³ pour linteau de l'entrée 15 x 40 | C39: m³ | D39: =q_3_5 -> 0.36 | E39: =ROUND('Déboursé sec'!H39*p_K/5,0)*5 -> 115170 | F39: =D39*E39 -> 41461.2 | G39: NON
A40: 3.6 | B40: Béton armé dosé à 350 kg/m³ pour chaînages rampants 15 x 15 (pente 20 %) | C40: m³ | D40: =q_3_6 -> 0.44091176 | E40: =ROUND('Déboursé sec'!H40*p_K/5,0)*5 -> 115170 | F40: =D40*E40 -> 50779.807 | G40: NON
A41: 3.7 | B41: Coffrage en bois ordinaire (poteaux, chaînages, linteau, rampants) | C41: m² | D41: =q_3_7 -> 173.30782 | E41: =ROUND('Déboursé sec'!H41*p_K/5,0)*5 -> 5325 | F41: =D41*E41 -> 922864.16 | G41: NON
A42: 3.8 | B42: Armatures HA10 FeE500 - élévation | C42: kg | D42: =q_3_8 -> 1202.7612 | E42: =ROUND('Déboursé sec'!H42*p_K/5,0)*5 -> 1230 | F42: =D42*E42 -> 1479396.3 | G42: NON
A43: 3.9 | B43: Armatures HA6 FeE500 - élévation | C43: kg | D43: =q_3_9 -> 316.54751 | E43: =ROUND('Déboursé sec'!H43*p_K/5,0)*5 -> 1300 | F43: =D43*E43 -> 411511.77 | G43: NON
B44: Sous-total lot 3 | F44: =SUM(F35:F43) -> 8563924.3
A46: LOT 4 | B46: STRUCTURE MÉTALLIQUE : PILIERS IPE 220 ET CONTREVENTEMENTS
A47: 4.1 | B47: Piliers en IPE 220 (S235) de ±0,00 à +6,00, fournis, fabriqués, peints et posés | C47: kg | D47: =q_4_1 -> 2698.6 | E47: =ROUND('Déboursé sec'!H47*p_K/5,0)*5 -> 1910 | F47: =D47*E47 -> 5154326 | G47: NON
A48: 4.2 | B48: Platines de pied et de tête 15 mm + raidisseurs, soudées | C48: kg | D48: =q_4_2 -> 255 | E48: =ROUND('Déboursé sec'!H48*p_K/5,0)*5 -> 2350 | F48: =D48*E48 -> 599250 | G48: NON
A49: 4.3 | B49: Calage et scellement des platines au mortier sans retrait | C49: u | D49: =q_4_3 -> 17 | E49: =ROUND('Déboursé sec'!H49*p_K/5,0)*5 -> 8440 | F49: =D49*E49 -> 143480 | G49: NON
A50: 4.4 | B50: Contreventements en cornières 50x50x5 : palées verticales en long pan et poutre au vent en toiture (goussets et boulons compris) | C50: kg | D50: =q_4_4 -> 496.03687 | E50: =ROUND('Déboursé sec'!H50*p_K/5,0)*5 -> 2065 | F50: =D50*E50 -> 1024316.1 | G50: NON
B51: Sous-total lot 4 | F51: =SUM(F47:F50) -> 6921372.1
A53: LOT 5 | B53: FORME EN LATÉRITE ET DALLAGE BA 20 cm
A54: 5.1 | B54: Décaissement / purge intérieure du sol de mauvaise portance (ép. = épaisseur de latérite) et évacuation | C54: m³ | D54: =q_5_1 -> 117.609 | E54: =ROUND('Déboursé sec'!H54*p_K/5,0)*5 -> 7480 | F54: =D54*E54 -> 879715.32 | G54: NON
A55: 5.2 | B55: Rechargement en latérite d'emprunt à l'intérieur, mis en œuvre par couches de 20 cm, arrosé et compacté à 95 % OPM | C55: m³ | D55: =q_5_2 -> 117.609 | E55: =ROUND('Déboursé sec'!H55*p_K/5,0)*5 -> 13465 | F55: =D55*E55 -> 1583605.2 | G55: NON
A56: 5.3 | B56: Essais de contrôle (Proctor modifié, densités in situ par couche, éprouvettes béton) | C56: ft | D56: =q_5_3 -> 1 | E56: =ROUND('Déboursé sec'!H56*p_K/5,0)*5 -> 328125 | F56: =D56*E56 -> 328125 | G56: NON
A57: 5.4 | B57: Traitement anti-termites sous dallage | C57: m² | D57: =q_5_4 -> 294.0225 | E57: =ROUND('Déboursé sec'!H57*p_K/5,0)*5 -> 1710 | F57: =D57*E57 -> 502778.47 | G57: NON
A58: 5.5 | B58: Film polyane 150 µ sous dallage (recouvrements 10 %) | C58: m² | D58: =q_5_5 -> 323.42475 | E58: =ROUND('Déboursé sec'!H58*p_K/5,0)*5 -> 570 | F58: =D58*E58 -> 184352.11 | G58: NON
A59: 5.6 | B59: Armatures HA10 FeE500 - dallage double nappe e = 20 cm + chaises | C59: kg | D59: =q_5_6 -> 4343.0005 | E59: =ROUND('Déboursé sec'!H59*p_K/5,0)*5 -> 1195 | F59: =D59*E59 -> 5189885.6 | G59: NON
A60: 5.7 | B60: Béton armé dosé à 350 kg/m³ pour dallage ép. 20 cm, vibré et surfacé | C60: m³ | D60: =q_5_7 -> 58.8045 | E60: =ROUND('Déboursé sec'!H60*p_K/5,0)*5 -> 101850 | F60: =D60*E60 -> 5989238.3 | G60: NON
A61: 5.8 | B61: Joints de retrait sciés (maille 5 m) et joint périphérique | C61: ml | D61: =q_5_8 -> 158.5 | E61: =ROUND('Déboursé sec'!H61*p_K/5,0)*5 -> 1605 | F61: =D61*E61 -> 254392.5 | G61: NON
B62: Sous-total lot 5 | F62: =SUM(F54:F61) -> 14912092
A64: LOT 6 | B64: ENDUITS (OPTION)
A65: 6.1 | B65: Enduit au mortier dosé à 300 kg/m³ ép. 2 cm, intérieur et extérieur | C65: m² | D65: =q_6_1 -> 926.24 | E65: =ROUND('Déboursé sec'!H65*p_K/5,0)*5 -> 3285 | F65: =D65*E65 -> 3042698.4 | G65: OUI
B66: Sous-total lot 6 | F66: =SUM(F65:F65) -> 3042698.4
A68: LOT 7 | B68: CHARPENTE DE TOITURE ET COUVERTURE - PENTE 20 % (OPTION)
A69: 7.1 | B69: Fermes / traverses de toiture sur têtes d'IPE 220 (hors pannes) - ratio à confirmer par note de calcul | C69: kg | D69: =q_7_1 -> 2728 | E69: =ROUND('Déboursé sec'!H69*p_K/5,0)*5 -> 1890 | F69: =D69*E69 -> 5155920 | G69: OUI
A70: 7.2 | B70: Pannes en Z 120 x 2 mm, entraxe ≤ 1,20 m, y compris échantignoles et boulonnerie | C70: kg | D70: =q_7_2 -> 1523.34 | E70: =ROUND('Déboursé sec'!H70*p_K/5,0)*5 -> 1605 | F70: =D70*E70 -> 2444960.7 | G70: OUI
A71: 7.3 | B71: Couverture en tôles bacs 5 ondulations sur pannes Z, pente 20 %, débords 0,50 m | C71: m² | D71: =q_7_3 -> 347.13921 | E71: =ROUND('Déboursé sec'!H71*p_K/5,0)*5 -> 7175 | F71: =D71*E71 -> 2490723.8 | G71: OUI
A72: 7.4 | B72: Faîtière | C72: ml | D72: =q_7_4 -> 31 | E72: =ROUND('Déboursé sec'!H72*p_K/5,0)*5 -> 5500 | F72: =D72*E72 -> 170500 | G72: OUI
B73: Sous-total lot 7 | F73: =SUM(F69:F72) -> 10262105
A75: LOT 8 | B75: MENUISERIE MÉTALLIQUE (OPTION)
A76: 8.1 | B76: Portail métallique coulissant 6,00 x 4,50 m | C76: u | D76: =q_8_1 -> 1 | E76: =ROUND('Déboursé sec'!H76*p_K/5,0)*5 -> 2702440 | F76: =D76*E76 -> 2702440 | G76: OUI
B77: Sous-total lot 8 | F77: =SUM(F76:F76) -> 2702440
B79: RÉCAPITULATIF
A80: Lot 0 | B80: INSTALLATION DE CHANTIER ET TRAVAUX PRÉPARATOIRES | F80: =F9 -> 874400
A81: Lot 1 | B81: TERRASSEMENTS | F81: =F17 -> 661418.7
A82: Lot 2 | B82: FONDATIONS | F82: =F32 -> 4536755.7
A83: Lot 3 | B83: ÉLÉVATION (MAÇONNERIE ET BÉTON ARMÉ) | F83: =F44 -> 8563924.3
A84: Lot 4 | B84: STRUCTURE MÉTALLIQUE : PILIERS IPE 220 ET CONTREVENTEMENTS | F84: =F51 -> 6921372.1
A85: Lot 5 | B85: FORME EN LATÉRITE ET DALLAGE BA 20 cm | F85: =F62 -> 14912092
B86: TOTAL GROS ŒUVRE HT (A) | F86: =SUM(F80:F85) -> 36469963
B87: TVA | E87: =p_TVA -> 0.18 | F87: =F86*p_TVA -> 6564593.4
B88: TOTAL GROS ŒUVRE TTC | F88: =F86+F87 -> 43034557
A90: Lot 6 | B90: ENDUITS (OPTION) | F90: =F66 -> 3042698.4
A91: Lot 7 | B91: CHARPENTE DE TOITURE ET COUVERTURE - PENTE 20 % (OPTION) | F91: =F73 -> 10262105
A92: Lot 8 | B92: MENUISERIE MÉTALLIQUE (OPTION) | F92: =F77 -> 2702440
B93: TOTAL OPTIONS HT (B) | F93: =SUM(F90:F92) -> 16007243
B95: TOTAL GÉNÉRAL HT (A + B) | F95: =F86+F93 -> 52477206
B96: TVA | E96: =p_TVA -> 0.18 | F96: =F95*p_TVA -> 9445897.1
B97: TOTAL GÉNÉRAL TTC (A + B) | F97: =F95+F96 -> 61923103
B99: Ratio gros œuvre HT par m² d'emprise | F99: =F86/(p_L*p_B) -> 121566.54
B100: Marge brute gros œuvre (PV HT - déboursé sec) | F100: =F86-'Déboursé sec'!$L$79 -> 8691387.2
B102: Fait à Abidjan, le 04/10/2026 - Établi par Moulo Jean Claude, Technicien Génie Civil BTP
B103: Pour ASSEYA SILVER CONSTRUCTION : cachet et signature
B104: ASSEYA SILVER CONSTRUCTION - N° CC : 2245191 D - RCCM : CI-BKE-01-2022-B13-00153 - Bank of Africa - compte n° 004619070000 - Impôts : TEE - Bouaké 1

Sheet Matériaux et MO
A1: ASSEYA SILVER CONSTRUCTION - Construction métallique et bâtiment - Bouaké - Tél : 07 08 39 02 66 / 05 05 10 76 82 - Email : asseyasilver@gmail.com
A2: Besoins en matériaux, main-d'œuvre et matériel - Bâtiment industriel 30,00 x 10,00 m - 04/10/2026 - établi par Moulo Jean Claude, Technicien Génie Civil BTP - BAEL 91 mod. 99 / EC2
A4: Code | B4: Désignation | C4: U | D4: Qté gros œuvre | E4: Qté avec options | F4: P.U. (FCFA) | G4: Montant gros œuvre | H4: Montant avec options | I4: Observation
A5: MATÉRIAUX
A6: ciment | B6: Ciment CPJ 42,5 (sac 50 kg) | C6: sac | D6: =SUMIFS('Sous-détails'!$J$5:$J$407,'Sous-détails'!$D$5:$D$407,A6,'Sous-détails'!$K$5:$K$407,"NON") -> 643.791 | E6: =SUMIFS('Sous-détails'!$J$5:$J$407,'Sous-détails'!$D$5:$D$407,A6) -> 764.2022 | F6: =px_ciment -> 5800 | G6: =D6*F6 -> 3733987.8 | H6: =E6*F6 -> 4432372.8 | I6: =ROUND(D6*50/1000,1)&" t (gros œuvre)" -> 32.2 t (gros œuvre)
A7: sable | B7: Sable lavé | C7: m³ | D7: =SUMIFS('Sous-détails'!$J$5:$J$407,'Sous-détails'!$D$5:$D$407,A7,'Sous-détails'!$K$5:$K$407,"NON") -> 51.414552 | E7: =SUMIFS('Sous-détails'!$J$5:$J$407,'Sous-détails'!$D$5:$D$407,A7) -> 74.570552 | F7: =px_sable -> 12000 | G7: =D7*F7 -> 616974.63 | H7: =E7*F7 -> 894846.63
A8: gravier | B8: Gravier concassé 5/15 - 15/25 | C8: m³ | D8: =SUMIFS('Sous-détails'!$J$5:$J$407,'Sous-détails'!$D$5:$D$407,A8,'Sous-détails'!$K$5:$K$407,"NON") -> 71.045857 | E8: =SUMIFS('Sous-détails'!$J$5:$J$407,'Sous-détails'!$D$5:$D$407,A8) -> 71.045857 | F8: =px_gravier -> 25000 | G8: =D8*F8 -> 1776146.4 | H8: =E8*F8 -> 1776146.4
A9: eau | B9: Eau | C9: m³ | D9: =SUMIFS('Sous-détails'!$J$5:$J$407,'Sous-détails'!$D$5:$D$407,A9,'Sous-détails'!$K$5:$K$407,"NON") -> 32.946798 | E9: =SUMIFS('Sous-détails'!$J$5:$J$407,'Sous-détails'!$D$5:$D$407,A9) -> 42.209198 | F9: =px_eau -> 1000 | G9: =D9*F9 -> 32946.798 | H9: =E9*F9 -> 42209.198
A10: agglo | B10: Agglo 15 plein 40x20x15 rendu chantier | C10: u | D10: =SUMIFS('Sous-détails'!$J$5:$J$407,'Sous-détails'!$D$5:$D$407,A10,'Sous-détails'!$K$5:$K$407,"NON") -> 5865.859 | E10: =SUMIFS('Sous-détails'!$J$5:$J$407,'Sous-détails'!$D$5:$D$407,A10) -> 5865.859 | F10: =px_agglo -> 500 | G10: =D10*F10 -> 2932929.5 | H10: =E10*F10 -> 2932929.5 | I10: =ROUNDUP(D10,0)&" agglos (GO)" -> 5866 agglos (GO)
A11: ha6 | B11: Acier HA6 FeE500 (barre 12 m = 2,66 kg à 2 300) | C11: kg | D11: =SUMIFS('Sous-détails'!$J$5:$J$407,'Sous-détails'!$D$5:$D$407,A11,'Sous-détails'!$K$5:$K$407,"NON") -> 453.28397 | E11: =SUMIFS('Sous-détails'!$J$5:$J$407,'Sous-détails'!$D$5:$D$407,A11) -> 453.28397 | F11: =px_ha6 -> 865 | G11: =D11*F11 -> 392090.64 | H11: =E11*F11 -> 392090.64 | I11: =ROUNDUP(D11/(12*p_KG6),0)&" barres de 12 m (GO)" -> 171 barres de 12 m (GO)
A12: ha10 | B12: Acier HA10 FeE500 (barre 12 m = 7,40 kg à 6 000) | C12: kg | D12: =SUMIFS('Sous-détails'!$J$5:$J$407,'Sous-détails'!$D$5:$D$407,A12,'Sous-détails'!$K$5:$K$407,"NON") -> 5991.4825 | E12: =SUMIFS('Sous-détails'!$J$5:$J$407,'Sous-détails'!$D$5:$D$407,A12) -> 5991.4825 | F12: =px_ha10 -> 810 | G12: =D12*F12 -> 4853100.8 | H12: =E12*F12 -> 4853100.8 | I12: =ROUNDUP(D12/(12*p_KG10),0)&" barres de 12 m (GO)" -> 810 barres de 12 m (GO)
A13: ha12 | B13: Acier HA12 FeE500 (barre 12 m = 10,66 kg à 8 500) | C13: kg | D13: =SUMIFS('Sous-détails'!$J$5:$J$407,'Sous-détails'!$D$5:$D$407,A13,'Sous-détails'!$K$5:$K$407,"NON") -> 288.48456 | E13: =SUMIFS('Sous-détails'!$J$5:$J$407,'Sous-détails'!$D$5:$D$407,A13) -> 288.48456 | F13: =px_ha12 -> 800 | G13: =D13*F13 -> 230787.65 | H13: =E13*F13 -> 230787.65 | I13: =ROUNDUP(D13/(12*p_KG12),0)&" barres de 12 m (GO)" -> 28 barres de 12 m (GO)
A14: fil | B14: Fil recuit | C14: kg | D14: =SUMIFS('Sous-détails'!$J$5:$J$407,'Sous-détails'!$D$5:$D$407,A14,'Sous-détails'!$K$5:$K$407,"NON") -> 100.99877 | E14: =SUMIFS('Sous-détails'!$J$5:$J$407,'Sous-détails'!$D$5:$D$407,A14) -> 100.99877 | F14: =px_fil -> 1500 | G14: =D14*F14 -> 151498.15 | H14: =E14*F14 -> 151498.15
A15: bois | B15: Bois de coffrage (amorti 3 emplois) | C15: m² | D15: =SUMIFS('Sous-détails'!$J$5:$J$407,'Sous-détails'!$D$5:$D$407,A15,'Sous-détails'!$K$5:$K$407,"NON") -> 248.75982 | E15: =SUMIFS('Sous-détails'!$J$5:$J$407,'Sous-détails'!$D$5:$D$407,A15) -> 248.75982 | F15: =px_bois -> 1800 | G15: =D15*F15 -> 447767.68 | H15: =E15*F15 -> 447767.68
A16: pointes | B16: Pointes | C16: kg | D16: =SUMIFS('Sous-détails'!$J$5:$J$407,'Sous-détails'!$D$5:$D$407,A16,'Sous-détails'!$K$5:$K$407,"NON") -> 36.293974 | E16: =SUMIFS('Sous-détails'!$J$5:$J$407,'Sous-détails'!$D$5:$D$407,A16) -> 36.293974 | F16: =px_pointes -> 1500 | G16: =D16*F16 -> 54440.96 | H16: =E16*F16 -> 54440.96
A17: huile | B17: Huile de décoffrage | C17: L | D17: =SUMIFS('Sous-détails'!$J$5:$J$407,'Sous-détails'!$D$5:$D$407,A17,'Sous-détails'!$K$5:$K$407,"NON") -> 24.195982 | E17: =SUMIFS('Sous-détails'!$J$5:$J$407,'Sous-détails'!$D$5:$D$407,A17) -> 24.195982 | F17: =px_huile -> 1000 | G17: =D17*F17 -> 24195.982 | H17: =E17*F17 -> 24195.982
A18: hydro | B18: Hydrofuge de masse | C18: L | D18: =SUMIFS('Sous-détails'!$J$5:$J$407,'Sous-détails'!$D$5:$D$407,A18,'Sous-détails'!$K$5:$K$407,"NON") -> 5.47725 | E18: =SUMIFS('Sous-détails'!$J$5:$J$407,'Sous-détails'!$D$5:$D$407,A18) -> 5.47725 | F18: =px_hydro -> 2000 | G18: =D18*F18 -> 10954.5 | H18: =E18*F18 -> 10954.5
A19: termite | B19: Produit anti-termites (dilué) | C19: m² | D19: =SUMIFS('Sous-détails'!$J$5:$J$407,'Sous-détails'!$D$5:$D$407,A19,'Sous-détails'!$K$5:$K$407,"NON") -> 348.8225 | E19: =SUMIFS('Sous-détails'!$J$5:$J$407,'Sous-détails'!$D$5:$D$407,A19) -> 348.8225 | F19: =px_termite -> 1200 | G19: =D19*F19 -> 418587 | H19: =E19*F19 -> 418587
A20: laterite | B20: Latérite d'emprunt rendue chantier | C20: m³ | D20: =SUMIFS('Sous-détails'!$J$5:$J$407,'Sous-détails'!$D$5:$D$407,A20,'Sous-détails'!$K$5:$K$407,"NON") -> 152.8917 | E20: =SUMIFS('Sous-détails'!$J$5:$J$407,'Sous-détails'!$D$5:$D$407,A20) -> 152.8917 | F20: =px_laterite -> 6000 | G20: =D20*F20 -> 917350.2 | H20: =E20*F20 -> 917350.2
A21: polyane | B21: Film polyane 150 µ | C21: m² | D21: =SUMIFS('Sous-détails'!$J$5:$J$407,'Sous-détails'!$D$5:$D$407,A21,'Sous-détails'!$K$5:$K$407,"NON") -> 323.42475 | E21: =SUMIFS('Sous-détails'!$J$5:$J$407,'Sous-détails'!$D$5:$D$407,A21) -> 323.42475 | F21: =px_polyane -> 400 | G21: =D21*F21 -> 129369.9 | H21: =E21*F21 -> 129369.9
A22: joint | B22: Fond de joint + mastic / joint périphérique | C22: ml | D22: =SUMIFS('Sous-détails'!$J$5:$J$407,'Sous-détails'!$D$5:$D$407,A22,'Sous-détails'!$K$5:$K$407,"NON") -> 158.5 | E22: =SUMIFS('Sous-détails'!$J$5:$J$407,'Sous-détails'!$D$5:$D$407,A22) -> 158.5 | F22: =px_joint -> 800 | G22: =D22*F22 -> 126800 | H22: =E22*F22 -> 126800
A23: ipe | B23: Profilé IPE 220 (S235) | C23: kg | D23: =SUMIFS('Sous-détails'!$J$5:$J$407,'Sous-détails'!$D$5:$D$407,A23,'Sous-détails'!$K$5:$K$407,"NON") -> 2833.53 | E23: =SUMIFS('Sous-détails'!$J$5:$J$407,'Sous-détails'!$D$5:$D$407,A23) -> 2833.53 | F23: =px_ipe -> 950 | G23: =D23*F23 -> 2691853.5 | H23: =E23*F23 -> 2691853.5
A24: corniere | B24: Cornière 50x50x5 (S235) | C24: kg | D24: =SUMIFS('Sous-détails'!$J$5:$J$407,'Sous-détails'!$D$5:$D$407,A24,'Sous-détails'!$K$5:$K$407,"NON") -> 520.83872 | E24: =SUMIFS('Sous-détails'!$J$5:$J$407,'Sous-détails'!$D$5:$D$407,A24) -> 520.83872 | F24: =px_corniere -> 900 | G24: =D24*F24 -> 468754.84 | H24: =E24*F24 -> 468754.84
A25: tole | B25: Tôle pour platines et goussets ép. 15 mm | C25: kg | D25: =SUMIFS('Sous-détails'!$J$5:$J$407,'Sous-détails'!$D$5:$D$407,A25,'Sous-détails'!$K$5:$K$407,"NON") -> 267.75 | E25: =SUMIFS('Sous-détails'!$J$5:$J$407,'Sous-détails'!$D$5:$D$407,A25) -> 267.75 | F25: =px_tole -> 900 | G25: =D25*F25 -> 240975 | H25: =E25*F25 -> 240975
A26: tige | B26: Tige d'ancrage M20 L = 600 coudée + 2 écrous + rondelle | C26: u | D26: =SUMIFS('Sous-détails'!$J$5:$J$407,'Sous-détails'!$D$5:$D$407,A26,'Sous-détails'!$K$5:$K$407,"NON") -> 68 | E26: =SUMIFS('Sous-détails'!$J$5:$J$407,'Sous-détails'!$D$5:$D$407,A26) -> 68 | F26: =px_tige -> 6000 | G26: =D26*F26 -> 408000 | H26: =E26*F26 -> 408000
A27: grout | B27: Mortier de calage sans retrait (sac 25 kg) | C27: sac | D27: =SUMIFS('Sous-détails'!$J$5:$J$407,'Sous-détails'!$D$5:$D$407,A27,'Sous-détails'!$K$5:$K$407,"NON") -> 8.5 | E27: =SUMIFS('Sous-détails'!$J$5:$J$407,'Sous-détails'!$D$5:$D$407,A27) -> 8.5 | F27: =px_grout -> 9000 | G27: =D27*F27 -> 76500 | H27: =E27*F27 -> 76500
A28: peint | B28: Peinture antirouille + finition (2 couches) | C28: kg | D28: =SUMIFS('Sous-détails'!$J$5:$J$407,'Sous-détails'!$D$5:$D$407,A28,'Sous-détails'!$K$5:$K$407,"NON") -> 3449.6369 | E28: =SUMIFS('Sous-détails'!$J$5:$J$407,'Sous-détails'!$D$5:$D$407,A28) -> 3449.6369 | F28: =px_peint -> 100 | G28: =D28*F28 -> 344963.69 | H28: =E28*F28 -> 344963.69
A29: acier_ch | B29: Profilés charpente de toiture + peinture | C29: kg | D29: =SUMIFS('Sous-détails'!$J$5:$J$407,'Sous-détails'!$D$5:$D$407,A29,'Sous-détails'!$K$5:$K$407,"NON") -> 0 | E29: =SUMIFS('Sous-détails'!$J$5:$J$407,'Sous-détails'!$D$5:$D$407,A29) -> 2864.4 | F29: =px_acier_ch -> 950 | G29: =D29*F29 -> 0 | H29: =E29*F29 -> 2721180
A30: bac | B30: Tôle bac 5 ondes (alu 6/10 ou acier prélaqué) + fixations | C30: m² | D30: =SUMIFS('Sous-détails'!$J$5:$J$407,'Sous-détails'!$D$5:$D$407,A30,'Sous-détails'!$K$5:$K$407,"NON") -> 0 | E30: =SUMIFS('Sous-détails'!$J$5:$J$407,'Sous-détails'!$D$5:$D$407,A30) -> 381.85313 | F30: =px_bac -> 4500 | G30: =D30*F30 -> 0 | H30: =E30*F30 -> 1718339.1
A31: zpanne | B31: Panne Z 120 x 2 galvanisée + échantignoles + boulons | C31: kg | D31: =SUMIFS('Sous-détails'!$J$5:$J$407,'Sous-détails'!$D$5:$D$407,A31,'Sous-détails'!$K$5:$K$407,"NON") -> 0 | E31: =SUMIFS('Sous-détails'!$J$5:$J$407,'Sous-détails'!$D$5:$D$407,A31) -> 1523.34 | F31: =px_zpanne -> 1000 | G31: =D31*F31 -> 0 | H31: =E31*F31 -> 1523340
A32: faitiere | B32: Faîtière aluminium | C32: ml | D32: =SUMIFS('Sous-détails'!$J$5:$J$407,'Sous-détails'!$D$5:$D$407,A32,'Sous-détails'!$K$5:$K$407,"NON") -> 0 | E32: =SUMIFS('Sous-détails'!$J$5:$J$407,'Sous-détails'!$D$5:$D$407,A32) -> 32.55 | F32: =px_faitiere -> 3500 | G32: =D32*F32 -> 0 | H32: =E32*F32 -> 113925
A33: ff_install | B33: Magasin, clôture provisoire, panneau de chantier | C33: ft | D33: =SUMIFS('Sous-détails'!$J$5:$J$407,'Sous-détails'!$D$5:$D$407,A33,'Sous-détails'!$K$5:$K$407,"NON") -> 1 | E33: =SUMIFS('Sous-détails'!$J$5:$J$407,'Sous-détails'!$D$5:$D$407,A33) -> 1 | F33: =px_ff_install -> 300000 | G33: =D33*F33 -> 300000 | H33: =E33*F33 -> 300000
A34: ff_implant | B34: Bois de chaises, cordeau, peinture | C34: ft | D34: =SUMIFS('Sous-détails'!$J$5:$J$407,'Sous-détails'!$D$5:$D$407,A34,'Sous-détails'!$K$5:$K$407,"NON") -> 1 | E34: =SUMIFS('Sous-détails'!$J$5:$J$407,'Sous-détails'!$D$5:$D$407,A34) -> 1 | F34: =px_ff_implant -> 40000 | G34: =D34*F34 -> 40000 | H34: =E34*F34 -> 40000
A35: ff_essais | B35: Essais labo (Proctor, densités in situ, écrasement béton) | C35: ft | D35: =SUMIFS('Sous-détails'!$J$5:$J$407,'Sous-détails'!$D$5:$D$407,A35,'Sous-détails'!$K$5:$K$407,"NON") -> 1 | E35: =SUMIFS('Sous-détails'!$J$5:$J$407,'Sous-détails'!$D$5:$D$407,A35) -> 1 | F35: =px_ff_essais -> 250000 | G35: =D35*F35 -> 250000 | H35: =E35*F35 -> 250000
A36: ff_portail | B36: Portail : tubes, tôle 15/10, rail, roulettes, peinture | C36: ft | D36: =SUMIFS('Sous-détails'!$J$5:$J$407,'Sous-détails'!$D$5:$D$407,A36,'Sous-détails'!$K$5:$K$407,"NON") -> 0 | E36: =SUMIFS('Sous-détails'!$J$5:$J$407,'Sous-détails'!$D$5:$D$407,A36) -> 1 | F36: =px_ff_portail -> 1600000 | G36: =D36*F36 -> 0 | H36: =E36*F36 -> 1600000
A37: MAIN-D'ŒUVRE
A38: mo_macon | B38: Maçon | C38: h.j | D38: =SUMIFS('Sous-détails'!$J$5:$J$407,'Sous-détails'!$D$5:$D$407,A38,'Sous-détails'!$K$5:$K$407,"NON") -> 62.504138 | E38: =SUMIFS('Sous-détails'!$J$5:$J$407,'Sous-détails'!$D$5:$D$407,A38) -> 139.69081 | F38: =px_mo_macon -> 10000 | G38: =D38*F38 -> 625041.38 | H38: =E38*F38 -> 1396908.1
A39: mo_ferr | B39: Ferrailleur | C39: h.j | D39: =SUMIFS('Sous-détails'!$J$5:$J$407,'Sous-détails'!$D$5:$D$407,A39,'Sous-détails'!$K$5:$K$407,"NON") -> 37.650006 | E39: =SUMIFS('Sous-détails'!$J$5:$J$407,'Sous-détails'!$D$5:$D$407,A39) -> 37.650006 | F39: =px_mo_ferr -> 10000 | G39: =D39*F39 -> 376500.06 | H39: =E39*F39 -> 376500.06
A40: mo_coff | B40: Coffreur | C40: h.j | D40: =SUMIFS('Sous-détails'!$J$5:$J$407,'Sous-détails'!$D$5:$D$407,A40,'Sous-détails'!$K$5:$K$407,"NON") -> 30.244978 | E40: =SUMIFS('Sous-détails'!$J$5:$J$407,'Sous-détails'!$D$5:$D$407,A40) -> 30.244978 | F40: =px_mo_coff -> 10000 | G40: =D40*F40 -> 302449.78 | H40: =E40*F40 -> 302449.78
A41: mo_soud | B41: Soudeur / couvreur | C41: h.j | D41: =SUMIFS('Sous-détails'!$J$5:$J$407,'Sous-détails'!$D$5:$D$407,A41,'Sous-détails'!$K$5:$K$407,"NON") -> 45.878281 | E41: =SUMIFS('Sous-détails'!$J$5:$J$407,'Sous-détails'!$D$5:$D$407,A41) -> 126.21236 | F41: =px_mo_soud -> 15000 | G41: =D41*F41 -> 688174.22 | H41: =E41*F41 -> 1893185.4
A42: mo_tech | B42: Technicien | C42: h.j | D42: =SUMIFS('Sous-détails'!$J$5:$J$407,'Sous-détails'!$D$5:$D$407,A42,'Sous-détails'!$K$5:$K$407,"NON") -> 2 | E42: =SUMIFS('Sous-détails'!$J$5:$J$407,'Sous-détails'!$D$5:$D$407,A42) -> 2 | F42: =px_mo_tech -> 15000 | G42: =D42*F42 -> 30000 | H42: =E42*F42 -> 30000
A43: mo_man | B43: Manœuvre | C43: h.j | D43: =SUMIFS('Sous-détails'!$J$5:$J$407,'Sous-détails'!$D$5:$D$407,A43,'Sous-détails'!$K$5:$K$407,"NON") -> 457.68653 | E43: =SUMIFS('Sous-détails'!$J$5:$J$407,'Sous-détails'!$D$5:$D$407,A43) -> 624.32954 | F43: =px_mo_man -> 5000 | G43: =D43*F43 -> 2288432.7 | H43: =E43*F43 -> 3121647.7
A44: MATÉRIEL
A45: mt_bet | B45: Bétonnière 350 L (location) | C45: j | D45: =SUMIFS('Sous-détails'!$J$5:$J$407,'Sous-détails'!$D$5:$D$407,A45,'Sous-détails'!$K$5:$K$407,"NON") -> 12.314913 | E45: =SUMIFS('Sous-détails'!$J$5:$J$407,'Sous-détails'!$D$5:$D$407,A45) -> 12.314913 | F45: =px_mt_bet -> 25000 | G45: =D45*F45 -> 307872.82 | H45: =E45*F45 -> 307872.82
A46: mt_vib | B46: Vibreur (location) | C46: j | D46: =SUMIFS('Sous-détails'!$J$5:$J$407,'Sous-détails'!$D$5:$D$407,A46,'Sous-détails'!$K$5:$K$407,"NON") -> 12.314913 | E46: =SUMIFS('Sous-détails'!$J$5:$J$407,'Sous-détails'!$D$5:$D$407,A46) -> 12.314913 | F46: =px_mt_vib -> 15000 | G46: =D46*F46 -> 184723.69 | H46: =E46*F46 -> 184723.69
A47: mt_dame | B47: Dame sauteuse (location) | C47: j | D47: =SUMIFS('Sous-détails'!$J$5:$J$407,'Sous-détails'!$D$5:$D$407,A47,'Sous-détails'!$K$5:$K$407,"NON") -> 2.0927625 | E47: =SUMIFS('Sous-détails'!$J$5:$J$407,'Sous-détails'!$D$5:$D$407,A47) -> 2.0927625 | F47: =px_mt_dame -> 20000 | G47: =D47*F47 -> 41855.25 | H47: =E47*F47 -> 41855.25
A48: mt_plaque | B48: Compacteur à plaque vibrante / rouleau 1 t (location) | C48: j | D48: =SUMIFS('Sous-détails'!$J$5:$J$407,'Sous-détails'!$D$5:$D$407,A48,'Sous-détails'!$K$5:$K$407,"NON") -> 2.940225 | E48: =SUMIFS('Sous-détails'!$J$5:$J$407,'Sous-détails'!$D$5:$D$407,A48) -> 2.940225 | F48: =px_mt_plaque -> 60000 | G48: =D48*F48 -> 176413.5 | H48: =E48*F48 -> 176413.5
A49: mt_cam | B49: Camion benne 10 m³ | C49: voyage | D49: =SUMIFS('Sous-détails'!$J$5:$J$407,'Sous-détails'!$D$5:$D$407,A49,'Sous-détails'!$K$5:$K$407,"NON") -> 17.689219 | E49: =SUMIFS('Sous-détails'!$J$5:$J$407,'Sous-détails'!$D$5:$D$407,A49) -> 17.689219 | F49: =px_mt_cam -> 25000 | G49: =D49*F49 -> 442230.47 | H49: =E49*F49 -> 442230.47
A50: mt_scie | B50: Scie à sol (location) | C50: j | D50: =SUMIFS('Sous-détails'!$J$5:$J$407,'Sous-détails'!$D$5:$D$407,A50,'Sous-détails'!$K$5:$K$407,"NON") -> 1.3208333 | E50: =SUMIFS('Sous-détails'!$J$5:$J$407,'Sous-détails'!$D$5:$D$407,A50) -> 1.3208333 | F50: =px_mt_scie -> 30000 | G50: =D50*F50 -> 39625 | H50: =E50*F50 -> 39625
A51: mt_niveau | B51: Niveau / théodolite (location) | C51: j | D51: =SUMIFS('Sous-détails'!$J$5:$J$407,'Sous-détails'!$D$5:$D$407,A51,'Sous-détails'!$K$5:$K$407,"NON") -> 2 | E51: =SUMIFS('Sous-détails'!$J$5:$J$407,'Sous-détails'!$D$5:$D$407,A51) -> 2 | F51: =px_mt_niveau -> 15000 | G51: =D51*F51 -> 30000 | H51: =E51*F51 -> 30000
A52: mt_branch | B52: Branchements provisoires eau et électricité | C52: ft | D52: =SUMIFS('Sous-détails'!$J$5:$J$407,'Sous-détails'!$D$5:$D$407,A52,'Sous-détails'!$K$5:$K$407,"NON") -> 1 | E52: =SUMIFS('Sous-détails'!$J$5:$J$407,'Sous-détails'!$D$5:$D$407,A52) -> 1 | F52: =px_mt_branch -> 100000 | G52: =D52*F52 -> 100000 | H52: =E52*F52 -> 100000
A53: mt_ch | B53: Poste à souder, meuleuse, levage (charpente) | C53: kg | D53: =SUMIFS('Sous-détails'!$J$5:$J$407,'Sous-détails'!$D$5:$D$407,A53,'Sous-détails'!$K$5:$K$407,"NON") -> 3449.6369 | E53: =SUMIFS('Sous-détails'!$J$5:$J$407,'Sous-détails'!$D$5:$D$407,A53) -> 6939.3069 | F53: =px_mt_ch -> 100 | G53: =D53*F53 -> 344963.69 | H53: =E53*F53 -> 693930.69
A54: mt_echaf | B54: Échafaudage (location) | C54: m² | D54: =SUMIFS('Sous-détails'!$J$5:$J$407,'Sous-détails'!$D$5:$D$407,A54,'Sous-détails'!$K$5:$K$407,"NON") -> 0 | E54: =SUMIFS('Sous-détails'!$J$5:$J$407,'Sous-détails'!$D$5:$D$407,A54) -> 926.24 | F54: =px_mt_echaf -> 150 | G54: =D54*F54 -> 0 | H54: =E54*F54 -> 138936
A55: mt_portail | B55: Poste à souder, meuleuse (portail) | C55: ft | D55: =SUMIFS('Sous-détails'!$J$5:$J$407,'Sous-détails'!$D$5:$D$407,A55,'Sous-détails'!$K$5:$K$407,"NON") -> 0 | E55: =SUMIFS('Sous-détails'!$J$5:$J$407,'Sous-détails'!$D$5:$D$407,A55) -> 1 | F55: =px_mt_portail -> 150000 | G55: =D55*F55 -> 0 | H55: =E55*F55 -> 150000
B56: TOTAL (contrôle = déboursé sec, hors petit outillage) | G56: =SUM(G5:G55) -> 27649258 | H56: =SUM(H5:H55) -> 39759558
